Workbook

Sheet Plan Maestro
A1: CRONOGRAMA DE OBRA
A2: OBRAS PRELIMINARES Y MOVIMIENTO DE TIERRAS | B2: SEM 01 | C2: SEM 02 | D2: SEM 03 | E2: SEM 04 | F2: SEM 05 | G2: SEM 06 | H2: SEM 07 | I2: SEM 08 | J2: SEM 09 | K2: SEM 10 | L2: SEM 11 | M2: SEM 12 | N2: SEM 13 | O2: SEM 14 | P2: SEM 15 | Q2: SEM 16
A3: OBRAS PRELIMINARES
A4: DEMOLICIÓN PARCIAL
A5: MOVIMIENTO DE TIERRAS
A6: SEGURIDAD Y SALUD
A7: 1 ER PISO
A8: OBRAS DE CONCRETO SIMPLE
A9: OBRAS DE CONCRETO ARMADO
A10: TABIQUERIA
A11: OBRAS HUMEDAS
A12: INSTALACIONES ELECTRICAS
A13: INSTALACIONES SANITARIAS
A14: 2 DO PISO
... A25: INSTALACIONES SANITARIAS

Sheet Look A Head
A1: LOOKAHEAD PLANNING - OBRA SURQUILLO
A3: ITEM | B3: DESCRIPCIÓN DE PARTIDAS | E3: Semana 01 (01/06 al 06/05) | L3: Semana 02 (08/06 al 13/06) | S3: Semana 03 (15/06 al 20/06)
E4: L | F4: M | G4: X | H4: J | I4: V | J4: S | K4: D | L4: L | M4: M | N4: X | O4: J | P4: V | Q4: S | R4: D | S4: L | T4: M | U4: X | V4: J | W4: V | X4: S | Y4: D
A5: 01.00.00.00 | B5: OBRAS PROVISIONALES, TRABAJOS PRELIMINARES, SEGURIDAD Y SALUD
A6: 01.01.00.00 | B6: OBRAS PROVISIONALES
A7: 01.01.01.00 | B7: TRANSPORTE DE EQUIPOS Y HERRAMIENTAS | C7: glb | D7: 1 | H7: X | I7: X
A8: 01.01.03.00 | B8: PROTECCIÓN CON MALLA RASCHELL | C8: ml | D8: 180 | H8: X | I8: X
A9: 01.02.00.00 | B9: DEMOLICIÓN Y MOVIMIENTO DE TIERRAS
A10: 01.02.01.00 | B10: DESMONTAJE Y ACARREO DE MATERIAL | C10: glb | D10: 1 | E10: X | F10: X | G10: X
A11: 01.02.02.00 | B11: APUNTALAMIENTO ESTRUCTURAL | C11: GLB | D11: 1 | H11: X | I11: X
A12: 01.02.03.00 | B12: DEMOLICIÓN DE MUROS DE AZOTEA | C12: glb | D12: 1 | J12: X
A13: 01.02.03.00 | B13: DEMOLICIÓN DE MUROS Y PISO DE 3ER PISO | C13: glb | D13: 1 | L13: X | M13: X
A14: 01.02.03.00 | B14: DEMOLICIÓN DE MUROS Y PISO DE 2DO PISO | C14: glb | D14: 1 | N14: X | O14: X
A15: 01.02.03.00 | B15: DEMOLICIÓN DE MUROS Y PISO DE 1ER PISO | C15: glb | D15: 1 | P15: X | Q15: X
B16: DEMOLICIÓN DE ZANJA PARA ZAPATAS | C16: glb | D16: 1 | S16: X | T16: X | U16: X
A17: 01.02.04.00 | B17: ELIMINACIÓN DE ESCOMBROS, DESMONTE | C17: glb | D17: 1 | Q17: X | X17: X
A18: 01.02.05.00 | B18: TRAZADO Y REPLANTEO S/EQUIPO | C18: m2 | D18: 206 | S18: X
B19: EXCAVACIÓN MANUAL DE ZANJA EN ZAPATAS | C19: m3 | T19: X
B20: COMPACTACIÓN PARA ZAPATAS | C20: m2 | U20: X
A21: 01.02.00.00 | B21: OBRAS DE CONCRETO ARMADO
B22: SOLADO DE CONCRETO | C22: m2 | V22: X
B23: ACERO DE ZAPATAS | C23: kg | W23: X
B24: ACERO DE PLACAS | C24: kg | X24: X
B25: VACIADO DE ZAPATAS | C25: m3 | X25: X
B26: ENCOFRADO DE PLACAS | C26: m2

Sheet Restricciones
A2: ANÁLISIS DE RESTRICCIONES
A4: ACTIVIDAD RELACIONADA | B4: MONTO ESTIMADO | C4: Fecha Max. | D4: TIPO DE RESTRICCIÓN | G4: RESPONSABLE | H4: ESTATUS
B5: MONTO ESTIMADO | D5: FINANZAS | E5: O.F. TECNICA | F5: M.OBRA
A6: Expediente de Anexo H | B6: 250 | C6: 46175 | E6: X | G6: Ing.Willy / Ing. Guillermo
A7: Cartel de Obra | B7: 200 | C7: 46177 | D7: X | G7: Francesa Barbieri
A8: Compras de palos y malla raschell | B8: 2000 | C8: 46178 | D8: X | E8: X | F8: X | G8: Ing. Guillermo / Barbieri
A9: EPPs, completos, polos y chalecos | B9: 2000 | C9: 46178 | D9: X | G9: Francesa Barbieri
A10: Planos de demolición | C10: 46176 | E10: X | G10: Arq. Pierina / Arq. Alan
A11: Actualizacion de planos de Estructuras | C11: 46183 | E11: X | G11: Ing. Willy / Ing. Cristhian
A12: Actualizacion de planos de Arquitectura | C12: 46183 | E12: X | G12: Arq. Pierina / Arq. Alan
B14: ============
A15: MONTO ESTIMADO DE INVERSIÓN | B15: =SUM(B6:B13) -> 4450
B19: planner
B20: jefe de produccion
B21: residente de obra

Sheet PPC S1
A1: PPC - OBRA SURQUILLO - SEMANA 1
A3: ITEM | B3: DESCRIPCIÓN DE PARTIDAS | C3: METRADO | D3: UNIDAD | E3: METRADO PLANIFICADO | F3: Semana 01 (01/06 al 06/05) | M3: METRADO REALIZADO | N3: % CUMPLIMIENTO | O3: CUMPLIMIENTO | P3: ANALISIS DE CAUSAS DE INCUMPLIMIENTO & MEDIDAS CORRECTIVAS
F4: L | G4: M | H4: X | I4: J | J4: V | K4: S | L4: D
A5: 01.00.00.00 | B5: OBRAS PROVISIONALES, TRABAJOS PRELIMINARES, SEGURIDAD Y SALUD | O5: SI/NO | P5: TIPO | Q5: COMENTARIO | R5: MEDIDA CORRECTIVVA
A6: 01.01.00.00 | B6: OBRAS PROVISIONALES
A7: 01.01.01.00 | B7: TRANSPORTE DE EQUIPOS Y HERRAMIENTAS | C7: glb | D7: 1 | E7: 1 | I7: X | J7: X | N7: =IF(M7>0,M7/E7,0) -> 0 | O7: =IF(N7=1,"SI","NO") -> NO
A8: 01.01.03.00 | B8: PROTECCIÓN CON MALLA RASCHELL | C8: ml | D8: 180 | E8: 180 | I8: X | J8: X | N8: =IF(M8>0,M8/E8,0) -> 0 | O8: =IF(N8=1,"SI","NO") -> NO
A9: 01.02.00.00 | B9: DEMOLICIÓN Y MOVIMIENTO DE TIERRAS
A10: 01.02.01.00 | B10: DESMONTAJE Y ACARREO DE MATERIAL | C10: glb | D10: 1 | E10: 1 | F10: X | G10: X | H10: X | N10: =IF(M10>0,M10/E10,0) -> 0 | O10: =IF(N10=1,"SI","NO") -> NO
A11: 01.02.02.00 | B11: APUNTALAMIENTO ESTRUCTURAL | C11: GLB | D11: 1 | E11: 1 | I11: X | J11: X | N11: =IF(M11>0,M11/E11,0) -> 0 | O11: =IF(N11=1,"SI","NO") -> NO
A12: 01.02.03.00 | B12: DEMOLICIÓN DE MUROS DE AZOTEA | C12: glb | D12: 1 | E12: 1 | K12: X | N12: =IF(M12>0,M12/E12,0) -> 0 | O12: =IF(N12=1,"SI","NO") -> NO
A13: 01.02.03.00 | B13: DEMOLICIÓN DE MUROS Y PISO DE 3ER PISO | C13: glb | D13: 1 | E13: 1 | N13: =IF(M13>0,M13/E13,0) -> 0 | O13: =IF(N13=1,"SI","NO") -> NO
A14: 01.02.03.00 | B14: DEMOLICIÓN DE MUROS Y PISO DE 2DO PISO | C14: glb | D14: 1 | E14: 1 | N14: =IF(M14>0,M14/E14,0) -> 0 | O14: =IF(N14=1,"SI","NO") -> NO
A15: 01.02.03.00 | B15: DEMOLICIÓN DE MUROS Y PISO DE 1ER PISO | C15: glb | D15: 1 | E15: 1 | N15: =IF(M15>0,M15/E15,0) -> 0 | O15: =IF(N15=1,"SI","NO") -> NO
B16: DEMOLICIÓN DE ZANJA PARA ZAPATAS | C16: glb | D16: 1 | E16: 1 | N16: =IF(M16>0,M16/E16,0) -> 0 | O16: =IF(N16=1,"SI","NO") -> NO
A17: 01.02.04.00 | B17: ELIMINACIÓN DE ESCOMBROS, DESMONTE | C17: glb | D17: 1 | E17: 1 | N17: =IF(M17>0,M17/E17,0) -> 0 | O17: =IF(N17=1,"SI","NO") -> NO
A18: 01.02.05.00 | B18: TRAZADO Y REPLANTEO S/EQUIPO | C18: m2 | D18: 206 | E18: 206 | N18: =IF(M18>0,M18/E18,0) -> 0 | O18: =IF(N18=1,"SI","NO") -> NO
B19: EXCAVACIÓN MANUAL DE ZANJA EN ZAPATAS | C19: m3 | N19: =IF(M19>0,M19/E19,0) -> 0 | O19: =IF(N19=1,"SI","NO") -> NO
B20: COMPACTACIÓN PARA ZAPATAS | C20: m2 | N20: =IF(M20>0,M20/E20,0) -> 0 | O20: =IF(N20=1,"SI","NO") -> NO
A21: 01.02.00.00 | B21: OBRAS DE CONCRETO ARMADO
B22: SOLADO DE CONCRETO | C22: m2 | N22: =IF(M22>0,M22/E22,0) -> 0 | O22: =IF(N22=1,"SI","NO") -> NO
B23: ACERO DE ZAPATAS | C23: kg | N23: =IF(M23>0,M23/E23,0) -> 0 | O23: =IF(N23=1,"SI","NO") -> NO
B24: ACERO DE PLACAS | C24: kg | N24: =IF(M24>0,M24/E24,0) -> 0 | O24: =IF(N24=1,"SI","NO") -> NO
B25: VACIADO DE ZAPATAS | C25: m3 | N25: =IF(M25>0,M25/E25,0) -> 0 | O25: =IF(N25=1,"SI","NO") -> NO
B26: ENCOFRADO DE PLACAS | C26: m2 | N26: =IF(M26>0,M26/E26,0) -> 0 | O26: =IF(N26=1,"SI","NO") -> NO
N27: =IF(M27>0,M27/E27,0) -> 0 | O27: =IF(N27=1,"SI","NO") -> NO
Q29: CALCULO DE PPC
Q30: ACTIVIDADES CUMPLIDAS (100%) | R30: =COUNTIF($O$7:$O$27,"SI") -> 0
Q31: ACTIVIDADES NO CUMPLIDAS | R31: =COUNTIF($O$7:$O$27,"NO") -> 19
Q32: ACTIVIDADES PROGRAMADAS | R32: =R30+R31 -> 19
Q33: % DE CUMPLIMIENTO (PPC) | R33: =R30/R32 -> 0
P37: CAUSAS DE INCUMPLIMIENTO
P38: COD | Q38: DESCRIPCION | R38: CANT
P39: CLI-MAT | Q39: CLIENTE - MATERIALES | R39: =COUNTIF($V$10:$V$61,P39) -> 0
P40: CLI-ING | Q40: CLIENTE - INGENIERÍA | R40: =COUNTIF($V$10:$V$61,P40) -> 0
P41: CLI-PRI | Q41: CLIENTE - PRIORIDADES | R41: =COUNTIF($V$10:$V$61,P41) -> 0
P42: CLI-CAM | Q42: CLIENTE - CAMBIO | R42: =COUNTIF($V$10:$V$61,P42) -> 0
P43: MAT | Q43: MATERIALES | R43: =COUNTIF($V$10:$V$61,P43) -> 0
P44: DT | Q44: DOCUMENTACION TECNICA | R44: =COUNTIF($V$10:$V$61,P44) -> 0
P45: AP | Q45: ACTIVIDADES PREVIAS | R45: =COUNTIF($V$10:$V$61,P45) -> 0
P46: EXT | Q46: EXTERNO | R46: =COUNTIF($V$10:$V$61,P46) -> 0
P47: EE | Q47: ERRORES DE EJECUCION | R47: =COUNTIF($V$10:$V$61,P47) -> 0
P48: QC | Q48: CONTROL DE CALIDAD | R48: =COUNTIF($V$10:$V$61,P48) -> 0
P49: PER | Q49: PERSONAL | R49: =COUNTIF($V$10:$V$61,P49) -> 0
P50: EQ | Q50: EQUIPOS | R50: =COUNTIF($V$10:$V$61,P50) -> 0
... P52: IOF | Q52: INCUMPLIMIENTO DE OTRO FRENTE | R52: =COUNTIF($V$10:$V$61,P52) -> 0

Sheet H PPC
C1: ANÁLISIS PPC
W2: Fecha de corte : | X2: 43853
B3: 1 | C3: % de cumplimiento General del proyecto
C5: % cumplimiento | D5: =AVERAGE(F10:F26) -> #DIV/0!
B7: 2 | C7: Historico de % semanal de cumplimiento en PPC
C9: SEMANA | D9: Actividades planificadas | E9: Actividades completadas | F9: %
C10: 1 | D10: ='PPC S1'!R32 -> 19 | E10: ='PPC S1'!R30 -> 0 | F10: =E10/D10 -> 0
C11: =C10+1 -> 2 | F11: =E11/D11 -> #DIV/0!
C12: =C11+1 -> 3 | F12: =E12/D12 -> #DIV/0!
C13: =C12+1 -> 4 | F13: =E13/D13 -> #DIV/0!
C14: =C13+1 -> 5 | F14: =E14/D14 -> #DIV/0!
C15: =C14+1 -> 6 | F15: =E15/D15 -> #DIV/0!
C16: =C15+1 -> 7 | F16: =E16/D16 -> #DIV/0!
C17: =C16+1 -> 8 | F17: =E17/D17 -> #DIV/0!
C18: =C17+1 -> 9 | F18: =E18/D18 -> #DIV/0!
C19: =C18+1 -> 10 | F19: =E19/D19 -> #DIV/0!
C20: =C19+1 -> 11 | F20: =E20/D20 -> #DIV/0!
C21: =C20+1 -> 12 | F21: =E21/D21 -> #DIV/0!
C22: =C21+1 -> 13 | F22: =E22/D22 -> #DIV/0!
... C26: =C25+1 -> 17 | F26: =E26/D26 -> #DIV/0!
B29: 3 | C29: Causas de incumplimiento Historico
C31: Semana | D31: TIPO | E31: RESPONSABLE | F31: DESCRIPCION
C32: 1 | D32: CLI-ING | E32: CLIENTE | F32: =INDEX($D$38:$D$51,MATCH(D32,$C$38:$C$51,0)) -> CLIENTE - INGENIERÍA
C33: 1 | D33: CLI-ING | E33: CLIENTE | F33: =INDEX($D$38:$D$51,MATCH(D33,$C$38:$C$51,0)) -> CLIENTE - INGENIERÍA
C34: 4 | D34: DT | E34: CONSTRUCTOR | F34: =INDEX($D$38:$D$51,MATCH(D34,$C$38:$C$51,0)) -> DOCUMENTACION TECNICA
C37: COD | D37: DESCRIPCION | F37: CANTIDAD
C38: CLI-MAT | D38: CLIENTE - MATERIALES | F38: =COUNTIF($D$32:$D$34,C38) -> 0
C39: CLI-ING | D39: CLIENTE - INGENIERÍA | F39: =COUNTIF($D$32:$D$34,C39) -> 2
C40: CLI-PRI | D40: CLIENTE - PRIORIDADES | F40: =COUNTIF($D$32:$D$34,C40) -> 0
C41: CLI-CAM | D41: CLIENTE - CAMBIO | F41: =COUNTIF($D$32:$D$34,C41) -> 0
C42: MAT | D42: MATERIALES | F42: =COUNTIF($D$32:$D$34,C42) -> 0
C43: DT | D43: DOCUMENTACION TECNICA | F43: =COUNTIF($D$32:$D$34,C43) -> 1
C44: AP | D44: ACTIVIDADES PREVIAS | F44: =COUNTIF($D$32:$D$34,C44) -> 0
C45: EXT | D45: EXTERNO | F45: =COUNTIF($D$32:$D$34,C45) -> 0
C46: EE | D46: ERRORES DE EJECUCION | F46: =COUNTIF($D$32:$D$34,C46) -> 0
C47: QC | D47: CONTROL DE CALIDAD | F47: =COUNTIF($D$32:$D$34,C47) -> 0
C48: PER | D48: PERSONAL | F48: =COUNTIF($D$32:$D$34,C48) -> 0
C49: EQ | D49: EQUIPOS | F49: =COUNTIF($D$32:$D$34,C49) -> 0
... C51: IOF | D51: INCUMPLIMIENTO DE OTRO FRENTE | F51: =COUNTIF($D$32:$D$34,C51) -> 0
D52: TOTAL | F52: =SUM(F38:F51) -> 3

Sheet Flujo de caja
B1: FLUJO DE CAJA OBRA SURQUILLO
A5: MONTO ADJUDICADO DE OBRA | B5: 370000 | C5: INC IGV
A7: INGRESOS | B7: TOTAL | C7: 46167 | D7: =+C7+7 -> 46174 | E7: =+D7+7 -> 46181 | F7: =+E7+7 -> 46188 | G7: =+F7+7 -> 46195
C8: =+C7+5 -> 46172 | D8: =+D7+5 -> 46179 | E8: =+E7+5 -> 46186 | F8: =+F7+5 -> 46193 | G8: =+G7+5 -> 46200
C9: Sem 01 | D9: Sem 02 | E9: Sem 03 | F9: Sem 04 | G9: Sem 05
A10: Adelanto de obra | B10: =SUM(C10:G10) -> 0
A11: Valorizaciones | B11: =SUM(C11:G11) -> 0
A12: TOTAL DE INGRESOS | B12: =SUM(B10:B11) -> 0 | C12: =SUM(C10:C11) -> 0 | D12: =SUM(D10:D11) -> 0 | E12: =SUM(E10:E11) -> 0 | F12: =SUM(F10:F11) -> 0 | G12: =SUM(G10:G11) -> 0
A14: EGRESOS | B14: TOTAL | C14: =+C7 -> 46167 | D14: =+C14+7 -> 46174 | E14: =+D14+7 -> 46181 | F14: =+E14+7 -> 46188 | G14: =+F14+7 -> 46195
C15: =+C14+5 -> 46172 | D15: =+D14+5 -> 46179 | E15: =+E14+5 -> 46186 | F15: =+F14+5 -> 46193 | G15: =+G14+5 -> 46200
C16: Sem 01 | D16: Sem 02 | E16: Sem 03 | F16: Sem 04 | G16: Sem 05
A17: COSTO DIRECTO
A18: Costo Materiales y otros
A19: Seguridad y salud | B19: =SUM(C19:G19) -> 0
A20: Movimiento de tierras
A21: Eliminación de desmonte | B21: =SUM(C21:G21) -> 0
A22: Subcontrato de Demolición
A23: Adelanto de desmontaje | B23: =SUM(C23:G23) -> 0
A24: Mano de Obra y equipos | B24: =SUM(C24:G24) -> 0
A25: Subcontrato de Obra gruesa
A26: Adelanto de subcontratista | B26: =SUM(C26:G26) -> 0
A27: Mano de Obra y equipos | B27: =SUM(C27:G27) -> 0
A28: TOTAL COSTO INDIRECTO | B28: =SUM(B18:B24) -> 0 | C28: =SUM(C18:C24) -> 0 | D28: =SUM(D18:D24) -> 0 | E28: =SUM(E18:E24) -> 0 | F28: =SUM(F18:F24) -> 0 | G28: =SUM(G18:G24) -> 0
A30: COSTO INDIRECTO
A31: Residente de Obra | B31: =SUM(C31:G31) -> 0
A32: Seguros y polizas | B32: =SUM(C32:G32) -> 0
A33: Gastos varios | B33: =SUM(C33:G33) -> 0
A34: COSTO DIRECTO | B34: =SUM(B31:B33) -> 0 | C34: =SUM(C31:C33) -> 0 | D34: =SUM(D31:D33) -> 0 | E34: =SUM(E31:E33) -> 0 | F34: =SUM(F31:F33) -> 0 | G34: =SUM(G31:G33) -> 0
A35: TOTAL DE EGRESOS | B35: =+B34+B28 -> 0 | C35: =+C34+C28 -> 0 | E35: =+E34+E28 -> 0 | F35: =+F34+F28 -> 0
A37: SALDO OPERATIVO | B37: =+B12-B35 -> 0 | C37: =+C12-C35 -> 0 | D37: =+D12-D35 -> 0 | E37: =+E12-E35 -> 0 | F37: =+F12-F35 -> 0 | G37: =+G12-G35 -> 0

Sheet Depositos
A1: MONTO DE CONTRATO DE OBRA = | C1: 370000 | D1: A suma alzada
A3: Descripción | B3: Fecha | C3: Monto | D3: Cuenta
A4: ADELANTO TOTAL | C4: =SUM(C5:C5) -> 50000 | D4: =+C4/C1 -> 0.13513514
A5: Adelanto de obra 1 | B5: 46119 | C5: 50000 | D5: Cuenta dolares Guillermo Casallo
A6: VALORIZACIONES | C6: =SUM(C7:C11) -> 0 | D6: =+C6/C1 -> 0
A7: Semana 01
A8: Semana 02
A9: Semana 03
A10: Semana 04
A11: Semana 05
A12: Depósito total = | C12: =+C4+C6 -> 50000 | D12: =+C12/C1 -> 0.13513514
A13: Saldo de obra = | C13: =+C1-C12 -> 320000 | D13: =+C13/C1 -> 0.86486486
A16: MONTO DE SUBCONTRATO = | C16: 100000 | D16: Mano de obra casco gris
A18: Descripción | B18: Fecha | C18: Monto | D18: Cuenta
A19: ADELANTO TOTAL | C19: =SUM(C20:C21) -> 0 | D19: =+C19/C16 -> 0
A22: Descripción | B22: Fecha | C22: Monto | D22: Cuenta
A23: VALORIZACIONES | C23: =SUM(C24:C37) -> 0 | D23: =+C23/C16 -> 0
A24: Semana 01
A25: Semana 02
A26: Semana 03
A27: Semana 04
A28: Semana 05
A29: Semana 06
A30: Semana 07
A31: Semana 08
A32: Semana 09
A33: Semana 10
A34: Semana 11
A35: Semana 12
... A37: Semana 14
B38: TOTAL PAGADO | C38: =+C23+C19 -> 0 | D38: =+C38/C16 -> 0
B39: SALDO | C39: =+C16-C38 -> 100000 | D39: =+C39/C16 -> 1

Sheet Presupuesto Real Comparativo
A1: PRESUPUESTO DE OBRA POR PARTIDAS
A2: PROYECTO:
A3: PROPIETARIO(S) :
A4: UBICACIÓN:
A5: ITEM | B5: DESCRIPCIÓN DE PARTIDAS | C5: PRESUPUESTO ACTUAL
C6: UND | D6: METRADO | E6: PRECIO MO | F6: PRECIO PARCIAL MO | G6: PRECIO MAT | H6: PRECIO PARCIAL MAT | I6: PRECIO UNITARIO | J6: PRECIO PARCIAL
D7: CONTRATO
A8: =+'O. GRUESA'!A7 -> 01.00.00.00 | B8: =+'O. GRUESA'!B7 -> OBRAS PROVISIONALES, TRABAJOS PRELIMINARES, SEGURIDAD Y SALUD | F8: =+F9+F14+F20 -> 8112.842 | H8: =+H9+H14+H20 -> 15358.89 | J8: =+J9+J14+J20 -> 46869.445
A9: =+'O. GRUESA'!A8 -> 01.01.00.00 | B9: =+'O. GRUESA'!B8 -> OBRAS PROVISIONALES | F9: =SUM(F10:F13) -> 1167.265 | H9: =SUM(H10:H13) -> 9699.3875 | J9: =+RESUMEN!C4 -> 10876.107
A10: 01.01.01.00 | B10: =+'O. GRUESA'!B9 -> TRANSPORTE DE EQUIPOS Y HERRAMIENTAS | C10: =+'O. GRUESA'!D9 -> glb | D10: =+'O. GRUESA'!J9 -> 1 | E10: 1000 | F10: =D10*E10 -> 1000 | G10: 1000 | H10: =D10*G10 -> 1000 | I10: =+E10+G10 -> 2000 | J10: =D10*I10 -> 2000
A11: 01.01.02.00 | B11: =+'O. GRUESA'!B12 -> CERCO PERIMETRICO PROVISIONAL | C11: =+'O. GRUESA'!D12 -> ml | D11: =+'O. GRUESA'!J12 -> 30 | E11: 0 | F11: =D11*E11 -> 0 | G11: =+'APUs Casco'!F59+'APUs Casco'!F63+'APUs Casco'!F68 -> 157.89625 | H11: =D11*G11 -> 4736.8875 | I11: =+E11+G11 -> 157.89625 | J11: =D11*I11 -> 4736.8875
A12: 01.01.03.00 | B12: =+'O. GRUESA'!B15 -> PROTECCIÓN CON MALLA RASCHELL | C12: =+'O. GRUESA'!D15 -> ml | D12: =+'O. GRUESA'!J15 -> 180 | E12: =+'APUs Casco'!F74+'APUs Casco'!F82 -> 0.92925 | F12: =D12*E12 -> 167.265 | G12: =+'APUs Casco'!F78 -> 13.125 | H12: =D12*G12 -> 2362.5 | I12: =+E12+G12 -> 14.05425 | J12: =D12*I12 -> 2529.765
A13: 01.01.04.00 | B13: =+'O. GRUESA'!B21 -> ALQUILER DE BAÑO PROVISIONAL | C13: =+'O. GRUESA'!D21 -> mes | D13: =+'O. GRUESA'!J21 -> 4 | E13: 0 | F13: =D13*E13 -> 0 | G13: 400 | H13: =D13*G13 -> 1600 | I13: =+E13+G13 -> 400 | J13: =D13*I13 -> 1600
A14: =+'O. GRUESA'!A24 -> 01.02.00.00 | B14: =+'O. GRUESA'!B24 -> DEMOLICIÓN Y TRABAJOS PRELIMINARES | F14: =SUM(F15:F19) -> 3345.577 | H14: =SUM(H15:H19) -> 3209.502 | J14: =+RESUMEN!C5 -> 28571.36
A15: 01.02.01.00 | B15: =+'O. GRUESA'!B25 -> DESMONTAJE Y ACARREO DE MATERIAL | C15: =+'O. GRUESA'!D25 -> glb | D15: =+'O. GRUESA'!J25 -> 1 | E15: 1500 | F15: =D15*E15 -> 1500 | G15: 0 | H15: =D15*G15 -> 0 | I15: 3000 | J15: =D15*I15 -> 3000
A16: 01.02.02.00 | B16: APUNTALAMIENTO ESTRUCTURAL | C16: GLB | D16: 1 | E16: 0 | F16: =D16*E16 -> 0 | G16: 0 | H16: =D16*G16 -> 0 | I16: 2500 | J16: =D16*I16 -> 2500
A17: 01.02.03.00 | B17: DEMOLICIÓN MANUAL CON ROTOMARTILLO 3 PISOS Y AZOTEA | C17: =+'O. GRUESA'!D28 -> glb | D17: =+'O. GRUESA'!J28 -> 1 | E17: 0 | F17: =D17*E17 -> 0 | G17: 0 | H17: =D17*G17 -> 0 | I17: 18000 | J17: =D17*I17 -> 18000
A18: 01.02.04.00 | B18: =+'O. GRUESA'!B34 -> ELIMINACIÓN DE ESCOMBROS, DESMONTE | C18: =+'O. GRUESA'!D34 -> glb | D18: =+'O. GRUESA'!J34 -> 1 | E18: 0 | F18: =D18*E18 -> 0 | G18: 3000 | H18: =D18*G18 -> 3000 | I18: 3000 | J18: =D18*I18 -> 3000
A19: 01.02.05.00 | B19: =+'O. GRUESA'!B40 -> TRAZADO Y REPLANTEO S/EQUIPO | C19: =+'O. GRUESA'!D40 -> m2 | D19: 206 | E19: =+'APUs Casco'!F23+'APUs Casco'!F31 -> 8.9591117 | F19: =D19*E19 -> 1845.577 | G19: =+'APUs Casco'!F27 -> 1.017 | H19: =D19*G19 -> 209.502 | I19: =+J19/D19 -> 10.055146 | J19: =+J14-SUM(J15:J18) -> 2071.36
A20: =+'O. GRUESA'!A43 -> 01.03.00.00 | B20: =+'O. GRUESA'!B43 -> SEGURIDAD Y SALUD | F20: =SUM(F21:F24) -> 3600 | H20: =SUM(H21:H24) -> 2450 | J20: =+RESUMEN!C7 -> 7421.9785
A21: =+'O. GRUESA'!A44 -> 01.03.01.00 | B21: =+'O. GRUESA'!B44 -> EQUIPOS DE PROTECCIÓN INDIVIDUAL | C21: =+'O. GRUESA'!D44 -> und | D21: 30 | E21: 120 | F21: =D21*E21 -> 3600 | G21: 30 | H21: =D21*G21 -> 900 | I21: =+E21+G21 -> 150 | J21: =D21*I21 -> 4500
A22: =+'O. GRUESA'!A47 -> 01.03.02.00 | B22: =+'O. GRUESA'!B47 -> EQUIPOS DE PROTECCIÓN COLECTIVA | C22: =+'O. GRUESA'!D47 -> glb | D22: =+'O. GRUESA'!J47 -> 1 | E22: 0 | F22: =D22*E22 -> 0 | G22: 500 | H22: =D22*G22 -> 500 | I22: =+J22 -> 1071.9785 | J22: =+J20-J21-J23-J24 -> 1071.9785
A23: =+'O. GRUESA'!A50 -> 01.03.03.00 | B23: =+'O. GRUESA'!B50 -> SEÑALIZACIÓN TEMPORAL DE SEGURIDAD | C23: =+'O. GRUESA'!D50 -> glb | D23: =+'O. GRUESA'!J50 -> 1 | E23: 0 | F23: =D23*E23 -> 0 | G23: 250 | H23: =D23*G23 -> 250 | I23: =+E23+G23 -> 250 | J23: =D23*I23 -> 250
A24: =+'O. GRUESA'!A53 -> 01.03.04.00 | B24: =+'O. GRUESA'!B53 -> SEGURO SCTR | C24: =+'O. GRUESA'!D53 -> mes | D24: =+'O. GRUESA'!J53 -> 4 | E24: 0 | F24: =D24*E24 -> 0 | G24: 200 | H24: =D24*G24 -> 800 | I24: 400 | J24: =D24*I24 -> 1600
A25: =+'O. GRUESA'!A56 -> 02.00.00.00 | B25: =+'O. GRUESA'!B56 -> MOVIMIENTO DE TIERRAS | F25: =SUM(F26:F30) -> 5964.1277 | H25: =SUM(H26:H30) -> 2253.3181 | J25: =+RESUMEN!C6 -> 7667.9579
A26: 02.01.00.00 | B26: ='O. GRUESA'!$B$57 -> EXCAVACIÓN MANUAL P/CIMIENTO Y ZAPATA | C26: ='O. GRUESA'!$D$57 -> m3 | D26: ='O. GRUESA'!$J$57 -> 54.705 | E26: ='APUs Casco'!$F$131 -> 45.888889 | F26: =D26*E26 -> 2510.3517 | G26: ='APUs Casco'!$F$134 -> 1.3766667 | H26: =D26*G26 -> 75.31055 | I26: =+J26/D26 -> 37.220991 | J26: =+J25-SUM(J27:J30) -> 2036.1743
A27: 02.02.00.00 | B27: =+'O. GRUESA'!B74 -> COMPACTACIÓN MANUAL P/CIMIENTO Y ZAPATA | C27: =+'O. GRUESA'!D74 -> m2 | D27: =+'O. GRUESA'!J74 -> 33.045 | E27: =+'APUs Casco'!F140 -> 23.993333 | F27: =D27*E27 -> 792.8597 | G27: =+'APUs Casco'!F144 -> 3.1198 | H27: =D27*G27 -> 103.09379 | I27: =+E27+G27 -> 27.113133 | J27: =D27*I27 -> 895.95349
A28: 02.03.00.00 | B28: =+'O. GRUESA'!B91 -> RELLENO COMPACTADO CON MATERIAL PROPIO | C28: =+'O. GRUESA'!D91 -> m3 | D28: =+'O. GRUESA'!J91 -> 28.584 | E28: =+'APUs Casco'!F151 -> 0.68833333 | F28: =D28*E28 -> 19.67532 | G28: =+'APUs Casco'!F154 -> 5.0344167 | H28: =D28*G28 -> 143.90377 | I28: =+E28+G28 -> 5.72275 | J28: =D28*I28 -> 163.57909
A29: 02.04.00.00 | B29: =+'O. GRUESA'!B108 -> ELIMINACION DE MATERIAL CON MAQUINARIA | C29: =+'O. GRUESA'!D108 -> m3 | D29: =+'O. GRUESA'!J108 -> 54.705 | E29: =+'APUs Casco'!F184 -> 7.8666667 | F29: =D29*E29 -> 430.346 | G29: 22 | H29: =D29*G29 -> 1203.51 | I29: =+E29+G29 -> 29.866667 | J29: =D29*I29 -> 1633.856
A30: 02.05.00.00 | B30: =+'O. GRUESA'!B112 -> NIVELACION DE TERRENO Y APISONADO C/20 CM. | C30: =+'O. GRUESA'!D112 -> m2 | D30: =+'O. GRUESA'!J112 -> 150 | E30: =+'APUs Casco'!F193+'APUs Casco'!F201 -> 14.7393 | F30: =D30*E30 -> 2210.895 | G30: =+'APUs Casco'!F198 -> 4.85 | H30: =D30*G30 -> 727.5 | I30: =+E30+G30 -> 19.5893 | J30: =D30*I30 -> 2938.395
A31: =+'O. GRUESA'!A116 -> 03.00.00.00 | B31: =+'O. GRUESA'!B116 -> 1ER PISO | F31: =+F32+F42+F70+F73 -> 50087.853 | H31: =+H32+H42+H70+H73 -> 55039.907 | J31: =+J32+J42+J70+J73+J82+J90 -> 129861.17
A32: 03.01.00.00 | B32: =+'O. GRUESA'!B117 -> CONCRETO SIMPLE | F32: =SUM(F33:F41) -> 6290.3482 | H32: =SUM(H33:H41) -> 10936.765 | J32: =+RESUMEN!C9 -> 17227.114
A33: 03.01.01.00 | B33: SOLADO
A34: 03.01.01.01 | B34: =+'O. GRUESA'!B119 -> CONCRETO, fc=100 kg/cm² | C34: =+'O. GRUESA'!D119 -> m2 | D34: =+'O. GRUESA'!J119 -> 17.67 | E34: =+'APUs Casco'!F208+'APUs Casco'!F217 -> 14.642056 | F34: =D34*E34 -> 258.72512 | G34: =+'APUs Casco'!F214 -> 28.775 | H34: =D34*G34 -> 508.45425 | I34: =+E34+G34 -> 43.417056 | J34: =D34*I34 -> 767.17937
A35: 03.01.02.00 | B35: =+'O. GRUESA'!B124 -> CIMIENTO CORRIDO
A36: 03.01.02.01 | B36: =+'O. GRUESA'!B125 -> CONCRETO f'c= 100 kg/cm² +30% P.G. (Tamaño maximo 6") | C36: =+'O. GRUESA'!D125 -> m3 | D36: =+'O. GRUESA'!J125 -> 18.45 | E36: =+'APUs Casco'!F300+'APUs Casco'!F309 -> 73.423111 | F36: =D36*E36 -> 1354.6564 | G36: =+'APUs Casco'!F305 -> 312.85 | H36: =D36*G36 -> 5772.0825 | I36: =+E36+G36 -> 386.27311 | J36: =D36*I36 -> 7126.7389
A37: 03.01.03.00 | B37: =+'O. GRUESA'!B139 -> SOBRECIMIENTO
A38: 03.01.03.01 | B38: =+'O. GRUESA'!B140 -> CONCRETO, f'c= 140 kg/cm² +25% P.M. (Tamaño maximo 3") | C38: =+'O. GRUESA'!D140 -> m3 | D38: =+'O. GRUESA'!J140 -> 2.74875 | E38: =+'APUs Casco'!F330+'APUs Casco'!F339 -> 110.13467 | F38: =D38*E38 -> 302.73267 | G38: =+'APUs Casco'!F335 -> 250.85 | H38: =D38*G38 -> 689.52394 | I38: =+E38+G38 -> 360.98467 | J38: =D38*I38 -> 992.2566
A39: 03.01.03.02 | B39: =+'O. GRUESA'!B154 -> ENCOFRADO Y DESENCOFRADO | C39: =+'O. GRUESA'!D154 -> m2 | D39: =+'O. GRUESA'!J154 -> 36.65 | E39: =+'APUs Casco'!F316+'APUs Casco'!F324 -> 35.449167 | F39: =D39*E39 -> 1299.212 | G39: =+'APUs Casco'!F321 -> 2.1 | H39: =D39*G39 -> 76.965 | I39: =+E39+G39 -> 37.549167 | J39: =D39*I39 -> 1376.177
A40: 03.01.04.00 | B40: =+'O. GRUESA'!B168 -> FALSO PISO
A41: 03.01.04.01 | B41: =+'O. GRUESA'!B169 -> FALSO PISO | C41: =+'O. GRUESA'!D169 -> m2 | D41: =+J41/I41 -> 142.48131 | E41: =+'APUs Casco'!F346+'APUs Casco'!F354 -> 21.581933 | F41: =D41*E41 -> 3075.0221 | G41: =+'APUs Casco'!F352 -> 27.3 | H41: =D41*G41 -> 3889.7397 | I41: =+E41+G41 -> 48.881933 | J41: =+J32-SUM(J34:J39) -> 6964.7618
A42: 03.02.00.00 | B42: =+'O. GRUESA'!B172 -> CONCRETO ARMADO + MUROS PORTANTES | F42: =+SUM(F43:F67) -> 21576.89 | H42: =+SUM(H43:H67) -> 32077.412 | J42: =+RESUMEN!C10 -> 54821.241
A43: 03.02.01.00 | B43: =+'O. GRUESA'!B173 -> ZAPATAS
A44: 03.02.01.01 | B44: =+'O. GRUESA'!B174 -> CONCRETO PREMEZCLADO f'c=210kg/cm2 | C44: =+'O. GRUESA'!D174 -> m3 | D44: =+'O. GRUESA'!J174 -> 10.602 | E44: ='APUs Casco'!$F$540+'APUs Casco'!$F$548 -> 49.7052 | F44: =D44*E44 -> 526.97453 | G44: ='APUs Casco'!$F$545 -> 330.75 | H44: =D44*G44 -> 3506.6115 | I44: =+E44+G44 -> 380.4552 | J44: =D44*I44 -> 4033.586
A45: 03.02.01.02 | B45: =+'O. GRUESA'!B179 -> ENCOFRADO Y DESENCOFRADO | C45: =+'O. GRUESA'!D179 -> m2 | D45: =+'O. GRUESA'!J179 -> 29.82 | E45: ='APUs Casco'!$F$685+'APUs Casco'!$F$694 -> 44.401583 | F45: =D45*E45 -> 1324.0552 | G45: ='APUs Casco'!$F$691 -> 3 | H45: =D45*G45 -> 89.46 | I45: =+E45+G45 -> 47.401583 | J45: =D45*I45 -> 1413.5152 | K45: 25
A46: 03.02.01.03 | B46: =+'O. GRUESA'!B184 -> ACERO fy=4200kg/cm2 | C46: =+'O. GRUESA'!D184 -> kg | D46: =+'O. GRUESA'!J184 -> 477.09 | E46: ='APUs Casco'!$F$848+'APUs Casco'!$F$855 -> 1.5143333 | F46: =D46*E46 -> 722.47329 | G46: ='APUs Casco'!$F$852 -> 5.85 | H46: =D46*G46 -> 2790.9765 | I46: =+E46+G46 -> 7.3643333 | J46: =D46*I46 -> 3513.4498
A47: 03.02.02.00 | B47: ='O. GRUESA'!B188 -> PLACAS
A48: 03.02.02.01 | B48: ='O. GRUESA'!$B$189 -> PLACAS - CONCRETO PREMEZCLADO f'c=210kg/cm2 | C48: ='O. GRUESA'!$D$189 -> m3 | D48: ='O. GRUESA'!$J$189 -> 12.9 | E48: ='APUs Casco'!$F$627+'APUs Casco'!$F$635 -> 88.708667 | F48: =D48*E48 -> 1144.3418 | G48: ='APUs Casco'!$F$632 -> 348.75 | H48: =D48*G48 -> 4498.875 | I48: =+E48+G48 -> 437.45867 | J48: =D48*I48 -> 5643.2168
A49: 03.02.02.02 | B49: ='O. GRUESA'!$B$194 -> PLACAS - ENCOFRADO Y DESENCOFRADO | C49: ='O. GRUESA'!$D$194 -> m2 | D49: ='O. GRUESA'!$J$194 -> 123.9 | E49: ='APUs Casco'!$F$760+'APUs Casco'!$F$769 -> 60.478167 | F49: =D49*E49 -> 7493.2449 | G49: ='APUs Casco'!$F$766 -> 2.35 | H49: =D49*G49 -> 291.165 | I49: =+E49+G49 -> 62.828167 | J49: =D49*I49 -> 7784.4099
A50: 03.02.02.03 | B50: ='O. GRUESA'!$B$199 -> PLACAS - ACERO fy=4200kg/cm2 | C50: ='O. GRUESA'!$D$199 -> kg | D50: ='O. GRUESA'!$J$199 -> 1225.5 | E50: ='APUs Casco'!$F$926+'APUs Casco'!$F$933 -> 2.2715 | F50: =D50*E50 -> 2783.7232 | G50: ='APUs Casco'!$F$930 -> 5.75 | H50: =D50*G50 -> 7046.625 | I50: =+E50+G50 -> 8.0215 | J50: =D50*I50 -> 9830.3482
A51: 03.02.03.00 | B51: =+'O. GRUESA'!B203 -> VIGAS
A52: 03.02.03.01 | B52: =+'O. GRUESA'!B204 -> VIGAS - CONCRETO PREMEZCLADO f'c=210kg/cm2 | C52: =+'O. GRUESA'!D204 -> m3 | D52: =+'O. GRUESA'!J204 -> 4.1165 | E52: =+'APUs Casco'!F480+'APUs Casco'!F488 -> 57.276533 | F52: =D52*E52 -> 235.77885 | G52: =+'APUs Casco'!F485 -> 330.75 | H52: =D52*G52 -> 1361.5324 | I52: =+E52+G52 -> 388.02653 | J52: =D52*I52 -> 1597.3112
A53: 03.02.03.02 | B53: =+'O. GRUESA'!B214 -> VIGAS - ENCOFRADO Y DESENCOFRADO | C53: =+'O. GRUESA'!D214 -> m2 | D53: =+'O. GRUESA'!J214 -> 30.1625 | E53: =+'APUs Casco'!F775+'APUs Casco'!F784 -> 46.902767 | F53: =D53*E53 -> 1414.7047 | G53: =+'APUs Casco'!F781 -> 2.2 | H53: =D53*G53 -> 66.3575 | I53: =+E53+G53 -> 49.102767 | J53: =D53*I53 -> 1481.0622
A54: 03.02.03.03 | B54: =+'O. GRUESA'!B224 -> VIGAS - ACERO fy=4200kg/cm2 | C54: =+'O. GRUESA'!D224 -> kg | D54: =+'O. GRUESA'!J224 -> 1029.125 | E54: =+'APUs Casco'!F939+'APUs Casco'!F946 -> 1.8172 | F54: =D54*E54 -> 1870.126 | G54: =+'APUs Casco'!F943 -> 5.6 | H54: =D54*G54 -> 5763.1 | I54: =+E54+G54 -> 7.4172 | J54: =D54*I54 -> 7633.226
A55: 03.02.04.00 | B55: =+'O. GRUESA'!B228 -> LOSA ALIGERADA
A56: 03.02.04.01 | B56: =+'O. GRUESA'!B229 -> LOSA ALIGERADA - CONCRETO PREMEZCLADO f'c=210kg/cm2 | C56: =+'O. GRUESA'!D229 -> m3 | D56: =+'O. GRUESA'!J229 -> 2.29275 | E56: =+'APUs Casco'!F495+'APUs Casco'!F503 -> 57.276533 | F56: =D56*E56 -> 131.32077 | G56: =+'APUs Casco'!F500 -> 330.75 | H56: =D56*G56 -> 758.32706 | I56: =+E56+G56 -> 388.02653 | J56: =D56*I56 -> 889.64783
A57: 03.02.04.02 | B57: =+'O. GRUESA'!B234 -> LOSA ALIGERADA - ENCOFRADO Y DESENCOFRADO | C57: =+'O. GRUESA'!D234 -> m2 | D57: =+'O. GRUESA'!J234 -> 22.9275 | E57: =+'APUs Casco'!F790+'APUs Casco'!F799 -> 31.934905 | F57: =D57*E57 -> 732.18753 | G57: =+'APUs Casco'!F796 -> 1.05 | H57: =D57*G57 -> 24.073875 | I57: =+E57+G57 -> 32.984905 | J57: =D57*I57 -> 756.2614
A58: 03.02.04.03 | B58: =+'O. GRUESA'!B239 -> LOSA ALIGERADA - LADRILLO HUECO DE 0.15X0.30X0.30 | C58: =+'O. GRUESA'!D239 -> und | D58: =+'O. GRUESA'!J239 -> 207 | E58: =+'APUs Casco'!F805+'APUs Casco'!F812 -> 1.0381542 | F58: =D58*E58 -> 214.89791 | G58: =+'APUs Casco'!F810 -> 3.675 | H58: =D58*G58 -> 760.725 | I58: =+E58+G58 -> 4.7131542 | J58: =D58*I58 -> 975.62291
A59: 03.02.04.04 | B59: =+'O. GRUESA'!B244 -> LOSA ALIGERADA - ACERO fy=4200kg/cm2 | C59: =+'O. GRUESA'!D244 -> kg | D59: =+'O. GRUESA'!J244 -> 275.13 | E59: =+'APUs Casco'!F952+'APUs Casco'!F959 -> 1.8172 | F59: =D59*E59 -> 499.96624 | G59: =+'APUs Casco'!F956 -> 5.6 | H59: =D59*G59 -> 1540.728 | I59: =+E59+G59 -> 7.4172 | J59: =D59*I59 -> 2040.6942
A60: 03.02.05.00 | B60: =+'O. GRUESA'!B248 -> LOSA MACIZA
A61: 03.02.05.01 | B61: =+'O. GRUESA'!B249 -> LOSA MACIZA - CONCRETO PREMEZCLADO f'c=210kg/cm2 | C61: =+'O. GRUESA'!D249 -> m3 | D61: =+'O. GRUESA'!J249 -> 2.0145 | E61: =+'APUs Casco'!F510+'APUs Casco'!F518 -> 57.276533 | F61: =D61*E61 -> 115.38358 | G61: =+'APUs Casco'!F515 -> 330.75 | H61: =D61*G61 -> 666.29588 | I61: =+E61+G61 -> 388.02653 | J61: =D61*I61 -> 781.67945
A62: 03.02.05.02 | B62: =+'O. GRUESA'!B252 -> LOSA MACIZA - ENCOFRADO Y DESENCOFRADO | C62: =+'O. GRUESA'!D252 -> m2 | D62: =+'O. GRUESA'!J252 -> 10.0725 | E62: =+'APUs Casco'!F818+'APUs Casco'!F827 -> 44.140405 | F62: =D62*E62 -> 444.60423 | G62: =+'APUs Casco'!F824 -> 1.2 | H62: =D62*G62 -> 12.087 | I62: =+E62+G62 -> 45.340405 | J62: =D62*I62 -> 456.69123
A63: 03.02.05.03 | B63: =+'O. GRUESA'!B255 -> LOSA MACIZA - ACERO fy=4200kg/cm2 | C63: =+'O. GRUESA'!D255 -> kg | D63: =+'O. GRUESA'!J255 -> 151.0875 | E63: =+'APUs Casco'!F978+'APUs Casco'!F985 -> 1.8172 | F63: =D63*E63 -> 274.55621 | G63: =+'APUs Casco'!F982 -> 5.6 | H63: =D63*G63 -> 846.09 | I63: =+E63+G63 -> 7.4172 | J63: =D63*I63 -> 1120.6462
A64: 03.02.06.00 | B64: =+'O. GRUESA'!B259 -> ESCALERA
A65: 03.02.06.01 | B65: =+'O. GRUESA'!B260 -> ESCALERA -CONCRETO PREMEZCLADO f'c=210kg/cm2 | C65: =+'O. GRUESA'!D260 -> m3 | D65: =+'O. GRUESA'!J260 -> 2.94 | E65: =+'APUs Casco'!F525+'APUs Casco'!F533 -> 71.595667 | F65: =D65*E65 -> 210.49126 | G65: =+'APUs Casco'!F530 -> 330.75 | H65: =D65*G65 -> 972.405 | I65: =+E65+G65 -> 402.34567 | J65: =D65*I65 -> 1182.8963
A66: 03.02.06.02 | B66: =+'O. GRUESA'!B264 -> ESCALERA - ENCOFRADO Y DESENCOFRADO | C66: =+'O. GRUESA'!D264 -> m2 | D66: =+'O. GRUESA'!J264 -> 15.756 | E66: =+'APUs Casco'!F833+'APUs Casco'!F842 -> 69.230306 | F66: =D66*E66 -> 1090.7927 | G66: =+'APUs Casco'!F839 -> 0.75 | H66: =D66*G66 -> 11.817 | I66: =+E66+G66 -> 69.980306 | J66: =D66*I66 -> 1102.6097
A67: 03.02.06.03 | B67: =+'O. GRUESA'!B270 -> ESCALERA - ACERO fy=4200kg/cm2 | C67: =+'O. GRUESA'!D270 -> kg | D67: =+'O. GRUESA'!J270 -> 191.1 | E67: =+'APUs Casco'!F978+'APUs Casco'!F985 -> 1.8172 | F67: =D67*E67 -> 347.26692 | G67: =+'APUs Casco'!F982 -> 5.6 | H67: =D67*G67 -> 1070.16 | I67: =+E67+G67 -> 7.4172 | J67: =D67*I67 -> 1417.4269
A68: 03.02.07.00 | B68: ADITIVOS SIKADUR GEL 32
A69: 03.02.07.01 | B69: COLOCACIÓN DE ADITIVOS | C69: glb | D69: 1 | E69: =+'APUs Casco'!F529+'APUs Casco'!F537 -> 409.9552 | F69: =D69*E69 -> 409.9552 | G69: =+'APUs Casco'!F534 -> 1.829 | H69: =D69*G69 -> 1.829 | I69: =+J69 -> 989.49906 | J69: 989.49906
A70: 03.03.00.00 | B70: TABIQUERÍA | F70: =SUM(F71:F72) -> 4520.1001 | H70: =SUM(H71:H72) -> 6993.5747 | J70: =+RESUMEN!C11 -> 11249.033
A71: 03.03.01.00 | B71: =+'O. HUMEDAD'!B10 -> MURO DE LADRILLO SOGA PANDERETA | C71: M2 | D71: =+'O. HUMEDAD'!J10 -> 92.25 | E71: =+'APUs Casco'!F1069+'APUs Casco'!F1077 -> 34.397833 | F71: =+D71*E71 -> 3173.2001 | G71: =+'APUs Casco'!F1073 -> 60.07127 | H71: =+D71*G71 -> 5541.5747 | I71: =+E71+G71 -> 94.469103 | J71: =+D71*I71 -> 8714.7748
A72: 03.03.02.00 | B72: =+'O. HUMEDAD'!B24 -> COLUMNETAS | C72: UND | D72: =+'O. HUMEDAD'!J24 -> 12 | E72: =+'APUs Casco'!M1024+'APUs Casco'!M1035 -> 112.24167 | F72: =+D72*E72 -> 1346.9 | G72: =+'APUs Casco'!M1029 -> 121 | H72: =+D72*G72 -> 1452 | I72: =+J72/D72 -> 211.18815 | J72: =+J70-J71 -> 2534.2578
A73: 03.04.00.00 | B73: OBRAS HÚMEDAS | F73: =SUM(F74:F81) -> 17700.515 | H73: =SUM(H74:H81) -> 5032.1551 | J73: =+RESUMEN!C12 -> 22732.67
A74: 03.04.01.00 | B74: =+'O. HUMEDAD'!B28 -> TARRAJEO EN INTERIORES FROTACHADO | C74: M2 | D74: =+'O. HUMEDAD'!J28 -> 184.5 | E74: =+'APUs Casco'!F1101+'APUs Casco'!F1110 -> 25.612722 | F74: =+D74*E74 -> 4725.5473 | G74: =+'APUs Casco'!F1106 -> 7.4075 | H74: =+D74*G74 -> 1366.6837 | I74: =+E74+G74 -> 33.020222 | J74: =+D74*I74 -> 6092.231
A75: 03.04.02.00 | B75: =+'O. HUMEDAD'!B42 -> TARRAJEO EN COLUMNAS Y PLACAS | C75: M2 | D75: =+'O. HUMEDAD'!J42 -> 96.752 | E75: =+'APUs Casco'!F1149+'APUs Casco'!F1158 -> 37.002833 | F75: =+D75*E75 -> 3580.0981 | G75: =+'APUs Casco'!F1154 -> 5.4421 | H75: =+D75*G75 -> 526.53406 | I75: =+E75+G75 -> 42.444933 | J75: =+D75*I75 -> 4106.6322
A76: 03.04.03.00 | B76: =+'O. HUMEDAD'!B72 -> TARRAJEO EN VIGAS | C76: M2 | D76: =+'O. HUMEDAD'!J72 -> 33.5125 | E76: =+'APUs Casco'!F1165+'APUs Casco'!F1174 -> 35.584167 | F76: =+D76*E76 -> 1192.5144 | G76: =+'APUs Casco'!F1170 -> 5.5521 | H76: =+D76*G76 -> 186.06475 | I76: =+E76+G76 -> 41.136267 | J76: =+D76*I76 -> 1378.5791
A77: 03.04.04.00 | B77: =+'O. HUMEDAD'!B93 -> VESTIDURA DE DERRAMES | C77: M | D77: =+'O. HUMEDAD'!J93 -> 28.95 | E77: =+'APUs Casco'!F1213+'APUs Casco'!F1222 -> 12.492417 | F77: =+D77*E77 -> 361.65547 | G77: =+'APUs Casco'!F1218 -> 0.534 | H77: =+D77*G77 -> 15.4593 | I77: =+E77+G77 -> 13.026417 | J77: =+D77*I77 -> 377.11477
A78: 03.04.05.00 | B78: =+'O. HUMEDAD'!B100 -> TARRAJEO EN CIELO RASO | C78: M2 | D78: =+J78/I78 -> 74.666231 | E78: =+'APUs Casco'!F1181+'APUs Casco'!F1190 -> 34.142693 | F78: =+D78*E78 -> 2549.3062 | G78: =+'APUs Casco'!F1186 -> 3.535 | H78: =+D78*G78 -> 263.94513 | I78: =+E78+G78 -> 37.677693 | J78: =+J73-SUM(J74:J77)-SUM(J79:J81) -> 2813.2513
A79: 03.04.06.00 | B79: =+'O. HUMEDAD'!B111 -> CONTRAPISO DE 48mm - TIPO CEMENTO PULIDO | C79: M2 | D79: =+'O. HUMEDAD'!J111 -> 132.19 | E79: =+'APUs Casco'!F1228+'APUs Casco'!F1237 -> 31.57675 | F79: =+D79*E79 -> 4174.1306 | G79: =+'APUs Casco'!F1234 -> 18.965 | H79: =+D79*G79 -> 2506.9834 | I79: =+E79+G79 -> 50.54175 | J79: =+D79*I79 -> 6681.1139
A80: 03.04.07.00 | B80: =+'O. HUMEDAD'!B114 -> TARRAJEO DE ESCALERA | C80: M2 | D80: =+'O. HUMEDAD'!J114 -> 15.664 | E80: =+'APUs Casco'!F1197+'APUs Casco'!F1206 -> 33.730693 | F80: =+D80*E80 -> 528.35758 | G80: =+'APUs Casco'!F1202 -> 3.535 | H80: =+D80*G80 -> 55.37224 | I80: =+E80+G80 -> 37.265693 | J80: =+D80*I80 -> 583.72982
A81: 03.04.08.00 | B81: =+'O. HUMEDAD'!B124 -> TARRAJEO EN EXTERIORES | C81: M2 | D81: 15 | E81: =+'APUs Casco'!F1117+'APUs Casco'!F1126 -> 39.260333 | F81: =+D81*E81 -> 588.905 | G81: =+'APUs Casco'!F1122 -> 7.4075 | H81: =+D81*G81 -> 111.1125 | I81: =+E81+G81 -> 46.667833 | J81: =+D81*I81 -> 700.0175
A82: 03.05.00.00 | B82: INSTALACIONES ELECTRICAS | F82: =SUM(F85:F99) -> 99240.332 | H82: =SUM(H85:H99) -> 115636.97 | J82: =+RESUMEN!C13 -> 11915.557
A83: 03.05.01.00 | B83: SALIDAS DE ALUMBRADO, TOMAS Y AIRE ACONDICIONADO | C83: GLB | D83: 1 | I83: 2000 | J83: =+I83 -> 2000
A84: 03.05.02.00 | B84: SALIDAS DE DETECCIÓN DE ALARMA CONTRAINCENDIO | C84: GLB | D84: 1 | I84: 1200 | J84: =+I84 -> 1200
A85: 03.05.03.00 | B85: SALIDAS DE VIDEO VIGILANCIA Y CCTV (SIN CABLEADO) | C85: GLB | D85: 1 | I85: 1200 | J85: =+I85 -> 1200
A86: 03.05.04.00 | B86: SALIDAS DE COMUNICACIONES (SIN CABLEADO) | C86: GLB | D86: 1 | I86: 1500 | J86: =+I86 -> 1500
A87: 03.05.05.00 | B87: CANALIZACIÓN Y ENTUBADOS DE PVC EMPORTADO | C87: GLB | D87: 1 | I87: 2000 | J87: =+I87 -> 2000
A88: 03.05.06.00 | B88: COLOCACIÓN DE TABLERO ELÉCTRICOS (SIN EQUIPO) | C88: GLB | D88: 1 | I88: 1000 | J88: =+I88 -> 1000
A89: 03.05.07.00 | B89: CABLEADO DE ALIMENTADORES Y CIRCUITOS ELÉCTRICOS | C89: GLB | D89: 1 | I89: =15.56+3000 -> 3015.56 | J89: =+I89 -> 3015.56
A90: 03.06.00.00 | B90: INSTALACIONES SANITARIAS | F90: =SUM(F93:F107) -> 54779.388 | H90: =SUM(H93:H107) -> 64228.04 | J90: =+RESUMEN!C14 -> 11915.557
A91: 03.06.01.00 | B91: SALIDAS DE AGUA | C91: GLB | D91: 1 | I91: 1500 | J91: =+I91 -> 1500
A92: 03.06.02.00 | B92: SALIDAS DE DESAGÚE | C92: GLB | D92: 1 | I92: 1500 | J92: =+I92 -> 1500
A93: 03.06.03.00 | B93: TUBERIAS Y MONTANTES DE AGUA FRÍA | C93: GLB | D93: 1 | I93: 2500 | J93: =+I93 -> 2500
A94: 03.06.04.00 | B94: DESAGUE Y MONTANTES DE AGUA FRIA | C94: GLB | D94: 1 | I94: =+J94 -> 3427.6673 | J94: =+J90-J91-J92-J93-J95 -> 3427.6673
A95: 03.06.05.00 | B95: CAJAS DE REGISTRO | C95: GLB | D95: 1 | I95: 2987.89 | J95: =+I95 -> 2987.89
A96: 04.00.00.00 | B96: =+'O. GRUESA'!B274 -> 2DO PISO | F96: =+F97+F115+F118 -> 30542.668 | H96: =+H97+H115+H118 -> 29384.709 | J96: =+J97+J115+J118+J127+J134 -> 77800.713
A97: 04.01.00.00 | B97: CONCRETO ARMADO | F97: =+SUM(F98:F114) -> 13157.599 | H97: =+SUM(H98:H114) -> 19033.695 | J97: =+RESUMEN!C16 -> 32191.293
A98: 04.01.01.00 | B98: =+'O. GRUESA'!B276 -> PLACAS
A99: 04.01.01.01 | B99: =+'O. GRUESA'!B277 -> PLACAS - CONCRETO PREMEZCLADO f'c=210kg/cm2 | C99: =+'O. GRUESA'!D277 -> m3 | D99: =+'O. GRUESA'!J277 -> 8.575 | E99: ='APUs Casco'!$F$627+'APUs Casco'!$F$635 -> 88.708667 | F99: =D99*E99 -> 760.67682 | G99: ='APUs Casco'!$F$632 -> 348.75 | H99: =D99*G99 -> 2990.5312 | I99: =+E99+G99 -> 437.45867 | J99: =D99*I99 -> 3751.2081
A100: 04.01.01.02 | B100: =+'O. GRUESA'!B282 -> PLACAS - ENCOFRADO Y DESENCOFRADO | C100: =+'O. GRUESA'!D282 -> m2 | D100: =+'O. GRUESA'!J282 -> 82.6 | E100: ='APUs Casco'!$F$760+'APUs Casco'!$F$769 -> 60.478167 | F100: =D100*E100 -> 4995.4966 | G100: ='APUs Casco'!$F$766 -> 2.35 | H100: =D100*G100 -> 194.11 | I100: =+E100+G100 -> 62.828167 | J100: =D100*I100 -> 5189.6066
...

Sheet Valorización
A1: PRESUPUESTO DE OBRA POR PARTIDAS
A2: PROYECTO:
A3: PROPIETARIO(S) :
A4: UBICACIÓN:
A5: ITEM | B5: DESCRIPCIÓN DE PARTIDAS | C5: PRESUPUESTO ACTUAL | K5: VALORIZACIÓN | Q5: SALDO
C6: UND | D6: METRADO | E6: PRECIO MO | F6: PRECIO PARCIAL MO | G6: PRECIO MAT | H6: PRECIO PARCIAL MAT | I6: PRECIO UNITARIO | J6: PRECIO PARCIAL | K6: ACUMULADO ANTERIOR | M6: AVANCE ACTUAL | O6: ACUMULADO ACTUAL
D7: CONTRATO | K7: % | L7: PRECIO | M7: % | N7: PRECIO | O7: % | P7: PRECIO | Q7: % | R7: PRECIO
A8: =+'O. GRUESA'!A7 -> 01.00.00.00 | B8: =+'O. GRUESA'!B7 -> OBRAS PROVISIONALES, TRABAJOS PRELIMINARES, SEGURIDAD Y SALUD | F8: =+F9+F14+F20 -> 8112.842 | H8: =+H9+H14+H20 -> 15358.89 | J8: =+J9+J14+J20 -> 46869.445 | L8: =+L9+L14+L20 -> 0 | N8: =+N9+N14+N20 -> 14338.631 | P8: =+P9+P14+P20 -> 14338.631 | R8: =+R9+R14+R20 -> 32521.36
A9: =+'O. GRUESA'!A8 -> 01.01.00.00 | B9: =+'O. GRUESA'!B8 -> OBRAS PROVISIONALES | F9: =SUM(F10:F13) -> 1167.265 | H9: =SUM(H10:H13) -> 9699.3875 | J9: =+RESUMEN!C4 -> 10876.107 | L9: =SUM(L10:L13) -> 0 | N9: =SUM(N10:N13) -> 8266.6525 | P9: =SUM(P10:P13) -> 8266.6525 | R9: =SUM(R10:R13) -> 2600
A10: 01.01.01.00 | B10: =+'O. GRUESA'!B9 -> TRANSPORTE DE EQUIPOS Y HERRAMIENTAS | C10: =+'O. GRUESA'!D9 -> glb | D10: =+'O. GRUESA'!J9 -> 1 | E10: 1000 | F10: =D10*E10 -> 1000 | G10: 1000 | H10: =D10*G10 -> 1000 | I10: =+E10+G10 -> 2000 | J10: =D10*I10 -> 2000 | L10: =+J10*K10 -> 0 | M10: 0.5 | N10: =+M10*J10 -> 1000 | O10: =+K10+M10 -> 0.5 | P10: =+N10+L10 -> 1000 | Q10: =100%-O10 -> 0.5 | R10: =+J10-P10 -> 1000
A11: 01.01.02.00 | B11: =+'O. GRUESA'!B12 -> CERCO PERIMETRICO PROVISIONAL | C11: =+'O. GRUESA'!D12 -> ml | D11: =+'O. GRUESA'!J12 -> 30 | E11: 0 | F11: =D11*E11 -> 0 | G11: 157.89625 | H11: =D11*G11 -> 4736.8875 | I11: =+E11+G11 -> 157.89625 | J11: =D11*I11 -> 4736.8875 | L11: =+J11*K11 -> 0 | M11: 1 | N11: =+M11*J11 -> 4736.8875 | O11: =+K11+M11 -> 1 | P11: =+N11+L11 -> 4736.8875 | Q11: =100%-O11 -> 0 | R11: =+J11-P11 -> 0
A12: 01.01.03.00 | B12: =+'O. GRUESA'!B15 -> PROTECCIÓN CON MALLA RASCHELL | C12: =+'O. GRUESA'!D15 -> ml | D12: =+'O. GRUESA'!J15 -> 180 | E12: 0.92925 | F12: =D12*E12 -> 167.265 | G12: 13.125 | H12: =D12*G12 -> 2362.5 | I12: =+E12+G12 -> 14.05425 | J12: =D12*I12 -> 2529.765 | L12: =+J12*K12 -> 0 | M12: 1 | N12: =+M12*J12 -> 2529.765 | O12: =+K12+M12 -> 1 | P12: =+N12+L12 -> 2529.765 | Q12: =100%-O12 -> 0 | R12: =+J12-P12 -> 0
A13: 01.01.04.00 | B13: =+'O. GRUESA'!B21 -> ALQUILER DE BAÑO PROVISIONAL | C13: =+'O. GRUESA'!D21 -> mes | D13: =+'O. GRUESA'!J21 -> 4 | E13: 0 | F13: =D13*E13 -> 0 | G13: 400 | H13: =D13*G13 -> 1600 | I13: =+E13+G13 -> 400 | J13: =D13*I13 -> 1600 | L13: =+J13*K13 -> 0 | N13: =+M13*J13 -> 0 | O13: =+K13+M13 -> 0 | P13: =+N13+L13 -> 0 | Q13: =100%-O13 -> 1 | R13: =+J13-P13 -> 1600
A14: =+'O. GRUESA'!A24 -> 01.02.00.00 | B14: =+'O. GRUESA'!B24 -> DEMOLICIÓN Y TRABAJOS PRELIMINARES | F14: =SUM(F15:F19) -> 3345.577 | H14: =SUM(H15:H19) -> 3209.502 | J14: =+RESUMEN!C5 -> 28571.36 | L14: =SUM(L15:L19) -> 0 | N14: =SUM(N15:N19) -> 3000 | P14: =SUM(P15:P19) -> 3000 | R14: =SUM(R15:R19) -> 25571.36
A15: 01.02.01.00 | B15: =+'O. GRUESA'!B25 -> DESMONTAJE Y ACARREO DE MATERIAL | C15: =+'O. GRUESA'!D25 -> glb | D15: =+'O. GRUESA'!J25 -> 1 | E15: 1500 | F15: =D15*E15 -> 1500 | G15: 0 | H15: =D15*G15 -> 0 | I15: 3000 | J15: =D15*I15 -> 3000 | L15: =+J15*K15 -> 0 | M15: 1 | N15: =+M15*J15 -> 3000 | O15: =+K15+M15 -> 1 | P15: =+N15+L15 -> 3000 | Q15: =100%-O15 -> 0 | R15: =+J15-P15 -> 0
A16: 01.02.02.00 | B16: APUNTALAMIENTO ESTRUCTURAL | C16: GLB | D16: 1 | E16: 0 | F16: =D16*E16 -> 0 | G16: 0 | H16: =D16*G16 -> 0 | I16: 2500 | J16: =D16*I16 -> 2500 | L16: =+J16*K16 -> 0 | N16: =+M16*J16 -> 0 | O16: =+K16+M16 -> 0 | P16: =+N16+L16 -> 0 | Q16: =100%-O16 -> 1 | R16: =+J16-P16 -> 2500
A17: 01.02.03.00 | B17: DEMOLICIÓN MANUAL CON ROTOMARTILLO 3 PISOS Y AZOTEA | C17: =+'O. GRUESA'!D28 -> glb | D17: =+'O. GRUESA'!J28 -> 1 | E17: 0 | F17: =D17*E17 -> 0 | G17: 0 | H17: =D17*G17 -> 0 | I17: 18000 | J17: =D17*I17 -> 18000 | L17: =+J17*K17 -> 0 | N17: =+M17*J17 -> 0 | O17: =+K17+M17 -> 0 | P17: =+N17+L17 -> 0 | Q17: =100%-O17 -> 1 | R17: =+J17-P17 -> 18000
A18: 01.02.04.00 | B18: =+'O. GRUESA'!B34 -> ELIMINACIÓN DE ESCOMBROS, DESMONTE | C18: =+'O. GRUESA'!D34 -> glb | D18: =+'O. GRUESA'!J34 -> 1 | E18: 0 | F18: =D18*E18 -> 0 | G18: 3000 | H18: =D18*G18 -> 3000 | I18: 3000 | J18: =D18*I18 -> 3000 | L18: =+J18*K18 -> 0 | N18: =+M18*J18 -> 0 | O18: =+K18+M18 -> 0 | P18: =+N18+L18 -> 0 | Q18: =100%-O18 -> 1 | R18: =+J18-P18 -> 3000
A19: 01.02.05.00 | B19: =+'O. GRUESA'!B40 -> TRAZADO Y REPLANTEO S/EQUIPO | C19: =+'O. GRUESA'!D40 -> m2 | D19: 206 | E19: 8.9591117 | F19: =D19*E19 -> 1845.577 | G19: 1.017 | H19: =D19*G19 -> 209.502 | I19: =+J19/D19 -> 10.055146 | J19: =+J14-SUM(J15:J18) -> 2071.36 | L19: =+J19*K19 -> 0 | N19: =+M19*J19 -> 0 | O19: =+K19+M19 -> 0 | P19: =+N19+L19 -> 0 | Q19: =100%-O19 -> 1 | R19: =+J19-P19 -> 2071.36
A20: =+'O. GRUESA'!A43 -> 01.03.00.00 | B20: =+'O. GRUESA'!B43 -> SEGURIDAD Y SALUD | F20: =SUM(F21:F24) -> 3600 | H20: =SUM(H21:H24) -> 2450 | J20: =+RESUMEN!C7 -> 7421.9785 | L20: =SUM(L21:L24) -> 0 | N20: =SUM(N21:N24) -> 3071.9785 | P20: =SUM(P21:P24) -> 3071.9785 | R20: =SUM(R21:R24) -> 4350
A21: =+'O. GRUESA'!A44 -> 01.03.01.00 | B21: =+'O. GRUESA'!B44 -> EQUIPOS DE PROTECCIÓN INDIVIDUAL | C21: =+'O. GRUESA'!D44 -> und | D21: 30 | E21: 120 | F21: =D21*E21 -> 3600 | G21: 30 | H21: =D21*G21 -> 900 | I21: =+E21+G21 -> 150 | J21: =D21*I21 -> 4500 | L21: =+J21*K21 -> 0 | M21: 0.3 | N21: =+M21*J21 -> 1350 | O21: =+K21+M21 -> 0.3 | P21: =+N21+L21 -> 1350 | Q21: =100%-O21 -> 0.7 | R21: =+J21-P21 -> 3150
A22: =+'O. GRUESA'!A47 -> 01.03.02.00 | B22: =+'O. GRUESA'!B47 -> EQUIPOS DE PROTECCIÓN COLECTIVA | C22: =+'O. GRUESA'!D47 -> glb | D22: =+'O. GRUESA'!J47 -> 1 | E22: 0 | F22: =D22*E22 -> 0 | G22: 500 | H22: =D22*G22 -> 500 | I22: =+J22 -> 1071.9785 | J22: =+J20-J21-J23-J24 -> 1071.9785 | L22: =+J22*K22 -> 0 | M22: 1 | N22: =+M22*J22 -> 1071.9785 | O22: =+K22+M22 -> 1 | P22: =+N22+L22 -> 1071.9785 | Q22: =100%-O22 -> 0 | R22: =+J22-P22 -> 0
A23: =+'O. GRUESA'!A50 -> 01.03.03.00 | B23: =+'O. GRUESA'!B50 -> SEÑALIZACIÓN TEMPORAL DE SEGURIDAD | C23: =+'O. GRUESA'!D50 -> glb | D23: =+'O. GRUESA'!J50 -> 1 | E23: 0 | F23: =D23*E23 -> 0 | G23: 250 | H23: =D23*G23 -> 250 | I23: =+E23+G23 -> 250 | J23: =D23*I23 -> 250 | L23: =+J23*K23 -> 0 | M23: 1 | N23: =+M23*J23 -> 250 | O23: =+K23+M23 -> 1 | P23: =+N23+L23 -> 250 | Q23: =100%-O23 -> 0 | R23: =+J23-P23 -> 0
A24: =+'O. GRUESA'!A53 -> 01.03.04.00 | B24: =+'O. GRUESA'!B53 -> SEGURO SCTR | C24: =+'O. GRUESA'!D53 -> mes | D24: =+'O. GRUESA'!J53 -> 4 | E24: 0 | F24: =D24*E24 -> 0 | G24: 200 | H24: =D24*G24 -> 800 | I24: 400 | J24: =D24*I24 -> 1600 | L24: =+J24*K24 -> 0 | M24: 0.25 | N24: =+M24*J24 -> 400 | O24: =+K24+M24 -> 0.25 | P24: =+N24+L24 -> 400 | Q24: =100%-O24 -> 0.75 | R24: =+J24-P24 -> 1200
A25: =+'O. GRUESA'!A56 -> 02.00.00.00 | B25: =+'O. GRUESA'!B56 -> MOVIMIENTO DE TIERRAS | F25: =SUM(F26:F30) -> 5964.1277 | H25: =SUM(H26:H30) -> 2253.3181 | J25: =+RESUMEN!C6 -> 7667.9579 | L25: =SUM(L26:L30) -> 0 | N25: =SUM(N26:N30) -> 0 | P25: =SUM(P26:P30) -> 0 | R25: =SUM(R26:R30) -> 7667.9579
A26: 02.01.00.00 | B26: ='O. GRUESA'!$B$57 -> EXCAVACIÓN MANUAL P/CIMIENTO Y ZAPATA | C26: ='O. GRUESA'!$D$57 -> m3 | D26: ='O. GRUESA'!$J$57 -> 54.705 | E26: 45.888889 | F26: =D26*E26 -> 2510.3517 | G26: 1.3766667 | H26: =D26*G26 -> 75.31055 | I26: =+J26/D26 -> 37.220991 | J26: =+J25-SUM(J27:J30) -> 2036.1743 | L26: =+J26*K26 -> 0 | N26: =+M26*J26 -> 0 | O26: =+K26+M26 -> 0 | P26: =+N26+L26 -> 0 | Q26: =100%-O26 -> 1 | R26: =+J26-P26 -> 2036.1743
A27: 02.02.00.00 | B27: =+'O. GRUESA'!B74 -> COMPACTACIÓN MANUAL P/CIMIENTO Y ZAPATA | C27: =+'O. GRUESA'!D74 -> m2 | D27: =+'O. GRUESA'!J74 -> 33.045 | E27: 23.993333 | F27: =D27*E27 -> 792.8597 | G27: 3.1198 | H27: =D27*G27 -> 103.09379 | I27: =+E27+G27 -> 27.113133 | J27: =D27*I27 -> 895.95349 | L27: =+J27*K27 -> 0 | N27: =+M27*J27 -> 0 | O27: =+K27+M27 -> 0 | P27: =+N27+L27 -> 0 | Q27: =100%-O27 -> 1 | R27: =+J27-P27 -> 895.95349
A28: 02.03.00.00 | B28: =+'O. GRUESA'!B91 -> RELLENO COMPACTADO CON MATERIAL PROPIO | C28: =+'O. GRUESA'!D91 -> m3 | D28: =+'O. GRUESA'!J91 -> 28.584 | E28: 0.68833333 | F28: =D28*E28 -> 19.67532 | G28: 5.0344167 | H28: =D28*G28 -> 143.90377 | I28: =+E28+G28 -> 5.72275 | J28: =D28*I28 -> 163.57909 | L28: =+J28*K28 -> 0 | N28: =+M28*J28 -> 0 | O28: =+K28+M28 -> 0 | P28: =+N28+L28 -> 0 | Q28: =100%-O28 -> 1 | R28: =+J28-P28 -> 163.57909
A29: 02.04.00.00 | B29: =+'O. GRUESA'!B108 -> ELIMINACION DE MATERIAL CON MAQUINARIA | C29: =+'O. GRUESA'!D108 -> m3 | D29: =+'O. GRUESA'!J108 -> 54.705 | E29: 7.8666667 | F29: =D29*E29 -> 430.346 | G29: 22 | H29: =D29*G29 -> 1203.51 | I29: =+E29+G29 -> 29.866667 | J29: =D29*I29 -> 1633.856 | L29: =+J29*K29 -> 0 | N29: =+M29*J29 -> 0 | O29: =+K29+M29 -> 0 | P29: =+N29+L29 -> 0 | Q29: =100%-O29 -> 1 | R29: =+J29-P29 -> 1633.856
A30: 02.05.00.00 | B30: =+'O. GRUESA'!B112 -> NIVELACION DE TERRENO Y APISONADO C/20 CM. | C30: =+'O. GRUESA'!D112 -> m2 | D30: =+'O. GRUESA'!J112 -> 150 | E30: 14.7393 | F30: =D30*E30 -> 2210.895 | G30: 4.85 | H30: =D30*G30 -> 727.5 | I30: =+E30+G30 -> 19.5893 | J30: =D30*I30 -> 2938.395 | L30: =+J30*K30 -> 0 | N30: =+M30*J30 -> 0 | O30: =+K30+M30 -> 0 | P30: =+N30+L30 -> 0 | Q30: =100%-O30 -> 1 | R30: =+J30-P30 -> 2938.395
A31: =+'O. GRUESA'!A116 -> 03.00.00.00 | B31: =+'O. GRUESA'!B116 -> 1ER PISO | F31: =+F32+F42+F70+F73 -> 50087.853 | H31: =+H32+H42+H70+H73 -> 55039.907 | J31: =+J32+J42+J70+J73+J82+J90 -> 129861.17 | L31: =SUM(L33:L41) -> 0 | N31: =SUM(N33:N41) -> 0 | P31: =SUM(P33:P41) -> 0 | R31: =+J31-P31 -> 129861.17
A32: 03.01.00.00 | B32: =+'O. GRUESA'!B117 -> CONCRETO SIMPLE | F32: =SUM(F33:F41) -> 6290.3482 | H32: =SUM(H33:H41) -> 10936.765 | J32: =+RESUMEN!C9 -> 17227.114 | L32: =+RESUMEN!E9 -> 0
A33: 03.01.01.00 | B33: SOLADO | R33: =+J33-P33 -> 0
A34: 03.01.01.01 | B34: =+'O. GRUESA'!B119 -> CONCRETO, fc=100 kg/cm² | C34: =+'O. GRUESA'!D119 -> m2 | D34: =+'O. GRUESA'!J119 -> 17.67 | E34: 14.642056 | F34: =D34*E34 -> 258.72512 | G34: 28.775 | H34: =D34*G34 -> 508.45425 | I34: =+E34+G34 -> 43.417056 | J34: =D34*I34 -> 767.17937 | L34: =+J34*K34 -> 0 | N34: =+M34*J34 -> 0 | O34: =+K34+M34 -> 0 | P34: =+N34+L34 -> 0 | Q34: =100%-O34 -> 1 | R34: =+J34-P34 -> 767.17937
A35: 03.01.02.00 | B35: =+'O. GRUESA'!B124 -> CIMIENTO CORRIDO | R35: =+J35-P35 -> 0
A36: 03.01.02.01 | B36: =+'O. GRUESA'!B125 -> CONCRETO f'c= 100 kg/cm² +30% P.G. (Tamaño maximo 6") | C36: =+'O. GRUESA'!D125 -> m3 | D36: =+'O. GRUESA'!J125 -> 18.45 | E36: 73.423111 | F36: =D36*E36 -> 1354.6564 | G36: 312.85 | H36: =D36*G36 -> 5772.0825 | I36: =+E36+G36 -> 386.27311 | J36: =D36*I36 -> 7126.7389 | L36: =+J36*K36 -> 0 | N36: =+M36*J36 -> 0 | O36: =+K36+M36 -> 0 | P36: =+N36+L36 -> 0 | Q36: =100%-O36 -> 1 | R36: =+J36-P36 -> 7126.7389
A37: 03.01.03.00 | B37: =+'O. GRUESA'!B139 -> SOBRECIMIENTO | R37: =+J37-P37 -> 0
A38: 03.01.03.01 | B38: =+'O. GRUESA'!B140 -> CONCRETO, f'c= 140 kg/cm² +25% P.M. (Tamaño maximo 3") | C38: =+'O. GRUESA'!D140 -> m3 | D38: =+'O. GRUESA'!J140 -> 2.74875 | E38: 110.13467 | F38: =D38*E38 -> 302.73267 | G38: 250.85 | H38: =D38*G38 -> 689.52394 | I38: =+E38+G38 -> 360.98467 | J38: =D38*I38 -> 992.2566 | L38: =+J38*K38 -> 0 | N38: =+M38*J38 -> 0 | O38: =+K38+M38 -> 0 | P38: =+N38+L38 -> 0 | Q38: =100%-O38 -> 1 | R38: =+J38-P38 -> 992.2566
A39: 03.01.03.02 | B39: =+'O. GRUESA'!B154 -> ENCOFRADO Y DESENCOFRADO | C39: =+'O. GRUESA'!D154 -> m2 | D39: =+'O. GRUESA'!J154 -> 36.65 | E39: 35.449167 | F39: =D39*E39 -> 1299.212 | G39: 2.1 | H39: =D39*G39 -> 76.965 | I39: =+E39+G39 -> 37.549167 | J39: =D39*I39 -> 1376.177 | L39: =+J39*K39 -> 0 | N39: =+M39*J39 -> 0 | O39: =+K39+M39 -> 0 | P39: =+N39+L39 -> 0 | Q39: =100%-O39 -> 1 | R39: =+J39-P39 -> 1376.177
A40: 03.01.04.00 | B40: =+'O. GRUESA'!B168 -> FALSO PISO | R40: =+J40-P40 -> 0
A41: 03.01.04.01 | B41: =+'O. GRUESA'!B169 -> FALSO PISO | C41: =+'O. GRUESA'!D169 -> m2 | D41: =+J41/I41 -> 142.48131 | E41: 21.581933 | F41: =D41*E41 -> 3075.0221 | G41: 27.3 | H41: =D41*G41 -> 3889.7397 | I41: =+E41+G41 -> 48.881933 | J41: =+J32-SUM(J34:J39) -> 6964.7618 | L41: =+J41*K41 -> 0 | N41: =+M41*J41 -> 0 | O41: =+K41+M41 -> 0 | P41: =+N41+L41 -> 0 | Q41: =100%-O41 -> 1 | R41: =+J41-P41 -> 6964.7618
A42: 03.02.00.00 | B42: =+'O. GRUESA'!B172 -> CONCRETO ARMADO + MUROS PORTANTES | F42: =+SUM(F43:F67) -> 21576.89 | H42: =+SUM(H43:H67) -> 32077.412 | J42: =+RESUMEN!C10 -> 54821.241 | L42: =+RESUMEN!E10 -> 0 | N42: =+SUM(N43:N67) -> 0 | P42: =+SUM(P43:P67) -> 0 | R42: =+J42-P42 -> 54821.241
A43: 03.02.01.00 | B43: =+'O. GRUESA'!B173 -> ZAPATAS | R43: =+J43-P43 -> 0
A44: 03.02.01.01 | B44: =+'O. GRUESA'!B174 -> CONCRETO PREMEZCLADO f'c=210kg/cm2 | C44: =+'O. GRUESA'!D174 -> m3 | D44: =+'O. GRUESA'!J174 -> 10.602 | E44: 49.7052 | F44: =D44*E44 -> 526.97453 | G44: 330.75 | H44: =D44*G44 -> 3506.6115 | I44: =+E44+G44 -> 380.4552 | J44: =D44*I44 -> 4033.586 | L44: =+J44*K44 -> 0 | N44: =+M44*J44 -> 0 | O44: =+K44+M44 -> 0 | P44: =+N44+L44 -> 0 | Q44: =100%-O44 -> 1 | R44: =+J44-P44 -> 4033.586
A45: 03.02.01.02 | B45: =+'O. GRUESA'!B179 -> ENCOFRADO Y DESENCOFRADO | C45: =+'O. GRUESA'!D179 -> m2 | D45: =+'O. GRUESA'!J179 -> 29.82 | E45: 44.401583 | F45: =D45*E45 -> 1324.0552 | G45: 3 | H45: =D45*G45 -> 89.46 | I45: =+E45+G45 -> 47.401583 | J45: =D45*I45 -> 1413.5152 | L45: =+J45*K45 -> 0 | N45: =+M45*J45 -> 0 | O45: =+K45+M45 -> 0 | P45: =+N45+L45 -> 0 | Q45: =100%-O45 -> 1 | R45: =+J45-P45 -> 1413.5152 | S45: 25
A46: 03.02.01.03 | B46: =+'O. GRUESA'!B184 -> ACERO fy=4200kg/cm2 | C46: =+'O. GRUESA'!D184 -> kg | D46: =+'O. GRUESA'!J184 -> 477.09 | E46: 1.5143333 | F46: =D46*E46 -> 722.47329 | G46: 5.85 | H46: =D46*G46 -> 2790.9765 | I46: =+E46+G46 -> 7.3643333 | J46: =D46*I46 -> 3513.4498 | L46: =+J46*K46 -> 0 | N46: =+M46*J46 -> 0 | O46: =+K46+M46 -> 0 | P46: =+N46+L46 -> 0 | Q46: =100%-O46 -> 1 | R46: =+J46-P46 -> 3513.4498
A47: 03.02.02.00 | B47: ='O. GRUESA'!B188 -> PLACAS | R47: =+J47-P47 -> 0
A48: 03.02.02.01 | B48: ='O. GRUESA'!$B$189 -> PLACAS - CONCRETO PREMEZCLADO f'c=210kg/cm2 | C48: ='O. GRUESA'!$D$189 -> m3 | D48: ='O. GRUESA'!$J$189 -> 12.9 | E48: 88.708667 | F48: =D48*E48 -> 1144.3418 | G48: 348.75 | H48: =D48*G48 -> 4498.875 | I48: =+E48+G48 -> 437.45867 | J48: =D48*I48 -> 5643.2168 | L48: =+J48*K48 -> 0 | N48: =+M48*J48 -> 0 | O48: =+K48+M48 -> 0 | P48: =+N48+L48 -> 0 | Q48: =100%-O48 -> 1 | R48: =+J48-P48 -> 5643.2168
A49: 03.02.02.02 | B49: ='O. GRUESA'!$B$194 -> PLACAS - ENCOFRADO Y DESENCOFRADO | C49: ='O. GRUESA'!$D$194 -> m2 | D49: ='O. GRUESA'!$J$194 -> 123.9 | E49: 60.478167 | F49: =D49*E49 -> 7493.2449 | G49: 2.35 | H49: =D49*G49 -> 291.165 | I49: =+E49+G49 -> 62.828167 | J49: =D49*I49 -> 7784.4099 | L49: =+J49*K49 -> 0 | N49: =+M49*J49 -> 0 | O49: =+K49+M49 -> 0 | P49: =+N49+L49 -> 0 | Q49: =100%-O49 -> 1 | R49: =+J49-P49 -> 7784.4099
A50: 03.02.02.03 | B50: ='O. GRUESA'!$B$199 -> PLACAS - ACERO fy=4200kg/cm2 | C50: ='O. GRUESA'!$D$199 -> kg | D50: ='O. GRUESA'!$J$199 -> 1225.5 | E50: 2.2715 | F50: =D50*E50 -> 2783.7232 | G50: 5.75 | H50: =D50*G50 -> 7046.625 | I50: =+E50+G50 -> 8.0215 | J50: =D50*I50 -> 9830.3482 | L50: =+J50*K50 -> 0 | N50: =+M50*J50 -> 0 | O50: =+K50+M50 -> 0 | P50: =+N50+L50 -> 0 | Q50: =100%-O50 -> 1 | R50: =+J50-P50 -> 9830.3482
A51: 03.02.03.00 | B51: =+'O. GRUESA'!B203 -> VIGAS | R51: =+J51-P51 -> 0
A52: 03.02.03.01 | B52: =+'O. GRUESA'!B204 -> VIGAS - CONCRETO PREMEZCLADO f'c=210kg/cm2 | C52: =+'O. GRUESA'!D204 -> m3 | D52: =+'O. GRUESA'!J204 -> 4.1165 | E52: 57.276533 | F52: =D52*E52 -> 235.77885 | G52: 330.75 | H52: =D52*G52 -> 1361.5324 | I52: =+E52+G52 -> 388.02653 | J52: =D52*I52 -> 1597.3112 | L52: =+J52*K52 -> 0 | N52: =+M52*J52 -> 0 | O52: =+K52+M52 -> 0 | P52: =+N52+L52 -> 0 | Q52: =100%-O52 -> 1 | R52: =+J52-P52 -> 1597.3112
A53: 03.02.03.02 | B53: =+'O. GRUESA'!B214 -> VIGAS - ENCOFRADO Y DESENCOFRADO | C53: =+'O. GRUESA'!D214 -> m2 | D53: =+'O. GRUESA'!J214 -> 30.1625 | E53: 46.902767 | F53: =D53*E53 -> 1414.7047 | G53: 2.2 | H53: =D53*G53 -> 66.3575 | I53: =+E53+G53 -> 49.102767 | J53: =D53*I53 -> 1481.0622 | L53: =+J53*K53 -> 0 | N53: =+M53*J53 -> 0 | O53: =+K53+M53 -> 0 | P53: =+N53+L53 -> 0 | Q53: =100%-O53 -> 1 | R53: =+J53-P53 -> 1481.0622
A54: 03.02.03.03 | B54: =+'O. GRUESA'!B224 -> VIGAS - ACERO fy=4200kg/cm2 | C54: =+'O. GRUESA'!D224 -> kg | D54: =+'O. GRUESA'!J224 -> 1029.125 | E54: 1.8172 | F54: =D54*E54 -> 1870.126 | G54: 5.6 | H54: =D54*G54 -> 5763.1 | I54: =+E54+G54 -> 7.4172 | J54: =D54*I54 -> 7633.226 | L54: =+J54*K54 -> 0 | N54: =+M54*J54 -> 0 | O54: =+K54+M54 -> 0 | P54: =+N54+L54 -> 0 | Q54: =100%-O54 -> 1 | R54: =+J54-P54 -> 7633.226
A55: 03.02.04.00 | B55: =+'O. GRUESA'!B228 -> LOSA ALIGERADA | R55: =+J55-P55 -> 0
A56: 03.02.04.01 | B56: =+'O. GRUESA'!B229 -> LOSA ALIGERADA - CONCRETO PREMEZCLADO f'c=210kg/cm2 | C56: =+'O. GRUESA'!D229 -> m3 | D56: =+'O. GRUESA'!J229 -> 2.29275 | E56: 57.276533 | F56: =D56*E56 -> 131.32077 | G56: 330.75 | H56: =D56*G56 -> 758.32706 | I56: =+E56+G56 -> 388.02653 | J56: =D56*I56 -> 889.64783 | L56: =+J56*K56 -> 0 | N56: =+M56*J56 -> 0 | O56: =+K56+M56 -> 0 | P56: =+N56+L56 -> 0 | Q56: =100%-O56 -> 1 | R56: =+J56-P56 -> 889.64783
A57: 03.02.04.02 | B57: =+'O. GRUESA'!B234 -> LOSA ALIGERADA - ENCOFRADO Y DESENCOFRADO | C57: =+'O. GRUESA'!D234 -> m2 | D57: =+'O. GRUESA'!J234 -> 22.9275 | E57: 31.934905 | F57: =D57*E57 -> 732.18753 | G57: 1.05 | H57: =D57*G57 -> 24.073875 | I57: =+E57+G57 -> 32.984905 | J57: =D57*I57 -> 756.2614 | L57: =+J57*K57 -> 0 | N57: =+M57*J57 -> 0 | O57: =+K57+M57 -> 0 | P57: =+N57+L57 -> 0 | Q57: =100%-O57 -> 1 | R57: =+J57-P57 -> 756.2614
A58: 03.02.04.03 | B58: =+'O. GRUESA'!B239 -> LOSA ALIGERADA - LADRILLO HUECO DE 0.15X0.30X0.30 | C58: =+'O. GRUESA'!D239 -> und | D58: =+'O. GRUESA'!J239 -> 207 | E58: 1.0381542 | F58: =D58*E58 -> 214.89791 | G58: 3.675 | H58: =D58*G58 -> 760.725 | I58: =+E58+G58 -> 4.7131542 | J58: =D58*I58 -> 975.62291 | L58: =+J58*K58 -> 0 | N58: =+M58*J58 -> 0 | O58: =+K58+M58 -> 0 | P58: =+N58+L58 -> 0 | Q58: =100%-O58 -> 1 | R58: =+J58-P58 -> 975.62291
A59: 03.02.04.04 | B59: =+'O. GRUESA'!B244 -> LOSA ALIGERADA - ACERO fy=4200kg/cm2 | C59: =+'O. GRUESA'!D244 -> kg | D59: =+'O. GRUESA'!J244 -> 275.13 | E59: 1.8172 | F59: =D59*E59 -> 499.96624 | G59: 5.6 | H59: =D59*G59 -> 1540.728 | I59: =+E59+G59 -> 7.4172 | J59: =D59*I59 -> 2040.6942 | L59: =+J59*K59 -> 0 | N59: =+M59*J59 -> 0 | O59: =+K59+M59 -> 0 | P59: =+N59+L59 -> 0 | Q59: =100%-O59 -> 1 | R59: =+J59-P59 -> 2040.6942
A60: 03.02.05.00 | B60: =+'O. GRUESA'!B248 -> LOSA MACIZA | R60: =+J60-P60 -> 0
A61: 03.02.05.01 | B61: =+'O. GRUESA'!B249 -> LOSA MACIZA - CONCRETO PREMEZCLADO f'c=210kg/cm2 | C61: =+'O. GRUESA'!D249 -> m3 | D61: =+'O. GRUESA'!J249 -> 2.0145 | E61: 57.276533 | F61: =D61*E61 -> 115.38358 | G61: 330.75 | H61: =D61*G61 -> 666.29588 | I61: =+E61+G61 -> 388.02653 | J61: =D61*I61 -> 781.67945 | L61: =+J61*K61 -> 0 | N61: =+M61*J61 -> 0 | O61: =+K61+M61 -> 0 | P61: =+N61+L61 -> 0 | Q61: =100%-O61 -> 1 | R61: =+J61-P61 -> 781.67945
A62: 03.02.05.02 | B62: =+'O. GRUESA'!B252 -> LOSA MACIZA - ENCOFRADO Y DESENCOFRADO | C62: =+'O. GRUESA'!D252 -> m2 | D62: =+'O. GRUESA'!J252 -> 10.0725 | E62: 44.140405 | F62: =D62*E62 -> 444.60423 | G62: 1.2 | H62: =D62*G62 -> 12.087 | I62: =+E62+G62 -> 45.340405 | J62: =D62*I62 -> 456.69123 | L62: =+J62*K62 -> 0 | N62: =+M62*J62 -> 0 | O62: =+K62+M62 -> 0 | P62: =+N62+L62 -> 0 | Q62: =100%-O62 -> 1 | R62: =+J62-P62 -> 456.69123
A63: 03.02.05.03 | B63: =+'O. GRUESA'!B255 -> LOSA MACIZA - ACERO fy=4200kg/cm2 | C63: =+'O. GRUESA'!D255 -> kg | D63: =+'O. GRUESA'!J255 -> 151.0875 | E63: 1.8172 | F63: =D63*E63 -> 274.55621 | G63: 5.6 | H63: =D63*G63 -> 846.09 | I63: =+E63+G63 -> 7.4172 | J63: =D63*I63 -> 1120.6462 | L63: =+J63*K63 -> 0 | N63: =+M63*J63 -> 0 | O63: =+K63+M63 -> 0 | P63: =+N63+L63 -> 0 | Q63: =100%-O63 -> 1 | R63: =+J63-P63 -> 1120.6462
A64: 03.02.06.00 | B64: =+'O. GRUESA'!B259 -> ESCALERA | R64: =+J64-P64 -> 0
A65: 03.02.06.01 | B65: =+'O. GRUESA'!B260 -> ESCALERA -CONCRETO PREMEZCLADO f'c=210kg/cm2 | C65: =+'O. GRUESA'!D260 -> m3 | D65: =+'O. GRUESA'!J260 -> 2.94 | E65: 71.595667 | F65: =D65*E65 -> 210.49126 | G65: 330.75 | H65: =D65*G65 -> 972.405 | I65: =+E65+G65 -> 402.34567 | J65: =D65*I65 -> 1182.8963 | L65: =+J65*K65 -> 0 | N65: =+M65*J65 -> 0 | O65: =+K65+M65 -> 0 | P65: =+N65+L65 -> 0 | Q65: =100%-O65 -> 1 | R65: =+J65-P65 -> 1182.8963
A66: 03.02.06.02 | B66: =+'O. GRUESA'!B264 -> ESCALERA - ENCOFRADO Y DESENCOFRADO | C66: =+'O. GRUESA'!D264 -> m2 | D66: =+'O. GRUESA'!J264 -> 15.756 | E66: 69.230306 | F66: =D66*E66 -> 1090.7927 | G66: 0.75 | H66: =D66*G66 -> 11.817 | I66: =+E66+G66 -> 69.980306 | J66: =D66*I66 -> 1102.6097 | L66: =+J66*K66 -> 0 | N66: =+M66*J66 -> 0 | O66: =+K66+M66 -> 0 | P66: =+N66+L66 -> 0 | Q66: =100%-O66 -> 1 | R66: =+J66-P66 -> 1102.6097
A67: 03.02.06.03 | B67: =+'O. GRUESA'!B270 -> ESCALERA - ACERO fy=4200kg/cm2 | C67: =+'O. GRUESA'!D270 -> kg | D67: =+'O. GRUESA'!J270 -> 191.1 | E67: 1.8172 | F67: =D67*E67 -> 347.26692 | G67: 5.6 | H67: =D67*G67 -> 1070.16 | I67: =+E67+G67 -> 7.4172 | J67: =D67*I67 -> 1417.4269 | L67: =+J67*K67 -> 0 | N67: =+M67*J67 -> 0 | O67: =+K67+M67 -> 0 | P67: =+N67+L67 -> 0 | Q67: =100%-O67 -> 1 | R67: =+J67-P67 -> 1417.4269
A68: 03.02.07.00 | B68: ADITIVOS SIKADUR GEL 32 | R68: =+J68-P68 -> 0
A69: 03.02.07.01 | B69: COLOCACIÓN DE ADITIVOS | C69: glb | D69: 1 | E69: 409.9552 | F69: =D69*E69 -> 409.9552 | G69: 1.829 | H69: =D69*G69 -> 1.829 | I69: =+J69 -> 989.49906 | J69: 989.49906 | L69: =+J69*K69 -> 0 | N69: =+M69*J69 -> 0 | O69: =+K69+M69 -> 0 | P69: =+N69+L69 -> 0 | Q69: =100%-O69 -> 1 | R69: =+J69-P69 -> 989.49906
A70: 03.03.00.00 | B70: TABIQUERÍA | F70: =SUM(F71:F72) -> 4520.1001 | H70: =SUM(H71:H72) -> 6993.5747 | J70: =+RESUMEN!C11 -> 11249.033 | L70: =+RESUMEN!E11 -> 0 | N70: =+#REF!+#REF! -> #REF! | P70: =+#REF!+#REF! -> #REF! | R70: =+#REF!+#REF! -> #REF!
A71: 03.03.01.00 | B71: =+'O. HUMEDAD'!B10 -> MURO DE LADRILLO SOGA PANDERETA | C71: M2 | D71: =+'O. HUMEDAD'!J10 -> 92.25 | E71: 34.397833 | F71: =+D71*E71 -> 3173.2001 | G71: 60.07127 | H71: =+D71*G71 -> 5541.5747 | I71: =+E71+G71 -> 94.469103 | J71: =+D71*I71 -> 8714.7748 | L71: =+J71*K71 -> 0 | N71: =+J71*M71 -> 0 | O71: =+K71+M71 -> 0 | P71: =+N71+L71 -> 0 | Q71: =100%-O71 -> 1 | R71: =+J71-P71 -> 8714.7748
A72: 03.03.02.00 | B72: =+'O. HUMEDAD'!B24 -> COLUMNETAS | C72: UND | D72: =+'O. HUMEDAD'!J24 -> 12 | E72: 112.24167 | F72: =+D72*E72 -> 1346.9 | G72: 121 | H72: =+D72*G72 -> 1452 | I72: =+J72/D72 -> 211.18815 | J72: =+J70-J71 -> 2534.2578 | L72: =+J72*K72 -> 0 | N72: =+J72*M72 -> 0 | O72: =+K72+M72 -> 0 | P72: =+N72+L72 -> 0 | Q72: =100%-O72 -> 1 | R72: =+J72-P72 -> 2534.2578
A73: 03.04.00.00 | B73: OBRAS HÚMEDAS | F73: =SUM(F74:F81) -> 17700.515 | H73: =SUM(H74:H81) -> 5032.1551 | J73: =+RESUMEN!C12 -> 22732.67 | L73: =+RESUMEN!E12 -> 0 | N73: =+#REF!+N117 -> #REF! | P73: =+#REF!+P117 -> #REF! | R73: =+#REF!+R117 -> #REF!
A74: 03.04.01.00 | B74: =+'O. HUMEDAD'!B28 -> TARRAJEO EN INTERIORES FROTACHADO | C74: M2 | D74: =+'O. HUMEDAD'!J28 -> 184.5 | E74: 25.612722 | F74: =+D74*E74 -> 4725.5473 | G74: 7.4075 | H74: =+D74*G74 -> 1366.6837 | I74: =+E74+G74 -> 33.020222 | J74: =+D74*I74 -> 6092.231 | L74: =+J74*K74 -> 0 | N74: =+J74*M74 -> 0 | O74: =+K74+M74 -> 0 | P74: =+N74+L74 -> 0 | Q74: =100%-O74 -> 1 | R74: =+J74-P74 -> 6092.231
A75: 03.04.02.00 | B75: =+'O. HUMEDAD'!B42 -> TARRAJEO EN COLUMNAS Y PLACAS | C75: M2 | D75: =+'O. HUMEDAD'!J42 -> 96.752 | E75: 37.002833 | F75: =+D75*E75 -> 3580.0981 | G75: 5.4421 | H75: =+D75*G75 -> 526.53406 | I75: =+E75+G75 -> 42.444933 | J75: =+D75*I75 -> 4106.6322 | L75: =+J75*K75 -> 0 | N75: =+J75*M75 -> 0 | O75: =+K75+M75 -> 0 | P75: =+N75+L75 -> 0 | Q75: =100%-O75 -> 1 | R75: =+J75-P75 -> 4106.6322
A76: 03.04.03.00 | B76: =+'O. HUMEDAD'!B72 -> TARRAJEO EN VIGAS | C76: M2 | D76: =+'O. HUMEDAD'!J72 -> 33.5125 | E76: 35.584167 | F76: =+D76*E76 -> 1192.5144 | G76: 5.5521 | H76: =+D76*G76 -> 186.06475 | I76: =+E76+G76 -> 41.136267 | J76: =+D76*I76 -> 1378.5791 | L76: =+J76*K76 -> 0 | N76: =+J76*M76 -> 0 | O76: =+K76+M76 -> 0 | P76: =+N76+L76 -> 0 | Q76: =100%-O76 -> 1 | R76: =+J76-P76 -> 1378.5791
A77: 03.04.04.00 | B77: =+'O. HUMEDAD'!B93 -> VESTIDURA DE DERRAMES | C77: M | D77: =+'O. HUMEDAD'!J93 -> 28.95 | E77: 12.492417 | F77: =+D77*E77 -> 361.65547 | G77: 0.534 | H77: =+D77*G77 -> 15.4593 | I77: =+E77+G77 -> 13.026417 | J77: =+D77*I77 -> 377.11477 | L77: =+J77*K77 -> 0 | N77: =+J77*M77 -> 0 | O77: =+K77+M77 -> 0 | P77: =+N77+L77 -> 0 | Q77: =100%-O77 -> 1 | R77: =+J77-P77 -> 377.11477
A78: 03.04.05.00 | B78: =+'O. HUMEDAD'!B100 -> TARRAJEO EN CIELO RASO | C78: M2 | D78: =+J78/I78 -> 74.666231 | E78: 34.142693 | F78: =+D78*E78 -> 2549.3062 | G78: 3.535 | H78: =+D78*G78 -> 263.94513 | I78: =+E78+G78 -> 37.677693 | J78: =+J73-SUM(J74:J77)-SUM(J79:J81) -> 2813.2513 | L78: =+J78*K78 -> 0 | N78: =+J78*M78 -> 0 | O78: =+K78+M78 -> 0 | P78: =+N78+L78 -> 0 | Q78: =100%-O78 -> 1 | R78: =+J78-P78 -> 2813.2513
A79: 03.04.06.00 | B79: =+'O. HUMEDAD'!B111 -> CONTRAPISO DE 48mm - TIPO CEMENTO PULIDO | C79: M2 | D79: =+'O. HUMEDAD'!J111 -> 132.19 | E79: 31.57675 | F79: =+D79*E79 -> 4174.1306 | G79: 18.965 | H79: =+D79*G79 -> 2506.9834 | I79: =+E79+G79 -> 50.54175 | J79: =+D79*I79 -> 6681.1139 | L79: =+J79*K79 -> 0 | N79: =+J79*M79 -> 0 | O79: =+K79+M79 -> 0 | P79: =+N79+L79 -> 0 | Q79: =100%-O79 -> 1 | R79: =+J79-P79 -> 6681.1139
A80: 03.04.07.00 | B80: =+'O. HUMEDAD'!B114 -> TARRAJEO DE ESCALERA | C80: M2 | D80: =+'O. HUMEDAD'!J114 -> 15.664 | E80: 33.730693 | F80: =+D80*E80 -> 528.35758 | G80: 3.535 | H80: =+D80*G80 -> 55.37224 | I80: =+E80+G80 -> 37.265693 | J80: =+D80*I80 -> 583.72982 | L80: =+J80*K80 -> 0 | N80: =+J80*M80 -> 0 | O80: =+K80+M80 -> 0 | P80: =+N80+L80 -> 0 | Q80: =100%-O80 -> 1 | R80: =+J80-P80 -> 583.72982
A81: 03.04.08.00 | B81: =+'O. HUMEDAD'!B124 -> TARRAJEO EN EXTERIORES | C81: M2 | D81: 15 | E81: 39.260333 | F81: =+D81*E81 -> 588.905 | G81: 7.4075 | H81: =+D81*G81 -> 111.1125 | I81: =+E81+G81 -> 46.667833 | J81: =+D81*I81 -> 700.0175 | L81: =+J81*K81 -> 0 | N81: =+J81*M81 -> 0 | O81: =+K81+M81 -> 0 | P81: =+N81+L81 -> 0 | Q81: =100%-O81 -> 1 | R81: =+J81-P81 -> 700.0175
A82: 03.05.00.00 | B82: INSTALACIONES ELECTRICAS | F82: =SUM(F85:F99) -> 99240.332 | H82: =SUM(H85:H99) -> 115636.97 | J82: =+RESUMEN!C13 -> 11915.557 | L82: =+RESUMEN!E13 -> 0 | N82: =+#REF!+#REF! -> #REF! | P82: =+#REF!+#REF! -> #REF! | R82: =+#REF!+#REF! -> #REF!
A83: 03.05.01.00 | B83: SALIDAS DE ALUMBRADO, TOMAS Y AIRE ACONDICIONADO | C83: GLB | D83: 1 | I83: 2000 | J83: =+I83 -> 2000
A84: 03.05.02.00 | B84: SALIDAS DE DETECCIÓN DE ALARMA CONTRAINCENDIO | C84: GLB | D84: 1 | I84: 1200 | J84: =+I84 -> 1200
A85: 03.05.03.00 | B85: SALIDAS DE VIDEO VIGILANCIA Y CCTV (SIN CABLEADO) | C85: GLB | D85: 1 | I85: 1200 | J85: =+I85 -> 1200
A86: 03.05.04.00 | B86: SALIDAS DE COMUNICACIONES (SIN CABLEADO) | C86: GLB | D86: 1 | I86: 1500 | J86: =+I86 -> 1500
A87: 03.05.05.00 | B87: CANALIZACIÓN Y ENTUBADOS DE PVC EMPORTADO | C87: GLB | D87: 1 | I87: 2000 | J87: =+I87 -> 2000
A88: 03.05.06.00 | B88: COLOCACIÓN DE TABLERO ELÉCTRICOS (SIN EQUIPO) | C88: GLB | D88: 1 | I88: 1000 | J88: =+I88 -> 1000
A89: 03.05.07.00 | B89: CABLEADO DE ALIMENTADORES Y CIRCUITOS ELÉCTRICOS | C89: GLB | D89: 1 | I89: =15.56+3000 -> 3015.56 | J89: =+I89 -> 3015.56
A90: 03.06.00.00 | B90: INSTALACIONES SANITARIAS | F90: =SUM(F93:F107) -> 54779.388 | H90: =SUM(H93:H107) -> 64228.04 | J90: =+RESUMEN!C14 -> 11915.557 | L90: =+RESUMEN!E14 -> 0 | N90: =+#REF!+#REF! -> #REF! | P90: =+#REF!+#REF! -> #REF! | R90: =+#REF!+#REF! -> #REF!
A91: 03.06.01.00 | B91: SALIDAS DE AGUA | C91: GLB | D91: 1 | I91: 1500 | J91: =+I91 -> 1500
A92: 03.06.02.00 | B92: SALIDAS DE DESAGÚE | C92: GLB | D92: 1 | I92: 1500 | J92: =+I92 -> 1500
A93: 03.06.03.00 | B93: TUBERIAS Y MONTANTES DE AGUA FRÍA | C93: GLB | D93: 1 | I93: 2500 | J93: =+I93 -> 2500
A94: 03.06.04.00 | B94: DESAGUE Y MONTANTES DE AGUA FRIA | C94: GLB | D94: 1 | I94: =+J94 -> 3427.6673 | J94: =+J90-J91-J92-J93-J95 -> 3427.6673
A95: 03.06.05.00 | B95: CAJAS DE REGISTRO | C95: GLB | D95: 1 | I95: 2987.89 | J95: =+I95 -> 2987.89
A96: 04.00.00.00 | B96: =+'O. GRUESA'!B274 -> 2DO PISO | F96: =+F97+F115+F118 -> 30542.668 | H96: =+H97+H115+H118 -> 29384.709 | J96: =+J97+J115+J118+J127+J134 -> 77800.713 | L96: =+L97+L115+L118+L127+L134 -> 0 | N96: =SUM(N98:N103) -> 0 | P96: =SUM(P98:P103) -> 0 | R96: =+J96-P96 -> 77800.713
A97: 04.01.00.00 | B97: CONCRETO ARMADO | F97: =+SUM(F98:F114) -> 13157.599 | H97: =+SUM(H98:H114) -> 19033.695 | J97: =+RESUMEN!C16 -> 32191.293 | L97: =+RESUMEN!E16 -> 0 | N97: =+SUM(N98:N114) -> 0 | P97: =+SUM(P98:P114) -> 0 | R97: =+J97-P97 -> 32191.293
A98: 04.01.01.00 | B98: =+'O. GRUESA'!B276 -> PLACAS | R98: =+J98-P98 -> 0
A99: 04.01.01.01 | B99: =+'O. GRUESA'!B277 -> PLACAS - CONCRETO PREMEZCLADO f'c=210kg/cm2 | C99: =+'O. GRUESA'!D277 -> m3 | D99: =+'O. GRUESA'!J277 -> 8.575 | E99: 88.708667 | F99: =D99*E99 -> 760.67682 | G99: 348.75 | H99: =D99*G99 -> 2990.5312 | I99: =+E99+G99 -> 437.45867 | J99: =D99*I99 -> 3751.2081 | L99: =+J99*K99 -> 0 | N99: =+M99*J99 -> 0 | O99: =+K99+M99 -> 0 | P99: =+N99+L99 -> 0 | Q99: =100%-O99 -> 1 | R99: =+J99-P99 -> 3751.2081
A100: 04.01.01.02 | B100: =+'O. GRUESA'!B282 -> PLACAS - ENCOFRADO Y DESENCOFRADO | C100: =+'O. GRUESA'!D282 -> m2 | D100: =+'O. GRUESA'!J282 -> 82.6 | E100: 60.478167 | F100: =D100*E100 -> 4995.4966 | G100: 2.35 | H100: =D100*G100 -> 194.11 | I100: =+E100+G100 -> 62.828167 | J100: =D100*I100 -> 5189.6066 | L100: =+J100*K100 -> 0 | N100: =+M100*J100 -> 0 | O100: =+K100+M100 -> 0 | P100: =+N100+L100 -> 0 | Q100: =100%-O100 -> 1 | R100: =+J100-P100 -> 5189.6066
...

Sheet O. GRUESA
A1: PLANILLA DE METRADO OBRA GRUESA
A2: PROYECTO: | B2: =Valorización!B2 -> 0
A3: PROPIETARIO(S) : | B3: =Valorización!B3 -> 0
A4: UBICACIÓN: | B4: LT 18 MZ DDF, JR. ALAMEDA EL ESPINEL, URB BRISAS DEL MAR - DISTRITO CHORRILLOS, DEPARTAMENTO Y PROVINCIA DE LIMA
A5: PARTIDA | B5: DESCRIPCION | D5: und | E5: CANT | F5: MEDIDAS | I5: PARCIAL | J5: TOTAL
F6: LARGO | G6: ANCHO | H6: ALTO
A7: 01.00.00.00 | B7: OBRAS PROVISIONALES, TRABAJOS PRELIMINARES, SEGURIDAD Y SALUD
A8: 01.01.00.00 | B8: OBRAS PROVISIONALES
A9: 01.01.01.00 | B9: TRANSPORTE DE EQUIPOS Y HERRAMIENTAS | D9: glb | J9: =SUM(I10:I11) -> 1 | K9: OK
E10: 1 | I10: =PRODUCT(E10:H10) -> 1
A12: 01.01.02.00 | B12: CERCO PERIMETRICO PROVISIONAL | D12: ml | J12: =SUM(I13:I14) -> 30 | K12: OK
E13: 1 | F13: PERIM= | G13: 30 | I13: =PRODUCT(E13:H13) -> 30
A15: 01.01.03.00 | B15: PROTECCIÓN CON MALLA RASCHELL | D15: ml | J15: =SUM(I16:I17) -> 180 | K15: OK
E16: 6 | F16: PERIM= | G16: 30 | I16: =PRODUCT(E16:H16) -> 180
A18: 01.01.04.00 | B18: INSTALACION DE OFICINA Y ALMACEN | D18: glb | J18: =SUM(I19:I20) -> 1 | K18: OK
E19: 1 | I19: =PRODUCT(E19:H19) -> 1
A21: 01.01.05.00 | B21: ALQUILER DE BAÑO PROVISIONAL | D21: mes | J21: =SUM(I22:I23) -> 4 | K21: OK
E22: 4 | F22: 1 | I22: =PRODUCT(E22:H22) -> 4
A24: 01.02.00.00 | B24: DEMOLICIÓN Y TRABAJOS PRELIMINARES
A25: 01.02.01.00 | B25: DESMONTAJE Y ACARREO DE MATERIAL | D25: glb | J25: =SUM(I26:I27) -> 1 | K25: OK
E26: 1 | I26: =PRODUCT(E26:H26) -> 1
A28: 01.02.02.00 | B28: DEMOLICIÓN MANUAL CON ROTOMARTILLO | D28: glb | J28: =SUM(I29:I30) -> 1 | K28: OK
E29: 1 | I29: =PRODUCT(E29:H29) -> 1
A31: 01.02.03.00 | B31: DEMOLICIÓN CON MAQUINARIA PESADA | D31: glb | J31: =SUM(I32:I33) -> 1 | K31: OK
E32: 1 | I32: =PRODUCT(E32:H32) -> 1
A34: 01.02.04.00 | B34: ELIMINACIÓN DE ESCOMBROS, DESMONTE | D34: glb | J34: =SUM(I35:I36) -> 1 | K34: OK
E35: 1 | I35: =PRODUCT(E35:H35) -> 1
A37: 01.02.05.00 | B37: LIMPIEZA DE TERRENO MANUAL | D37: m2 | J37: =SUM(I38:I39) -> 150 | K37: OK
B38: AREA DE TERRENO | D38: m2 | E38: 1 | F38: 5 | G38: 30 | I38: =PRODUCT(E38:H38) -> 150
A40: 01.02.06.00 | B40: TRAZADO Y REPLANTEO S/EQUIPO | D40: m2 | J40: =SUM(I41:I42) -> 150 | K40: OK
D41: m2 | E41: =+E38 -> 1 | F41: 5 | G41: 30 | I41: =PRODUCT(E41:H41) -> 150
A43: 01.03.00.00 | B43: SEGURIDAD Y SALUD
A44: 01.03.01.00 | B44: EQUIPOS DE PROTECCIÓN INDIVIDUAL | D44: und | J44: =SUM(I45:I46) -> 30 | K44: OK
E45: 30 | I45: =PRODUCT(E45:H45) -> 30
A47: 01.03.02.00 | B47: EQUIPOS DE PROTECCIÓN COLECTIVA | D47: glb | J47: =SUM(I48:I49) -> 1 | K47: OK
E48: 1 | I48: =PRODUCT(E48:H48) -> 1
A50: 01.03.03.00 | B50: SEÑALIZACIÓN TEMPORAL DE SEGURIDAD | D50: glb | J50: =SUM(I51:I52) -> 1 | K50: OK
E51: 1 | I51: =PRODUCT(E51:H51) -> 1
A53: 01.03.04.00 | B53: SEGURO SCTR | D53: mes | J53: =SUM(I54:I55) -> 4 | K53: OK
E54: 4 | I54: =PRODUCT(E54:H54) -> 4
A56: 02.00.00.00 | B56: MOVIMIENTO DE TIERRAS
A57: 02.03.00.00 | B57: EXCAVACIÓN MANUAL P/CIMIENTO Y ZAPATA | D57: m3 | J57: =SUM(I58:I73) -> 54.705
B58: Z-1 | D58: m3 | E58: 1 | F58: 3 | G58: 3.25 | H58: 2.5 | I58: =PRODUCT(E58:H58) -> 24.375
B59: Z-2 | D59: m3 | E59: 1 | F59: 3 | G59: 1.2 | H59: 1.5 | I59: =PRODUCT(E59:H59) -> 5.4
B60: Z-3 | D60: m3 | E60: 1 | F60: 3.6 | G60: 1.2 | H60: 1.5 | I60: =PRODUCT(E60:H60) -> 6.48
B61: CC-1 | D61: m3 | E61: 1 | F61: 2.2 | G61: 0.5 | H61: 1.2 | I61: =PRODUCT(E61:H61) -> 1.32
B62: CC-2 | D62: m3 | E62: 1 | F62: 3.95 | G62: 0.5 | H62: 1.2 | I62: =PRODUCT(E62:H62) -> 2.37
B63: CC-3 | D63: m3 | E63: 1 | F63: 2.2 | G63: 0.5 | H63: 1.2 | I63: =PRODUCT(E63:H63) -> 1.32
B64: CC-4 | D64: m3 | E64: 1 | F64: 1.8 | G64: 0.5 | H64: 1.2 | I64: =PRODUCT(E64:H64) -> 1.08
B65: CC-5 | D65: m3 | E65: 1 | F65: 1.2 | G65: 0.5 | H65: 1.2 | I65: =PRODUCT(E65:H65) -> 0.72
B66: CC-6 | D66: m3 | E66: 1 | F66: 0.65 | G66: 0.5 | H66: 1.2 | I66: =PRODUCT(E66:H66) -> 0.39
B67: CC-7 | D67: m3 | E67: 1 | F67: 2.4 | G67: 0.5 | H67: 1.2 | I67: =PRODUCT(E67:H67) -> 1.44
B68: CC-8 | D68: m3 | E68: 1 | F68: 2.95 | G68: 0.5 | H68: 1.2 | I68: =PRODUCT(E68:H68) -> 1.77
B69: CC-9 | D69: m3 | E69: 1 | F69: 3.2 | G69: 0.5 | H69: 1.2 | I69: =PRODUCT(E69:H69) -> 1.92
... B72: CC-10 | D72: m3 | E72: 1 | F72: 3.5 | G72: 0.5 | H72: 1.2 | I72: =PRODUCT(E72:H72) -> 2.1
A74: 02.04.00.00 | B74: COMPACTACIÓN MANUAL P/CIMIENTO Y ZAPATA | D74: m2 | J74: =SUM(I75:I90) -> 33.045
B75: Z-1 | D75: m2 | E75: 1 | F75: 3 | G75: 3.25 | I75: =PRODUCT(E75:H75) -> 9.75
B76: Z-2 | D76: m2 | E76: 1 | F76: 3 | G76: 1.2 | I76: =PRODUCT(E76:H76) -> 3.6
B77: Z-3 | D77: m2 | E77: 1 | F77: 3.6 | G77: 1.2 | I77: =PRODUCT(E77:H77) -> 4.32
B78: CC-1 | D78: m2 | E78: 1 | F78: 2.2 | G78: 0.5 | I78: =PRODUCT(E78:H78) -> 1.1
B79: CC-2 | D79: m2 | E79: 1 | F79: 3.95 | G79: 0.5 | I79: =PRODUCT(E79:H79) -> 1.975
B80: CC-3 | D80: m2 | E80: 1 | F80: 2.2 | G80: 0.5 | I80: =PRODUCT(E80:H80) -> 1.1
B81: CC-4 | D81: m2 | E81: 1 | F81: 1.8 | G81: 0.5 | I81: =PRODUCT(E81:H81) -> 0.9
B82: CC-5 | D82: m2 | E82: 1 | F82: 1.2 | G82: 0.5 | I82: =PRODUCT(E82:H82) -> 0.6
B83: CC-6 | D83: m2 | E83: 1 | F83: 0.65 | G83: 0.5 | I83: =PRODUCT(E83:H83) -> 0.325
B84: CC-7 | D84: m2 | E84: 1 | F84: 2.4 | G84: 0.5 | I84: =PRODUCT(E84:H84) -> 1.2
B85: CC-8 | D85: m2 | E85: 1 | F85: 2.95 | G85: 0.5 | I85: =PRODUCT(E85:H85) -> 1.475
B86: CC-9 | D86: m2 | E86: 1 | F86: 3.2 | G86: 0.5 | I86: =PRODUCT(E86:H86) -> 1.6
... B89: CC-10 | D89: m2 | E89: 1 | F89: 3.5 | G89: 0.5 | I89: =PRODUCT(E89:H89) -> 1.75
A91: 02.05.00.00 | B91: =+'[1]APUs Casco'!A110 -> RELLENO COMPACTADO CON MATERIAL PROPIO | D91: m3 | J91: =SUM(I92:I107)*1.2 -> 28.584
B92: Z-1 | D92: m3 | E92: 1 | F92: 3 | G92: 3.25 | H92: 1 | I92: =PRODUCT(E92:H92) -> 9.75
B93: Z-2 | D93: m3 | E93: 1 | F93: 3 | G93: 1.2 | H93: 1 | I93: =PRODUCT(E93:H93) -> 3.6
B94: Z-3 | D94: m3 | E94: 1 | F94: 3.6 | G94: 1.2 | H94: 1 | I94: =PRODUCT(E94:H94) -> 4.32
B95: CC-1 | D95: m3 | E95: 1 | F95: 2.2 | G95: 0.5 | H95: 0.4 | I95: =PRODUCT(E95:H95) -> 0.44
B96: CC-2 | D96: m3 | E96: 1 | F96: 3.95 | G96: 0.5 | H96: 0.4 | I96: =PRODUCT(E96:H96) -> 0.79
B97: CC-3 | D97: m3 | E97: 1 | F97: 2.2 | G97: 0.5 | H97: 0.4 | I97: =PRODUCT(E97:H97) -> 0.44
B98: CC-4 | D98: m3 | E98: 1 | F98: 1.8 | G98: 0.5 | H98: 0.4 | I98: =PRODUCT(E98:H98) -> 0.36
B99: CC-5 | D99: m3 | E99: 1 | F99: 1.2 | G99: 0.5 | H99: 0.4 | I99: =PRODUCT(E99:H99) -> 0.24
B100: CC-6 | D100: m3 | E100: 1 | F100: 0.65 | G100: 0.5 | H100: 0.4 | I100: =PRODUCT(E100:H100) -> 0.13
B101: CC-7 | D101: m3 | E101: 1 | F101: 2.4 | G101: 0.5 | H101: 0.4 | I101: =PRODUCT(E101:H101) -> 0.48
B102: CC-8 | D102: m3 | E102: 1 | F102: 2.95 | G102: 0.5 | H102: 0.4 | I102: =PRODUCT(E102:H102) -> 0.59
B103: CC-9 | D103: m3 | E103: 1 | F103: 3.2 | G103: 0.5 | H103: 0.4 | I103: =PRODUCT(E103:H103) -> 0.64
... B106: CC-10 | D106: m3 | E106: 1 | F106: 3.5 | G106: 0.5 | H106: 0.4 | I106: =PRODUCT(E106:H106) -> 0.7
A108: 02.08.00.00 | B108: =+'[1]APUs Casco'!A144 -> ELIMINACION DE MATERIAL CON MAQUINARIA | D108: m3 | J108: =+G110 -> 54.705
B109: PROVENIENTE DE EXCAVACIÓN
B110: EXCAVACIÓN DE ZANJAS CON MAQUINARIA | D110: m3 | E110: 1 | F110: VOL= | G110: =+J57 -> 54.705 | H110: 1.5 | I110: =PRODUCT(E110:H110) -> 82.0575
A112: 02.09.00.00 | B112: =+'[1]APUs Casco'!A153 -> NIVELACION DE TERRENO Y APISONADO C/20 CM. | D112: m2 | J112: =SUM(I113:I115) -> 150
B113: PARA FALSO PISO
C114: 2 capas | D114: m2 | E114: 1 | F114: AREA= | G114: 150 | I114: =PRODUCT(E114:H114) -> 150
A116: 03.00.00.00 | B116: 1ER PISO
A117: 01.03.00.00 | B117: CONCRETO SIMPLE
A118: 03.01.00.00 | B118: SOLADO
A119: 03.01.01.00 | B119: CONCRETO, fc=100 kg/cm² | D119: m2 | J119: =SUM(I120:I123) -> 17.67 | K119: OK
B120: Z-1 | D120: m2 | E120: 1 | F120: 3 | G120: 3.25 | I120: =PRODUCT(E120:H120) -> 9.75
B121: Z-2 | D121: m2 | E121: 1 | F121: 3 | G121: 1.2 | I121: =PRODUCT(E121:H121) -> 3.6
B122: Z-3 | D122: m2 | E122: 1 | F122: 3.6 | G122: 1.2 | I122: =PRODUCT(E122:H122) -> 4.32
A124: 03.02.00.00 | B124: CIMIENTO CORRIDO
A125: 03.02.01.00 | B125: CONCRETO f'c= 100 kg/cm² +30% P.G. (Tamaño maximo 6") | D125: m3 | J125: =SUM(I126:I138) -> 18.45 | K125: OK
B126: CC-1 | D126: m3 | E126: 1 | F126: 2.2 | G126: 0.5 | H126: 1.2 | I126: =PRODUCT(E126:H126) -> 1.32
B127: CC-2 | D127: m3 | E127: 1 | F127: 3.95 | G127: 0.5 | H127: 1.2 | I127: =PRODUCT(E127:H127) -> 2.37
...

Sheet ACERO
A1: PLANILLA DE METRADO: ACERO
A2: =Valorización!A2 -> PROYECTO: | B2: =Valorización!B2 -> 0
A3: =Valorización!A3 -> PROPIETARIO(S) : | B3: =Valorización!B3 -> 0
A4: =Valorización!A4 -> UBICACIÓN: | B4: LT 18 MZ DDF, JR. ALAMEDA EL ESPINEL, URB BRISAS DEL MAR - DISTRITO CHORRILLOS, DEPARTAMENTO Y PROVINCIA DE LIMA
A5: PARTIDA | B5: DESCRIPCION | D5: UNIDAD | E5: CANT | F5: DIAMETRO | G5: ESTRUTURAS | H5: LONGITUD
G6: IGUALES | I6: 6mm | J6: 8mm | K6: 3/8 | L6: 1/2 | M6: 5/8 | N6: 3/4 | O6: 1 | P6: TOTAL
B7: 1ER PISO
A8: 01.01.00 | B8: ACERO ASTM f'y = 4200 kg/cm2 EN ZAPATAS | P8: =SUM(I32:O32) -> 917.7074
B9: Z-1 | C9: EJE X | D9: KG | E9: 1 | F9: 5/8 | G9: 5 | H9: 1.77 | I9: =IF($F9=$I$6,$E9*$G9*$H9,"") | J9: =IF($F9=$J$6,$E9*$G9*$H9,"") | K9: =IF($F9=$K$6,$E9*$G9*$H9,"") | L9: =IF($F9=$L$6,$E9*$G9*$H9,"") | M9: =IF($F9=$M$6,$E9*$G9*$H9,"") -> 8.85 | N9: =IF($F9=$N$6,$E9*$G9*$H9,"") | O9: =IF($F9=$O$6,$E9*$G9*$H9,"") | P9: =IF($F9=$P$6,$E9*$G9*$H9,"")
C10: EJE Y | D10: KG | E10: 1 | F10: 5/8 | G10: 8 | H10: 1.27 | I10: =IF($F10=$I$6,$E10*$G10*$H10,"") | J10: =IF($F10=$J$6,$E10*$G10*$H10,"") | K10: =IF($F10=$K$6,$E10*$G10*$H10,"") | L10: =IF($F10=$L$6,$E10*$G10*$H10,"") | M10: =IF($F10=$M$6,$E10*$G10*$H10,"") -> 10.16 | N10: =IF($F10=$N$6,$E10*$G10*$H10,"") | O10: =IF($F10=$O$6,$E10*$G10*$H10,"") | P10: =IF($F10=$P$6,$E10*$G10*$H10,"")
B11: Z-2 | C11: EJE X | D11: KG | E11: 1 | F11: 5/8 | G11: 5 | H11: 2.37 | I11: =IF($F11=$I$6,$E11*$G11*$H11,"") | J11: =IF($F11=$J$6,$E11*$G11*$H11,"") | K11: =IF($F11=$K$6,$E11*$G11*$H11,"") | L11: =IF($F11=$L$6,$E11*$G11*$H11,"") | M11: =IF($F11=$M$6,$E11*$G11*$H11,"") -> 11.85 | N11: =IF($F11=$N$6,$E11*$G11*$H11,"") | O11: =IF($F11=$O$6,$E11*$G11*$H11,"") | P11: =IF($F11=$P$6,$E11*$G11*$H11,"")
C12: EJE Y | D12: KG | E12: 1 | F12: 5/8 | G12: 11 | H12: 1.27 | I12: =IF($F12=$I$6,$E12*$G12*$H12,"") | J12: =IF($F12=$J$6,$E12*$G12*$H12,"") | K12: =IF($F12=$K$6,$E12*$G12*$H12,"") | L12: =IF($F12=$L$6,$E12*$G12*$H12,"") | M12: =IF($F12=$M$6,$E12*$G12*$H12,"") -> 13.97 | N12: =IF($F12=$N$6,$E12*$G12*$H12,"") | O12: =IF($F12=$O$6,$E12*$G12*$H12,"") | P12: =IF($F12=$P$6,$E12*$G12*$H12,"")
B13: Z-3 | C13: EJE X | D13: KG | E13: 3 | F13: 5/8 | G13: 10 | H13: 1.27 | I13: =IF($F13=$I$6,$E13*$G13*$H13,"") | J13: =IF($F13=$J$6,$E13*$G13*$H13,"") | K13: =IF($F13=$K$6,$E13*$G13*$H13,"") | L13: =IF($F13=$L$6,$E13*$G13*$H13,"") | M13: =IF($F13=$M$6,$E13*$G13*$H13,"") -> 38.1 | N13: =IF($F13=$N$6,$E13*$G13*$H13,"") | O13: =IF($F13=$O$6,$E13*$G13*$H13,"") | P13: =IF($F13=$P$6,$E13*$G13*$H13,"")
C14: EJE Y | D14: KG | E14: 3 | F14: 5/8 | G14: 5 | H14: 2.27 | I14: =IF($F14=$I$6,$E14*$G14*$H14,"") | J14: =IF($F14=$J$6,$E14*$G14*$H14,"") | K14: =IF($F14=$K$6,$E14*$G14*$H14,"") | L14: =IF($F14=$L$6,$E14*$G14*$H14,"") | M14: =IF($F14=$M$6,$E14*$G14*$H14,"") -> 34.05 | N14: =IF($F14=$N$6,$E14*$G14*$H14,"") | O14: =IF($F14=$O$6,$E14*$G14*$H14,"") | P14: =IF($F14=$P$6,$E14*$G14*$H14,"")
B15: Z-4 | C15: EJE X | D15: KG | E15: 2 | F15: 5/8 | G15: 9 | H15: 1.37 | I15: =IF($F15=$I$6,$E15*$G15*$H15,"") | J15: =IF($F15=$J$6,$E15*$G15*$H15,"") | K15: =IF($F15=$K$6,$E15*$G15*$H15,"") | L15: =IF($F15=$L$6,$E15*$G15*$H15,"") | M15: =IF($F15=$M$6,$E15*$G15*$H15,"") -> 24.66 | N15: =IF($F15=$N$6,$E15*$G15*$H15,"") | O15: =IF($F15=$O$6,$E15*$G15*$H15,"") | P15: =IF($F15=$P$6,$E15*$G15*$H15,"")
C16: EJE Y | D16: KG | E16: 2 | F16: 5/8 | G16: 6 | H16: 2.07 | I16: =IF($F16=$I$6,$E16*$G16*$H16,"") | J16: =IF($F16=$J$6,$E16*$G16*$H16,"") | K16: =IF($F16=$K$6,$E16*$G16*$H16,"") | L16: =IF($F16=$L$6,$E16*$G16*$H16,"") | M16: =IF($F16=$M$6,$E16*$G16*$H16,"") -> 24.84 | N16: =IF($F16=$N$6,$E16*$G16*$H16,"") | O16: =IF($F16=$O$6,$E16*$G16*$H16,"") | P16: =IF($F16=$P$6,$E16*$G16*$H16,"")
B17: Z-5 | C17: EJE X | D17: KG | E17: 1 | F17: 5/8 | G17: 23 | H17: 1.27 | I17: =IF($F17=$I$6,$E17*$G17*$H17,"") | J17: =IF($F17=$J$6,$E17*$G17*$H17,"") | K17: =IF($F17=$K$6,$E17*$G17*$H17,"") | L17: =IF($F17=$L$6,$E17*$G17*$H17,"") | M17: =IF($F17=$M$6,$E17*$G17*$H17,"") -> 29.21 | N17: =IF($F17=$N$6,$E17*$G17*$H17,"") | O17: =IF($F17=$O$6,$E17*$G17*$H17,"") | P17: =IF($F17=$P$6,$E17*$G19*$H17,"")
C18: EJE Y | D18: KG | E18: 1 | F18: 5/8 | G18: 5 | H18: 4.77 | I18: =IF($F18=$I$6,$E18*$G18*$H18,"") | J18: =IF($F18=$J$6,$E18*$G18*$H18,"") | K18: =IF($F18=$K$6,$E18*$G18*$H18,"") | L18: =IF($F18=$L$6,$E18*$G18*$H18,"") | M18: =IF($F18=$M$6,$E18*$G18*$H18,"") -> 23.85 | N18: =IF($F18=$N$6,$E18*$G18*$H18,"") | O18: =IF($F18=$O$6,$E18*$G18*$H18,"") | P18: =IF($F18=$P$6,$E18*$G22*$H18,"")
B19: Z-6 (INFERIOR Y SUPERIOR) | C19: EJE X | D19: KG | E19: 1 | F19: 5/8 | G19: =2*20 -> 40 | H19: 2.37 | I19: =IF($F19=$I$6,$E19*$G19*$H19,"") | J19: =IF($F19=$J$6,$E19*$G19*$H19,"") | K19: =IF($F19=$K$6,$E19*$G19*$H19,"") | L19: =IF($F19=$L$6,$E19*$G19*$H19,"") | M19: =IF($F19=$M$6,$E19*$G19*$H19,"") -> 94.8 | N19: =IF($F19=$N$6,$E19*$G19*$H19,"") | O19: =IF($F19=$O$6,$E19*$G19*$H19,"") | P19: =IF($F19=$P$6,$E19*$G23*$H19,"")
C20: EJE Y | D20: KG | E20: 1 | F20: 3/4 | G20: =2*11 -> 22 | H20: 4.17 | I20: =IF($F20=$I$6,$E20*$G22*$H22,"") | J20: =IF($F20=$J$6,$E20*$G22*$H22,"") | K20: =IF($F20=$K$6,$E20*$G22*$H22,"") | L20: =IF($F20=$L$6,$E20*$G22*$H22,"") | M20: =IF($F20=$M$6,$E20*$G20*$H20,"") | N20: =IF($F20=$N$6,$E20*$G20*$H20,"") -> 91.74 | O20: =IF($F20=$O$6,$E20*$G22*$H22,"") | P20: =IF($F20=$P$6,$E20*$G24*$H22,"")
B21: Z-7 | C21: EJE X | D21: KG | E21: 1 | F21: 5/8 | G21: 7 | H21: 1.57 | I21: =IF($F21=$I$6,$E21*$G23*$H23,"") | J21: =IF($F21=$J$6,$E21*$G23*$H23,"") | K21: =IF($F21=$K$6,$E21*$G23*$H23,"") | L21: =IF($F21=$L$6,$E21*$G23*$H23,"") | M21: =IF($F21=$M$6,$E21*$G21*$H21,"") -> 10.99 | N21: =IF($F21=$N$6,$E21*$G21*$H21,"") | O21: =IF($F21=$O$6,$E21*$G23*$H23,"") | P21: =IF($F21=$P$6,$E21*#REF!*$H23,"")
C22: EJE Y | D22: KG | E22: 1 | F22: 5/8 | G22: 7 | H22: 1.67 | I22: =IF($F22=$I$6,$E22*$G24*$H24,"") | J22: =IF($F22=$J$6,$E22*$G24*$H24,"") | K22: =IF($F22=$K$6,$E22*$G24*$H24,"") | L22: =IF($F22=$L$6,$E22*$G24*$H24,"") | M22: =IF($F22=$M$6,$E22*$G22*$H22,"") -> 11.69 | N22: =IF($F22=$N$6,$E22*$G22*$H22,"") | O22: =IF($F22=$O$6,$E22*$G24*$H24,"") | P22: =IF($F22=$P$6,$E22*#REF!*$H24,"")
B23: Z-8 | C23: EJE X | D23: KG | E23: 1 | F23: 5/8 | G23: 24 | H23: 1.27 | I23: =IF($F23=$I$6,$E23*#REF!*#REF!,"") | J23: =IF($F23=$J$6,$E23*#REF!*#REF!,"") | K23: =IF($F23=$K$6,$E23*#REF!*#REF!,"") | L23: =IF($F23=$L$6,$E23*#REF!*#REF!,"") | M23: =IF($F23=$M$6,$E23*$G23*$H23,"") -> 30.48 | N23: =IF($F23=$N$6,$E23*$G23*$H23,"") | O23: =IF($F23=$O$6,$E23*#REF!*#REF!,"")
C24: EJE Y | D24: KG | E24: 1 | F24: 5/8 | G24: 5 | H24: 4.97 | I24: =IF($F24=$I$6,$E24*#REF!*#REF!,"") | J24: =IF($F24=$J$6,$E24*#REF!*#REF!,"") | K24: =IF($F24=$K$6,$E24*#REF!*#REF!,"") | L24: =IF($F24=$L$6,$E24*#REF!*#REF!,"") | M24: =IF($F24=$M$6,$E24*$G24*$H24,"") -> 24.85 | N24: =IF($F24=$N$6,$E24*$G24*$H24,"") | O24: =IF($F24=$O$6,$E24*#REF!*#REF!,"")
B25: Z-9 | C25: EJE X | D25: KG | E25: 1 | F25: 5/8 | G25: 23 | H25: 1.57 | I25: =IF($F25=$I$6,$E25*$G25*$H25,"") | J25: =IF($F25=$J$6,$E25*$G25*$H25,"") | K25: =IF($F25=$K$6,$E25*$G25*$H25,"") | L25: =IF($F25=$L$6,$E25*$G25*$H25,"") | M25: =IF($F25=$M$6,$E25*$G25*$H25,"") -> 36.11 | N25: =IF($F25=$N$6,$E25*$G25*$H25,"") | O25: =IF($F25=$O$6,$E25*$G25*$H25,"")
C26: EJE Y | D26: KG | E26: 1 | F26: 5/8 | G26: 7 | H26: 4.87 | I26: =IF($F26=$I$6,$E26*$G26*$H26,"") | J26: =IF($F26=$J$6,$E26*$G26*$H26,"") | K26: =IF($F26=$K$6,$E26*$G26*$H26,"") | L26: =IF($F26=$L$6,$E26*$G26*$H26,"") | M26: =IF($F26=$M$6,$E26*$G26*$H26,"") -> 34.09 | N26: =IF($F26=$N$6,$E26*$G26*$H26,"") | O26: =IF($F26=$O$6,$E26*$G26*$H26,"")
B27: CIMIENTO TABIQUERIA | C27: EJE X | D27: KG | E27: 1 | F27: 3/8 | G27: 44 | H27: 1.5 | I27: =IF($F27=$I$6,$E27*$G27*$H27,"") | J27: =IF($F27=$J$6,$E27*$G27*$H27,"") | K27: =IF($F27=$K$6,$E27*$G27*$H27,"") -> 66 | L27: =IF($F27=$L$6,$E27*$G27*$H27,"") | M27: =IF($F27=$M$6,$E27*$G27*$H27,"") | N27: =IF($F27=$N$6,$E27*$G27*$H27,"") | O27: =IF($F27=$O$6,$E27*$G27*$H27,"")
C28: EJE Y | D28: KG | E28: 1 | F28: 3/8 | G28: 2 | H28: 13.05 | I28: =IF($F28=$I$6,$E28*$G28*$H28,"") | J28: =IF($F28=$J$6,$E28*$G28*$H28,"") | K28: =IF($F28=$K$6,$E28*$G28*$H28,"") -> 26.1 | L28: =IF($F28=$L$6,$E28*$G28*$H28,"") | M28: =IF($F28=$M$6,$E28*$G28*$H28,"") | N28: =IF($F28=$N$6,$E28*$G28*$H28,"") | O28: =IF($F28=$O$6,$E28*$G28*$H28,"")
N29: =IF($F29=$N$6,$E29*$G29*$H29,"")
G30: LONGITUD TOTAL | I30: =SUM(I9:I29) -> 0 | J30: =SUM(J9:J29) -> 0 | K30: =SUM(K9:K29) -> 92.1 | L30: =SUM(L9:L29) -> 0 | M30: =SUM(M9:M29) -> 462.55 | N30: =SUM(N9:N29) -> 91.74 | O30: =SUM(O9:O29) -> 0
G31: PESO UNITARIO | I31: 0.21 | J31: 0.38 | K31: 0.53 | L31: 0.94 | M31: 1.46 | N31: 2.11 | O31: 3.74
G32: PESO TOTAL | I32: =I30*I31 -> 0 | J32: =J30*J31 -> 0 | K32: =K30*K31 -> 48.813 | L32: =L30*L31 -> 0 | M32: =M30*M31 -> 675.323 | N32: =N30*N31 -> 193.5714 | O32: =O30*O31 -> 0
G33: # DE VARILLA | I33: =ROUNDUP(I30*1.07/9,0) -> 0 | J33: =ROUNDUP(J30*1.07/9,0) -> 0 | K33: =ROUNDUP(K30*1.07/9,0) -> 11 | L33: =ROUNDUP(L30*1.07/9,0) -> 0 | M33: =ROUNDUP(M30*1.07/9,0) -> 55 | N33: =ROUNDUP(N30*1.07/9,0) -> 11 | O33: =ROUNDUP(O30*1.07/9,0) -> 0
A34: 01.01.00 | B34: ACERO ASTM f'y = 4200 kg/cm2 EN VIGAS DE CIMENTACION | P34: =SUM(I46:O46) -> 855.2704
B35: VC-1 | I35: =IF($F35=$I$6,$E35*$G35*$H35,"") | J35: =IF($F35=$J$6,$E35*$G35*$H35,"") | K35: =IF($F35=$K$6,$E35*$G35*$H35,"") | L35: =IF($F35=$L$6,$E35*$G35*$H35,"") | M35: =IF($F35=$M$6,$E35*$G35*$H35,"") | N35: =IF($F35=$N$6,$E35*$G35*$H35,"") | O35: =IF($F35=$O$6,$E35*$G35*$H35,"")
B36: ACE. SUPERIOR | D36: KG | E36: 5 | F36: 3/4 | G36: 4 | H36: 5.44 | I36: =IF($F36=$I$6,$E36*$G36*$H36,"") | J36: =IF($F36=$J$6,$E36*$G36*$H36,"") | K36: =IF($F36=$K$6,$E36*$G36*$H36,"") | L36: =IF($F36=$L$6,$E36*$G36*$H36,"") | M36: =IF($F36=$M$6,$E36*$G36*$H36,"") | N36: =IF($F36=$N$6,$E36*$G36*$H36,"") -> 108.8 | O36: =IF($F36=$O$6,$E36*$G36*$H36,"")
B37: ACE. INFERIOR | D37: KG | E37: 5 | F37: 3/4 | G37: 3 | H37: 5.44 | I37: =IF($F37=$I$6,$E37*$G37*$H37,"") | J37: =IF($F37=$J$6,$E37*$G37*$H37,"") | K37: =IF($F37=$K$6,$E37*$G37*$H37,"") | L37: =IF($F37=$L$6,$E37*$G37*$H37,"") | M37: =IF($F37=$M$6,$E37*$G37*$H37,"") | N37: =IF($F37=$N$6,$E37*$G37*$H37,"") -> 81.6 | O37: =IF($F37=$O$6,$E37*$G37*$H37,"")
B38: ESTRIBOS | D38: KG | E38: 5 | F38: 3/8 | G38: 38 | H38: 1.34 | I38: =IF($F38=$I$6,$E38*$G38*$H38,"") | J38: =IF($F38=$J$6,$E38*$G38*$H38,"") | K38: =IF($F38=$K$6,$E38*$G38*$H38,"") -> 254.6 | L38: =IF($F38=$L$6,$E38*$G38*$H38,"") | M38: =IF($F38=$M$6,$E38*$G38*$H38,"") | N38: =IF($F38=$N$6,$E38*$G38*$H38,"") | O38: =IF($F38=$O$6,$E38*$G38*$H38,"")
B39: VC-2 | I39: =IF($F39=$I$6,$E39*$G39*$H39,"") | J39: =IF($F39=$J$6,$E39*$G39*$H39,"") | K39: =IF($F39=$K$6,$E39*$G39*$H39,"") | L39: =IF($F39=$L$6,$E39*$G39*$H39,"") | M39: =IF($F39=$M$6,$E39*$G39*$H39,"") | N39: =IF($F39=$N$6,$E39*$G39*$H39,"") | O39: =IF($F39=$O$6,$E39*$G39*$H39,"")
B40: ACE. SUPERIOR | D40: KG | E40: 2 | F40: 3/4 | G40: 5 | H40: 5.44 | I40: =IF($F40=$I$6,$E40*$G40*$H40,"") | J40: =IF($F40=$J$6,$E40*$G40*$H40,"") | K40: =IF($F40=$K$6,$E40*$G40*$H40,"") | L40: =IF($F40=$L$6,$E40*$G40*$H40,"") | M40: =IF($F40=$M$6,$E40*$G40*$H40,"") | N40: =IF($F40=$N$6,$E40*$G40*$H40,"") -> 54.4 | O40: =IF($F40=$O$6,$E40*$G40*$H40,"")
B41: ACE. INFERIOR | D41: KG | E41: 2 | F41: 3/4 | G41: 4 | H41: 5.44 | I41: =IF($F41=$I$6,$E41*$G41*$H41,"") | J41: =IF($F41=$J$6,$E41*$G41*$H41,"") | K41: =IF($F41=$K$6,$E41*$G41*$H41,"") | L41: =IF($F41=$L$6,$E41*$G41*$H41,"") | M41: =IF($F41=$M$6,$E41*$G41*$H41,"") | N41: =IF($F41=$N$6,$E41*$G41*$H41,"") -> 43.52 | O41: =IF($F41=$O$6,$E41*$G41*$H41,"")
B42: ESTRIBOS | D42: KG | E42: 2 | F42: 3/8 | G42: 34 | H42: 1.68 | I42: =IF($F42=$I$6,$E42*$G42*$H42,"") | J42: =IF($F42=$J$6,$E42*$G42*$H42,"") | K42: =IF($F42=$K$6,$E42*$G42*$H42,"") -> 114.24 | L42: =IF($F42=$L$6,$E42*$G42*$H42,"") | M42: =IF($F42=$M$6,$E42*$G42*$H42,"") | N42: =IF($F42=$N$6,$E42*$G42*$H42,"") | O42: =IF($F42=$O$6,$E42*$G42*$H42,"")
I43: =IF($F43=$I$6,$E43*$G43*$H43,"") | J43: =IF($F43=$J$6,$E43*$G43*$H43,"") | K43: =IF($F43=$K$6,$E43*$G43*$H43,"") | L43: =IF($F43=$L$6,$E43*$G43*$H43,"") | M43: =IF($F43=$M$6,$E43*$G43*$H43,"") | N43: =IF($F43=$N$6,$E43*$G43*$H43,"") | O43: =IF($F43=$O$6,$E43*$G43*$H43,"")
G44: LONGITUD TOTAL | I44: =SUM(I35:I43) -> 0 | J44: =SUM(J35:J43) -> 0 | K44: =SUM(K35:K43) -> 368.84 | L44: =SUM(L35:L43) -> 0 | M44: =SUM(M35:M43) -> 0 | N44: =SUM(N35:N43) -> 288.32 | O44: =SUM(O35:O43) -> 0
G45: PESO UNITARIO | I45: 0.25 | J45: 3.97 | K45: 0.56 | L45: 1.02 | M45: 1.56 | N45: 2.25 | O45: 0.395
G46: PESO TOTAL | I46: =I44*I45 -> 0 | J46: =J44*J45 -> 0 | K46: =K44*K45 -> 206.5504 | L46: =L44*L45 -> 0 | M46: =M44*M45 -> 0 | N46: =N44*N45 -> 648.72 | O46: =O44*O45 -> 0
G47: # DE VARILLA | I47: =ROUNDUP(I44*1.07/9,0) -> 0 | J47: =ROUNDUP(J44*1.07/9,0) -> 0 | K47: =ROUNDUP(K44*1.07/9,0) -> 44 | L47: =ROUNDUP(L44*1.07/9,0) -> 0 | M47: =ROUNDUP(M44*1.07/9,0) -> 0 | N47: =ROUNDUP(N44*1.07/9,0) -> 35 | O47: =ROUNDUP(O44*1.07/9,0) -> 0
A48: 01.01.00 | B48: ACERO ASTM f'y = 4200 kg/cm2 EN CISTERNA CONSUMO DIARIO | P48: =SUM(I69:O69) -> 348.8564
B49: BASE | I49: =IF($F49=$I$6,$E49*$G49*$H49,"") | J49: =IF($F49=$J$6,$E49*$G49*$H49,"") | K49: =IF($F49=$K$6,$E49*$G49*$H49,"") | L49: =IF($F49=$L$6,$E49*$G49*$H49,"") | M49: =IF($F49=$M$6,$E49*$G49*$H49,"")
B50: ACE. SUPERIOR E INFERIOR EJE X | D50: KG | E50: 2 | F50: 3/8 | G50: 12 | H50: 2.27 | I50: =IF($F50=$I$6,$E50*$G50*$H50,"") | J50: =IF($F50=$J$6,$E50*$G50*$H50,"") | K50: =IF($F50=$K$6,$E50*$G50*$H50,"") -> 54.48 | L50: =IF($F50=$L$6,$E50*$G50*$H50,"") | M50: =IF($F50=$M$6,$E50*$G50*$H50,"")
B51: ACE. SUPERIOR E INFERIOR EJE Y | D51: KG | E51: 2 | F51: 3/8 | G51: 10 | H51: 2.65 | I51: =IF($F51=$I$6,$E51*$G51*$H51,"") | J51: =IF($F51=$J$6,$E51*$G51*$H51,"") | K51: =IF($F51=$K$6,$E51*$G51*$H51,"") -> 53 | L51: =IF($F51=$L$6,$E51*$G51*$H51,"") | M51: =IF($F51=$M$6,$E51*$G51*$H51,"")
B52: PARED EJE Y | I52: =IF($F52=$I$6,$E52*$G52*$H52,"") | J52: =IF($F52=$J$6,$E52*$G52*$H52,"") | K52: =IF($F52=$K$6,$E52*$G52*$H52,"") | L52: =IF($F52=$L$6,$E52*$G52*$H52,"") | M52: =IF($F52=$M$6,$E52*$G52*$H52,"")
B53: ACE. VERTICAL | D53: KG | E53: 2 | F53: 3/8 | G53: =2*12 -> 24 | H53: 2.76 | I53: =IF($F53=$I$6,$E53*$G53*$H53,"") | J53: =IF($F53=$J$6,$E53*$G53*$H53,"") | K53: =IF($F53=$K$6,$E53*$G53*$H53,"") -> 132.48 | L53: =IF($F53=$L$6,$E53*$G53*$H53,"") | M53: =IF($F53=$M$6,$E53*$G53*$H53,"")
B54: ACE. HORIZONTAL | D54: KG | E54: 2 | F54: 3/8 | G54: =2*8 -> 16 | H54: 2.65 | I54: =IF($F54=$I$6,$E54*$G54*$H54,"") | J54: =IF($F54=$J$6,$E54*$G54*$H54,"") | K54: =IF($F54=$K$6,$E54*$G54*$H54,"") -> 84.8 | L54: =IF($F54=$L$6,$E54*$G54*$H54,"") | M54: =IF($F54=$M$6,$E54*$G54*$H54,"")
B55: PARED EJE X | I55: =IF($F55=$I$6,$E55*$G55*$H55,"") | J55: =IF($F55=$J$6,$E55*$G55*$H55,"") | K55: =IF($F55=$K$6,$E55*$G55*$H55,"") | L55: =IF($F55=$L$6,$E55*$G55*$H55,"") | M55: =IF($F55=$M$6,$E55*$G55*$H55,"")
B56: ACE. VERTICAL | D56: KG | E56: 2 | F56: 3/8 | G56: =2*10 -> 20 | H56: 2.76 | I56: =IF($F56=$I$6,$E56*$G56*$H56,"") | J56: =IF($F56=$J$6,$E56*$G56*$H56,"") | K56: =IF($F56=$K$6,$E56*$G56*$H56,"") -> 110.4 | L56: =IF($F56=$L$6,$E56*$G56*$H56,"") | M56: =IF($F56=$M$6,$E56*$G56*$H56,"")
B57: ACE. HORIZONTAL | D57: KG | E57: 2 | F57: 3/8 | G57: =2*8 -> 16 | H57: 2.27 | I57: =IF($F57=$I$6,$E57*$G57*$H57,"") | J57: =IF($F57=$J$6,$E57*$G57*$H57,"") | K57: =IF($F57=$K$6,$E57*$G57*$H57,"") -> 72.64 | L57: =IF($F57=$L$6,$E57*$G57*$H57,"") | M57: =IF($F57=$M$6,$E57*$G57*$H57,"")
B58: TECHO | I58: =IF($F58=$I$6,$E58*$G58*$H58,"") | J58: =IF($F58=$J$6,$E58*$G58*$H58,"") | K58: =IF($F58=$K$6,$E58*$G58*$H58,"") | L58: =IF($F58=$L$6,$E58*$G58*$H58,"") | M58: =IF($F58=$M$6,$E58*$G58*$H58,"")
B59: ACE. SUPERIOR E INFERIOR EJE X | D59: KG | E59: 2 | F59: 3/8 | G59: 11 | H59: 2.27 | I59: =IF($F59=$I$6,$E59*$G59*$H59,"") | J59: =IF($F59=$J$6,$E59*$G59*$H59,"") | K59: =IF($F59=$K$6,$E59*$G59*$H59,"") -> 49.94 | L59: =IF($F59=$L$6,$E59*$G59*$H59,"") | M59: =IF($F59=$M$6,$E59*$G59*$H59,"")
B60: ACE. SUPERIOR E INFERIOR EJE Y | D60: KG | E60: 2 | F60: 3/8 | G60: 9 | H60: 2.65 | I60: =IF($F60=$I$6,$E60*$G60*$H60,"") | J60: =IF($F60=$J$6,$E60*$G60*$H60,"") | K60: =IF($F60=$K$6,$E60*$G60*$H60,"") -> 47.7 | L60: =IF($F60=$L$6,$E60*$G60*$H60,"") | M60: =IF($F60=$M$6,$E60*$G60*$H60,"")
B61: CONTORNO TAPA | I61: =IF($F61=$I$6,$E61*$G61*$H61,"") | J61: =IF($F61=$J$6,$E61*$G61*$H61,"") | K61: =IF($F61=$K$6,$E61*$G61*$H61,"") | L61: =IF($F61=$L$6,$E61*$G61*$H61,"") | M61: =IF($F61=$M$6,$E61*$G61*$H61,"")
B62: ACE.HORIZONTAL | D62: KG | E62: 4 | F62: 3/8 | G62: 2 | H62: 1.32 | I62: =IF($F62=$I$6,$E62*$G62*$H62,"") | J62: =IF($F62=$J$6,$E62*$G62*$H62,"") | K62: =IF($F62=$K$6,$E62*$G62*$H62,"") -> 10.56 | L62: =IF($F62=$L$6,$E62*$G62*$H62,"") | M62: =IF($F62=$M$6,$E62*$G62*$H62,"")
B63: TAPA | I63: =IF($F63=$I$6,$E63*$G63*$H63,"") | J63: =IF($F63=$J$6,$E63*$G63*$H63,"") | K63: =IF($F63=$K$6,$E63*$G63*$H63,"") | L63: =IF($F63=$L$6,$E63*$G63*$H63,"") | M63: =IF($F63=$M$6,$E63*$G63*$H63,"")
B64: EJE X | D64: KG | E64: 1 | F64: 1/2 | G64: 2 | H64: 1.21 | I64: =IF($F64=$I$6,$E64*$G64*$H64,"") | J64: =IF($F64=$J$6,$E64*$G64*$H64,"") | K64: =IF($F64=$K$6,$E64*$G64*$H64,"") | L64: =IF($F64=$L$6,$E64*$G64*$H64,"") -> 2.42 | M64: =IF($F64=$M$6,$E64*$G64*$H64,"")
B65: EJE Y | D65: KG | E65: 1 | F65: 1/2 | G65: 1 | H65: 1.4 | I65: =IF($F65=$I$6,$E65*$G65*$H65,"") | J65: =IF($F65=$J$6,$E65*$G65*$H65,"") | K65: =IF($F65=$K$6,$E65*$G65*$H65,"") | L65: =IF($F65=$L$6,$E65*$G65*$H65,"") -> 1.4 | M65: =IF($F65=$M$6,$E65*$G65*$H65,"")
I66: =IF($F66=$I$6,$E66*$G66*$H66,"") | J66: =IF($F66=$J$6,$E66*$G66*$H66,"") | K66: =IF($F66=$K$6,$E66*$G66*$H66,"") | L66: =IF($F66=$L$6,$E66*$G66*$H66,"") | M66: =IF($F66=$M$6,$E66*$G66*$H66,"")
G67: LONGITUD TOTAL | I67: =SUM(I49:I66) -> 0 | J67: =SUM(J49:J66) -> 0 | K67: =SUM(K49:K66) -> 616 | L67: =SUM(L49:L66) -> 3.82 | M67: =SUM(M49:M66) -> 0 | N67: =SUM(N49:N66) -> 0
G68: PESO UNITARIO | I68: 0.25 | J68: 3.97 | K68: 0.56 | L68: 1.02 | M68: 1.56 | N68: 2.25
G69: PESO TOTAL | I69: =I67*I68 -> 0 | J69: =J67*J68 -> 0 | K69: =K67*K68 -> 344.96 | L69: =L67*L68 -> 3.8964 | M69: =M67*M68 -> 0 | N69: =N67*N68 -> 0
G70: # DE VARILLA | I70: =ROUNDUP(I67*1.07/9,0) -> 0 | J70: =ROUNDUP(J67*1.07/9,0) -> 0 | K70: =ROUNDUP(K67*1.07/9,0) -> 74 | L70: =ROUNDUP(L67*1.07/9,0) -> 1 | M70: =ROUNDUP(M67*1.07/9,0) -> 0 | N70: =ROUNDUP(N67*1.07/9,0) -> 0
A71: 01.01.00 | B71: ACERO ASTM f'y = 4200 kg/cm2 EN COLUMNAS | P71: =SUM(I93:O93) -> 1776.6098
B72: COLUMNA C-1 | I72: =IF($F72=$I$6,$E72*$G72*$H72,"") | J72: =IF($F72=$J$6,$E72*$G72*$H72,"") | K72: =IF($F72=$K$6,$E72*$G72*$H72,"") | L72: =IF($F72=$L$6,$E72*$G72*$H72,"") | M72: =IF($F72=$M$6,$E72*$G72*$H72,"") | N72: =IF($F72=$N$6,$E72*$G72*$H72,"") | O72: =IF($F72=$O$6,$E72*$G72*$H72,"")
B73: ACE. VERTICAL | D73: KG | E73: 3 | F73: 5/8 | G73: 8 | H73: 9 | I73: =IF($F73=$I$6,$E73*$G73*$H73,"") | J73: =IF($F73=$J$6,$E73*$G73*$H73,"") | K73: =IF($F73=$K$6,$E73*$G73*$H73,"") | L73: =IF($F73=$L$6,$E73*$G73*$H73,"") | M73: =IF($F73=$M$6,$E73*$G73*$H73,"") -> 216 | N73: =IF($F73=$N$6,$E73*$G73*$H73,"") | O73: =IF($F73=$O$6,$E73*$G73*$H73,"")
B74: ESTRIBOS | D74: KG | E74: 3 | F74: 3/8 | G74: 35 | H74: =2*1.54 -> 3.08 | I74: =IF($F74=$I$6,$E74*$G74*$H74,"") | J74: =IF($F74=$J$6,$E74*$G74*$H74,"") | K74: =IF($F74=$K$6,$E74*$G74*$H74,"") -> 323.4 | L74: =IF($F74=$L$6,$E74*$G74*$H74,"") | M74: =IF($F74=$M$6,$E74*$G74*$H74,"") | N74: =IF($F74=$N$6,$E74*$G74*$H74,"") | O74: =IF($F74=$O$6,$E74*$G74*$H74,"")
B75: COLUMNA C-2 | I75: =IF($F75=$I$6,$E75*$G75*$H75,"") | J75: =IF($F75=$J$6,$E75*$G75*$H75,"") | K75: =IF($F75=$K$6,$E75*$G75*$H75,"") | L75: =IF($F75=$L$6,$E75*$G75*$H75,"") | M75: =IF($F75=$M$6,$E75*$G75*$H75,"") | N75: =IF($F75=$N$6,$E75*$G75*$H75,"") | O75: =IF($F75=$O$6,$E75*$G75*$H75,"")
B76: ACE. VERTICAL | D76: KG | E76: 1 | F76: 5/8 | G76: 12 | H76: 9 | I76: =IF($F76=$I$6,$E76*$G76*$H76,"") | J76: =IF($F76=$J$6,$E76*$G76*$H76,"") | K76: =IF($F76=$K$6,$E76*$G76*$H76,"") | L76: =IF($F76=$L$6,$E76*$G76*$H76,"") | M76: =IF($F76=$M$6,$E76*$G76*$H76,"") -> 108 | N76: =IF($F76=$N$6,$E76*$G76*$H76,"") | O76: =IF($F76=$O$6,$E76*$G76*$H76,"")
B77: ESTRIBOS | D77: KG | E77: 1 | F77: 3/8 | G77: 33 | H77: =2*1.74 -> 3.48 | I77: =IF($F77=$I$6,$E77*$G77*$H77,"") | J77: =IF($F77=$J$6,$E77*$G77*$H77,"") | K77: =IF($F77=$K$6,$E77*$G77*$H77,"") -> 114.84 | L77: =IF($F77=$L$6,$E77*$G77*$H77,"") | M77: =IF($F77=$M$6,$E77*$G77*$H77,"") | N77: =IF($F77=$N$6,$E77*$G77*$H77,"") | O77: =IF($F77=$O$6,$E77*$G77*$H77,"")
B78: COLUMNA C-3 | I78: =IF($F78=$I$6,$E78*$G78*$H78,"") | J78: =IF($F78=$J$6,$E78*$G78*$H78,"") | K78: =IF($F78=$K$6,$E78*$G78*$H78,"") | L78: =IF($F78=$L$6,$E78*$G78*$H78,"") | M78: =IF($F78=$M$6,$E78*$G78*$H78,"") | N78: =IF($F78=$N$6,$E78*$G78*$H78,"") | O78: =IF($F78=$O$6,$E78*$G78*$H78,"")
B79: ACE. VERTICAL | D79: KG | E79: 2 | F79: 5/8 | G79: 12 | H79: 9 | I79: =IF($F79=$I$6,$E79*$G79*$H79,"") | J79: =IF($F79=$J$6,$E79*$G79*$H79,"") | K79: =IF($F79=$K$6,$E79*$G79*$H79,"") | L79: =IF($F79=$L$6,$E79*$G79*$H79,"") | M79: =IF($F79=$M$6,$E79*$G79*$H79,"") -> 216 | N79: =IF($F79=$N$6,$E79*$G79*$H79,"") | O79: =IF($F79=$O$6,$E79*$G79*$H79,"")
B80: ESTRIBOS | D80: KG | E80: 2 | F80: 3/8 | G80: 35 | H80: =2*1.44 -> 2.88 | I80: =IF($F80=$I$6,$E80*$G80*$H80,"") | J80: =IF($F80=$J$6,$E80*$G80*$H80,"") | K80: =IF($F80=$K$6,$E80*$G80*$H80,"") -> 201.6 | L80: =IF($F80=$L$6,$E80*$G80*$H80,"") | M80: =IF($F80=$M$6,$E80*$G80*$H80,"") | N80: =IF($F80=$N$6,$E80*$G80*$H80,"") | O80: =IF($F80=$O$6,$E80*$G80*$H80,"")
B81: COLUMNA C-4 | I81: =IF($F81=$I$6,$E81*$G81*$H81,"") | J81: =IF($F81=$J$6,$E81*$G81*$H81,"") | K81: =IF($F81=$K$6,$E81*$G81*$H81,"") | L81: =IF($F81=$L$6,$E81*$G81*$H81,"") | M81: =IF($F81=$M$6,$E81*$G81*$H81,"") | N81: =IF($F81=$N$6,$E81*$G81*$H81,"") | O81: =IF($F81=$O$6,$E81*$G81*$H81,"")
B82: ACE. VERTICAL | D82: KG | E82: 1 | F82: 5/8 | G82: 12 | H82: 9 | I82: =IF($F82=$I$6,$E82*$G82*$H82,"") | J82: =IF($F82=$J$6,$E82*$G82*$H82,"") | K82: =IF($F82=$K$6,$E82*$G82*$H82,"") | L82: =IF($F82=$L$6,$E82*$G82*$H82,"") | M82: =IF($F82=$M$6,$E82*$G82*$H82,"") -> 108 | N82: =IF($F82=$N$6,$E82*$G82*$H82,"") | O82: =IF($F82=$O$6,$E82*$G82*$H82,"")
B83: ESTRIBOS | D83: KG | E83: 1 | F83: 3/8 | G83: 33 | H83: =2*1.94 -> 3.88 | I83: =IF($F83=$I$6,$E83*$G83*$H83,"") | J83: =IF($F83=$J$6,$E83*$G83*$H83,"") | K83: =IF($F83=$K$6,$E83*$G83*$H83,"") -> 128.04 | L83: =IF($F83=$L$6,$E83*$G83*$H83,"") | M83: =IF($F83=$M$6,$E83*$G83*$H83,"") | N83: =IF($F83=$N$6,$E83*$G83*$H83,"") | O83: =IF($F83=$O$6,$E83*$G83*$H83,"")
B84: COLUMNETA Ca | I84: =IF($F84=$I$6,$E84*$G84*$H84,"") | J84: =IF($F84=$J$6,$E84*$G84*$H84,"") | K84: =IF($F84=$K$6,$E84*$G84*$H84,"") | L84: =IF($F84=$L$6,$E84*$G84*$H84,"") | M84: =IF($F84=$M$6,$E84*$G84*$H84,"") | N84: =IF($F84=$N$6,$E84*$G84*$H84,"") | O84: =IF($F84=$O$6,$E84*$G84*$H84,"")
B85: ACE. VERTICAL | D85: KG | E85: 7 | F85: 1/2 | G85: 4 | H85: 4.8 | I85: =IF($F85=$I$6,$E85*$G85*$H85,"") | J85: =IF($F85=$J$6,$E85*$G85*$H85,"") | K85: =IF($F85=$K$6,$E85*$G85*$H85,"") | L85: =IF($F85=$L$6,$E85*$G85*$H85,"") -> 134.4 | M85: =IF($F85=$M$6,$E85*$G85*$H85,"") | N85: =IF($F85=$N$6,$E85*$G85*$H85,"") | O85: =IF($F85=$O$6,$E85*$G85*$H85,"")
B86: ESTRIBOS | D86: KG | E86: 7 | F86: 6mm | G86: 25 | H86: 0.86 | I86: =IF($F86=$I$6,$E86*$G86*$H86,"") -> 150.5 | J86: =IF($F86=$J$6,$E86*$G86*$H86,"") | K86: =IF($F86=$K$6,$E86*$G86*$H86,"") | L86: =IF($F86=$L$6,$E86*$G86*$H86,"") | M86: =IF($F86=$M$6,$E86*$G86*$H86,"") | N86: =IF($F86=$N$6,$E86*$G86*$H86,"") | O86: =IF($F86=$O$6,$E86*$G86*$H86,"")
B87: COLUMNETA Cb | I87: =IF($F87=$I$6,$E87*$G87*$H87,"") | J87: =IF($F87=$J$6,$E87*$G87*$H87,"") | K87: =IF($F87=$K$6,$E87*$G87*$H87,"") | L87: =IF($F87=$L$6,$E87*$G87*$H87,"") | M87: =IF($F87=$M$6,$E87*$G87*$H87,"") | N87: =IF($F87=$N$6,$E87*$G87*$H87,"") | O87: =IF($F87=$O$6,$E87*$G87*$H87,"")
B88: ACE. VERTICAL | D88: KG | E88: 6 | F88: 1/2 | G88: 4 | H88: 4.8 | I88: =IF($F88=$I$6,$E88*$G88*$H88,"") | J88: =IF($F88=$J$6,$E88*$G88*$H88,"") | K88: =IF($F88=$K$6,$E88*$G88*$H88,"") | L88: =IF($F88=$L$6,$E88*$G88*$H88,"") -> 115.2 | M88: =IF($F88=$M$6,$E88*$G88*$H88,"") | N88: =IF($F88=$N$6,$E88*$G88*$H88,"") | O88: =IF($F88=$O$6,$E88*$G88*$H88,"")
B89: ESTRIBOS | D89: KG | E89: 6 | F89: 6mm | G89: 25 | H89: 1.16 | I89: =IF($F89=$I$6,$E89*$G89*$H89,"") -> 174 | J89: =IF($F89=$J$6,$E89*$G89*$H89,"") | K89: =IF($F89=$K$6,$E89*$G89*$H89,"") | L89: =IF($F89=$L$6,$E89*$G89*$H89,"") | M89: =IF($F89=$M$6,$E89*$G89*$H89,"") | N89: =IF($F89=$N$6,$E89*$G89*$H89,"") | O89: =IF($F89=$O$6,$E89*$G89*$H89,"")
I90: =IF($F90=$I$6,$E90*$G90*$H90,"") | J90: =IF($F90=$J$6,$E90*$G90*$H90,"") | K90: =IF($F90=$K$6,$E90*$G90*$H90,"") | L90: =IF($F90=$L$6,$E90*$G90*$H90,"") | M90: =IF($F90=$M$6,$E90*$G90*$H90,"") | N90: =IF($F90=$N$6,$E90*$G90*$H90,"") | O90: =IF($F90=$O$6,$E90*$G90*$H90,"")
I91: =SUM(I72:I90) -> 324.5 | J91: =SUM(J72:J90) -> 0 | K91: =SUM(K72:K90) -> 767.88 | L91: =SUM(L72:L90) -> 249.6 | M91: =SUM(M72:M90) -> 648 | N91: =SUM(N72:N90) -> 0 | O91: =SUM(O72:O90) -> 0
G92: PESO UNITARIO | I92: 0.25 | J92: 3.97 | K92: 0.56 | L92: 1.02 | M92: 1.56 | N92: 2.25 | O92: 0.395
G93: PESO TOTAL | I93: =I91*I92 -> 81.125 | J93: =J91*J92 -> 0 | K93: =K91*K92 -> 430.0128 | L93: =L91*L92 -> 254.592 | M93: =M91*M92 -> 1010.88 | N93: =N91*N92 -> 0 | O93: =O91*O92 -> 0
G94: # DE VARILLA | I94: =ROUNDUP(I91*1.07/9,0) -> 39 | J94: =ROUNDUP(J91*1.07/9,0) -> 0 | K94: =ROUNDUP(K91*1.07/9,0) -> 92 | L94: =ROUNDUP(L91*1.07/9,0) -> 30 | M94: =ROUNDUP(M91*1.07/9,0) -> 78 | N94: =ROUNDUP(N91*1.07/9,0) -> 0 | O94: =ROUNDUP(O91*1.07/9,0) -> 0
A95: 01.01.00 | B95: ACERO ASTM f'y = 4200 kg/cm2 EN PLACAS | P95: =SUM(I144:O144) -> 2969.228
B96: PLACA PL-1 | I96: =IF($F96=$I$6,$E96*$G96*$H96,"") | J96: =IF($F96=$J$6,$E96*$G96*$H96,"") | K96: =IF($F96=$K$6,$E96*$G96*$H96,"") | L96: =IF($F96=$L$6,$E96*$G96*$H96,"") | M96: =IF($F96=$M$6,$E96*$G96*$H96,"") | N96: =IF($F96=$N$6,$E96*$G96*$H96,"") | O96: =IF($F96=$O$6,$E96*$G96*$H96,"")
B97: ACE. VERTICAL | D97: KG | E97: 1 | F97: 3/8 | G97: 18 | H97: 9 | I97: =IF($F97=$I$6,$E97*$G97*$H97,"") | J97: =IF($F97=$J$6,$E97*$G97*$H97,"") | K97: =IF($F97=$K$6,$E97*$G97*$H97,"") -> 162 | L97: =IF($F97=$L$6,$E97*$G97*$H97,"") | M97: =IF($F97=$M$6,$E97*$G97*$H97,"") | N97: =IF($F97=$N$6,$E97*$G97*$H97,"") | O97: =IF($F97=$O$6,$E97*$G97*$H97,"")
B98: ACE. HORIZONTAL | D98: KG | E98: 1 | F98: 3/8 | G98: 27 | H98: 4.42 | I98: =IF($F98=$I$6,$E98*$G98*$H98,"") | J98: =IF($F98=$J$6,$E98*$G98*$H98,"") | K98: =IF($F98=$K$6,$E98*$G98*$H98,"") -> 119.34 | L98: =IF($F98=$L$6,$E98*$G98*$H98,"") | M98: =IF($F98=$M$6,$E98*$G98*$H98,"") | N98: =IF($F98=$N$6,$E98*$G98*$H98,"") | O98: =IF($F98=$O$6,$E98*$G98*$H98,"")
B99: N-1 | I99: =IF($F99=$I$6,$E99*$G99*$H99,"") | J99: =IF($F99=$J$6,$E99*$G99*$H99,"") | K99: =IF($F99=$K$6,$E99*$G99*$H99,"") | L99: =IF($F99=$L$6,$E99*$G99*$H99,"") | M99: =IF($F99=$M$6,$E99*$G99*$H99,"") | N99: =IF($F99=$N$6,$E99*$G99*$H99,"") | O99: =IF($F99=$O$6,$E99*$G99*$H99,"")
B100: ACE. VERTICAL | D100: KG | E100: 2 | F100: 5/8 | G100: 12 | H100: 9 | I100: =IF($F100=$I$6,$E100*$G100*$H100,"") | J100: =IF($F100=$J$6,$E100*$G100*$H100,"") | K100: =IF($F100=$K$6,$E100*$G100*$H100,"") | L100: =IF($F100=$L$6,$E100*$G100*$H100,"") | M100: =IF($F100=$M$6,$E100*$G100*$H100,"") -> 216 | N100: =IF($F100=$N$6,$E100*$G100*$H100,"") | O100: =IF($F100=$O$6,$E100*$G100*$H100,"")
...

Sheet O. HUMEDAD
A2: =Valorización!A2 -> PROYECTO: | B2: =Valorización!B2 -> 0
A3: =Valorización!A3 -> PROPIETARIO(S) : | B3: =Valorización!B3 -> 0
A4: =Valorización!A4 -> UBICACIÓN: | B4: LT 18 MZ DDF, JR. ALAMEDA EL ESPINEL, URB BRISAS DEL MAR - DISTRITO CHORRILLOS, DEPARTAMENTO Y PROVINCIA DE LIMA
A5: PARTIDA | B5: DESCRIPCION | D5: und | E5: CANT | F5: MEDIDAS | I5: PARCIAL
F6: LARGO | G6: ANCHO | H6: ALTO
A7: 03.00.00.00 | B7: TABIQUERIA Y OBRAS HÚMEDAS
A8: 03.00.00.00 | B8: 1ER PISO
A9: 03.01.01.00 | B9: TABIQUE DE LADRILLO
A10: 03.03.01.01 | B10: MURO DE LADRILLO SOGA PANDERETA | D10: M2 | J10: =SUM(I11:I23) -> 92.25
B11: MURO 1 | D11: m2 | E11: 1 | F11: 2.2 | H11: 3 | I11: =PRODUCT(E11:H11) -> 6.6
B12: MURO 2 | D12: m2 | E12: 1 | F12: 3.95 | H12: 3 | I12: =PRODUCT(E12:H12) -> 11.85
B13: MURO 3 | D13: m2 | E13: 1 | F13: 2.2 | H13: 3 | I13: =PRODUCT(E13:H13) -> 6.6
B14: MURO 4 | D14: m2 | E14: 1 | F14: 1.8 | H14: 3 | I14: =PRODUCT(E14:H14) -> 5.4
B15: MURO 5 | D15: m2 | E15: 1 | F15: 1.2 | H15: 3 | I15: =PRODUCT(E15:H15) -> 3.6
B16: MURO 6 | D16: m2 | E16: 1 | F16: 0.65 | H16: 3 | I16: =PRODUCT(E16:H16) -> 1.95
B17: MURO 7 | D17: m2 | E17: 1 | F17: 2.4 | H17: 3 | I17: =PRODUCT(E17:H17) -> 7.2
B18: MURO 8 | D18: m2 | E18: 1 | F18: 2.95 | H18: 3 | I18: =PRODUCT(E18:H18) -> 8.85
B19: MURO 9 | D19: m2 | E19: 1 | F19: 3.2 | H19: 3 | I19: =PRODUCT(E19:H19) -> 9.6
B20: MURO 10 | D20: m2 | E20: 1 | F20: 5.45 | H20: 3 | I20: =PRODUCT(E20:H20) -> 16.35
B21: MURO 11 | D21: m2 | E21: 1 | F21: 1.25 | H21: 3 | I21: =PRODUCT(E21:H21) -> 3.75
B22: MURO 12 | D22: m2 | E22: 1 | F22: 3.5 | H22: 3 | I22: =PRODUCT(E22:H22) -> 10.5
A24: 03.03.01.01 | B24: COLUMNETAS | D24: UND | J24: =SUM(I25:I25) -> 12
B25: Ca | D25: UND | E25: 12 | I25: =PRODUCT(E25:H25) -> 12
A27: 02.03.02.00 | B27: REVESTIMIENTOS Y ENLUCIDOS
A28: 02.03.02.01 | B28: TARRAJEO EN INTERIORES FROTACHADO | D28: M2 | J28: =SUM(I29:I41) -> 184.5
B29: MURO 1 | D29: m2 | E29: 2 | F29: 2.2 | H29: 3 | I29: =PRODUCT(E29:H29) -> 13.2
B30: MURO 2 | D30: m2 | E30: 2 | F30: 3.95 | H30: 3 | I30: =PRODUCT(E30:H30) -> 23.7
B31: MURO 3 | D31: m2 | E31: 2 | F31: 2.2 | H31: 3 | I31: =PRODUCT(E31:H31) -> 13.2
B32: MURO 4 | D32: m2 | E32: 2 | F32: 1.8 | H32: 3 | I32: =PRODUCT(E32:H32) -> 10.8
B33: MURO 5 | D33: m2 | E33: 2 | F33: 1.2 | H33: 3 | I33: =PRODUCT(E33:H33) -> 7.2
B34: MURO 6 | D34: m2 | E34: 2 | F34: 0.65 | H34: 3 | I34: =PRODUCT(E34:H34) -> 3.9
B35: MURO 7 | D35: m2 | E35: 2 | F35: 2.4 | H35: 3 | I35: =PRODUCT(E35:H35) -> 14.4
B36: MURO 8 | D36: m2 | E36: 2 | F36: 2.95 | H36: 3 | I36: =PRODUCT(E36:H36) -> 17.7
B37: MURO 9 | D37: m2 | E37: 2 | F37: 3.2 | H37: 3 | I37: =PRODUCT(E37:H37) -> 19.2
B38: MURO 10 | D38: m2 | E38: 2 | F38: 5.45 | H38: 3 | I38: =PRODUCT(E38:H38) -> 32.7
B39: MURO 11 | D39: m2 | E39: 2 | F39: 1.25 | H39: 3 | I39: =PRODUCT(E39:H39) -> 7.5
B40: MURO 12 | D40: m2 | E40: 2 | F40: 3.5 | H40: 3 | I40: =PRODUCT(E40:H40) -> 21
A42: 02.03.02.04 | B42: TARRAJEO EN COLUMNAS Y PLACAS | D42: M2 | J42: =SUM(I43:I71) -> 96.752
B43: C-1 | D43: m2 | E43: 1 | F43: PERIM = | G43: 0.9 | H43: 3 | I43: =PRODUCT(E43:H43) -> 2.7
B44: C-2 | D44: m2 | E44: 1 | F44: PERIM = | G44: 1.15 | H44: 3 | I44: =PRODUCT(E44:H44) -> 3.45
B45: C-3 | D45: m2 | E45: 1 | F45: PERIM = | G45: 0.8 | H45: 3 | I45: =PRODUCT(E45:H45) -> 2.4
B46: C-4 | D46: m2 | E46: 1 | F46: PERIM = | G46: 0.9 | H46: 3 | I46: =PRODUCT(E46:H46) -> 2.7
B47: C-5 | D47: m2 | E47: 1 | F47: PERIM = | G47: 0.8 | H47: 3 | I47: =PRODUCT(E47:H47) -> 2.4
B48: C-6 | D48: m2 | E48: 1 | F48: PERIM = | G48: 0.9 | H48: 3 | I48: =PRODUCT(E48:H48) -> 2.7
B49: C-7 | D49: m2 | E49: 1 | F49: PERIM = | G49: 0.675 | H49: 3 | I49: =PRODUCT(E49:H49) -> 2.025
B51: Ca-1 | D51: m2 | E51: 1 | F51: PERIM = | G51: 0.25 | H51: 2.7 | I51: =PRODUCT(E51:H51) -> 0.675
B52: Ca-2 | D52: m2 | E52: 2 | F52: PERIM = | G52: 0.24 | H52: 2.7 | I52: =PRODUCT(E52:H52) -> 1.296
B53: Ca-3 | D53: m2 | E53: 1 | F53: PERIM = | G53: 0.63 | H53: 2.7 | I53: =PRODUCT(E53:H53) -> 1.701
B54: Ca-4 | D54: m2 | E54: 1 | F54: PERIM = | G54: 0.25 | H54: 2.8 | I54: =PRODUCT(E54:H54) -> 0.7
B55: Ca-5 | D55: m2 | E55: 1 | F55: PERIM = | G55: 0.25 | H55: 2.8 | I55: =PRODUCT(E55:H55) -> 0.7
... B70: PL-5 | D70: m2 | E70: 1 | F70: PERIM = | G70: 1.275 | H70: 3 | I70: =PRODUCT(E70:H70) -> 3.825
A72: 02.03.02.06 | B72: TARRAJEO EN VIGAS | D72: M2 | J72: =SUM(I73:I92) -> 33.5125
B73: V-1 | D73: m2 | E73: 1 | F73: 3.85 | H73: 0.55 | I73: =PRODUCT(E73:H73) -> 2.1175
B74: V-2 | D74: m2 | E74: 1 | F74: 4.05 | H74: 0.85 | I74: =PRODUCT(E74:H74) -> 3.4425
B75: V-3 | D75: m2 | E75: 1 | F75: 3.8 | H75: 0.2 | I75: =PRODUCT(E75:H75) -> 0.76
B76: V-4 | D76: m2 | E76: 1 | F76: 4.2 | H76: 0.6 | I76: =PRODUCT(E76:H76) -> 2.52
B77: V-5 | D77: m2 | E77: 1 | F77: 4.2 | H77: 0.2 | I77: =PRODUCT(E77:H77) -> 0.84
B78: V-6 | D78: m2 | E78: 1 | F78: 4.05 | H78: 0.85 | I78: =PRODUCT(E78:H78) -> 3.4425
B79: V-7 | D79: m2 | E79: 1 | F79: 4.3 | H79: 0.2 | I79: =PRODUCT(E79:H79) -> 0.86
B80: V-8 | D80: m2 | E80: 1 | F80: 4.7 | H80: 0.2 | I80: =PRODUCT(E80:H80) -> 0.94
B81: V-9 | D81: m2 | E81: 1 | F81: 3.15 | H81: 0.85 | I81: =PRODUCT(E81:H81) -> 2.6775
B82: V-10 | D82: m2 | E82: 1 | F82: 3.15 | H82: 0.85 | I82: =PRODUCT(E82:H82) -> 2.6775
B83: V-11 | D83: m2 | E83: 1 | F83: 6.15 | H83: 0.2 | I83: =PRODUCT(E83:H83) -> 1.23
B84: V-12 | D84: m2 | E84: 1 | F84: 6.4 | H84: 0.2 | I84: =PRODUCT(E84:H84) -> 1.28
... B91: V-19 | D91: m2 | E91: 1 | F91: 2.7 | H91: 0.3 | I91: =PRODUCT(E91:H91) -> 0.81
A93: 02.03.02.08 | B93: VESTIDURA DE DERRAMES | D93: M | J93: =SUM(I94:I99) -> 28.95
B94: D-2 | D94: m | E94: 1 | F94: PERIM = | G94: 7.4 | I94: =PRODUCT(E94:H94) -> 7.4
B95: D-3 | D95: m | E95: 1 | F95: PERIM = | G95: 6.75 | I95: =PRODUCT(E95:H95) -> 6.75
B96: D-4 | D96: m | E96: 1 | F96: PERIM = | G96: 6.2 | I96: =PRODUCT(E96:H96) -> 6.2
B97: D-5 | D97: m | E97: 1 | F97: PERIM = | G97: 6.7 | I97: =PRODUCT(E97:H97) -> 6.7
B98: D-6 | D98: m | E98: 1 | F98: PERIM = | G98: 1.9 | I98: =PRODUCT(E98:H98) -> 1.9
A100: 02.03.02.05 | B100: TARRAJEO EN CIELO RASO | D100: M2 | J100: =SUM(I101:I110) -> 121.545
B101: TH-1 | D101: m2 | E101: 1 | F101: AREA = | G101: 3.28 | I101: =PRODUCT(E101:H101) -> 3.28
B102: TH-2 | D102: m2 | E102: 1 | F102: AREA = | G102: 10.2175 | I102: =PRODUCT(E102:H102) -> 10.2175
B103: TH-3 | D103: m2 | E103: 1 | F103: AREA = | G103: 14.07 | I103: =PRODUCT(E103:H103) -> 14.07
B104: TH-4 | D104: m2 | E104: 1 | F104: AREA = | G104: 21.58 | I104: =PRODUCT(E104:H104) -> 21.58
B105: TH-5 | D105: m2 | E105: 1 | F105: AREA = | G105: 10.77 | I105: =PRODUCT(E105:H105) -> 10.77
B106: TH-6 | D106: m2 | E106: 1 | F106: AREA = | G106: 30.0525 | I106: =PRODUCT(E106:H106) -> 30.0525
B107: TH-7 | D107: m2 | E107: 1 | F107: AREA = | G107: 16.195 | I107: =PRODUCT(E107:H107) -> 16.195
B108: TH-8 | D108: m2 | E108: 1 | F108: AREA = | G108: 12.44 | I108: =PRODUCT(E108:H108) -> 12.44
B109: B-1 | D109: m2 | E109: 1 | F109: AREA = | G109: 2.94 | I109: =PRODUCT(E109:H109) -> 2.94
A111: 02.03.03.01 | B111: CONTRAPISO DE 48mm - TIPO CEMENTO PULIDO | D111: M2 | J111: =SUM(I112:I113) -> 132.19
B112: PAÑO 1 | D112: m2 | E112: 1 | F112: AREA = | G112: 132.19 | I112: =PRODUCT(E112:H112) -> 132.19
A114: 02.03.02.07 | B114: TARRAJEO DE ESCALERA | D114: M2 | J114: =SUM(I115:I123) -> 15.664
A115: TRAMO 1 | B115: GARGANTA | D115: m2 | E115: 1 | F115: 1.1 | G115: 2 | I115: =PRODUCT(E115:H115) -> 2.2
B116: PASOS | D116: m2 | E116: 7 | F116: 1.1 | G116: 0.25 | I116: =PRODUCT(E116:H116) -> 1.925
B117: CONTRAPASOS | D117: m2 | E117: 8 | F117: 1.1 | G117: 0.18 | I117: =PRODUCT(E117:H117) -> 1.584
A118: DESCANSO | B118: GARGANTA | D118: m2 | E118: 1 | F118: 1.1 | G118: 1 | I118: =PRODUCT(E118:H118) -> 1.1
B119: PISO SUPERIOR | D119: m2 | E119: 1 | F119: 1.1 | G119: 1 | I119: =PRODUCT(E119:H119) -> 1.1
A120: TRAMO 2 | B120: GARGANTA | D120: m2 | E120: 1 | F120: 1.1 | G120: 3 | I120: =PRODUCT(E120:H120) -> 3.3
B121: PASOS | D121: m2 | E121: 9 | F121: 1.1 | G121: 0.25 | I121: =PRODUCT(E121:H121) -> 2.475
B122: CONTRAPASOS | D122: m2 | E122: 10 | F122: 1.1 | G122: 0.18 | I122: =PRODUCT(E122:H122) -> 1.98
A124: 02.03.02.01 | B124: TARRAJEO EN EXTERIORES | D124: M2 | J124: =SUM(I125:I126) -> 1
D125: m2 | E125: 1 | I125: =PRODUCT(E125:H125) -> 1
A127: 03.00.00.00 | B127: 2DO PISO
A128: 03.01.01.00 | B128: TABIQUE DE LADRILLO
A129: 03.01.01.01 | B129: MURO DE LADRILLO SOGA KK 18 HUECOS | D129: M2 | J129: =SUM(I130:I153) -> 109.165
B130: MURO 1 | D130: m2 | E130: 1 | F130: 3.8 | H130: 2.4 | I130: =PRODUCT(E130:H130) -> 9.12
B131: MURO 2 | D131: m2 | E131: 1 | F131: 4.2 | H131: 2.4 | I131: =PRODUCT(E131:H131) -> 10.08
B132: MURO 3 | D132: m2 | E132: 1 | F132: 1.6 | H132: 2.4 | I132: =PRODUCT(E132:H132) -> 3.84
...

Sheet APUs Casco
A2: OBRAS PRELIMINARES
A3: TRANSPORTE DE EQUIPOS Y HERRAMIENTAS | E3: CU | F3: =F6+F8 -> 2000
A4: RENDIMIENTO | B4: 1 | C4: GLB/d | D4: JORNADA | E4: 8 | F4: horas/dia
A5: Descripción de Recurso | B5: Unidad | C5: Cuadrilla | D5: Cantidad | E5: Precio (S/.) | F5: Parcial (S/.)
A6: MANO DE OBRA | F6: =SUM(F7) -> 1800
A7: MANO DE OBRA- T | B7: GLB | D7: 1 | E7: 1800 | F7: =PRODUCT(D7:E7) -> 1800
A8: EQUIPOS | F8: =SUM(F9) -> 200
A9: HERRAMIENTA-T | B9: GLB | D9: 1 | E9: 200 | F9: =PRODUCT(D9:E9) -> 200
A11: LIMPIEZA DE TERRENO MANUAL | E11: CU | F11: =F14+F17 -> 7.3422222
A12: RENDIMIENTO | B12: 75 | C12: m2/d | D12: JORNADA | E12: 8 | F12: horas/dia
A13: Descripción de Recurso | B13: Unidad | C13: Cuadrilla | D13: Cantidad | E13: Precio (S/.) | F13: Parcial (S/.)
A14: MANO DE OBRA | F14: =SUM(F15:F16) -> 1.8355556
A15: CAPATAZ | B15: hh | C15: 0.1 | D15: =C15*$E$12/$B$12 -> 0.010666667 | E15: =VLOOKUP(A15,INSUMOS!$B$7:$D$42,3,0) -> 49.166667 | F15: =PRODUCT(D15:E15) -> 0.52444444
A16: PEON | B16: hh | C16: 1 | D16: =C16*$E$12/$B$12 -> 0.10666667 | E16: =VLOOKUP(A16,INSUMOS!$B$7:$D$42,3,0) -> 12.291667 | F16: =PRODUCT(D16:E16) -> 1.3111111
A17: EQUIPOS | F17: =SUM(F18) -> 5.5066667
A18: HERRAMIENTAS MANUALES | B18: %mo | D18: 3 | E18: =+F14 -> 1.8355556 | F18: =PRODUCT(D18:E18) -> 5.5066667
A20: TRAZADO Y REPLANTEO S/EQUIPO | E20: CU | F20: =F23+F27+F31 -> 9.9761117
A21: RENDIMIENTO | B21: 80 | C21: m2/d | D21: JORNADA | E21: 8 | F21: horas/dia
A22: Descripción de Recurso | B22: Unidad | C22: Cuadrilla | D22: Cantidad | E22: Precio (S/.) | F22: Parcial (S/.)
A23: MANO DE OBRA | F23: =SUM(F24:F26) -> 8.6981667
A24: CAPATAZ | B24: hh | C24: 0.1 | D24: =C24*$E$21/$B$21 -> 0.01 | E24: =VLOOKUP(A24,INSUMOS!$B$7:$D$42,3,0) -> 49.166667 | F24: =PRODUCT(D24:E24) -> 0.49166667
A25: OPERARIO | B25: hh | C25: 3 | D25: =C25*$E$21/$B$21 -> 0.3 | E25: =VLOOKUP(A25,INSUMOS!$B$7:$D$42,3,0) -> 27.041667 | F25: =PRODUCT(D25:E25) -> 8.1125
A26: MADERA TORNILLO | B26: p2 | D26: 0.02 | E26: 4.7 | F26: =PRODUCT(D26:E26) -> 0.094
A27: MATERIALES | F27: =SUM(F28:F30) -> 1.017
A28: CLAVOS CON CABEZA | B28: kg | D28: 0.01 | E28: 2.9 | F28: =PRODUCT(D28:E28) -> 0.029
A29: CAL (BOLSA x 20kg) | B29: bl | D29: 0.1 | E29: 9.5 | F29: =PRODUCT(D29:E29) -> 0.95
A30: CORDEL | B30: m | D30: 0.19 | E30: 0.2 | F30: =PRODUCT(D30:E30) -> 0.038
A31: EQUIPOS | F31: =SUM(F32) -> 0.260945
A32: HERRAMIENTAS MANUALES | B32: %mo | D32: 3 | E32: =F23 -> 8.6981667 | F32: =D32*E32/100 -> 0.260945
A34: TRAZADO Y REPLANTEO C/EQUIPO | E34: CU | F34: =F37+F41+F45 -> 15.196667
A35: RENDIMIENTO | B35: 50 | C35: m2/d | D35: JORNADA | E35: 8 | F35: horas/dia
A36: Descripción de Recurso | B36: Unidad | C36: Cuadrilla | D36: Cantidad | E36: Precio (S/.) | F36: Parcial (S/.)
A37: MANO DE OBRA | F37: =SUM(F38:F40) -> 13.766667
A38: CAPATAZ | B38: hh | C38: 0.1 | D38: =C38*$E$35/$B$35 -> 0.016 | E38: =VLOOKUP(A38,INSUMOS!$B$7:$D$42,3,0) -> 49.166667 | F38: =PRODUCT(D38:E38) -> 0.78666667
A39: OPERARIO | B39: hh | C39: 3 | D39: =C39*$E$35/$B$35 -> 0.48 | E39: =VLOOKUP(A39,INSUMOS!$B$7:$D$42,3,0) -> 27.041667 | F39: =PRODUCT(D39:E39) -> 12.98
A40: MADERA TORNILLO | B40: p2 | D40: =C40*$E$35/$B$35 -> 0 | E40: 4.7 | F40: =PRODUCT(D40:E40) -> 0
A41: MATERIALES | F41: =SUM(F42:F44) -> 1.017
A42: CLAVOS CON CABEZA | B42: kg | D42: 0.01 | E42: 2.9 | F42: =PRODUCT(D42:E42) -> 0.029
A43: CAL (BOLSA x 20kg) | B43: bl | D43: 0.1 | E43: 9.5 | F43: =PRODUCT(D43:E43) -> 0.95
A44: CORDEL | B44: m | D44: 0.19 | E44: 0.2 | F44: =PRODUCT(D44:E44) -> 0.038
A45: EQUIPOS | F45: =SUM(F46) -> 0.413
A46: HERRAMIENTAS MANUALES | B46: %mo | D46: 3 | E46: =F37 -> 13.766667 | F46: =D46*E46/100 -> 0.413
A48: CASETA, ALMACEN Y BAÑOS | E48: CU | F48: =F51+F53 -> 1750
A49: RENDIMIENTO | B49: 8 | C49: GLB/d | D49: JORNADA | E49: 8 | F49: horas/dia
A50: Descripción de Recurso | B50: Unidad | C50: Cuadrilla | D50: Cantidad | E50: Precio (S/.) | F50: Parcial (S/.)
A51: MANO DE OBRA | F51: =SUM(F52) -> 250
A52: MANO DE OBRA- A | B52: GLB | D52: 1 | E52: 250 | F52: =PRODUCT(D52:E52) -> 250
A53: MATERIALES | F53: =SUM(F54) -> 1500
A54: MADERA TORNILLO | B54: GLB | D54: 1 | E54: 1500 | F54: =PRODUCT(D54:E54) -> 1500
A56: CERCO PERIMETRICO PROVISIONAL | E56: CU | F56: =F59+F63+F68 -> 157.89625
A57: RENDIMIENTO | B57: 40 | C57: ml/d | D57: JORNADA | E57: 8 | F57: horas/dia
A58: Descripción de Recurso | B58: Unidad | C58: Cuadrilla | D58: Cantidad | E58: Precio (S/.) | F58: Parcial (S/.)
A59: MANO DE OBRA | F59: =SUM(F60:F62) -> 22.125
A60: CAPATAZ | B60: hh | C60: 0.1 | D60: =C60*$E$57/$B$57 -> 0.02 | E60: =VLOOKUP(A60,INSUMOS!$B$7:$D$42,3,0) -> 49.166667 | F60: =PRODUCT(D60:E60) -> 0.98333333
A61: OPERARIO | B61: hh | C61: 3 | D61: =C61*$E$57/$B$57 -> 0.6 | E61: =VLOOKUP(A61,INSUMOS!$B$7:$D$42,3,0) -> 27.041667 | F61: =PRODUCT(D61:E61) -> 16.225
A62: PEON | B62: hh | C62: 2 | D62: =C62*$E$57/$B$57 -> 0.4 | E62: =VLOOKUP(A62,INSUMOS!$B$7:$D$42,3,0) -> 12.291667 | F62: =PRODUCT(D62:E62) -> 4.9166667
A63: MATERIALES | F63: =SUM(F64:F67) -> 134.665
A64: ALAMBRE NEGRO Nº 16 | B64: kg | D64: 0.2 | E64: =VLOOKUP(A64,INSUMOS!$B$7:$D$42,3,0) -> 5 | F64: =PRODUCT(D64:E64) -> 1
A65: CLAVOS CON CABEZA | B65: kg | D65: 0.2 | E65: =VLOOKUP(A65,INSUMOS!$B$7:$D$42,3,0) -> 5 | F65: =PRODUCT(D65:E65) -> 1
A66: MADERA EUCALIPTO 4"x4" x 3m | B66: und | D66: 1.25 | E66: 28 | F66: =PRODUCT(D66:E66) -> 35
A67: TRIPLAY FENÓLICO 18 mm 1.22 x 2.44m | B67: und | D67: 0.85 | E67: =VLOOKUP(A67,INSUMOS!$B$7:$D$42,3,0) -> 114.9 | F67: =PRODUCT(D67:E67) -> 97.665
A68: EQUIPOS | F68: =SUM(F69) -> 1.10625
A69: HERRAMIENTAS MANUALES | B69: %mo | D69: 5 | E69: =F59 -> 22.125 | F69: =D69*E69/100 -> 1.10625
A71: PROTECCIÓN CON MALLA RASCHELL | E71: CU | F71: =F74+F78+F82 -> 14.05425
A72: RENDIMIENTO | B72: 400 | C72: ml/d | D72: JORNADA | E72: 8 | F72: horas/dia
A73: Descripción de Recurso | B73: Unidad | C73: Cuadrilla | D73: Cantidad | E73: Precio (S/.) | F73: Parcial (S/.)
A74: MANO DE OBRA | F74: =SUM(F75:F77) -> 0.885
A75: CAPATAZ | B75: hh | C75: 0.1 | D75: =C75*$E$72/$B$72 -> 0.002 | E75: =VLOOKUP(A75,INSUMOS!$B$7:$D$42,3,0) -> 49.166667 | F75: =PRODUCT(D75:E75) -> 0.098333333
A76: OPERARIO | B76: hh | C76: 1 | D76: =C76*$E$72/$B$72 -> 0.02 | E76: =VLOOKUP(A76,INSUMOS!$B$7:$D$42,3,0) -> 27.041667 | F76: =PRODUCT(D76:E76) -> 0.54083333
A77: PEON | B77: hh | C77: 1 | D77: =C77*$E$72/$B$72 -> 0.02 | E77: =VLOOKUP(A77,INSUMOS!$B$7:$D$42,3,0) -> 12.291667 | F77: =PRODUCT(D77:E77) -> 0.24583333
A78: MATERIALES | F78: =SUM(F79:F81) -> 13.125
A79: ALAMBRE NEGRO Nº 16 | B79: kg | D79: 0.1 | E79: =VLOOKUP(A79,INSUMOS!$B$7:$D$42,3,0) -> 5 | F79: =PRODUCT(D79:E79) -> 0.5
A80: MADERA EUCALIPTO 4"x4" x 3m | B80: und | D80: 0.25 | E80: 28 | F80: =PRODUCT(D80:E80) -> 7
A81: ROLLO MALLA RASCHEL 95%, 4.20m x 100m | B81: rollo | D81: 0.0075 | E81: =VLOOKUP(A81,INSUMOS!$B$7:$D$42,3,0) -> 750 | F81: =PRODUCT(D81:E81) -> 5.625
A82: EQUIPOS | F82: =SUM(F83) -> 0.04425
A83: HERRAMIENTAS MANUALES | B83: %mo | D83: 5 | E83: =F74 -> 0.885 | F83: =D83*E83/100 -> 0.04425
A85: DEMOLICION CON MAQUINARIA | E85: CU | F85: =F88+F92 -> 56.823333
A86: RENDIMIENTO | B86: 50 | C86: m2/d | D86: JORNADA | E86: 8 | F86: horas/dia
A87: Descripción de Recurso | B87: Unidad | C87: Cuadrilla | D87: Cantidad | E87: Precio (S/.) | F87: Parcial (S/.)
A88: MANO DE OBRA | F88: =SUM(F89:F91) -> 16.333333
A89: CAPATAZ | B89: hh | C89: 0.1 | D89: =C89*$E$86/$B$86 -> 0.016 | E89: =VLOOKUP(A89,INSUMOS!$B$7:$D$42,3,0) -> 49.166667 | F89: =PRODUCT(D89:E89) -> 0.78666667
A90: PEON | B90: hh | C90: 4 | D90: =C90*$E$86/$B$86 -> 0.64 | E90: =VLOOKUP(A90,INSUMOS!$B$7:$D$42,3,0) -> 12.291667 | F90: =PRODUCT(D90:E90) -> 7.8666667
A91: ROTOMARTILLO | B91: hh | C91: 4 | D91: =C91*$E$86/$B$86 -> 0.64 | E91: =VLOOKUP(A91,INSUMOS!$B$7:$D$42,3,0) -> 12 | F91: =PRODUCT(D91:E91) -> 7.68
A92: EQUIPOS | F92: =SUM(F93:F94) -> 40.49
A93: RETROEXCAVADORA CON LLANTAS | B93: hm | C93: 1 | D93: =C93*$E$86/$B$86 -> 0.16 | E93: =VLOOKUP(A93,INSUMOS!$B$7:$D$42,3,0) -> 250 | F93: =D93*E93 -> 40
A94: HERRAMIENTAS MANUALES | B94: %mo | D94: 3 | E94: =F88 -> 16.333333 | F94: =D94*E94/100 -> 0.49
A96: DEMOLICION DE CIMENTACIÓN EXISTENTE | E96: CU | F96: =F99+F103 -> 440.84
A97: RENDIMIENTO | B97: 1 | C97: m3/d | D97: JORNADA | E97: 8 | F97: horas/dia
A98: Descripción de Recurso | B98: Unidad | C98: Cuadrilla | D98: Cantidad | E98: Precio (S/.) | F98: Parcial (S/.)
A99: MANO DE OBRA | F99: =SUM(F100:F102) -> 428
A100: CAPATAZ | B100: hh | C100: 0.1 | D100: =C100*$E$97/$B$97 -> 0.8 | E100: =VLOOKUP(A100,INSUMOS!$B$7:$D$42,3,0) -> 49.166667 | F100: =PRODUCT(D100:E100) -> 39.333333
A101: PEON | B101: hh | C101: 2 | D101: =C101*$E$97/$B$97 -> 16 | E101: =VLOOKUP(A101,INSUMOS!$B$7:$D$42,3,0) -> 12.291667 | F101: =PRODUCT(D101:E101) -> 196.66667
A102: ROTOMARTILLO | B102: hh | C102: 2 | D102: =C102*$E$97/$B$97 -> 16 | E102: =VLOOKUP(A102,INSUMOS!$B$7:$D$42,3,0) -> 12 | F102: =PRODUCT(D102:E102) -> 192
A103: EQUIPOS | F103: =SUM(F104:F104) -> 12.84
A104: HERRAMIENTAS MANUALES | B104: %mo | D104: 3 | E104: =F99 -> 428 | F104: =D104*E104/100 -> 12.84
A106: PERFILADO DE CIMIENTOS | E106: CU | F106: =F109+F114+F112 -> 29.724583
A107: RENDIMIENTO | B107: 8 | C107: m2/d | D107: JORNADA | E107: 8 | F107: horas/dia
A108: Descripción de Recurso | B108: Unidad | C108: Cuadrilla | D108: Cantidad | E108: Precio (S/.) | F108: Parcial (S/.)
A109: MANO DE OBRA | F109: =SUM(F110:F111) -> 17.208333
A110: CAPATAZ | B110: hh | C110: 0.1 | D110: =C110*$E$107/$B$107 -> 0.1 | E110: =VLOOKUP(A110,INSUMOS!$B$7:$D$42,3,0) -> 49.166667 | F110: =PRODUCT(D110:E110) -> 4.9166667
...

Sheet RESUMEN
B1: PRESUPUESTO DE OBRA | D1: VALORIZACIONES | L1: VALORIZACIONES | T1: VALORIZACIONES | AB1: VALORIZACIONES
B2: DESCRIPCIÓN DE PARTIDAS | C2: MONTO | D2: semana 01 | F2: semana 02 | H2: semana 03 | J2: semana 04 | L2: semana 05 | N2: semana 06 | P2: semana 07 | R2: semana 08 | T2: semana 09 | V2: semana 10 | X2: semana 11 | Z2: semana 12 | AB2: semana 13 | AD2: semana 14 | AF2: semana 15 | AH2: semana 16
B3: OBRAS PRELIMINARES Y MOVIMIENTO DE TIERRAS | C3: =SUM(C4:C7) -> 54537.403 | E3: =SUM(E4:E7) -> 16611.609 | G3: =SUM(G4:G7) -> 19465.501 | I3: =SUM(I4:I7) -> 12893.808 | K3: =SUM(K4:K7) -> 0 | M3: =SUM(M4:M7) -> 1855.4946 | O3: =SUM(O4:O7) -> 0 | Q3: =SUM(Q4:Q7) -> 0 | S3: =SUM(S4:S7) -> 0 | U3: =SUM(U4:U7) -> 1855.4946 | W3: =SUM(W4:W7) -> 0 | Y3: =SUM(Y4:Y7) -> 0 | AA3: =SUM(AA4:AA7) -> 0 | AC3: =SUM(AC4:AC7) -> 1855.4946 | AE3: =SUM(AE4:AE7) -> 0 | AG3: =SUM(AG4:AG7) -> 0 | AI3: =SUM(AI4:AI7) -> 0
A4: =+D4+F4+H4+J4+L4+N4+P4+R4+T4+V4+X4+Z4+AB4+AD4+AF4+AH4 -> 1 | B4: OBRAS PRELIMINARES | C4: 10876.107 | D4: 0.7 | E4: =+C4*D4 -> 7613.2747 | F4: 0.3 | G4: =+C4*F4 -> 3262.832 | H4: 0 | I4: =+C4*H4 -> 0 | J4: 0 | K4: =+C4*J4 -> 0 | L4: 0 | M4: =+L4*C4 -> 0 | N4: 0 | O4: =+N4*C4 -> 0 | P4: 0 | Q4: =+P4*C4 -> 0 | R4: 0 | S4: =+R4*C4 -> 0 | T4: 0 | U4: =+C4*T4 -> 0 | V4: 0 | W4: =+C4*V4 -> 0 | X4: 0 | Y4: =+C4*X4 -> 0 | Z4: 0 | AA4: =+C4*Z4 -> 0 | AB4: 0 | AC4: =+C4*AB4 -> 0 | AD4: 0 | AE4: =+C4*AD4 -> 0 | AF4: 0 | AG4: =+C4*AF4 -> 0 | AH4: 0 | AI4: =+AH4*C4 -> 0
A5: =+D5+F5+H5+J5+L5+N5+P5+R5+T5+V5+X5+Z5+AB5+AD5+AF5+AH5 -> 1 | B5: DEMOLICIÓN PARCIAL | C5: 28571.36 | D5: 0.25 | E5: =+C5*D5 -> 7142.84 | F5: 0.5 | G5: =+C5*F5 -> 14285.68 | H5: 0.25 | I5: =+C5*H5 -> 7142.84 | J5: 0 | K5: =+C5*J5 -> 0 | L5: 0 | M5: =+L5*C5 -> 0 | N5: 0 | O5: =+N5*C5 -> 0 | P5: 0 | Q5: =+P5*C5 -> 0 | R5: 0 | S5: =+R5*C5 -> 0 | T5: 0 | U5: =+C5*T5 -> 0 | V5: 0 | W5: =+C5*V5 -> 0 | X5: 0 | Y5: =+C5*X5 -> 0 | Z5: 0 | AA5: =+C5*Z5 -> 0 | AB5: 0 | AC5: =+C5*AB5 -> 0 | AD5: 0 | AE5: =+C5*AD5 -> 0 | AF5: 0 | AG5: =+C5*AF5 -> 0 | AH5: 0 | AI5: =+AH5*C5 -> 0
A6: =+D6+F6+H6+J6+L6+N6+P6+R6+T6+V6+X6+Z6+AB6+AD6+AF6+AH6 -> 1 | B6: MOVIMIENTO DE TIERRAS | C6: 7667.9579 | D6: 0 | E6: =+C6*D6 -> 0 | F6: 0.25 | G6: =+C6*F6 -> 1916.9895 | H6: 0.75 | I6: =+C6*H6 -> 5750.9684 | J6: 0 | K6: =+C6*J6 -> 0 | L6: 0 | M6: =+L6*C6 -> 0 | N6: 0 | O6: =+N6*C6 -> 0 | P6: 0 | Q6: =+P6*C6 -> 0 | R6: 0 | S6: =+R6*C6 -> 0 | T6: 0 | U6: =+C6*T6 -> 0 | V6: 0 | W6: =+C6*V6 -> 0 | X6: 0 | Y6: =+C6*X6 -> 0 | Z6: 0 | AA6: =+C6*Z6 -> 0 | AB6: 0 | AC6: =+C6*AB6 -> 0 | AD6: 0 | AE6: =+C6*AD6 -> 0 | AF6: 0 | AG6: =+C6*AF6 -> 0 | AH6: 0 | AI6: =+AH6*C6 -> 0
A7: =+D7+F7+H7+J7+L7+N7+P7+R7+T7+V7+X7+Z7+AB7+AD7+AF7+AH7 -> 1 | B7: SEGURIDAD Y SALUD | C7: 7421.9785 | D7: 0.25 | E7: =+C7*D7 -> 1855.4946 | F7: 0 | G7: =+C7*F7 -> 0 | H7: 0 | I7: =+C7*H7 -> 0 | J7: 0 | K7: =+C7*J7 -> 0 | L7: 0.25 | M7: =+L7*C7 -> 1855.4946 | N7: 0 | O7: =+N7*C7 -> 0 | P7: 0 | Q7: =+P7*C7 -> 0 | R7: 0 | S7: =+R7*C7 -> 0 | T7: 0.25 | U7: =+C7*T7 -> 1855.4946 | V7: 0 | W7: =+C7*V7 -> 0 | X7: 0 | Y7: =+C7*X7 -> 0 | Z7: 0 | AA7: =+C7*Z7 -> 0 | AB7: 0.25 | AC7: =+C7*AB7 -> 1855.4946 | AD7: 0 | AE7: =+C7*AD7 -> 0 | AF7: 0 | AG7: =+C7*AF7 -> 0 | AH7: 0 | AI7: =+AH7*C7 -> 0
B8: 1 ER PISO | C8: =SUM(C9:C14) -> 129861.17 | E8: =SUM(E9:E14) -> 0 | G8: =SUM(G9:G14) -> 0 | I8: =SUM(I9:I14) -> 8223.1862 | K8: =SUM(K9:K14) -> 21614.506 | M8: =SUM(M9:M14) -> 20910.146 | O8: =SUM(O9:O14) -> 8066.1912 | Q8: =SUM(Q9:Q14) -> 13234.325 | S8: =SUM(S9:S14) -> 0 | U8: =SUM(U9:U14) -> 5683.1674 | W8: =SUM(W9:W14) -> 11307.684 | Y8: =SUM(Y9:Y14) -> 11307.684 | AA8: =SUM(AA9:AA14) -> 11640.946 | AC8: =SUM(AC9:AC14) -> 5957.7786 | AE8: =SUM(AE9:AE14) -> 5957.7786 | AG8: =SUM(AG9:AG14) -> 5957.7786 | AI8: =SUM(AI9:AI14) -> 0
A9: =+D9+F9+H9+J9+L9+N9+P9+R9+T9+V9+X9+Z9+AB9+AD9+AF9+AH9 -> 1 | B9: OBRAS DE CONCRETO SIMPLE | C9: 17227.114 | D9: 0 | E9: =+C9*D9 -> 0 | F9: 0 | G9: =+C9*F9 -> 0 | H9: 0 | I9: =+C9*H9 -> 0 | J9: 0.3 | K9: =+C9*J9 -> 5168.1341 | L9: 0.1 | M9: =+L9*C9 -> 1722.7114 | N9: 0.15 | O9: =+N9*C9 -> 2584.067 | P9: 0.45 | Q9: =+P9*C9 -> 7752.2011 | R9: 0 | S9: =+R9*C9 -> 0 | T9: 0 | U9: =+C9*T9 -> 0 | V9: 0 | W9: =+C9*V9 -> 0 | X9: 0 | Y9: =+C9*X9 -> 0 | Z9: 0 | AA9: =+C9*Z9 -> 0 | AB9: 0 | AC9: =+C9*AB9 -> 0 | AD9: 0 | AE9: =+C9*AD9 -> 0 | AF9: 0 | AG9: =+C9*AF9 -> 0 | AH9: 0 | AI9: =+AH9*C9 -> 0
A10: =+D10+F10+H10+J10+L10+N10+P10+R10+T10+V10+X10+Z10+AB10+AD10+AF10+AH10 -> 1 | B10: OBRAS DE CONCRETO ARMADO | C10: 54821.241 | D10: 0 | E10: =+C10*D10 -> 0 | F10: 0 | G10: =+C10*F10 -> 0 | H10: 0.15 | I10: =+C10*H10 -> 8223.1862 | J10: 0.3 | K10: =+C10*J10 -> 16446.372 | L10: 0.35 | M10: =+L10*C10 -> 19187.434 | N10: 0.1 | O10: =+N10*C10 -> 5482.1241 | P10: 0.1 | Q10: =+P10*C10 -> 5482.1241 | R10: 0 | S10: =+R10*C10 -> 0 | T10: 0 | U10: =+C10*T10 -> 0 | V10: 0 | W10: =+C10*V10 -> 0 | X10: 0 | Y10: =+C10*X10 -> 0 | Z10: 0 | AA10: =+C10*Z10 -> 0 | AB10: 0 | AC10: =+C10*AB10 -> 0 | AD10: 0 | AE10: =+C10*AD10 -> 0 | AF10: 0 | AG10: =+C10*AF10 -> 0 | AH10: 0 | AI10: =+AH10*C10 -> 0
A11: =+D11+F11+H11+J11+L11+N11+P11+R11+T11+V11+X11+Z11+AB11+AD11+AF11+AH11 -> 1 | B11: TABIQUERIA | C11: 11249.033 | D11: 0 | E11: =+C11*D11 -> 0 | F11: 0 | G11: =+C11*F11 -> 0 | H11: 0 | I11: =+C11*H11 -> 0 | J11: 0 | K11: =+C11*J11 -> 0 | L11: 0 | M11: =+L11*C11 -> 0 | N11: 0 | O11: =+N11*C11 -> 0 | P11: 0 | Q11: =+P11*C11 -> 0 | R11: 0 | S11: =+R11*C11 -> 0 | T11: 0 | U11: =+C11*T11 -> 0 | V11: 0.5 | W11: =+C11*V11 -> 5624.5163 | X11: 0.5 | Y11: =+C11*X11 -> 5624.5163 | AA11: =+C11*Z11 -> 0 | AB11: 0 | AC11: =+C11*AB11 -> 0 | AD11: 0 | AE11: =+C11*AD11 -> 0 | AF11: 0 | AG11: =+C11*AF11 -> 0 | AH11: 0 | AI11: =+AH11*C11 -> 0
A12: =+D12+F12+H12+J12+L12+N12+P12+R12+T12+V12+X12+Z12+AB12+AD12+AF12+AH12 -> 1 | B12: OBRAS HUMEDAS | C12: 22732.67 | D12: 0 | E12: =+C12*D12 -> 0 | F12: 0 | G12: =+C12*F12 -> 0 | H12: 0 | I12: =+C12*H12 -> 0 | J12: 0 | K12: =+C12*J12 -> 0 | L12: 0 | M12: =+L12*C12 -> 0 | N12: 0 | O12: =+N12*C12 -> 0 | P12: 0 | Q12: =+P12*C12 -> 0 | R12: 0 | S12: =+R12*C12 -> 0 | T12: 0.25 | U12: =+C12*T12 -> 5683.1674 | V12: 0.25 | W12: =+C12*V12 -> 5683.1674 | X12: 0.25 | Y12: =+C12*X12 -> 5683.1674 | Z12: 0.25 | AA12: =+C12*Z12 -> 5683.1674 | AC12: =+C12*AB12 -> 0 | AD12: 0 | AE12: =+C12*AD12 -> 0 | AF12: 0 | AG12: =+C12*AF12 -> 0 | AH12: 0 | AI12: =+AH12*C12 -> 0
A13: =+D13+F13+H13+J13+L13+N13+P13+R13+T13+V13+X13+Z13+AB13+AD13+AF13+AH13 -> 1 | B13: INSTALACIONES ELECTRICAS | C13: 11915.557 | D13: 0 | E13: =+C13*D13 -> 0 | F13: 0 | G13: =+C13*F13 -> 0 | H13: 0 | I13: =+C13*H13 -> 0 | J13: 0 | K13: =+C13*J13 -> 0 | L13: 0 | M13: =+L13*C13 -> 0 | N13: 0 | O13: =+N13*C13 -> 0 | P13: 0 | Q13: =+P13*C13 -> 0 | R13: 0 | S13: =+R13*C13 -> 0 | T13: 0 | U13: =+C13*T13 -> 0 | V13: 0 | W13: =+C13*V13 -> 0 | X13: 0 | Y13: =+C13*X13 -> 0 | Z13: 0.25 | AA13: =+C13*Z13 -> 2978.8893 | AB13: 0.25 | AC13: =+C13*AB13 -> 2978.8893 | AD13: 0.25 | AE13: =+C13*AD13 -> 2978.8893 | AF13: 0.25 | AG13: =+C13*AF13 -> 2978.8893 | AH13: 0 | AI13: =+AH13*C13 -> 0
A14: =+D14+F14+H14+J14+L14+N14+P14+R14+T14+V14+X14+Z14+AB14+AD14+AF14+AH14 -> 1 | B14: INSTALACIONES SANITARIAS | C14: 11915.557 | D14: 0 | E14: =+C14*D14 -> 0 | F14: 0 | G14: =+C14*F14 -> 0 | H14: 0 | I14: =+C14*H14 -> 0 | J14: 0 | K14: =+C14*J14 -> 0 | L14: 0 | M14: =+L14*C14 -> 0 | N14: 0 | O14: =+N14*C14 -> 0 | P14: 0 | Q14: =+P14*C14 -> 0 | R14: 0 | S14: =+R14*C14 -> 0 | T14: 0 | U14: =+C14*T14 -> 0 | V14: 0 | W14: =+C14*V14 -> 0 | X14: 0 | Y14: =+C14*X14 -> 0 | Z14: 0.25 | AA14: =+C14*Z14 -> 2978.8893 | AB14: 0.25 | AC14: =+C14*AB14 -> 2978.8893 | AD14: 0.25 | AE14: =+C14*AD14 -> 2978.8893 | AF14: 0.25 | AG14: =+C14*AF14 -> 2978.8893 | AH14: 0 | AI14: =+AH14*C14 -> 0
A15: =+D15+F15+H15+J15+L15+N15+P15+R15+T15+V15+X15+Z15+AB15+AD15+AF15+AH15 -> 0 | B15: 2 DO PISO | C15: =SUM(C16:C20) -> 77800.713 | E15: =SUM(E16:E20) -> 0 | G15: =SUM(G16:G20) -> 0 | I15: =SUM(I16:I20) -> 0 | K15: =SUM(K16:K20) -> 0 | M15: =SUM(M16:M20) -> 0 | O15: =SUM(O16:O20) -> 16095.647 | Q15: =SUM(Q16:Q20) -> 11266.953 | S15: =SUM(S16:S20) -> 4828.694 | U15: =SUM(U16:U20) -> 4468.334 | W15: =SUM(W16:W20) -> 9811.6245 | Y15: =SUM(Y16:Y20) -> 9811.6245 | AA15: =SUM(AA16:AA20) -> 8730.7096 | AC15: =SUM(AC16:AC20) -> 4262.3756 | AE15: =SUM(AE16:AE20) -> 8524.7511 | AG15: =SUM(AG16:AG20) -> 0 | AI15: =SUM(AI16:AI20) -> 0
A16: =+D16+F16+H16+J16+L16+N16+P16+R16+T16+V16+X16+Z16+AB16+AD16+AF16+AH16 -> 1 | B16: OBRAS DE CONCRETO ARMADO | C16: 32191.293 | D16: 0 | E16: =+C16*D16 -> 0 | F16: 0 | G16: =+C16*F16 -> 0 | H16: 0 | I16: =+C16*H16 -> 0 | J16: 0 | K16: =+C16*J16 -> 0 | L16: 0 | M16: =+L16*C16 -> 0 | N16: 0.5 | O16: =+N16*C16 -> 16095.647 | P16: 0.35 | Q16: =+P16*C16 -> 11266.953 | R16: 0.15 | S16: =+R16*C16 -> 4828.694 | T16: 0 | U16: =+C16*T16 -> 0 | V16: 0 | W16: =+C16*V16 -> 0 | X16: 0 | Y16: =+C16*X16 -> 0 | Z16: 0 | AA16: =+C16*Z16 -> 0 | AB16: 0 | AC16: =+C16*AB16 -> 0 | AD16: 0 | AE16: =+C16*AD16 -> 0 | AF16: 0 | AG16: =+C16*AF16 -> 0 | AH16: 0 | AI16: =+AH16*C16 -> 0
A17: =+D17+F17+H17+J17+L17+N17+P17+R17+T17+V17+X17+Z17+AB17+AD17+AF17+AH17 -> 1 | B17: TABIQUERIA | C17: 10686.581 | D17: 0 | E17: =+C17*D17 -> 0 | F17: 0 | G17: =+C17*F17 -> 0 | H17: 0 | I17: =+C17*H17 -> 0 | J17: 0 | K17: =+C17*J17 -> 0 | L17: 0 | M17: =+L17*C17 -> 0 | N17: 0 | O17: =+N17*C17 -> 0 | P17: 0 | Q17: =+P17*C17 -> 0 | R17: 0 | S17: =+R17*C17 -> 0 | T17: 0 | U17: =+C17*T17 -> 0 | V17: 0.5 | W17: =+C17*V17 -> 5343.2905 | X17: 0.5 | Y17: =+C17*X17 -> 5343.2905 | Z17: 0 | AA17: =+C17*Z17 -> 0 | AB17: 0 | AC17: =+C17*AB17 -> 0 | AD17: 0 | AE17: =+C17*AD17 -> 0 | AF17: 0 | AG17: =+C17*AF17 -> 0 | AH17: 0 | AI17: =+AH17*C17 -> 0
A18: =+D18+F18+H18+J18+L18+N18+P18+R18+T18+V18+X18+Z18+AB18+AD18+AF18+AH18 -> 1 | B18: OBRAS HUMEDAS | C18: 17049.502 | D18: 0 | E18: =+C18*D18 -> 0 | F18: 0 | G18: =+C18*F18 -> 0 | H18: 0 | I18: =+C18*H18 -> 0 | J18: 0 | K18: =+C18*J18 -> 0 | L18: 0 | M18: =+L18*C18 -> 0 | N18: 0 | O18: =+N18*C18 -> 0 | P18: 0 | Q18: =+P18*C18 -> 0 | R18: 0 | S18: =+R18*C18 -> 0 | T18: 0 | U18: =+C18*T18 -> 0 | V18: 0 | W18: =+C18*V18 -> 0 | X18: 0 | Y18: =+C18*X18 -> 0 | Z18: 0.25 | AA18: =+C18*Z18 -> 4262.3756 | AB18: 0.25 | AC18: =+C18*AB18 -> 4262.3756 | AD18: 0.5 | AE18: =+C18*AD18 -> 8524.7511 | AF18: 0 | AG18: =+C18*AF18 -> 0 | AH18: 0 | AI18: =+AH18*C18 -> 0
A19: =+D19+F19+H19+J19+L19+N19+P19+R19+T19+V19+X19+Z19+AB19+AD19+AF19+AH19 -> 1 | B19: INSTALACIONES ELECTRICAS | C19: 8936.668 | D19: 0 | E19: =+C19*D19 -> 0 | F19: 0 | G19: =+C19*F19 -> 0 | H19: 0 | I19: =+C19*H19 -> 0 | J19: 0 | K19: =+C19*J19 -> 0 | L19: 0 | M19: =+L19*C19 -> 0 | N19: 0 | O19: =+N19*C19 -> 0 | P19: 0 | Q19: =+P19*C19 -> 0 | R19: 0 | S19: =+R19*C19 -> 0 | T19: 0.25 | U19: =+C19*T19 -> 2234.167 | V19: 0.25 | W19: =+C19*V19 -> 2234.167 | X19: 0.25 | Y19: =+C19*X19 -> 2234.167 | Z19: 0.25 | AA19: =+C19*Z19 -> 2234.167 | AB19: 0 | AC19: =+C19*AB19 -> 0 | AD19: 0 | AE19: =+C19*AD19 -> 0 | AF19: 0 | AG19: =+C19*AF19 -> 0 | AH19: 0 | AI19: =+AH19*C19 -> 0
A20: =+D20+F20+H20+J20+L20+N20+P20+R20+T20+V20+X20+Z20+AB20+AD20+AF20+AH20 -> 1 | B20: INSTALACIONES SANITARIAS | C20: 8936.668 | D20: 0 | E20: =+C20*D20 -> 0 | F20: 0 | G20: =+C20*F20 -> 0 | H20: 0 | I20: =+C20*H20 -> 0 | J20: 0 | K20: =+C20*J20 -> 0 | L20: 0 | M20: =+L20*C20 -> 0 | N20: 0 | O20: =+N20*C20 -> 0 | P20: 0 | Q20: =+P20*C20 -> 0 | R20: 0 | S20: =+R20*C20 -> 0 | T20: 0.25 | U20: =+C20*T20 -> 2234.167 | V20: 0.25 | W20: =+C20*V20 -> 2234.167 | X20: 0.25 | Y20: =+C20*X20 -> 2234.167 | Z20: 0.25 | AA20: =+C20*Z20 -> 2234.167 | AB20: 0 | AC20: =+C20*AB20 -> 0 | AD20: 0 | AE20: =+C20*AD20 -> 0 | AF20: 0 | AG20: =+C20*AF20 -> 0 | AH20: 0 | AI20: =+AH20*C20 -> 0
A21: =+D21+F21+H21+J21+L21+N21+P21+R21+T21+V21+X21+Z21+AB21+AD21+AF21+AH21 -> 0 | B21: 3ER PISO | C21: =SUM(C22:C26) -> 77800.713 | E21: =SUM(E22:E26) -> 0 | G21: =SUM(G22:G26) -> 0 | I21: =SUM(I22:I26) -> 0 | K21: =SUM(K22:K26) -> 0 | M21: =SUM(M22:M26) -> 0 | O21: =SUM(O22:O26) -> 0 | Q21: =SUM(Q22:Q26) -> 0 | S21: =SUM(S22:S26) -> 19314.776 | U21: =SUM(U22:U26) -> 12876.517 | W21: =SUM(W22:W26) -> 2671.6452 | Y21: =SUM(Y22:Y26) -> 2671.6452 | AA21: =SUM(AA22:AA26) -> 2671.6452 | AC21: =SUM(AC22:AC26) -> 7139.9792 | AE21: =SUM(AE22:AE26) -> 4468.334 | AG21: =SUM(AG22:AG26) -> 12993.085 | AI21: =SUM(AI22:AI26) -> 12993.085
A22: =+D22+F22+H22+J22+L22+N22+P22+R22+T22+V22+X22+Z22+AB22+AD22+AF22+AH22 -> 1 | B22: OBRAS DE CONCRETO ARMADO | C22: 32191.293 | D22: 0 | E22: =+C22*D22 -> 0 | F22: 0 | G22: =+C22*F22 -> 0 | H22: 0 | I22: =+C22*H22 -> 0 | J22: 0 | K22: =+C22*J22 -> 0 | L22: 0 | M22: =+L22*C22 -> 0 | N22: 0 | O22: =+N22*C22 -> 0 | P22: 0 | Q22: =+P22*C22 -> 0 | R22: 0.6 | S22: =+R22*C22 -> 19314.776 | T22: 0.4 | U22: =+C22*T22 -> 12876.517 | W22: =+C22*V22 -> 0 | X22: 0 | Y22: =+C22*X22 -> 0 | AA22: =+C22*Z22 -> 0 | AC22: =+C22*AB22 -> 0 | AD22: 0 | AE22: =+C22*AD22 -> 0 | AF22: 0 | AG22: =+C22*AF22 -> 0 | AH22: 0 | AI22: =+AH22*C22 -> 0
A23: =+D23+F23+H23+J23+L23+N23+P23+R23+T23+V23+X23+Z23+AB23+AD23+AF23+AH23 -> 1 | B23: TABIQUERIA | C23: 10686.581 | D23: 0 | E23: =+C23*D23 -> 0 | F23: 0 | G23: =+C23*F23 -> 0 | H23: 0 | I23: =+C23*H23 -> 0 | J23: 0 | K23: =+C23*J23 -> 0 | L23: 0 | M23: =+L23*C23 -> 0 | N23: 0 | O23: =+N23*C23 -> 0 | P23: 0 | Q23: =+P23*C23 -> 0 | R23: 0 | S23: =+R23*C23 -> 0 | T23: 0 | U23: =+C23*T23 -> 0 | V23: 0.25 | W23: =+C23*V23 -> 2671.6452 | X23: 0.25 | Y23: =+C23*X23 -> 2671.6452 | Z23: 0.25 | AA23: =+C23*Z23 -> 2671.6452 | AB23: 0.25 | AC23: =+C23*AB23 -> 2671.6452 | AD23: 0 | AE23: =+C23*AD23 -> 0 | AF23: 0 | AG23: =+C23*AF23 -> 0 | AH23: 0 | AI23: =+AH23*C23 -> 0
A24: =+D24+F24+H24+J24+L24+N24+P24+R24+T24+V24+X24+Z24+AB24+AD24+AF24+AH24 -> 1 | B24: OBRAS HUMEDAS | C24: 17049.502 | D24: 0 | E24: =+C24*D24 -> 0 | F24: 0 | G24: =+C24*F24 -> 0 | H24: 0 | I24: =+C24*H24 -> 0 | J24: 0 | K24: =+C24*J24 -> 0 | L24: 0 | M24: =+L24*C24 -> 0 | N24: 0 | O24: =+N24*C24 -> 0 | P24: 0 | Q24: =+P24*C24 -> 0 | R24: 0 | S24: =+R24*C24 -> 0 | T24: 0 | U24: =+C24*T24 -> 0 | V24: 0 | W24: =+C24*V24 -> 0 | X24: 0 | Y24: =+C24*X24 -> 0 | Z24: 0 | AA24: =+C24*Z24 -> 0 | AB24: 0 | AC24: =+C24*AB24 -> 0 | AD24: 0 | AE24: =+C24*AD24 -> 0 | AF24: 0.5 | AG24: =+C24*AF24 -> 8524.7511 | AH24: 0.5 | AI24: =+AH24*C24 -> 8524.7511
A25: =+D25+F25+H25+J25+L25+N25+P25+R25+T25+V25+X25+Z25+AB25+AD25+AF25+AH25 -> 1 | B25: INSTALACIONES ELECTRICAS | C25: 8936.668 | D25: 0 | E25: =+C25*D25 -> 0 | F25: 0 | G25: =+C25*F25 -> 0 | H25: 0 | I25: =+C25*H25 -> 0 | J25: 0 | K25: =+C25*J25 -> 0 | L25: 0 | M25: =+L25*C25 -> 0 | N25: 0 | O25: =+N25*C25 -> 0 | P25: 0 | Q25: =+P25*C25 -> 0 | R25: 0 | S25: =+R25*C25 -> 0 | T25: 0 | U25: =+C25*T25 -> 0 | V25: 0 | W25: =+C25*V25 -> 0 | X25: 0 | Y25: =+C25*X25 -> 0 | Z25: 0 | AA25: =+C25*Z25 -> 0 | AB25: 0.25 | AC25: =+C25*AB25 -> 2234.167 | AD25: 0.25 | AE25: =+C25*AD25 -> 2234.167 | AF25: 0.25 | AG25: =+C25*AF25 -> 2234.167 | AH25: 0.25 | AI25: =+AH25*C25 -> 2234.167
A26: =+D26+F26+H26+J26+L26+N26+P26+R26+T26+V26+X26+Z26+AB26+AD26+AF26+AH26 -> 1 | B26: INSTALACIONES SANITARIAS | C26: 8936.668 | D26: 0 | E26: =+C26*D26 -> 0 | F26: 0 | G26: =+C26*F26 -> 0 | H26: 0 | I26: =+C26*H26 -> 0 | J26: 0 | K26: =+C26*J26 -> 0 | L26: 0 | M26: =+L26*C26 -> 0 | N26: 0 | O26: =+N26*C26 -> 0 | P26: 0 | Q26: =+P26*C26 -> 0 | R26: 0 | S26: =+R26*C26 -> 0 | T26: 0 | U26: =+C26*T26 -> 0 | V26: 0 | W26: =+C26*V26 -> 0 | X26: 0 | Y26: =+C26*X26 -> 0 | Z26: 0 | AA26: =+C26*Z26 -> 0 | AB26: 0.25 | AC26: =+C26*AB26 -> 2234.167 | AD26: 0.25 | AE26: =+C26*AD26 -> 2234.167 | AF26: 0.25 | AG26: =+C26*AF26 -> 2234.167 | AH26: 0.25 | AI26: =+AH26*C26 -> 2234.167
A27: =+C27/$C$30 -> 0.91891892 | B27: COSTO DIRECTO | C27: =+C21+C15+C8+C3 -> 340000 | E27: =+E21+E15+E8+E3 -> 16611.609 | G27: =+G21+G15+G8+G3 -> 19465.501 | I27: =+I21+I15+I8+I3 -> 21116.995 | K27: =+K21+K15+K8+K3 -> 21614.506 | M27: =+M21+M15+M8+M3 -> 22765.64 | O27: =+O21+O15+O8+O3 -> 24161.838 | Q27: =+Q21+Q15+Q8+Q3 -> 24501.278 | S27: =+S21+S15+S8+S3 -> 24143.47 | U27: =+U21+U15+U8+U3 -> 24883.513 | W27: =+W21+W15+W8+W3 -> 23790.953 | Y27: =+Y21+Y15+Y8+Y3 -> 23790.953 | AA27: =+AA21+AA15+AA8+AA3 -> 23043.301 | AC27: =+AC21+AC15+AC8+AC3 -> 19215.628 | AE27: =+AE21+AE15+AE8+AE3 -> 18950.864 | AG27: =+AG21+AG15+AG8+AG3 -> 18950.864 | AI27: =+AI21+AI15+AI8+AI3 -> 12993.085
A28: =+C28/$C$30 -> 0.081081081 | B28: GASTOS GENERALES | C28: 30000 | E28: =+E27*$A$29 -> 1465.7302 | G28: =+G27*$A$29 -> 1717.5442 | I28: =+I27*$A$29 -> 1863.2642 | K28: =+K27*$A$29 -> 1907.1623 | M28: =+M27*$A$29 -> 2008.733 | O28: =+O27*$A$29 -> 2131.9269 | Q28: =+Q27*$A$29 -> 2161.8775 | S28: =+S27*$A$29 -> 2130.3062 | U28: =+U27*$A$29 -> 2195.6041 | W28: =+W27*$A$29 -> 2099.2018 | Y28: =+Y27*$A$29 -> 2099.2018 | AA28: =+AA27*$A$29 -> 2033.2324 | AC28: =+AC27*$A$29 -> 1695.4966 | AE28: =+AE27*$A$29 -> 1672.135 | AG28: =+AG27*$A$29 -> 1672.135 | AI28: =+AI27*$A$29 -> 1146.4487
A29: =+A28/A27 -> 0.088235294 | C29: ============= | E29: ============= | G29: ============= | I29: ============= | K29: ============= | M29: ============= | O29: ============= | Q29: ============= | S29: ============= | U29: ============= | W29: ============= | Y29: ============= | AA29: ============= | AC29: ============= | AE29: ============= | AG29: ============= | AI29: =============
B30: PRESUPUESTO TOTAL | C30: =+C27+C28 -> 370000 | E30: =+E27+E28 -> 18077.34 | G30: =+G27+G28 -> 21183.046 | I30: =+I27+I28 -> 22980.259 | K30: =+K27+K28 -> 23521.669 | M30: =+M27+M28 -> 24774.373 | O30: =+O27+O28 -> 26293.765 | Q30: =+Q27+Q28 -> 26663.155 | S30: =+S27+S28 -> 26273.776 | U30: =+U27+U28 -> 27079.118 | W30: =+W27+W28 -> 25890.155 | Y30: =+Y27+Y28 -> 25890.155 | AA30: =+AA27+AA28 -> 25076.533 | AC30: =+AC27+AC28 -> 20911.125 | AE30: =+AE27+AE28 -> 20622.999 | AG30: =+AG27+AG28 -> 20622.999 | AI30: =+AI27+AI28 -> 14139.534
E31: =+E30/$C$30 -> 0.048857674 | G31: =+G30/$C$30 -> 0.057251475 | I31: =+I30/$C$30 -> 0.062108808 | K31: =+K30/$C$30 -> 0.063572078 | M31: =+M30/$C$30 -> 0.066957766 | O31: =+O30/$C$30 -> 0.071064229 | Q31: =+Q30/$C$30 -> 0.072062582 | S31: =+S30/$C$30 -> 0.071010206 | U31: =+U30/$C$30 -> 0.073186804 | W31: =+W30/$C$30 -> 0.069973392 | Y31: =+Y30/$C$30 -> 0.069973392 | AA31: =+AA30/$C$30 -> 0.067774414 | AC31: =+AC30/$C$30 -> 0.056516553 | AE31: =+AE30/$C$30 -> 0.055737835 | AG31: =+AG30/$C$30 -> 0.055737835 | AI31: =+AI30/$C$30 -> 0.038214956
B32: ADELANTO 15% | C32: -50000 | E32: =+$C$32*E31 -> -2442.8837 | G32: =+$C$32*G31 -> -2862.5737 | I32: =+$C$32*I31 -> -3105.4404 | K32: =+$C$32*K31 -> -3178.6039 | M32: =+$C$32*M31 -> -3347.8883 | O32: =+$C$32*O31 -> -3553.2115 | Q32: =+$C$32*Q31 -> -3603.1291 | S32: =+$C$32*S31 -> -3550.5103 | U32: =+$C$32*U31 -> -3659.3402 | W32: =+$C$32*W31 -> -3498.6696 | Y32: =+$C$32*Y31 -> -3498.6696 | AA32: =+$C$32*AA31 -> -3388.7207 | AC32: =+$C$32*AC31 -> -2825.8277 | AE32: =+$C$32*AE31 -> -2786.8917 | AG32: =+$C$32*AG31 -> -2786.8917 | AI32: =+$C$32*AI31 -> -1910.7478
C33: ============= | E33: ============= | G33: ============= | I33: ============= | K33: ============= | M33: ============= | O33: ============= | Q33: ============= | S33: ============= | U33: ============= | W33: ============= | Y33: ============= | AA33: ============= | AC33: ============= | AE33: ============= | AG33: ============= | AI33: =============
C34: =+C32/C30 -> -0.13513514 | E34: =+E30+E32 -> 15634.456 | G34: =+G30+G32 -> 18320.472 | I34: =+I30+I32 -> 19874.818 | K34: =+K30+K32 -> 20343.065 | M34: =+M30+M32 -> 21426.485 | O34: =+O30+O32 -> 22740.553 | Q34: =+Q30+Q32 -> 23060.026 | S34: =+S30+S32 -> 22723.266 | U34: =+U30+U32 -> 23419.777 | W34: =+W30+W32 -> 22391.486 | Y34: =+Y30+Y32 -> 22391.486 | AA34: =+AA30+AA32 -> 21687.813 | AC34: =+AC30+AC32 -> 18085.297 | AE34: =+AE30+AE32 -> 17836.107 | AG34: =+AG30+AG32 -> 17836.107 | AI34: =+AI30+AI32 -> 12228.786
C38: =+C30/16 -> 23125
C40: VALORIZACIÓN | E40: MONTO
C41: ADELANTO | E41: =-C32 -> 50000
C42: SEMANA 1 | E42: 20000 | G42: =100/16 -> 6.25
C43: SEMANA 2 | E43: 20000
C44: SEMANA 3 | E44: 20000
C45: SEMANA 4 | E45: 20000
C46: SEMANA 5 | E46: 20000
C47: SEMANA 6 | E47: 20000
C48: SEMANA 7 | E48: 20000
C49: SEMANA 8 | E49: 20000
C50: SEMANA 9 | E50: 20000
C51: SEMANA 10 | E51: 20000
C52: SEMANA 11 | E52: 20000
C53: SEMANA 12 | E53: 20000
C54: SEMANA 13 | E54: 20000
... C57: SEMANA 16 | E57: 20000
E58: =============
E59: =SUM(E41:E57) -> 370000

Sheet INSUMOS
B6: MANO DE OBRA | C6: UND | D6: PRECIO UNITARIO
B7: CAPATAZ | C7: hh | D7: =E7/48 -> 49.166667 | E7: =1.18*2000 -> 2360 | F7: SEMANAL
B8: OPERARIO | C8: hh | D8: =E8/48 -> 27.041667 | E8: =1.18*1100 -> 1298 | F8: SEMANAL
B9: OFICIAL | C9: hh | D9: =E9/48 -> 19.666667 | E9: =1.18*800 -> 944 | F9: SEMANAL
B10: PEON | C10: hh | D10: =E10/48 -> 12.291667 | E10: =1.18*500 -> 590 | F10: SEMANAL
B11: MATERIALES | C11: UND | D11: PRECIO UNITARIO
B12: ARENA GRUESA | C12: m3 | D12: =1.18*85 -> 100.3 | E12: =D12*15 -> 1504.5 | F12: CAMION DE 15M3
B13: ARENA FINA | C13: m3 | D13: =1.18*85 -> 100.3 | E13: =D13*15 -> 1504.5 | F13: CAMION DE 15M3
B14: PIEDRA CHANCADA | C14: m3 | D14: =1.18*85 -> 100.3 | E14: =D14*15 -> 1504.5 | F14: CAMION DE 15M3
B15: PIEDRA GRANDE | C15: m3 | D15: =1.18*65 -> 76.7 | E15: =D15*15 -> 1150.5 | F15: CAMION DE 15M3
B16: HORMIGON | C16: m3 | D16: =1.18*75 -> 88.5 | E16: =D16*15 -> 1327.5 | F16: CAMION DE 15M3
B17: AFIRMADO | C17: m3 | D17: =1.18*60 -> 70.8 | E17: =D17*15 -> 1062 | F17: CAMION DE 15M3
B18: CEMENTO PORTLAND TIPO MS (42.5 kg) | C18: bol | D18: 29 | E18: =D18*100 -> 2900 | F18: 100 BOLSAS
B19: CEMENTO PORTLAND TIPO I (42.5 kg) | C19: bol | D19: 31 | E19: =D19*100 -> 3100 | F19: 100 BOLSAS
B20: LADRILLO KK 18 HUECOS 9X13X24 cm | C20: und | D20: 1.2 | E20: =1000*D20 -> 1200 | F20: MILLAR
B21: LADRILLO PANDERETA 9X13X24 cm | C21: und | D21: 1 | E21: =1000*D21 -> 1000 | F21: MILLAR
B22: LADRILLO PARA TECHO 15x30x30 CM | C22: und | D22: 3.5 | E22: =1000*D22 -> 3500 | F22: MILLAR
B23: ALAMBRE NEGRO Nº 8 | C23: kg | D23: 5 | E23: =100*D23 -> 500 | F23: 100 KILOS
B24: ALAMBRE NEGRO Nº 16 | C24: kg | D24: 5 | E24: =100*D24 -> 500 | F24: 100 KILOS
B25: CLAVOS CON CABEZA | C25: kg | D25: 5 | E25: =D25*10 -> 50 | F25: 10 KILOS
B26: MADERA TORNILLO | C26: p2 | D26: 5
B27: ACERO CORRUGADO | C27: kg | D27: 5
B28: MEZCLADORA DE CONCRETO 11P3 | C28: hm | D28: 6
B29: VIBRADOR A GASOLINA 13/4", 4HP | C29: hm | D29: 22
B30: ANDAMIO NORMALIZADO (inc armado) | C30: he | D30: 5
B31: PLANCHA COMPACTADORA VIBRAT. 4HP | C31: he | D31: 15
B32: CAMION VOLQUETE DE 20M3 | C32: hm | D32: 130
B33: CONCRETO PREMEZCLADO f'c=140 kg/cm2 | C33: m3 | D33: 260
B34: CONCRETO PREMEZCLADO f'c=210 kg/cm2 | C34: m3 | D34: 275
B35: CONCRETO PREMEZCLADO f'c=280 kg/cm2 | C35: m3 | D35: 350
B36: BOMBA ESTACIONARIA | C36: m3 | D36: 40
B37: RETROEXCAVADORA CON LLANTAS | C37: hm | D37: 250
... B42: ROTOMARTILLO | C42: he | D42: 12

Sheet COSTO DE ACERO
B2: PEE: | C2: 1010 | D2: ="+IGV" -> +IGV | E2: =C3*C2*1.18/1000 -> 3.99253
B3: PRECIO DEL DÓLAR | C3: 3.35
B5: Descripción | C5: Cantidad de Varillas | D5: Peso (kg/m) | E5: Peso (kg/var) | F5: Peso parcial (kg) | G5: Precio de Varilla ($) | H5: Precio de Varilla (S/.) | I5: Costo Parcial
B6: Varilla de 1.3/8" | D6: 7.433 | E6: =D6*9.05 -> 67.26865 | F6: =C6*E6 -> 0 | G6: =E6*($C$2*1.18)/1000 -> 80.170777 | H6: =G6*$C$3 -> 268.5721 | I6: =C6*H6 -> 0
B7: Varilla de 1" | D7: 3.735 | E7: =D7*9.05 -> 33.80175 | F7: =C7*E7 -> 0 | G7: =E7*($C$2*1.18)/1000 -> 40.284926 | H7: =G7*$C$3 -> 134.9545 | I7: =C7*H7 -> 0
B8: Varilla de 3/4" | D8: 2.101 | E8: =D8*9.05 -> 19.01405 | F8: =C8*E8 -> 0 | G8: =E8*($C$2*1.18)/1000 -> 22.660945 | H8: =G8*$C$3 -> 75.914165 | I8: =C8*H8 -> 0
B9: Varilla de 5/8" | C9: 200 | D9: 1.459 | E9: =D9*9.05 -> 13.20395 | F9: =C9*E9 -> 2640.79 | G9: =E9*($C$2*1.18)/1000 -> 15.736468 | H9: =G9*$C$3 -> 52.717166 | I9: =C9*H9 -> 10543.433
B10: Varilla de 1/2" | C10: 50 | D10: 0.934 | E10: =D10*9.05 -> 8.4527 | F10: =C10*E10 -> 422.635 | G10: =E10*($C$2*1.18)/1000 -> 10.073928 | H10: =G10*$C$3 -> 33.747658 | I10: =C10*H10 -> 1687.3829
B11: Varilla de 12mm | D11: 0.835 | E11: =D11*9.05 -> 7.55675 | F11: =C11*E11 -> 0 | G11: =E11*($C$2*1.18)/1000 -> 9.0061346 | H11: =G11*$C$3 -> 30.170551 | I11: =C11*H11 -> 0
B12: Varilla de 3/8" | C12: 20 | D12: 0.526 | E12: =D12*9.05 -> 4.7603 | F12: =C12*E12 -> 95.206 | G12: =E12*($C$2*1.18)/1000 -> 5.6733255 | H12: =G12*$C$3 -> 19.005641 | I12: =C12*H12 -> 380.11281
B13: Varilla de 8mm | D13: 0.371 | E13: =D13*9.05 -> 3.35755 | F13: =C13*E13 -> 0 | G13: =E13*($C$2*1.18)/1000 -> 4.0015281 | H13: =G13*$C$3 -> 13.405119 | I13: =C13*H13 -> 0
B14: Varilla de 6mm | D14: 0.207 | E14: =D14*9.05 -> 1.87335 | F14: =C14*E14 -> 0 | G14: =E14*($C$2*1.18)/1000 -> 2.2326585 | H14: =G14*$C$3 -> 7.4794061 | I14: =C14*H14 -> 0
E15: PESO TOTAL = | F15: =SUM(F6:F14) -> 3158.631 | H15: COSTO TOTAL = | I15: =SUM(I6:I14) -> 12610.929

Sheet RATIO
A2: PRESUPUESTO DE OBRA - RESUMEN
A3: =+Valorización!B2 -> 0
A4: =+Valorización!B3 -> 0
A5: =+Valorización!B4 -> 0
A7: TIPO DE CAMBIO | B7: 3.86
A9: COSTO POR RATIOS | B9: MONTO | C9: I = INCIDENCIA % | D9: ÁREA CONSTRUIDA | E9: RATIO (s/./m2) | F9: RATIO ($/m2)
A10: MONTO DE CONTRATO | B10: =+B32 -> 266494.84
A12: =+Valorización!B8 -> OBRAS PROVISIONALES, TRABAJOS PRELIMINARES, SEGURIDAD Y SALUD | B12: =SUM(B13:B15) -> 46869.445 | C12: =B12/$B$10 -> 0.17587375 | D12: 150 | E12: =B12/D12 -> 312.46297 | F12: =E12/$B$7 -> 80.948955
A13: =+Valorización!B9 -> OBRAS PROVISIONALES | B13: =+Valorización!J9 -> 10876.107 | C13: =+B13/$B$12 -> 0.23205111 | E13: =+B13/$D$12 -> 72.507378 | F13: =E13/$B$7 -> 18.784295
A14: =+Valorización!B14 -> DEMOLICIÓN Y TRABAJOS PRELIMINARES | B14: =+Valorización!J14 -> 28571.36 | C14: =+B14/$B$12 -> 0.60959459 | E14: =+B14/$D$12 -> 190.47573 | F14: =E14/$B$7 -> 49.346045
A15: =+Valorización!B20 -> SEGURIDAD Y SALUD | B15: =+Valorización!J20 -> 7421.9785 | C15: =+B15/$B$12 -> 0.15835431 | E15: =+B15/$D$12 -> 49.479857 | F15: =E15/$B$7 -> 12.818616
A16: =+Valorización!B25 -> MOVIMIENTO DE TIERRAS | B16: =+Valorización!J25 -> 7667.9579 | D16: 150 | E16: =B16/D16 -> 51.119719 | F16: =E16/$B$7 -> 13.243451
A17: 1ER PISO | B17: =SUM(B18:B23) -> 116030.06 | D17: 150 | E17: =B17/D17 -> 773.53371 | F17: =E17/$B$7 -> 200.39734
A18: =+Valorización!B32 -> CONCRETO SIMPLE | B18: =+Valorización!J32 -> 17227.114 | E18: =+B18/$D$17 -> 114.84742 | F18: =E18/$B$7 -> 29.753219
A19: =+Valorización!B42 -> CONCRETO ARMADO + MUROS PORTANTES | B19: =+Valorización!J42 -> 54821.241 | E19: =+B19/$D$17 -> 365.47494 | F19: =E19/$B$7 -> 94.682627
A20: =+Valorización!B70 -> TABIQUERÍA | B20: =+Valorización!J70 -> 11249.033 | E20: =+B20/$D$17 -> 74.993551 | F20: =E20/$B$7 -> 19.428381
A21: =+Valorización!B73 -> OBRAS HÚMEDAS | B21: =+Valorización!J73 -> 22732.67 | E21: =+B21/$D$17 -> 151.55113 | F21: =E21/$B$7 -> 39.261951
A22: INST. ELÉCTRICAS | B22: 5000
A23: INST. SANITARIAS | B23: 5000
A24: 1ER PISO | B24: =SUM(B25:B29) -> 65927.377 | D24: 150 | E24: =B24/D24 -> 439.51584 | F24: =E24/$B$7 -> 113.86421
A25: =+Valorización!B97 -> CONCRETO ARMADO | B25: =+Valorización!J97 -> 32191.293 | E25: =+B25/$D$17 -> 214.60862 | F25: =E25/$B$7 -> 55.598089
A26: =+Valorización!B115 -> TABIQUE DE LADRILLO | B26: =+Valorización!J115 -> 10686.581 | E26: =+B26/$D$17 -> 71.243873 | F26: =E26/$B$7 -> 18.456962
A27: =+Valorización!B118 -> OBRAS HÚMEDAS | B27: =+Valorización!J118 -> 17049.502 | E27: =+B27/$D$17 -> 113.66335 | F27: =E27/$B$7 -> 29.446463
A28: INST. ELÉCTRICAS | B28: 3000
A29: INST. SANITARIAS | B29: 3000
A30: COSTO DIRECTO | B30: =+B24+B17+B16+B12 -> 236494.84
A31: GASTOS GENERALES | B31: =+Valorización!J184 -> 30000
A32: PRESUPUESTO TOTAL | B32: =SUM(B30:B31) -> 266494.84
B35: MIN | C35: MEDIO | D35: MAX
A36: SEMISOTANO | B36: 320 | C36: 350 | D36: 380
A37: 1ER PISO | B37: 250 | C37: 280 | D37: 300
A38: PISO TIPICO | B38: 200 | C38: 215 | D38: 230
A39: AZOTEA | B39: =B38*1.3 -> 260 | C39: =C38*1.3 -> 279.5 | D39: =D38*1.3 -> 299
A44: 130 | B44: 380 | C44: =+A44*B44 -> 49400 | D44: =C44*3.7 -> 182780
A45: 140 | B45: 230 | C45: =+A45*B45 -> 32200 | D45: =C45*3.7 -> 119140
A46: 140 | B46: 230 | C46: =+A46*B46 -> 32200 | D46: =C46*3.7 -> 119140
A47: 140 | B47: 230 | C47: =+A47*B47 -> 32200 | D47: =C47*3.7 -> 119140
C48: =SUM(C44:C47) -> 146000 | D48: =C48*3.7 -> 540200

Sheet II.EE
A1: PLANILLA DE METRADOS: INSTALACIONES SANITARIAS
A2: PROYECTO: | C2: =+Valorización!B2 -> 0
A3: PROPIETARIO: | C3: =+Valorización!B3 -> 0
A4: UBICACIÓN: | C4: =+Valorización!B4 -> 0
A5: ITEM | C5: DESCRIPCION | D5: UNIDAD | I5: TOTAL
E6: SEMISOTANO | F6: 1er PISO | G6: 2do PISO | H6: 3er PISO
A7: OE. | B7: 0.1 | C7: SALIDAS PARA ALUMBRADO Y TOMACORRIENTES
A8: OE. | B8: 1.01.1 | C8: SALIDAS PARA ALUMBRADO
A9: OE. | B9: 1.01.1.1 | C9: SALIDA PARA CENTRO DE LUZ ADOSADO | D9: PTO | I9: =SUM(E9:H9) -> 0
A10: OE. | B10: 1.01.1.2 | C10: SALIDA PARA BRAQUETE ADOSADO | D10: PTO | I10: =SUM(E10:H10) -> 0
A11: OE. | B11: 1.01.1.3 | C11: SALIDA FLOURECENTE EN TECHO | D11: PTO | I11: =SUM(E11:H11) -> 0
A12: OE. | B12: 1.01.1.4 | C12: SPOT EMPOTRABLE FIJO DE 12V, CON ANILLO ANTIDESLUMBRANTE LAMPARA DICROICA 1xGx5.3 20/50W | D12: PTO | I12: =SUM(E12:H12) -> 0
A13: OE. | B13: 1.01.1.5 | C13: SALIDA PARA BRAQUETE SPOT EMPOTRABLE FIJO MODELO A DEFINIR EN OBRA | D13: PTO | I13: =SUM(E13:H13) -> 0
A14: OE. | B14: 1.01.1.6 | C14: SALIDA PARA LUMINARIA SUSPENDIDA | D14: PTO | I14: =SUM(E14:H14) -> 0
A15: 02. | B15: 0 | C15: SALIDAS DE INTERRUPTORES
A16: 02. | B16: 1 | C16: SALIDA PARA INTERRUPTOR UNIPOLAR SIMPLE 10A, 250V | D16: PTO | I16: =SUM(E16:H16) -> 0
A17: 02. | B17: 1 | C17: SALIDA PARA INTERRUPTOR UNIPOLAR DOBLE 10A, 250V | D17: PTO | I17: =SUM(E17:H17) -> 0
A18: 02. | B18: 2 | C18: SALIDA PARA INTERRUPTOR DE CONMUTACION 10A, 250V | D18: PTO | I18: =SUM(E18:H18) -> 0
A19: 02. | B19: 1 | C19: INTERRUPTOR BIPOLAR CON FUSIBLES | D19: PTO | I19: =SUM(E19:H19) -> 0
A20: 03. | B20: 0 | C20: SALIDAS DE TOMACORRIENTE
A21: 03. | B21: 1 | C21: SALIDA TOMACORRIENTE DOBLE 2P UNIVERSAL ∅ 4.8mm 16A 250 V CON PUESTA A TIERRA | D21: PTO | I21: =SUM(E21:H21) -> 0
A22: 03. | B22: 1 | C22: SALIDA TOMACORRIENTE DOBLE 2P UNIVERSAL ∅ 4.8mm 16A 250 V CON TACTOS LATERALES Y CENTRALES DE TIERRA | D22: PTO | I22: =SUM(E22:H22) -> 0
A23: 03. | B23: 0 | C23: SALIDAS DE FUERZA
A24: 3 | B24: 1 | C24: SALIDA DE FUERZA MONOFÁSICA | D24: PTO | I24: =SUM(E24:H24) -> 0
A25: 03. | B25: 0 | C25: SALIDAS PARA INTERCOMUNICADORES
C26: SALIDA PARA INTERCOMUNICADOR | D26: PTO | I26: =SUM(E26:H26) -> 0
A27: 03. | B27: 0 | C27: SALIDAS DE SEÑALES DEBILES (DATA Y COMUNICACIÓN)
C28: SALIDA PARA TV CABLE | D28: PTO | I28: =SUM(E28:H28) -> 0
C29: SALIDA PARA TELEFONO | D29: PTO | I29: =SUM(E29:H29) -> 0
A30: 04. | B30: 0 | C30: CAJA DE PASE
A31: 4 | B31: 1 | C31: CAJA DE PASO CUADRADA CON TAPA CIEGA | D31: UND. | I31: =SUM(E31:H31) -> 0
A32: 4 | B32: 1 | C32: CAJA DE PASO OCTOGONAL CON TAPA CIEGA | D32: UND. | I32: =SUM(E32:H32) -> 0
A33: 4 | B33: 1 | C33: CAJA TELEFONICA TIPO "C" PARA TELEFONO 650x350x150mm ; h=0.40m. BORDE INFERIOR | D33: UND. | I33: =SUM(E33:H33) -> 0
A34: 4 | B34: 1 | C34: CAJA TIPO TV PARA TV-POR CABLE 650x350x150mm ; h=0.40m. BORDE INFERIOR | D34: UND. | I34: =SUM(E34:H34) -> 0
A35: 4 | B35: 1 | C35: CAJA PASE PARA MONTANTE DE TELEFONOS PORTEROS dimensiones indicado en plano, h=0.40m borde inferior | D35: UND. | I35: =SUM(E35:H35) -> 0
A36: 5 | B36: 0 | C36: TUBERIAS
A37: 0.5 | B37: 1 | C37: ALUMBRADO | D37: ML | I37: =SUM(E37:H37) -> 0
A38: 0.5 | B38: 1 | C38: TOMACORRIENTE TW: 2-1x4mm2 +1x4mm2 (T) - Ø20mm PVC-SAP | D38: ML | I38: =SUM(E38:H38) -> 0
A39: 0.5 | B39: 1 | C39: INTERCOMUNICADOR TW: 2-1x4mm2 +1x4mm2 (T) - Ø20mm PVC-SAP | D39: ML | I39: =SUM(E39:H39) -> 0
A40: 0.5 | B40: 1 | C40: TV CABLE Tubo de 25mmØ PVC-P | D40: ML | I40: =SUM(E40:H40) -> 0
A41: 0.5 | B41: 1 | C41: TELEFONO Tubo de 25mmØ PVC-P | D41: ML | I41: =SUM(E41:H41) -> 0
A42: 08. | B42: 0 | C42: TABLEROS ELECTRICOS
A43: 08. | B43: 1 | C43: TABLERO GENERAL (T-SG) | D43: PZA | I43: =SUM(E43:H43) -> 0
A44: 08. | B44: 2 | C44: TABLERO DE DISTRIBUCION (TD) | D44: PZA | I44: =SUM(E44:H44) -> 0
A45: 10. | B45: 0 | C45: POZO DE TIERRA
A46: 10. | B46: 1 | C46: POZO DE TIERRA INCLUIDO CABLE (R<25 Ohmios) | D46: PZA | I46: =SUM(E46:H46) -> 0
A47: 10. | B47: 0 | C47: ACCESORIOS
A48: 10. | B48: 1 | C48: CERRADURA ELECTRICA | D48: UND. | I48: =SUM(E48:H48) -> 0
A49: 10. | B49: 1 | C49: DIRECTORIO TELEFONO PORTERO O INTERCOMUNICADOR | D49: UND. | I49: =SUM(E49:H49) -> 0

Sheet GG
B2: MONTO DEL CONTRATO | G2: =+RATIO!B10 -> 266494.84 | H2: 0.1 | I2: =G2*H2 -> 26649.484
I4: =+I2-G25 -> -35900.516
A5: ITEM | B5: DESCRIPCION | C5: UND | D5: CANTIDAD | E5: COSTO (S/.) | F5: % PARTIC. | G5: PARCIAL S/.
A7: 1 | B7: GASTOS GENERALES VARIABLES | G7: =SUM(G8:G14) -> 58800
A8: 1.01 | B8: PERSONAL PROFESIONAL
A9: 01.01.01 | B9: GERENTE DE PROYECTO | C9: SEMANA | D9: 21 | E9: 1500 | F9: 1 | G9: =PRODUCT(D9:F9) -> 31500
A10: 01.01.01 | B10: ING. CIVIL, RESIDENTE DE OBRA | C10: SEMANA | D10: 21 | E10: 1000 | F10: 1 | G10: =PRODUCT(D10:F10) -> 21000
A11: 01.01.01 | B11: ADMINISTRADOR | C11: SEMANA | D11: 0 | E11: 250 | F11: 1 | G11: =PRODUCT(D11:F11) -> 0
A12: 01.01.01 | B12: PREVENCIONISTA | C12: SEMANA | D12: 0 | E12: 750 | F12: 1 | G12: =PRODUCT(D12:F12) -> 0
A13: 1.03 | B13: PERSONAL ALMACEN DE OBRA
A14: 01.03.04 | B14: GUARDIAN | C14: SEMANA | D14: 21 | E14: 300 | F14: 1 | G14: =PRODUCT(D14:F14) -> 6300
A15: 2 | B15: GASTOS GENERALES FIJO | G15: =SUM(G16:G18) -> 3750
A16: 2.01 | B16: VARIOS
B17: SINDICATO | C17: SEMANA | D17: 1 | E17: 750 | G17: =PRODUCT(D17:F17) -> 750
B18: EPP | C18: EST | D18: 1 | E18: 3000 | G18: =PRODUCT(D18:F18) -> 3000
B20: GASTOS GENERALES VARIABLES | G20: =+G7 -> 58800 | H20: =G20/$G$2 -> 0.22064217
B21: GASTOS GENERALES FIJOS | G21: =+G15 -> 3750 | H21: =G21/$G$2 -> 0.014071567
B22: GASTOS GENERALES | G22: =SUM(G20:G21) -> 62550 | H22: =G22/$G$2 -> 0.23471374
B23: UTILIDAD | G23: =+G2*H23 -> 0 | H23: 0
B25: GASTOS GENERALES Y UTILIDAD | G25: =G23+G22 -> 62550 | H25: =G25/$G$2 -> 0.23471374
B29: DEPOSITOS | C29: =SUM(C30:C39) -> 30000
B30: 44751 | C30: 3000
B31: 44756 | C31: 17000
B32: 44762 | C32: 10000
