Workbook
Name BI: #REF!
Name H: #REF!
Name Responsable: [1]Responsables!$C$5:$C$34
Name VGD: #REF!

Sheet GASTOS FIJOS + VARIABLES
A1: GASTOS FIJOS MENSUALES
A2: TIPO DE COSTO | B2: SUB TIPO | C2: COSTOS FIJOS | D2: CANTIDAD | E2: UNIDAD | F2: COSTO UNITARIO | G2: SUBTOTAL DEL COSTO
A3: FIJOS | B3: ADMINISTATIVO | C3: LOCAL | D3: 1 | E3: LOCAL | F3: 1200 | G3: =F3*D3 -> 1200
C4: SUNAT | D4: 1 | E4: LOCAL | F4: 1200 | G4: =F4*D4 -> 1200
C5: CONTABILIDAD MENSUAL | D5: 1 | E5: MES | F5: 450 | G5: =F5*D5 -> 450
C6: CONTABILIDAD ANUAL | D6: 12 | E6: MES | F6: 125 | G6: =F6*D6 -> 1500
C7: GERENTE GENERAL + VENDEDOR | D7: 1 | E7: PERSONA | F7: 3500 | G7: =F7*D7 -> 3500
C8: ADMINISTRADOR GENERAL | D8: 1 | E8: PERSONA | F8: 4000 | G8: =F8*D8 -> 4000
C9: SECRETARIA | D9: 1 | E9: PERSONA | F9: 1500 | G9: =F9*D9 -> 1500
C10: GESTORA DE PROYECTOS + INGENIERA | D10: 1 | E10: PERSONA | F10: 2500 | G10: =F10*D10 -> 2500
B11: OPERATIVO | C11: DIBUJANTE CADISTA | D11: =SUM(D12:D12) -> 0 | E11: PERSONA | F11: 1500 | G11: =F11*D11 -> 0
E12: PERSONA
C13: ARQUITECTO JUNIOR | D13: =SUM(D14:D14) -> 1 | E13: PERSONA | F13: 1500 | G13: =F13*D13 -> 1500
C14: ALAN | D14: 1 | E14: PERSONA
C15: ARQUITECTO SEMISENIOR | D15: =SUM(D16:D18) -> 3 | E15: PERSONA | F15: 2500 | G15: =SUM(F15*D15) -> 7500
C16: ANGELO | D16: 1 | E16: PERSONA
C17: KARLA | D17: 1 | E17: PERSONA
C18: PIERINA | D18: 1 | E18: PERSONA
C19: INGENIERO ESTRUC. JUNIOR | D19: =D20 -> 1 | E19: PERSONA | F19: 1500 | G19: =F19*D19 -> 1500
C20: CRISTIAN | D20: 1 | E20: PERSONA
C21: INGENIERO ESTRUCT. SEMISENIOR | D21: =D22 -> 1 | E21: PERSONA | F21: 2500 | G21: =F21*D21 -> 2500
C22: ALDAIR | D22: 1 | E22: PERSONA
C23: INGENIERO SANITARIO SEMISENIOR | D23: =D24 -> 0 | E23: PERSONA | F23: 2300 | G23: =F23*D23 -> 0
E24: PERSONA
C25: INGENIERO ELECTRICO SEMISENIOR | D25: =D26 -> 0 | E25: PERSONA | F25: 2000 | G25: =F25*D25 -> 0
E26: PERSONA
C27: FIRMA ESTRUCTURAL | D27: 1 | E27: PERSONA | F27: 200 | G27: =F27*D27 -> 200
C28: FIRMA ARQUITECTURA | D28: 1 | E28: PERSONA | F28: 500 | G28: =F28*D28 -> 500
C29: FIRMA SANITARIO | D29: 1 | E29: PERSONA | F29: 400 | G29: =F29*D29 -> 400
C30: FIRMA ELECTRICO | D30: 1 | E30: PERSONA | F30: 400 | G30: =F30*D30 -> 400
B31: VENTAS | C31: MARKETERA | D31: 1 | E31: PERSONA | F31: 1500 | G31: =F31*D31 -> 1500
C32: VENDEDORA | D32: 1 | E32: PERSONA | F32: 1500 | G32: =F32*D32 -> 1500
B33: LIMPIEZA | C33: LIMPIEZA | D33: 4 | E33: DIAS | F33: 75 | G33: =D33*F33 -> 300
C34: TOTAL GASTOS FIJOS | G34: =SUM(G3:G10)+G11+G13+G15+G19+G21+G23+G25+G27+G28+G29+G30+G31+G32+G33 -> 33650
A35: GASTOS VARIABLES MENSUALES
A36: TIPO DE COSTO | B36: SUB TIPO | C36: COSTOS FIJOS | D36: CANTIDAD | E36: UNIDAD | F36: COSTO UNITARIO | G36: SUBTOTAL DEL COSTO
A37: OTROS | B37: OTROS | C37: PUBLICIDAD FACEBOOK | D37: 2 | E37: CAMPAÑAS | F37: 400 | G37: =D37*F37 -> 800
C38: PLOTEOS PLANOS | G38: 1500
C39: TOTAL GASTOS FIJOS | G39: =SUM(G37:G38) -> 2300

Sheet EDIT
A1: LEYENDA
A2: Caract. 1 | B2: Caract. 2 | C2: Caract. 3 | D2: ESPECIALIDADES | E2: PUESTOS | F2: CALENDARIO
A3: Exp. Obra (UNIFAMILIAR) | B3: Viv. Unifamiliar | C3: Fuera de Lima | D3: ARQUITECTURA | E3: DIBUJANTE CADISTA | F3: INICIO
A4: Exp. Obra (MULTIFAMILIAR) | B4: Viv. Multifamiliar | C4: Ancón | D4: ESTRUCTURAS | E4: PRACTICANTE DE ARQUITECTURA | F4: MES 1 (PARTE 1)
A5: Exp. Obra (COMERCIO) | B5: Comercio | C5: Carabayllo | D5: INST. SANITARIAS | E5: ARQUITECTO JUNIOR | F5: MES 1 (PARTE 2)
A6: Exp. Licencia mod. A | B6: Casa de Campo | C6: Comas | D6: INST. ELECTRICAS | E6: ARQUITECTO SEMISENIOR | F6: MES 2 (PARTE 1)
A7: Exp. Licencia mod. B | B7: Casa de Playa | C7: Independencia | D7: INST. MECANICAS | E7: ARQUITECTO SEMISENIOR ACCIONISTA | F7: MES 2 (PARTE 2)
A8: Exp. Licencia mod. C | C8: Los Olivos | D8: INST. GAS | E8: ARQUITECTO SEMISENIOR COLEGIADO | F8: MES 3 (PARTE 1)
A9: Exp. Obra + EMS | C9: Puente Piedra | D9: SUELOS | E9: ARQUITECTO SENIOR COLEGIADO | F9: MES 3 (PARTE 2)
A10: Exp. Licencia | C10: San Martín de Porres | D10: GESTIÓN Y ADMINISTRACIÓN | E10: PRACTICANTE DE ESTRUCTURAS | F10: MES 4 (PARTE 1)
A11: EMS | C11: Santa Rosa | E11: INGENIERO ESTRUC. JUNIOR | F11: MES 4 (PARTE 2)
A12: Render | C12: Barranco | E12: INGENIERO ESTRUC. JUNIOR COLEGIADO | F12: MES 5 (PARTE 1)
A13: Visita Tecnica | C13: Breña | E13: INGENIERO ESTRUCT. SEMISENIOR | F13: MES 5 (PARTE 2)
A14: Declaratoria | C14: Jesús María | E14: INGENIERO ESTRUCT. SEMISENIOR COLEGIADO | F14: MES 6 (PARTE 1)
A15: Declaratoria + Independización | C15: La Victoria | E15: INGENIERO ESTRUCT. SENIOR COLEGIADO | F15: MES 6 (PARTE 2)
A16: Independización | C16: Lima | E16: INGENIERO SANITARIO SEMISENIOR
A17: Acumulación de Lotes | C17: Lince | E17: INGENIERO SANITARIO SEMISENIOR COLEGIADO
A18: Subdivisión | C18: Magdalena del Mar | E18: INGENIERO SANITARIO SEMISENIOR COLEGIADO
A19: Tasación | C19: Miraflores | E19: INGENIERO ELECTRICO SEMISENIOR
A20: Solo 1 especialidad | C20: Pueblo Libre | E20: INGENIERO ELECTRICO SEMISENIOR COLEGIADO
A21: Solo memorias | C21: Rímac | E21: INGENIERO SANITARIO SEMISENIOR COLEGIADO
A22: Inspeccion técnica de seguridad en edificacion | C22: San Borja | E22: FIRMA ESTRUCTURAL
A23: Firma | C23: San Isidro | E23: FIRMA ARQUITECTURA
A24: Tramite SEDAPAL | C24: San Miguel | E24: FIRMA SANITARIO
C25: Santiago de Surco | E25: FIRMA ELECTRICO
C26: Surquillo | E26: MARKETERA
C27: Ate | E27: VENDEDORA
C28: Chaclacayo | E28: LIMPIEZA
C29: Cieneguilla | E29: GESTORA DE PROYECTOS
C30: El Agustino
C31: Huaycán (Comunidad)
C32: La Molina
C33: Lurigancho
C34: San Juan de Lurigancho
C35: San Luis
C36: Santa Anita
C37: Chorrillos
C38: Lurín
C39: Pachacamac
C40: Pucusana
C41: Punta Hermosa
... C59: Marcona

Sheet DATOS PROYECTO
A1: CÓDIGO DE PROYECTO | B1: NOMBRE DE CLIENTE | C1: FECHA DE INICIO DE ANALISIS | D1: INICIO DE PROYECTO | E1: TIPO DE PROYECTO | F1: TIPO DE EDIFICACIÓN | G1: DISTRITO
A2: LAM4 -1225- San Miguel - Antonio Burneo | B2: Antonio Burneo | C2: 46052 | D2: 45995 | E2: Exp. Licencia mod. B | F2: Viv. Multifamiliar | G2: Chorrillos

Sheet APUs
A1: ITEM | B1: PARTIDA | C1: SALARIO 2026 | D1: DIAS CALENDARIO LABORADOS | E1: COSTO POR DIA CALENDARIO | F1: HORAS LABORADAS | G1: COSTO POR HORA LABORADAS | H1: % DE RENDIMIENTO IDEAL | I1: % DE RENDIMIENTO REAL
A2: 01.00.00 | B2: ARQUITECTURA
A3: 01.01.00 | B3: PRACTICANTE DE ARQUITECTURA | C3: 1200 | D3: 21 | E3: =C3/D3 -> 57.142857 | F3: 10 | G3: =E3/F3 -> 5.7142857 | H3: 0.75 | I3: 0.75
A4: 01.01.01
A5: 01.02.00 | B5: ARQUITECTO JUNIOR | C5: 1500 | D5: 21 | E5: =C5/D5 -> 71.428571 | F5: 10 | G5: =E5/F5 -> 7.1428571 | H5: 0.85 | I5: 0.85
A6: 01.02.01 | B6: ALAN
A7: 01.03.00 | B7: ARQUITECTO SEMISENIOR | C7: 2500 | D7: 21 | E7: =C7/D7 -> 119.04762 | F7: 10 | G7: =E7/F7 -> 11.904762 | H7: 0.9 | I7: 0.9
A8: 01.03.01 | B8: ANGELO
A9: 01.04.00 | B9: ARQUITECTO SEMISENIOR ACCIONISTA | C9: 3500 | D9: 21 | E9: =C9/D9 -> 166.66667 | F9: 10 | G9: =E9/F9 -> 16.666667 | H9: 0.9 | I9: 0.9
A10: 01.04.01 | B10: PIERINA
A11: 01.05.00 | B11: ARQUITECTO SEMISENIOR COLEGIADO | C11: =SUM(C12:C13) -> 3000 | D11: 21 | E11: =C11/D11 -> 142.85714 | F11: 10 | G11: =E11/F11 -> 14.285714 | H11: 0.97 | I11: 0.97
A12: 01.05.01 | B12: KARLA | C12: 2500
B13: FIRMA DE ARQUITECTURA | C13: 500
A14: 01.06.00 | B14: ARQUITECTO SENIOR COLEGIADO | C14: =SUM(C15:C17) -> 4000 | D14: 21 | E14: =C14/D14 -> 190.47619 | F14: 10 | G14: =E14/F14 -> 19.047619 | H14: 1 | I14: 1 | J14: AL MÁS CAPO, SE LE CONSIDERA COMO RENDIMIENTO 100%..LOS DEMÁS SON EN BASE AL RENDIMIENTO DEL MÁS CAPO. LA PESTAÑA "MAPEO DE HORAS" ES CONSIDERANDO LAS HORAS DEL QUE TIENE UN RENDIMIENTO DE 100%, ES DECIR, DEL MÁS CAPO.
A15: 01.06.01 | B15: XXXX | C15: 3000
B16: FIRMA DE ARQUITECTO | C16: 1000
A17: 02.00.00 | B17: ESTRUCTURAS
A18: 02.01.00 | B18: PRACTICANTE DE ESTRUCTURAS | C18: 1200 | D18: 21 | E18: =C18/D18 -> 57.142857 | F18: 10 | G18: =E18/F18 -> 5.7142857 | H18: 0.75 | I18: 0.75
A19: 02.01.01 | B19: XXXX
A20: 02.02.00 | B20: INGENIERO ESTRUC. JUNIOR | C20: 1500 | D20: 21 | E20: =C20/D20 -> 71.428571 | F20: 10 | G20: =E20/F20 -> 7.1428571 | H20: 0.85 | I20: 0.85
A21: 02.02.01 | B21: CRISTIAN
A22: 02.03.00 | B22: INGENIERO ESTRUC. JUNIOR COLEGIADO | C22: 2500 | D22: 21 | E22: =C22/D22 -> 119.04762 | F22: 10 | G22: =E22/F22 -> 11.904762 | H22: 0.9 | I22: 0.9
A23: 02.03.01 | B23: ALDAIR
A24: 01.04.00 | B24: INGENIERO ESTRUCT. SEMISENIOR | C24: =SUM(C25:C25) -> 3000 | D24: 21 | E24: =C24/D24 -> 142.85714 | F24: 10 | G24: =E24/F24 -> 14.285714 | H24: 0.97 | I24: 0.97
A25: 01.04.01 | B25: OSCAR | C25: 3000
A26: 01.05.00 | B26: INGENIERO ESTRUCT. SEMISENIOR COLEGIADO | C26: =SUM(C27:C28) -> 4000 | D26: 21 | E26: =C26/D26 -> 190.47619 | F26: 10 | G26: =E26/F26 -> 19.047619 | H26: 1 | I26: 1
A27: 01.05.01 | B27: XXXX | C27: 3000
B28: FIRMA DE ESTRUCTURAL | C28: 1000
A29: 01.05.00 | B29: INGENIERO ESTRUCT. SENIOR COLEGIADO | C29: =SUM(C30:C31) -> 5000 | D29: 21 | E29: =C29/D29 -> 238.09524 | F29: 10 | G29: =E29/F29 -> 23.809524 | H29: 1.3 | I29: 1
A30: 01.05.01 | B30: XXXX | C30: 4000
B31: FIRMA DE ESTRUCTURAL | C31: 1000
A32: 03.00.00 | B32: INST. SANITARIAS
A33: 03.01.00 | B33: INGENIERO SANITARIO SEMISENIOR | C33: 2200 | D33: 21 | E33: =C33/D33 -> 104.7619 | F33: 10 | G33: =E33/F33 -> 10.47619 | H33: 0.9 | I33: 0.9
A34: 03.01.01 | B34: KEVIN DIAZ
A35: 03.02.00 | B35: INGENIERO SANITARIO SEMISENIOR COLEGIADO | C35: =SUM(C36:C37) -> 3000 | D35: 21 | E35: =C35/D35 -> 142.85714 | F35: 10 | G35: =E35/F35 -> 14.285714 | H35: 1 | I35: 1
A36: 03.02.01 | B36: XXXX | C36: 2500
B37: FIRMA DE SANITARIO | C37: 500
A38: 04.00.00 | B38: INST. ELECTRICAS
A39: 04.01.00 | B39: INGENIERO ELECTRICO SEMISENIOR | C39: 2200 | D39: 21 | E39: =C39/D39 -> 104.7619 | F39: 10 | G39: =E39/F39 -> 10.47619 | H39: 0.9 | I39: 0.9
A40: 04.01.01 | B40: XXXX
A41: 04.02.00 | B41: INGENIERO SANITARIO SEMISENIOR COLEGIADO | C41: =SUM(C42:C43) -> 3000 | D41: 21 | E41: =C41/D41 -> 142.85714 | F41: 10 | G41: =E41/F41 -> 14.285714 | H41: 1 | I41: 1
A42: 04.02.01 | B42: XXXX | C42: 2500
B43: FIRMA DE SANITARIO | C43: 500
A44: 05.00.00 | B44: INST. GAS
A45: 05.01.00 | B45: INGENIERO ELECTRICO SEMISENIOR | C45: 1200 | D45: 21 | E45: =C45/D45 -> 57.142857 | F45: 10 | G45: =E45/F45 -> 5.7142857 | H45: 0.85 | I45: 0.85
A46: 05.01.01 | B46: XXXX
A47: 05.00.00 | B47: GESTIÓN Y ADMINISTRACIÓN
A48: 05.01.00 | B48: GESTORA DE PROYECTOS | C48: 3500 | D48: 21 | E48: =C48/D48 -> 166.66667 | F48: 10 | G48: =E48/F48 -> 16.666667 | H48: 0.95 | I48: 0.85
A49: 05.01.01 | B49: ROMINA CASALLO

Sheet MH-LAM4 -1225-San Miguel-Antoni
A1: NOMBRE DE PROYECTO | B1: TIPO DE EXPEDIENTE | C1: ESPECIALIDAD | D1: PARTIDA | E1: VERSIÓN | F1: HORAS CALENDARIO TECNICOS LABORADOS PARA PERSONA CON RENDIMIENTO AL 100% | G1: HORAS CALENDARIO EN REUNIONES CON CLIENTES PARA PERSONA CON RENDIMIENTO AL 100% | H1: TOTAL | I1: HORAS ADCIONALES | J1: TOTAL HORAS RESTANTES
A2: LAM4 -1225- San Miguel - Antonio Burneo | B2: Exp. Licencia mod. B | C2: ARQUITECTURA | D2: ARQUITECTURA - Render 3D de interiores | E2: V 3.0 - PRELIMINAR A ENTREGA A MUNI | F2: 12 | H2: =F2+G2 -> 12 | J2: =H2+I2-VLOOKUP(D2,'CONTROL DE HORAS'!D1:BI88,58,FALSE) -> 12 | K2: =IF(J2<0,"CAMBIAR HORAS CALENDARIO!","OK") -> OK
A3: LAM4 -1225- San Miguel - Antonio Burneo | B3: Exp. Licencia mod. B | C3: ARQUITECTURA | D3: ARQUITECTURA - Reunión con cliente para ver interiores | E3: V 3.0 - PRELIMINAR A ENTREGA A MUNI | F3: 12 | H3: =F3+G3 -> 12 | J3: =H3+I3-VLOOKUP(D3,'CONTROL DE HORAS'!D2:BI89,58,FALSE) -> 12 | K3: =IF(J3<0,"CAMBIAR HORAS CALENDARIO!","OK") -> OK
A4: LAM4 -1225- San Miguel - Antonio Burneo | B4: Exp. Licencia mod. B | C4: ARQUITECTURA | D4: TAREAS ADMINISTRATIVAS - Corroborar bloque actualizado en todas las especialidades | E4: V 3.0 - PRELIMINAR A ENTREGA A MUNI | F4: 0 | H4: =F4+G4 -> 0 | J4: =H4+I4-VLOOKUP(D4,'CONTROL DE HORAS'!D3:BI90,58,FALSE) -> 0 | K4: =IF(J4<0,"CAMBIAR HORAS CALENDARIO!","OK") -> OK
A5: LAM4 -1225- San Miguel - Antonio Burneo | B5: Exp. Licencia mod. B | C5: ARQUITECTURA | D5: TAREAS ADMINISTRATIVAS - MANDAR A IMPRENTA PLANOS A PLOTEAR | E5: V 3.0 - PRELIMINAR A ENTREGA A MUNI | F5: 0 | H5: =F5+G5 -> 0 | J5: =H5+I5-VLOOKUP(D5,'CONTROL DE HORAS'!D4:BI91,58,FALSE) -> 0 | K5: =IF(J5<0,"CAMBIAR HORAS CALENDARIO!","OK") -> OK
A6: LAM4 -1225- San Miguel - Antonio Burneo | B6: Exp. Licencia mod. B | C6: ARQUITECTURA | D6: TAREAS ADMINISTRATIVAS - Corroborar membrete de todas las especialidades | E6: V 3.0 - PRELIMINAR A ENTREGA A MUNI | F6: 4 | H6: =F6+G6 -> 4 | J6: =H6+I6-VLOOKUP(D6,'CONTROL DE HORAS'!D5:BI92,58,FALSE) -> 4 | K6: =IF(J6<0,"CAMBIAR HORAS CALENDARIO!","OK") -> OK
A7: LAM4 -1225- San Miguel - Antonio Burneo | B7: Exp. Licencia mod. B | C7: ARQUITECTURA | D7: ARQUITECTURA - Revisión Muni | E7: V 3.1 - ENTREGA TÉCNICA FINAL A MUNI | F7: 0 | H7: =F7+G7 -> 0 | J7: =H7+I7-VLOOKUP(D7,'CONTROL DE HORAS'!D6:BI93,58,FALSE) -> 0 | K7: =IF(J7<0,"CAMBIAR HORAS CALENDARIO!","OK") -> OK
A8: LAM4 -1225- San Miguel - Antonio Burneo | B8: Exp. Licencia mod. B | C8: ARQUITECTURA | D8: ARQUITECTURA - Lev. de observaciones Municipalidad | E8: V 3.0 - PRELIMINAR A ENTREGA A MUNI | F8: 5 | H8: =F8+G8 -> 5 | J8: =H8+I8-VLOOKUP(D8,'CONTROL DE HORAS'!D7:BI94,58,FALSE) -> 5 | K8: =IF(J8<0,"CAMBIAR HORAS CALENDARIO!","OK") -> OK
A9: LAM4 -1225- San Miguel - Antonio Burneo | B9: Exp. Licencia mod. B | C9: ESTRUCTURAS | D9: ESTRUCTURAS - Rev. de Muni | E9: V 3.1 - ENTREGA TÉCNICA FINAL A MUNI | F9: 0 | H9: =F9+G9 -> 0 | J9: =H9+I9-VLOOKUP(D9,'CONTROL DE HORAS'!D9:BI96,58,FALSE) -> 0 | K9: =IF(J9<0,"CAMBIAR HORAS CALENDARIO!","OK") -> OK
A10: LAM4 -1225- San Miguel - Antonio Burneo | B10: Exp. Licencia mod. B | C10: ESTRUCTURAS | D10: ESTRUCTURAS - Lev. de Observaciones de Muni | E10: V 3.0 - PRELIMINAR A ENTREGA A MUNI | F10: 9 | H10: =F10+G10 -> 9 | J10: =H10+I10-VLOOKUP(D10,'CONTROL DE HORAS'!D10:BI97,58,FALSE) -> 9 | K10: =IF(J10<0,"CAMBIAR HORAS CALENDARIO!","OK") -> OK
A11: LAM4 -1225- San Miguel - Antonio Burneo | B11: Exp. Licencia mod. B | C11: INST. ELECTRICAS | D11: IIEE - Lev. de observaciones de Muni | E11: V 3.0 - PRELIMINAR A ENTREGA A MUNI | F11: 4 | H11: =F11+G11 -> 4 | J11: =H11+I11-VLOOKUP(D11,'CONTROL DE HORAS'!D11:BI98,58,FALSE) -> 4 | K11: =IF(J11<0,"CAMBIAR HORAS CALENDARIO!","OK") -> OK
A12: LAM4 -1225- San Miguel - Antonio Burneo | B12: Exp. Licencia mod. B | C12: INST. ELECTRICAS | D12: IIEE - Lev. de observaciones de Revisores | E12: V 2.0 - PRELIMINAR A ENTREGA A REVISORES | F12: 4 | H12: =F12+G12 -> 4 | I12: -4 | J12: =H12+I12-VLOOKUP(D12,'CONTROL DE HORAS'!D12:BI99,58,FALSE) -> 0 | K12: =IF(J12<0,"CAMBIAR HORAS CALENDARIO!","OK") -> OK
A13: LAM4 -1225- San Miguel - Antonio Burneo | B13: Exp. Licencia mod. B | C13: INST. ELECTRICAS | D13: IIEE - Revisión de Revisores | E13: V 2.1 - ENTREGA TÉCNICA FINAL A REVISORES | F13: 0 | H13: =F13+G13 -> 0 | J13: =H13+I13-VLOOKUP(D13,'CONTROL DE HORAS'!D13:BI100,58,FALSE) -> 0 | K13: =IF(J13<0,"CAMBIAR HORAS CALENDARIO!","OK") -> OK
A14: LAM4 -1225- San Miguel - Antonio Burneo | B14: Exp. Licencia mod. B | C14: INST. ELECTRICAS | D14: IIEE - Revisión de Municipalidad | E14: V 3.1 - ENTREGA TÉCNICA FINAL A MUNI | F14: 0 | H14: =F14+G14 -> 0 | J14: =H14+I14-VLOOKUP(D14,'CONTROL DE HORAS'!D14:BI101,58,FALSE) -> 0 | K14: =IF(J14<0,"CAMBIAR HORAS CALENDARIO!","OK") -> OK
A15: LAM4 -1225- San Miguel - Antonio Burneo | B15: Exp. Licencia mod. B | C15: INST. SANITARIAS | D15: IISS - Revisión de Municipalidad | E15: V 3.1 - ENTREGA TÉCNICA FINAL A MUNI | F15: 0 | H15: =F15+G15 -> 0 | J15: =H15+I15-VLOOKUP(D15,'CONTROL DE HORAS'!D15:BI102,58,FALSE) -> 0 | K15: =IF(J15<0,"CAMBIAR HORAS CALENDARIO!","OK") -> OK
A16: LAM4 -1225- San Miguel - Antonio Burneo | B16: Exp. Licencia mod. B | C16: INST. SANITARIAS | D16: IISS - Lev. de observaciones Muni | E16: V 3.0 - PRELIMINAR A ENTREGA A MUNI | F16: 5 | H16: =F16+G16 -> 5 | J16: =H16+I16-VLOOKUP(D16,'CONTROL DE HORAS'!D18:BI105,58,FALSE) -> 5 | K16: =IF(J16<0,"CAMBIAR HORAS CALENDARIO!","OK") -> OK
A17: LAM4 -1225- San Miguel - Antonio Burneo | B17: Exp. Licencia mod. B | C17: INST. GAS | D17: IIGG - Lev. de Observaciones de Muni | E17: V 3.0 - PRELIMINAR A ENTREGA A MUNI | F17: 1 | H17: =F17+G17 -> 1 | J17: =H17+I17-VLOOKUP(D17,'CONTROL DE HORAS'!D21:BI108,58,FALSE) -> 1 | K17: =IF(J17<0,"CAMBIAR HORAS CALENDARIO!","OK") -> OK
A18: LAM4 -1225- San Miguel - Antonio Burneo | B18: Exp. Licencia mod. B | C18: INST. GAS | D18: IIGG - Revisión de Municipalidad | E18: V 3.1 - ENTREGA TÉCNICA FINAL A MUNI | F18: 0 | H18: =F18+G18 -> 0 | J18: =H18+I18-VLOOKUP(D18,'CONTROL DE HORAS'!D22:BI109,58,FALSE) -> 0 | K18: =IF(J18<0,"CAMBIAR HORAS CALENDARIO!","OK") -> OK
A19: LAM4 -1225- San Miguel - Antonio Burneo | B19: Exp. Licencia mod. B | C19: SUELOS | D19: EMS - Excel de ensayos | E19: V 1.0 - PRELIMINAR A LA APROBACIÓN ARQUITECTÓNICA | F19: 0 | H19: =F19+G19 -> 0 | J19: =H19+I19-VLOOKUP(D19,'CONTROL DE HORAS'!D23:BI110,58,FALSE) -> 0 | K19: =IF(J19<0,"CAMBIAR HORAS CALENDARIO!","OK") -> OK
A20: LAM4 -1225- San Miguel - Antonio Burneo | B20: Exp. Licencia mod. B | C20: SUELOS | D20: EMS - Plano topográfico | E20: V 2.0 - PRELIMINAR A ENTREGA A REVISORES | F20: 0 | H20: =F20+G20 -> 0 | J20: =H20+I20-VLOOKUP(D20,'CONTROL DE HORAS'!D24:BI111,58,FALSE) -> 0 | K20: =IF(J20<0,"CAMBIAR HORAS CALENDARIO!","OK") -> OK
A21: LAM4 -1225- San Miguel - Antonio Burneo | B21: Exp. Licencia mod. B | C21: SUELOS | D21: EMS - Informe de EMS | E21: V 2.0 - PRELIMINAR A ENTREGA A REVISORES | F21: 0 | H21: =F21+G21 -> 0 | J21: =H21+I21-VLOOKUP(D21,'CONTROL DE HORAS'!D25:BI112,58,FALSE) -> 0 | K21: =IF(J21<0,"CAMBIAR HORAS CALENDARIO!","OK") -> OK
A22: LAM4 -1225- San Miguel - Antonio Burneo | B22: Exp. Licencia mod. B | C22: GESTIÓN Y ADMINISTRACIÓN | D22: TAREAS ADMINISTRATIVAS - COORDINAR ENTREGA DE EXPEDIENTE CON CLIENTE | E22: V 2.0 - PRELIMINAR A ENTREGA A REVISORES | F22: 0 | H22: =F22+G22 -> 0 | J22: =H22+I22-VLOOKUP(D22,'CONTROL DE HORAS'!D26:BI113,58,FALSE) -> 0 | K22: =IF(J22<0,"CAMBIAR HORAS CALENDARIO!","OK") -> OK
A23: LAM4 -1225- San Miguel - Antonio Burneo | B23: Exp. Licencia mod. B | C23: GESTIÓN Y ADMINISTRACIÓN | D23: TAREAS ADMINISTRATIVAS - Entrega de expediente impreso a cliente | E23: V 2.1 - ENTREGA TÉCNICA FINAL A REVISORES | F23: 0 | H23: =F23+G23 -> 0 | J23: =H23+I23-VLOOKUP(D23,'CONTROL DE HORAS'!D27:BI114,58,FALSE) -> 0 | K23: =IF(J23<0,"CAMBIAR HORAS CALENDARIO!","OK") -> OK

Sheet CONTROL DE HORAS
A1: CODIGO | B1: TIPO DE PROYECTO | C1: ITEM | D1: PARTIDA | E1: FASE | F1: NIVEL DE COMPLEJIDAD | G1: P. UNITARIO / FACTOR SEGUN NIVEL DE COMPLEJIDAD | H1: HORAS CALENDARIO TECNICOS LABORADOS | I1: HORAS CALENDARIO EN REUNIONES CON CLIENTES | J1: % DE RENDIMIENTO PROYECTADO | K1: SUBTOTAL DEL COSTO | M1: % PROGR. | N1: % EJEC. | O1: HORAS | P1: PRECIO | Q1: % PROGR. | R1: % EJEC. | S1: HORAS | T1: PRECIO | U1: % PROGR. | V1: % EJEC. | W1: HORAS | X1: PRECIO | Y1: % PROGR. | Z1: % EJEC. | AA1: HORAS | AB1: PRECIO | AC1: % PROGR. | AD1: % EJEC. | AE1: HORAS | AF1: PRECIO | AG1: % PROGR. | AH1: % EJEC. | AI1: HORAS | AJ1: PRECIO | AK1: % PROGR. | AL1: % EJEC. | AM1: HORAS | AN1: PRECIO | AO1: % PROGR. | AP1: % EJEC. | AQ1: HORAS | AR1: PRECIO | AS1: % PROGR. | AT1: % EJEC. | AU1: HORAS | AV1: PRECIO | AW1: % PROGR. | AX1: % EJEC. | AY1: HORAS | AZ1: PRECIO | BA1: % PROGR. | BB1: % EJEC. | BC1: HORAS | BD1: PRECIO | BE1: % PROGR. | BF1: % EJEC. | BG1: HORAS | BH1: PRECIO | BI1: HORAS CALENDARIO TECNICOS LABORADOS | BJ1: SUBTOTAL DEL COSTO | BK1: % DE RENDIMIENTO REAL
M2: =VLOOKUP(A5,'DATOS PROYECTO'!A1:G10,3,FALSE) -> 46052 | N2: HASTA | O2: =M2+15 -> 46067 | Q2: =O2+1 -> 46068 | R2: HASTA | S2: =Q2+15 -> 46083 | U2: =S2+1 -> 46084 | V2: HASTA | W2: =U2+15 -> 46099 | Y2: =W2+1 -> 46100 | Z2: HASTA | AA2: =Y2+15 -> 46115 | AC2: =AA2+1 -> 46116 | AD2: HASTA | AE2: =AC2+15 -> 46131 | AG2: =AE2+1 -> 46132 | AH2: HASTA | AI2: =AG2+15 -> 46147 | AK2: =AI2+1 -> 46148 | AL2: HASTA | AM2: =AK2+15 -> 46163 | AO2: =AM2+1 -> 46164 | AP2: HASTA | AQ2: =AO2+15 -> 46179 | AS2: =AQ2+1 -> 46180 | AT2: HASTA | AU2: =AS2+15 -> 46195 | AW2: =AU2+1 -> 46196 | AX2: HASTA | AY2: =AW2+15 -> 46211 | BA2: =AY2+1 -> 46212 | BB2: HASTA | BC2: =BA2+15 -> 46227 | BE2: =BC2+1 -> 46228 | BF2: HASTA | BG2: =BE2+15 -> 46243
M3: MES 1 (PARTE 1) | Q3: MES 1 (PARTE 2) | U3: MES 2 (PARTE 1) | Y3: MES 2 (PARTE 2) | AC3: MES 3 (PARTE 1) | AG3: MES 3 (PARTE 2) | AK3: MES 4 (PARTE 1) | AO3: MES 4 (PARTE 2) | AS3: MES 5 (PARTE 1) | AW3: MES 5 (PARTE 2) | BA3: MES 6 (PARTE 1) | BE3: MES 6 (PARTE 2)
M4: =AVERAGE(M6,M19,M28,M34,M41,M51,M56) -> 0 | N4: =AVERAGE(N6,N19,N28,N34,N41,N51,N56) -> 0 | Q4: =AVERAGE(Q6,Q19,Q28,Q34,Q41,Q51,Q56) -> 0 | R4: =AVERAGE(R6,R19,R28,R34,R41,R51,R56) -> 0 | U4: =AVERAGE(U6,U19,U28,U34,U41,U51,U56) -> 0 | V4: =AVERAGE(V6,V19,V28,V34,V41,V51,V56) -> 0 | Y4: =AVERAGE(Y6,Y19,Y28,Y34,Y41,Y51,Y56) -> 0 | Z4: =AVERAGE(Z6,Z19,Z28,Z34,Z41,Z51,Z56) -> 0 | AC4: =AVERAGE(AC6,AC19,AC28,AC34,AC41,AC51,AC56) -> 0 | AD4: =AVERAGE(AD6,AD19,AD28,AD34,AD41,AD51,AD56) -> 0 | AG4: =AVERAGE(AG6,AG19,AG28,AG34,AG41,AG51,AG56) -> 0 | AH4: =AVERAGE(AH6,AH19,AH28,AH34,AH41,AH51,AH56) -> 0 | AK4: =AVERAGE(AK6,AK19,AK28,AK34,AK41,AK51,AK56) -> 0 | AL4: =AVERAGE(AL6,AL19,AL28,AL34,AL41,AL51,AL56) -> 0 | AO4: =AVERAGE(AO6,AO19,AO28,AO34,AO41,AO51,AO56) -> 0 | AP4: =AVERAGE(AP6,AP19,AP28,AP34,AP41,AP51,AP56) -> 0 | AS4: =AVERAGE(AS6,AS19,AS28,AS34,AS41,AS51,AS56) -> 0 | AT4: =AVERAGE(AT6,AT19,AT28,AT34,AT41,AT51,AT56) -> 0 | AW4: =AVERAGE(AW6,AW19,AW28,AW34,AW41,AW51,AW56) -> 0 | AX4: =AVERAGE(AX6,AX19,AX28,AX34,AX41,AX51,AX56) -> 0 | BA4: =AVERAGE(BA6,BA19,BA28,BA34,BA41,BA51,BA56) -> 0 | BB4: =AVERAGE(BB6,BB19,BB28,BB34,BB41,BB51,BB56) -> 0 | BE4: =AVERAGE(BE6,BE19,BE28,BE34,BE41,BE51,BE56) -> 0 | BF4: =AVERAGE(BF6,BF19,BF28,BF34,BF41,BF51,BF56) -> 0
A5: LAM4 -1225- San Miguel - Antonio Burneo | B5: =VLOOKUP(A5,DatosProyecto[#All],5,FALSE) -> Exp. Licencia mod. B | C5: 01.00.00 | D5: ARQUITECTURA | M5: =M6 -> 0 | N5: =N6 -> 0 | O5: =O6 -> 0 | P5: =P6 -> 0 | Q5: =Q6 -> 0 | R5: =R6 -> 0 | S5: =S6 -> 0 | T5: =T6 -> 0 | ... BH5: =BH6 -> 0
C6: 01.01.00 | D6: ARQUITECTO SEMISENIOR ACCIONISTA | G6: =VLOOKUP(D6,APUs!$B$2:$G$50,6,FALSE) -> 16.666667 | H6: =SUM(H7:H17) -> #REF! | I6: =SUM(I7:I17) -> #REF! | J6: =VLOOKUP($D$6,APUs!$B$2:$I$50,7,FALSE) -> 0.9 | K6: =$G$6*(H6+I6)/J6 -> #REF! | M6: =IFERROR(AVERAGE(M7:M17),"0") -> 0 | N6: =IFERROR(AVERAGE(N7:N17),0) -> 0 | O6: =IFERROR(SUM(O7:O17),0) -> 0 | P6: =IFERROR(SUM(P7:P17),0) -> 0 | Q6: =IFERROR(AVERAGE(Q7:Q17),"0") -> 0 | R6: =IFERROR(AVERAGE(R7:R17),0) -> 0 | S6: =IFERROR(SUM(S7:S17),0) -> 0 | T6: =IFERROR(SUM(T7:T17),0) -> 0 | U6: =IFERROR(AVERAGE(U7:U17),"0") -> 0 | V6: =IFERROR(AVERAGE(V7:V17),0) -> 0 | W6: =IFERROR(SUM(W7:W17),0) -> 0 | X6: =IFERROR(SUM(X7:X17),0) -> 0 | Y6: =IFERROR(AVERAGE(Y7:Y17),"0") -> 0 | Z6: =IFERROR(AVERAGE(Z7:Z17),0) -> 0 | AA6: =IFERROR(SUM(AA7:AA17),0) -> 0 | AB6: =IFERROR(SUM(AB7:AB17),0) -> 0 | AC6: =IFERROR(AVERAGE(AC7:AC17),"0") -> 0 | AD6: =IFERROR(AVERAGE(AD7:AD17),0) -> 0 | AE6: =IFERROR(SUM(AE7:AE17),0) -> 0 | AF6: =IFERROR(SUM(AF7:AF17),0) -> 0 | AG6: =IFERROR(AVERAGE(AG7:AG17),"0") -> 0 | AH6: =IFERROR(AVERAGE(AH7:AH17),0) -> 0 | AI6: =IFERROR(SUM(AI7:AI17),0) -> 0 | AJ6: =IFERROR(SUM(AJ7:AJ17),0) -> 0 | AK6: =IFERROR(AVERAGE(AK7:AK17),"0") -> 0 | AL6: =IFERROR(AVERAGE(AL7:AL17),0) -> 0 | AM6: =IFERROR(SUM(AM7:AM17),0) -> 0 | AN6: =IFERROR(SUM(AN7:AN17),0) -> 0 | AO6: =IFERROR(AVERAGE(AO7:AO17),"0") -> 0 | AP6: =IFERROR(AVERAGE(AP7:AP17),0) -> 0 | AQ6: =IFERROR(SUM(AQ7:AQ17),0) -> 0 | AR6: =IFERROR(SUM(AR7:AR17),0) -> 0 | AS6: =IFERROR(AVERAGE(AS7:AS17),"0") -> 0 | AT6: =IFERROR(AVERAGE(AT7:AT17),0) -> 0 | AU6: =IFERROR(SUM(AU7:AU17),0) -> 0 | AV6: =IFERROR(SUM(AV7:AV17),0) -> 0 | AW6: =IFERROR(AVERAGE(AW7:AW17),"0") -> 0 | AX6: =IFERROR(AVERAGE(AX7:AX17),0) -> 0 | AY6: =IFERROR(SUM(AY7:AY17),0) -> 0 | AZ6: =IFERROR(SUM(AZ7:AZ17),0) -> 0 | BA6: =IFERROR(AVERAGE(BA7:BA17),"0") -> 0 | BB6: =IFERROR(AVERAGE(BB7:BB17),0) -> 0 | BC6: =IFERROR(SUM(BC7:BC17),0) -> 0 | BD6: =IFERROR(SUM(BD7:BD17),0) -> 0 | BE6: =IFERROR(AVERAGE(BE7:BE17),"0") -> 0 | BF6: =IFERROR(AVERAGE(BF7:BF17),0) -> 0 | BG6: =IFERROR(SUM(BG7:BG17),0) -> 0 | BH6: =IFERROR(SUM(BH7:BH17),0) -> 0 | BI6: =O6+S6+W6+AA6+AE6+AI6+AM6+AQ6+AU6+AY6+BC6+BG6 -> 0 | BJ6: =BI6*$G$6 -> 0 | BK6: =J6*(H6+I6)/(BI6) -> #REF!
C7: 01.01.01 | D7: ='MH-LAM4 -1225-San Miguel-Antoni'!D2 -> ARQUITECTURA - Render 3D de interiores | E7: =VLOOKUP(D7,'MH-LAM4 -1225-San Miguel-Antoni'!$D$2:$E$84,2,FALSE) -> V 3.0 - PRELIMINAR A ENTREGA A MUNI | F7: MEDIA | G7: =IF(F7="BAJA",0.8,IF(F7="MEDIA",1,IF(F7="ALTA",1.4,IF(F7="MUY ALTA",2)))) -> 1 | H7: {=G7*INDEX('MH-LAM4 -1225-San Miguel-Antoni'!$B$2:$G$68,MATCH($D$5&D7&$B$5,'MH-LAM4 -1225-San Miguel-Antoni'!$C$2:$C$68&'MH-LAM4 -1225-San Miguel-Antoni'!$D$2:$D$68&'MH-LAM4 -1225-San Miguel-Antoni'!$B$2:$B$68,0),5)/J7} -> 13.333333 | I7: {=G7*INDEX('MH-LAM4 -1225-San Miguel-Antoni'!$B$2:$G$68,MATCH($D$5&D7&$B$5,'MH-LAM4 -1225-San Miguel-Antoni'!$C$2:$C$68&'MH-LAM4 -1225-San Miguel-Antoni'!$D$2:$D$68&'MH-LAM4 -1225-San Miguel-Antoni'!$B$2:$B$68,0),6)/J7} -> 0 | J7: =VLOOKUP($D$6,APUs!$B$2:$I$50,7,FALSE) -> 0.9 | K7: =$G$6*(H7+I7)/J7 -> 246.91358 | P7: =O7*$G$6 -> 0 | T7: =S7*$G$6 -> 0 | X7: =W7*$G$6 -> 0 | AB7: =AA7*$G$6 -> 0 | AF7: =AE7*$G$6 -> 0 | AJ7: =AI7*$G$6 -> 0 | AN7: =AM7*$G$6 -> 0 | AR7: =AQ7*$G$6 -> 0 | AV7: =AU7*$G$6 -> 0 | AZ7: =AY7*$G$6 -> 0 | BD7: =BC7*$G$6 -> 0 | BH7: =BG7*$G$6 -> 0 | BI7: =O7+S7+W7+AA7+AE7+AI7+AM7+AQ7+AU7+AY7+BC7+BG7 -> 0
C8: 01.01.02 | D8: ='MH-LAM4 -1225-San Miguel-Antoni'!D3 -> ARQUITECTURA - Reunión con cliente para ver interiores | E8: =VLOOKUP(D8,'MH-LAM4 -1225-San Miguel-Antoni'!$D$2:$E$84,2,FALSE) -> V 3.0 - PRELIMINAR A ENTREGA A MUNI | F8: MEDIA | G8: =IF(F8="BAJA",0.8,IF(F8="MEDIA",1,IF(F8="ALTA",1.4,IF(F8="MUY ALTA",2)))) -> 1 | H8: {=G8*INDEX('MH-LAM4 -1225-San Miguel-Antoni'!$B$2:$G$68,MATCH($D$5&D8&$B$5,'MH-LAM4 -1225-San Miguel-Antoni'!$C$2:$C$68&'MH-LAM4 -1225-San Miguel-Antoni'!$D$2:$D$68&'MH-LAM4 -1225-San Miguel-Antoni'!$B$2:$B$68,0),5)/J8} -> 13.333333 | I8: {=G8*INDEX('MH-LAM4 -1225-San Miguel-Antoni'!$B$2:$G$68,MATCH($D$5&D8&$B$5,'MH-LAM4 -1225-San Miguel-Antoni'!$C$2:$C$68&'MH-LAM4 -1225-San Miguel-Antoni'!$D$2:$D$68&'MH-LAM4 -1225-San Miguel-Antoni'!$B$2:$B$68,0),6)/J8} -> 0 | J8: =VLOOKUP($D$6,APUs!$B$2:$I$50,7,FALSE) -> 0.9 | K8: =$G$6*(H8+I8)/J8 -> 246.91358 | P8: =O8*$G$6 -> 0 | T8: =S8*$G$6 -> 0 | X8: =W8*$G$6 -> 0 | AB8: =AA8*$G$6 -> 0 | AF8: =AE8*$G$6 -> 0 | AJ8: =AI8*$G$6 -> 0 | AN8: =AM8*$G$6 -> 0 | AR8: =AQ8*$G$6 -> 0 | AV8: =AU8*$G$6 -> 0 | AZ8: =AY8*$G$6 -> 0 | BD8: =BC8*$G$6 -> 0 | BH8: =BG8*$G$6 -> 0 | BI8: =O8+S8+W8+AA8+AE8+AI8+AM8+AQ8+AU8+AY8+BC8+BG8 -> 0
C9: 01.01.02 | D9: ='MH-LAM4 -1225-San Miguel-Antoni'!D4 -> TAREAS ADMINISTRATIVAS - Corroborar bloque actualizado en todas las especialidades | E9: =VLOOKUP(D9,'MH-LAM4 -1225-San Miguel-Antoni'!$D$2:$E$84,2,FALSE) -> V 3.0 - PRELIMINAR A ENTREGA A MUNI | F9: MEDIA | G9: =IF(F9="BAJA",0.8,IF(F9="MEDIA",1,IF(F9="ALTA",1.4,IF(F9="MUY ALTA",2)))) -> 1 | H9: {=G9*INDEX('MH-LAM4 -1225-San Miguel-Antoni'!$B$2:$G$68,MATCH($D$5&D9&$B$5,'MH-LAM4 -1225-San Miguel-Antoni'!$C$2:$C$68&'MH-LAM4 -1225-San Miguel-Antoni'!$D$2:$D$68&'MH-LAM4 -1225-San Miguel-Antoni'!$B$2:$B$68,0),5)/J9} -> 0 | I9: {=G9*INDEX('MH-LAM4 -1225-San Miguel-Antoni'!$B$2:$G$68,MATCH($D$5&D9&$B$5,'MH-LAM4 -1225-San Miguel-Antoni'!$C$2:$C$68&'MH-LAM4 -1225-San Miguel-Antoni'!$D$2:$D$68&'MH-LAM4 -1225-San Miguel-Antoni'!$B$2:$B$68,0),6)/J9} -> 0 | J9: =VLOOKUP($D$6,APUs!$B$2:$I$50,7,FALSE) -> 0.9 | K9: =$G$6*(H9+I9)/J9 -> 0 | P9: =O9*$G$6 -> 0 | T9: =S9*$G$6 -> 0 | X9: =W9*$G$6 -> 0 | AB9: =AA9*$G$6 -> 0 | AF9: =AE9*$G$6 -> 0 | AJ9: =AI9*$G$6 -> 0 | AN9: =AM9*$G$6 -> 0 | AR9: =AQ9*$G$6 -> 0 | AV9: =AU9*$G$6 -> 0 | AZ9: =AY9*$G$6 -> 0 | BD9: =BC9*$G$6 -> 0 | BH9: =BG9*$G$6 -> 0 | BI9: =O9+S9+W9+AA9+AE9+AI9+AM9+AQ9+AU9+AY9+BC9+BG9 -> 0
C10: 01.01.02 | D10: ='MH-LAM4 -1225-San Miguel-Antoni'!D5 -> TAREAS ADMINISTRATIVAS - MANDAR A IMPRENTA PLANOS A PLOTEAR | E10: =VLOOKUP(D10,'MH-LAM4 -1225-San Miguel-Antoni'!$D$2:$E$84,2,FALSE) -> V 3.0 - PRELIMINAR A ENTREGA A MUNI | F10: MEDIA | G10: =IF(F10="BAJA",0.8,IF(F10="MEDIA",1,IF(F10="ALTA",1.4,IF(F10="MUY ALTA",2)))) -> 1 | H10: {=G10*INDEX('MH-LAM4 -1225-San Miguel-Antoni'!$B$2:$G$68,MATCH($D$5&D10&$B$5,'MH-LAM4 -1225-San Miguel-Antoni'!$C$2:$C$68&'MH-LAM4 -1225-San Miguel-Antoni'!$D$2:$D$68&'MH-LAM4 -1225-San Miguel-Antoni'!$B$2:$B$68,0),5)/J10} -> 0 | I10: {=G10*INDEX('MH-LAM4 -1225-San Miguel-Antoni'!$B$2:$G$68,MATCH($D$5&D10&$B$5,'MH-LAM4 -1225-San Miguel-Antoni'!$C$2:$C$68&'MH-LAM4 -1225-San Miguel-Antoni'!$D$2:$D$68&'MH-LAM4 -1225-San Miguel-Antoni'!$B$2:$B$68,0),6)/J10} -> 0 | J10: =VLOOKUP($D$6,APUs!$B$2:$I$50,7,FALSE) -> 0.9 | K10: =$G$6*(H10+I10)/J10 -> 0 | P10: =O10*$G$6 -> 0 | T10: =S10*$G$6 -> 0 | X10: =W10*$G$6 -> 0 | AB10: =AA10*$G$6 -> 0 | AF10: =AE10*$G$6 -> 0 | AJ10: =AI10*$G$6 -> 0 | AN10: =AM10*$G$6 -> 0 | AR10: =AQ10*$G$6 -> 0 | AV10: =AU10*$G$6 -> 0 | AZ10: =AY10*$G$6 -> 0 | BD10: =BC10*$G$6 -> 0 | BH10: =BG10*$G$6 -> 0 | BI10: =O10+S10+W10+AA10+AE10+AI10+AM10+AQ10+AU10+AY10+BC10+BG10 -> 0
C11: 01.01.02 | D11: ='MH-LAM4 -1225-San Miguel-Antoni'!D6 -> TAREAS ADMINISTRATIVAS - Corroborar membrete de todas las especialidades | E11: =VLOOKUP(D11,'MH-LAM4 -1225-San Miguel-Antoni'!$D$2:$E$84,2,FALSE) -> V 3.0 - PRELIMINAR A ENTREGA A MUNI | F11: MEDIA | G11: =IF(F11="BAJA",0.8,IF(F11="MEDIA",1,IF(F11="ALTA",1.4,IF(F11="MUY ALTA",2)))) -> 1 | H11: {=G11*INDEX('MH-LAM4 -1225-San Miguel-Antoni'!$B$2:$G$68,MATCH($D$5&D11&$B$5,'MH-LAM4 -1225-San Miguel-Antoni'!$C$2:$C$68&'MH-LAM4 -1225-San Miguel-Antoni'!$D$2:$D$68&'MH-LAM4 -1225-San Miguel-Antoni'!$B$2:$B$68,0),5)/J11} -> 4.4444444 | I11: {=G11*INDEX('MH-LAM4 -1225-San Miguel-Antoni'!$B$2:$G$68,MATCH($D$5&D11&$B$5,'MH-LAM4 -1225-San Miguel-Antoni'!$C$2:$C$68&'MH-LAM4 -1225-San Miguel-Antoni'!$D$2:$D$68&'MH-LAM4 -1225-San Miguel-Antoni'!$B$2:$B$68,0),6)/J11} -> 0 | J11: =VLOOKUP($D$6,APUs!$B$2:$I$50,7,FALSE) -> 0.9 | K11: =$G$6*(H11+I11)/J11 -> 82.304527 | P11: =O11*$G$6 -> 0 | T11: =S11*$G$6 -> 0 | X11: =W11*$G$6 -> 0 | AB11: =AA11*$G$6 -> 0 | AF11: =AE11*$G$6 -> 0 | AJ11: =AI11*$G$6 -> 0 | AN11: =AM11*$G$6 -> 0 | AR11: =AQ11*$G$6 -> 0 | AV11: =AU11*$G$6 -> 0 | AZ11: =AY11*$G$6 -> 0 | BD11: =BC11*$G$6 -> 0 | BH11: =BG11*$G$6 -> 0 | BI11: =O11+S11+W11+AA11+AE11+AI11+AM11+AQ11+AU11+AY11+BC11+BG11 -> 0
C12: 01.01.02 | D12: ='MH-LAM4 -1225-San Miguel-Antoni'!D7 -> ARQUITECTURA - Revisión Muni | E12: =VLOOKUP(D12,'MH-LAM4 -1225-San Miguel-Antoni'!$D$2:$E$84,2,FALSE) -> V 3.1 - ENTREGA TÉCNICA FINAL A MUNI | F12: MEDIA | G12: =IF(F12="BAJA",0.8,IF(F12="MEDIA",1,IF(F12="ALTA",1.4,IF(F12="MUY ALTA",2)))) -> 1 | H12: {=G12*INDEX('MH-LAM4 -1225-San Miguel-Antoni'!$B$2:$G$68,MATCH($D$5&D12&$B$5,'MH-LAM4 -1225-San Miguel-Antoni'!$C$2:$C$68&'MH-LAM4 -1225-San Miguel-Antoni'!$D$2:$D$68&'MH-LAM4 -1225-San Miguel-Antoni'!$B$2:$B$68,0),5)/J12} -> 0 | I12: {=G12*INDEX('MH-LAM4 -1225-San Miguel-Antoni'!$B$2:$G$68,MATCH($D$5&D12&$B$5,'MH-LAM4 -1225-San Miguel-Antoni'!$C$2:$C$68&'MH-LAM4 -1225-San Miguel-Antoni'!$D$2:$D$68&'MH-LAM4 -1225-San Miguel-Antoni'!$B$2:$B$68,0),6)/J12} -> 0 | J12: =VLOOKUP($D$6,APUs!$B$2:$I$50,7,FALSE) -> 0.9 | K12: =$G$6*(H12+I12)/J12 -> 0 | P12: =O12*$G$6 -> 0 | T12: =S12*$G$6 -> 0 | X12: =W12*$G$6 -> 0 | AB12: =AA12*$G$6 -> 0 | AF12: =AE12*$G$6 -> 0 | AJ12: =AI12*$G$6 -> 0 | AN12: =AM12*$G$6 -> 0 | AR12: =AQ12*$G$6 -> 0 | AV12: =AU12*$G$6 -> 0 | AZ12: =AY12*$G$6 -> 0 | BD12: =BC12*$G$6 -> 0 | BH12: =BG12*$G$6 -> 0 | BI12: =O12+S12+W12+AA12+AE12+AI12+AM12+AQ12+AU12+AY12+BC12+BG12 -> 0
C13: 01.01.02 | D13: ='MH-LAM4 -1225-San Miguel-Antoni'!D8 -> ARQUITECTURA - Lev. de observaciones Municipalidad | E13: =VLOOKUP(D13,'MH-LAM4 -1225-San Miguel-Antoni'!$D$2:$E$84,2,FALSE) -> V 3.0 - PRELIMINAR A ENTREGA A MUNI | F13: MEDIA | G13: =IF(F13="BAJA",0.8,IF(F13="MEDIA",1,IF(F13="ALTA",1.4,IF(F13="MUY ALTA",2)))) -> 1 | H13: {=G13*INDEX('MH-LAM4 -1225-San Miguel-Antoni'!$B$2:$G$68,MATCH($D$5&D13&$B$5,'MH-LAM4 -1225-San Miguel-Antoni'!$C$2:$C$68&'MH-LAM4 -1225-San Miguel-Antoni'!$D$2:$D$68&'MH-LAM4 -1225-San Miguel-Antoni'!$B$2:$B$68,0),5)/J13} -> 5.5555556 | I13: {=G13*INDEX('MH-LAM4 -1225-San Miguel-Antoni'!$B$2:$G$68,MATCH($D$5&D13&$B$5,'MH-LAM4 -1225-San Miguel-Antoni'!$C$2:$C$68&'MH-LAM4 -1225-San Miguel-Antoni'!$D$2:$D$68&'MH-LAM4 -1225-San Miguel-Antoni'!$B$2:$B$68,0),6)/J13} -> 0 | J13: =VLOOKUP($D$6,APUs!$B$2:$I$50,7,FALSE) -> 0.9 | K13: =$G$6*(H13+I13)/J13 -> 102.88066 | P13: =O13*$G$6 -> 0 | T13: =S13*$G$6 -> 0 | X13: =W13*$G$6 -> 0 | AB13: =AA13*$G$6 -> 0 | AF13: =AE13*$G$6 -> 0 | AJ13: =AI13*$G$6 -> 0 | AN13: =AM13*$G$6 -> 0 | AR13: =AQ13*$G$6 -> 0 | AV13: =AU13*$G$6 -> 0 | AZ13: =AY13*$G$6 -> 0 | BD13: =BC13*$G$6 -> 0 | BH13: =BG13*$G$6 -> 0 | BI13: =O13+S13+W13+AA13+AE13+AI13+AM13+AQ13+AU13+AY13+BC13+BG13 -> 0
C14: 01.01.02 | D14: ='MH-LAM4 -1225-San Miguel-Antoni'!#REF! -> #REF! | E14: =VLOOKUP(D14,'MH-LAM4 -1225-San Miguel-Antoni'!$D$2:$E$84,2,FALSE) -> #REF! | F14: MEDIA | G14: =IF(F14="BAJA",0.8,IF(F14="MEDIA",1,IF(F14="ALTA",1.4,IF(F14="MUY ALTA",2)))) -> 1 | H14: {=G14*INDEX('MH-LAM4 -1225-San Miguel-Antoni'!$B$2:$G$68,MATCH($D$5&D14&$B$5,'MH-LAM4 -1225-San Miguel-Antoni'!$C$2:$C$68&'MH-LAM4 -1225-San Miguel-Antoni'!$D$2:$D$68&'MH-LAM4 -1225-San Miguel-Antoni'!$B$2:$B$68,0),5)/J14} -> #REF! | I14: {=G14*INDEX('MH-LAM4 -1225-San Miguel-Antoni'!$B$2:$G$68,MATCH($D$5&D14&$B$5,'MH-LAM4 -1225-San Miguel-Antoni'!$C$2:$C$68&'MH-LAM4 -1225-San Miguel-Antoni'!$D$2:$D$68&'MH-LAM4 -1225-San Miguel-Antoni'!$B$2:$B$68,0),6)/J14} -> #REF! | J14: =VLOOKUP($D$6,APUs!$B$2:$I$50,7,FALSE) -> 0.9 | K14: =$G$6*(H14+I14)/J14 -> #REF! | P14: =O14*$G$6 -> 0 | T14: =S14*$G$6 -> 0 | X14: =W14*$G$6 -> 0 | AB14: =AA14*$G$6 -> 0 | AF14: =AE14*$G$6 -> 0 | AJ14: =AI14*$G$6 -> 0 | AN14: =AM14*$G$6 -> 0 | AR14: =AQ14*$G$6 -> 0 | AV14: =AU14*$G$6 -> 0 | AZ14: =AY14*$G$6 -> 0 | BD14: =BC14*$G$6 -> 0 | BH14: =BG14*$G$6 -> 0 | BI14: =O14+S14+W14+AA14+AE14+AI14+AM14+AQ14+AU14+AY14+BC14+BG14 -> 0
C15: 01.01.02 | D15: ='MH-LAM4 -1225-San Miguel-Antoni'!#REF! -> #REF! | E15: =VLOOKUP(D15,'MH-LAM4 -1225-San Miguel-Antoni'!$D$2:$E$84,2,FALSE) -> #REF! | F15: MEDIA | G15: =IF(F15="BAJA",0.8,IF(F15="MEDIA",1,IF(F15="ALTA",1.4,IF(F15="MUY ALTA",2)))) -> 1 | H15: {=G15*INDEX('MH-LAM4 -1225-San Miguel-Antoni'!$B$2:$G$68,MATCH($D$5&D15&$B$5,'MH-LAM4 -1225-San Miguel-Antoni'!$C$2:$C$68&'MH-LAM4 -1225-San Miguel-Antoni'!$D$2:$D$68&'MH-LAM4 -1225-San Miguel-Antoni'!$B$2:$B$68,0),5)/J15} -> #REF! | I15: {=G15*INDEX('MH-LAM4 -1225-San Miguel-Antoni'!$B$2:$G$68,MATCH($D$5&D15&$B$5,'MH-LAM4 -1225-San Miguel-Antoni'!$C$2:$C$68&'MH-LAM4 -1225-San Miguel-Antoni'!$D$2:$D$68&'MH-LAM4 -1225-San Miguel-Antoni'!$B$2:$B$68,0),6)/J15} -> #REF! | J15: =VLOOKUP($D$6,APUs!$B$2:$I$50,7,FALSE) -> 0.9 | K15: =$G$6*(H15+I15)/J15 -> #REF! | P15: =O15*$G$6 -> 0 | T15: =S15*$G$6 -> 0 | X15: =W15*$G$6 -> 0 | AB15: =AA15*$G$6 -> 0 | AF15: =AE15*$G$6 -> 0 | AJ15: =AI15*$G$6 -> 0 | AN15: =AM15*$G$6 -> 0 | AR15: =AQ15*$G$6 -> 0 | AV15: =AU15*$G$6 -> 0 | AZ15: =AY15*$G$6 -> 0 | BD15: =BC15*$G$6 -> 0 | BH15: =BG15*$G$6 -> 0 | BI15: =O15+S15+W15+AA15+AE15+AI15+AM15+AQ15+AU15+AY15+BC15+BG15 -> 0
C16: 01.01.02 | D16: ='MH-LAM4 -1225-San Miguel-Antoni'!#REF! -> #REF! | E16: =VLOOKUP(D16,'MH-LAM4 -1225-San Miguel-Antoni'!$D$2:$E$84,2,FALSE) -> #REF! | F16: MEDIA | G16: =IF(F16="BAJA",0.8,IF(F16="MEDIA",1,IF(F16="ALTA",1.4,IF(F16="MUY ALTA",2)))) -> 1 | H16: {=G16*INDEX('MH-LAM4 -1225-San Miguel-Antoni'!$B$2:$G$68,MATCH($D$5&D16&$B$5,'MH-LAM4 -1225-San Miguel-Antoni'!$C$2:$C$68&'MH-LAM4 -1225-San Miguel-Antoni'!$D$2:$D$68&'MH-LAM4 -1225-San Miguel-Antoni'!$B$2:$B$68,0),5)/J16} -> #REF! | I16: {=G16*INDEX('MH-LAM4 -1225-San Miguel-Antoni'!$B$2:$G$68,MATCH($D$5&D16&$B$5,'MH-LAM4 -1225-San Miguel-Antoni'!$C$2:$C$68&'MH-LAM4 -1225-San Miguel-Antoni'!$D$2:$D$68&'MH-LAM4 -1225-San Miguel-Antoni'!$B$2:$B$68,0),6)/J16} -> #REF! | J16: =VLOOKUP($D$6,APUs!$B$2:$I$50,7,FALSE) -> 0.9 | K16: =$G$6*(H16+I16)/J16 -> #REF! | P16: =O16*$G$6 -> 0 | T16: =S16*$G$6 -> 0 | X16: =W16*$G$6 -> 0 | AB16: =AA16*$G$6 -> 0 | AF16: =AE16*$G$6 -> 0 | AJ16: =AI16*$G$6 -> 0 | AN16: =AM16*$G$6 -> 0 | AR16: =AQ16*$G$6 -> 0 | AV16: =AU16*$G$6 -> 0 | AZ16: =AY16*$G$6 -> 0 | BD16: =BC16*$G$6 -> 0 | BH16: =BG16*$G$6 -> 0 | BI16: =O16+S16+W16+AA16+AE16+AI16+AM16+AQ16+AU16+AY16+BC16+BG16 -> 0
C17: 01.01.02 | D17: ='MH-LAM4 -1225-San Miguel-Antoni'!#REF! -> #REF! | E17: =VLOOKUP(D17,'MH-LAM4 -1225-San Miguel-Antoni'!$D$2:$E$84,2,FALSE) -> #REF! | F17: MEDIA | G17: =IF(F17="BAJA",0.8,IF(F17="MEDIA",1,IF(F17="ALTA",1.4,IF(F17="MUY ALTA",2)))) -> 1 | H17: {=G17*INDEX('MH-LAM4 -1225-San Miguel-Antoni'!$B$2:$G$68,MATCH($D$5&D17&$B$5,'MH-LAM4 -1225-San Miguel-Antoni'!$C$2:$C$68&'MH-LAM4 -1225-San Miguel-Antoni'!$D$2:$D$68&'MH-LAM4 -1225-San Miguel-Antoni'!$B$2:$B$68,0),5)/J17} -> #REF! | I17: {=G17*INDEX('MH-LAM4 -1225-San Miguel-Antoni'!$B$2:$G$68,MATCH($D$5&D17&$B$5,'MH-LAM4 -1225-San Miguel-Antoni'!$C$2:$C$68&'MH-LAM4 -1225-San Miguel-Antoni'!$D$2:$D$68&'MH-LAM4 -1225-San Miguel-Antoni'!$B$2:$B$68,0),6)/J17} -> #REF! | J17: =VLOOKUP($D$6,APUs!$B$2:$I$50,7,FALSE) -> 0.9 | K17: =$G$6*(H17+I17)/J17 -> #REF! | P17: =O17*$G$6 -> 0 | T17: =S17*$G$6 -> 0 | X17: =W17*$G$6 -> 0 | AB17: =AA17*$G$6 -> 0 | AF17: =AE17*$G$6 -> 0 | AJ17: =AI17*$G$6 -> 0 | AN17: =AM17*$G$6 -> 0 | AR17: =AQ17*$G$6 -> 0 | AV17: =AU17*$G$6 -> 0 | AZ17: =AY17*$G$6 -> 0 | BD17: =BC17*$G$6 -> 0 | BH17: =BG17*$G$6 -> 0 | BI17: =O17+S17+W17+AA17+AE17+AI17+AM17+AQ17+AU17+AY17+BC17+BG17 -> 0
C18: 02.00.00 | D18: ESTRUCTURAS | M18: =M19 -> 0 | N18: =N19 -> 0 | O18: =O19 -> 0 | P18: =P19 -> 0 | Q18: =Q19 -> 0 | R18: =R19 -> 0 | S18: =S19 -> 0 | T18: =T19 -> 0 | ... BH18: =BH19 -> 0
C19: 01.01.00 | D19: INGENIERO ESTRUC. JUNIOR | G19: =VLOOKUP(D19,APUs!$B$2:$G$50,6,FALSE) -> 7.1428571 | H19: =SUM(H20:H26) -> #REF! | I19: =SUM(I20:I26) -> #REF! | J19: =VLOOKUP($D$19,APUs!$B$2:$I$50,7,FALSE) -> 0.85 | K19: =G19*(H19+I19)/J19 -> #REF! | M19: =IFERROR(AVERAGE(M20:M26),"0") -> 0 | N19: =IFERROR(AVERAGE(N20:N26),0) -> 0 | O19: =IFERROR(SUM(O20:O26),0) -> 0 | P19: =IFERROR(SUM(P20:P26),0) -> 0 | Q19: =IFERROR(AVERAGE(Q20:Q26),"0") -> 0 | R19: =IFERROR(AVERAGE(R20:R26),0) -> 0 | S19: =IFERROR(SUM(S20:S26),0) -> 0 | T19: =IFERROR(SUM(T20:T26),0) -> 0 | U19: =IFERROR(AVERAGE(U20:U26),"0") -> 0 | V19: =IFERROR(AVERAGE(V20:V26),0) -> 0 | W19: =IFERROR(SUM(W20:W26),0) -> 0 | X19: =IFERROR(SUM(X20:X26),0) -> 0 | Y19: =IFERROR(AVERAGE(Y20:Y26),"0") -> 0 | Z19: =IFERROR(AVERAGE(Z20:Z26),0) -> 0 | AA19: =IFERROR(SUM(AA20:AA26),0) -> 0 | AB19: =IFERROR(SUM(AB20:AB26),0) -> 0 | AC19: =IFERROR(AVERAGE(AC20:AC26),"0") -> 0 | AD19: =IFERROR(AVERAGE(AD20:AD26),0) -> 0 | AE19: =IFERROR(SUM(AE20:AE26),0) -> 0 | AF19: =IFERROR(SUM(AF20:AF26),0) -> 0 | AG19: =IFERROR(AVERAGE(AG20:AG26),"0") -> 0 | AH19: =IFERROR(AVERAGE(AH20:AH26),0) -> 0 | AI19: =IFERROR(SUM(AI20:AI26),0) -> 0 | AJ19: =IFERROR(SUM(AJ20:AJ26),0) -> 0 | AK19: =IFERROR(AVERAGE(AK20:AK26),"0") -> 0 | AL19: =IFERROR(AVERAGE(AL20:AL26),0) -> 0 | AM19: =IFERROR(SUM(AM20:AM26),0) -> 0 | AN19: =IFERROR(SUM(AN20:AN26),0) -> 0 | AO19: =IFERROR(AVERAGE(AO20:AO26),"0") -> 0 | AP19: =IFERROR(AVERAGE(AP20:AP26),0) -> 0 | AQ19: =IFERROR(SUM(AQ20:AQ26),0) -> 0 | AR19: =IFERROR(SUM(AR20:AR26),0) -> 0 | AS19: =IFERROR(AVERAGE(AS20:AS26),"0") -> 0 | AT19: =IFERROR(AVERAGE(AT20:AT26),0) -> 0 | AU19: =IFERROR(SUM(AU20:AU26),0) -> 0 | AV19: =IFERROR(SUM(AV20:AV26),0) -> 0 | AW19: =IFERROR(AVERAGE(AW20:AW26),"0") -> 0 | AX19: =IFERROR(AVERAGE(AX20:AX26),0) -> 0 | AY19: =IFERROR(SUM(AY20:AY26),0) -> 0 | AZ19: =IFERROR(SUM(AZ20:AZ26),0) -> 0 | BA19: =IFERROR(AVERAGE(BA20:BA26),"0") -> 0 | BB19: =IFERROR(AVERAGE(BB20:BB26),0) -> 0 | BC19: =IFERROR(SUM(BC20:BC26),0) -> 0 | BD19: =IFERROR(SUM(BD20:BD26),0) -> 0 | BE19: =IFERROR(AVERAGE(BE20:BE26),"0") -> 0 | BF19: =IFERROR(AVERAGE(BF20:BF26),0) -> 0 | BG19: =IFERROR(SUM(BG20:BG26),0) -> 0 | BH19: =IFERROR(SUM(BH20:BH26),0) -> 0 | BI19: =O19+S19+W19+AA19+AE19+AI19+AM19+AQ19+AU19+AY19+BC19+BG19 -> 0 | BJ19: =BI19*$G$19 -> 0 | BK19: =J19*(H19+I19)/(BI19) -> #REF!
C20: 01.01.01 | D20: ='MH-LAM4 -1225-San Miguel-Antoni'!#REF! -> #REF! | E20: =VLOOKUP(D20,'MH-LAM4 -1225-San Miguel-Antoni'!$D$2:$E$84,2,FALSE) -> #REF! | F20: MEDIA | G20: =IF(F20="BAJA",0.8,IF(F20="MEDIA",1,IF(F20="ALTA",1.4,IF(F20="MUY ALTA",2)))) -> 1 | H20: {=G20*INDEX('MH-LAM4 -1225-San Miguel-Antoni'!$B$2:$G$68,MATCH($D$18&D20&$B$5,'MH-LAM4 -1225-San Miguel-Antoni'!$C$2:$C$68&'MH-LAM4 -1225-San Miguel-Antoni'!$D$2:$D$68&'MH-LAM4 -1225-San Miguel-Antoni'!$B$2:$B$68,0),5)/J20} -> #REF! | I20: {=G20*INDEX('MH-LAM4 -1225-San Miguel-Antoni'!$B$2:$G$68,MATCH($D$18&D20&$B$5,'MH-LAM4 -1225-San Miguel-Antoni'!$C$2:$C$68&'MH-LAM4 -1225-San Miguel-Antoni'!$D$2:$D$68&'MH-LAM4 -1225-San Miguel-Antoni'!$B$2:$B$68,0),6)/J20} -> #REF! | J20: =VLOOKUP($D$19,APUs!$B$2:$I$50,7,FALSE) -> 0.85 | K20: =$G$19*(H20+I20)/J20 -> #REF! | P20: =O20*$G$19 -> 0 | T20: =S20*$G$19 -> 0 | X20: =W20*$G$19 -> 0 | AB20: =AA20*$G$19 -> 0 | AF20: =AE20*$G$19 -> 0 | AJ20: =AI20*$G$19 -> 0 | AN20: =AM20*$G$19 -> 0 | AR20: =AQ20*$G$19 -> 0 | AV20: =AU20*$G$19 -> 0 | AZ20: =AY20*$G$19 -> 0 | BD20: =BC20*$G$19 -> 0 | BH20: =BG20*$G$19 -> 0 | BI20: =O20+S20+W20+AA20+AE20+AI20+AM20+AQ20+AU20+AY20+BC20+BG20 -> 0
C21: 01.01.02 | D21: ='MH-LAM4 -1225-San Miguel-Antoni'!D9 -> ESTRUCTURAS - Rev. de Muni | E21: =VLOOKUP(D21,'MH-LAM4 -1225-San Miguel-Antoni'!$D$2:$E$84,2,FALSE) -> V 3.1 - ENTREGA TÉCNICA FINAL A MUNI | F21: MEDIA | G21: =IF(F21="BAJA",0.8,IF(F21="MEDIA",1,IF(F21="ALTA",1.4,IF(F21="MUY ALTA",2)))) -> 1 | H21: {=G21*INDEX('MH-LAM4 -1225-San Miguel-Antoni'!$B$2:$G$68,MATCH($D$18&D21&$B$5,'MH-LAM4 -1225-San Miguel-Antoni'!$C$2:$C$68&'MH-LAM4 -1225-San Miguel-Antoni'!$D$2:$D$68&'MH-LAM4 -1225-San Miguel-Antoni'!$B$2:$B$68,0),5)/J21} -> 0 | I21: {=G21*INDEX('MH-LAM4 -1225-San Miguel-Antoni'!$B$2:$G$68,MATCH($D$18&D21&$B$5,'MH-LAM4 -1225-San Miguel-Antoni'!$C$2:$C$68&'MH-LAM4 -1225-San Miguel-Antoni'!$D$2:$D$68&'MH-LAM4 -1225-San Miguel-Antoni'!$B$2:$B$68,0),6)/J21} -> 0 | J21: =VLOOKUP($D$19,APUs!$B$2:$I$50,7,FALSE) -> 0.85 | K21: =$G$19*(H21+I21)/J21 -> 0 | P21: =O21*$G$19 -> 0 | T21: =S21*$G$19 -> 0 | X21: =W21*$G$19 -> 0 | AB21: =AA21*$G$19 -> 0 | AF21: =AE21*$G$19 -> 0 | AJ21: =AI21*$G$19 -> 0 | AN21: =AM21*$G$19 -> 0 | AR21: =AQ21*$G$19 -> 0 | AV21: =AU21*$G$19 -> 0 | AZ21: =AY21*$G$19 -> 0 | BD21: =BC21*$G$19 -> 0 | BH21: =BG21*$G$19 -> 0 | BI21: =O21+S21+W21+AA21+AE21+AI21+AM21+AQ21+AU21+AY21+BC21+BG21 -> 0
C22: 01.01.03 | D22: ='MH-LAM4 -1225-San Miguel-Antoni'!D10 -> ESTRUCTURAS - Lev. de Observaciones de Muni | E22: =VLOOKUP(D22,'MH-LAM4 -1225-San Miguel-Antoni'!$D$2:$E$84,2,FALSE) -> V 3.0 - PRELIMINAR A ENTREGA A MUNI | F22: MEDIA | G22: =IF(F22="BAJA",0.8,IF(F22="MEDIA",1,IF(F22="ALTA",1.4,IF(F22="MUY ALTA",2)))) -> 1 | H22: {=G22*INDEX('MH-LAM4 -1225-San Miguel-Antoni'!$B$2:$G$68,MATCH($D$18&D22&$B$5,'MH-LAM4 -1225-San Miguel-Antoni'!$C$2:$C$68&'MH-LAM4 -1225-San Miguel-Antoni'!$D$2:$D$68&'MH-LAM4 -1225-San Miguel-Antoni'!$B$2:$B$68,0),5)/J22} -> 10.588235 | I22: {=G22*INDEX('MH-LAM4 -1225-San Miguel-Antoni'!$B$2:$G$68,MATCH($D$18&D22&$B$5,'MH-LAM4 -1225-San Miguel-Antoni'!$C$2:$C$68&'MH-LAM4 -1225-San Miguel-Antoni'!$D$2:$D$68&'MH-LAM4 -1225-San Miguel-Antoni'!$B$2:$B$68,0),6)/J22} -> 0 | J22: =VLOOKUP($D$19,APUs!$B$2:$I$50,7,FALSE) -> 0.85 | K22: =$G$19*(H22+I22)/J22 -> 88.976767 | P22: =O22*$G$19 -> 0 | T22: =S22*$G$19 -> 0 | X22: =W22*$G$19 -> 0 | AB22: =AA22*$G$19 -> 0 | AF22: =AE22*$G$19 -> 0 | AJ22: =AI22*$G$19 -> 0 | AN22: =AM22*$G$19 -> 0 | AR22: =AQ22*$G$19 -> 0 | AV22: =AU22*$G$19 -> 0 | AZ22: =AY22*$G$19 -> 0 | BD22: =BC22*$G$19 -> 0 | BH22: =BG22*$G$19 -> 0 | BI22: =O22+S22+W22+AA22+AE22+AI22+AM22+AQ22+AU22+AY22+BC22+BG22 -> 0
C23: 01.01.04 | D23: ='MH-LAM4 -1225-San Miguel-Antoni'!#REF! -> #REF! | E23: =VLOOKUP(D23,'MH-LAM4 -1225-San Miguel-Antoni'!$D$2:$E$84,2,FALSE) -> #REF! | F23: MEDIA | G23: =IF(F23="BAJA",0.8,IF(F23="MEDIA",1,IF(F23="ALTA",1.4,IF(F23="MUY ALTA",2)))) -> 1 | H23: {=G23*INDEX('MH-LAM4 -1225-San Miguel-Antoni'!$B$2:$G$68,MATCH($D$18&D23&$B$5,'MH-LAM4 -1225-San Miguel-Antoni'!$C$2:$C$68&'MH-LAM4 -1225-San Miguel-Antoni'!$D$2:$D$68&'MH-LAM4 -1225-San Miguel-Antoni'!$B$2:$B$68,0),5)/J23} -> #REF! | I23: {=G23*INDEX('MH-LAM4 -1225-San Miguel-Antoni'!$B$2:$G$68,MATCH($D$18&D23&$B$5,'MH-LAM4 -1225-San Miguel-Antoni'!$C$2:$C$68&'MH-LAM4 -1225-San Miguel-Antoni'!$D$2:$D$68&'MH-LAM4 -1225-San Miguel-Antoni'!$B$2:$B$68,0),6)/J23} -> #REF! | J23: =VLOOKUP($D$19,APUs!$B$2:$I$50,7,FALSE) -> 0.85 | K23: =$G$19*(H23+I23)/J23 -> #REF! | P23: =O23*$G$19 -> 0 | T23: =S23*$G$19 -> 0 | X23: =W23*$G$19 -> 0 | AB23: =AA23*$G$19 -> 0 | AF23: =AE23*$G$19 -> 0 | AJ23: =AI23*$G$19 -> 0 | AN23: =AM23*$G$19 -> 0 | AR23: =AQ23*$G$19 -> 0 | AV23: =AU23*$G$19 -> 0 | AZ23: =AY23*$G$19 -> 0 | BD23: =BC23*$G$19 -> 0 | BH23: =BG23*$G$19 -> 0 | BI23: =O23+S23+W23+AA23+AE23+AI23+AM23+AQ23+AU23+AY23+BC23+BG23 -> 0
C24: 01.01.05 | D24: ='MH-LAM4 -1225-San Miguel-Antoni'!#REF! -> #REF! | E24: =VLOOKUP(D24,'MH-LAM4 -1225-San Miguel-Antoni'!$D$2:$E$84,2,FALSE) -> #REF! | F24: MEDIA | G24: =IF(F24="BAJA",0.8,IF(F24="MEDIA",1,IF(F24="ALTA",1.4,IF(F24="MUY ALTA",2)))) -> 1 | H24: {=G24*INDEX('MH-LAM4 -1225-San Miguel-Antoni'!$B$2:$G$68,MATCH($D$18&D24&$B$5,'MH-LAM4 -1225-San Miguel-Antoni'!$C$2:$C$68&'MH-LAM4 -1225-San Miguel-Antoni'!$D$2:$D$68&'MH-LAM4 -1225-San Miguel-Antoni'!$B$2:$B$68,0),5)/J24} -> #REF! | I24: {=G24*INDEX('MH-LAM4 -1225-San Miguel-Antoni'!$B$2:$G$68,MATCH($D$18&D24&$B$5,'MH-LAM4 -1225-San Miguel-Antoni'!$C$2:$C$68&'MH-LAM4 -1225-San Miguel-Antoni'!$D$2:$D$68&'MH-LAM4 -1225-San Miguel-Antoni'!$B$2:$B$68,0),6)/J24} -> #REF! | J24: =VLOOKUP($D$19,APUs!$B$2:$I$50,7,FALSE) -> 0.85 | K24: =$G$19*(H24+I24)/J24 -> #REF! | P24: =O24*$G$19 -> 0 | T24: =S24*$G$19 -> 0 | X24: =W24*$G$19 -> 0 | AB24: =AA24*$G$19 -> 0 | AF24: =AE24*$G$19 -> 0 | AJ24: =AI24*$G$19 -> 0 | AN24: =AM24*$G$19 -> 0 | AR24: =AQ24*$G$19 -> 0 | AV24: =AU24*$G$19 -> 0 | AZ24: =AY24*$G$19 -> 0 | BD24: =BC24*$G$19 -> 0 | BH24: =BG24*$G$19 -> 0 | BI24: =O24+S24+W24+AA24+AE24+AI24+AM24+AQ24+AU24+AY24+BC24+BG24 -> 0
C25: 01.01.06 | D25: ='MH-LAM4 -1225-San Miguel-Antoni'!#REF! -> #REF! | E25: =VLOOKUP(D25,'MH-LAM4 -1225-San Miguel-Antoni'!$D$2:$E$84,2,FALSE) -> #REF! | F25: MEDIA | G25: =IF(F25="BAJA",0.8,IF(F25="MEDIA",1,IF(F25="ALTA",1.4,IF(F25="MUY ALTA",2)))) -> 1 | H25: {=G25*INDEX('MH-LAM4 -1225-San Miguel-Antoni'!$B$2:$G$68,MATCH($D$18&D25&$B$5,'MH-LAM4 -1225-San Miguel-Antoni'!$C$2:$C$68&'MH-LAM4 -1225-San Miguel-Antoni'!$D$2:$D$68&'MH-LAM4 -1225-San Miguel-Antoni'!$B$2:$B$68,0),5)/J25} -> #REF! | I25: {=G25*INDEX('MH-LAM4 -1225-San Miguel-Antoni'!$B$2:$G$68,MATCH($D$18&D25&$B$5,'MH-LAM4 -1225-San Miguel-Antoni'!$C$2:$C$68&'MH-LAM4 -1225-San Miguel-Antoni'!$D$2:$D$68&'MH-LAM4 -1225-San Miguel-Antoni'!$B$2:$B$68,0),6)/J25} -> #REF! | J25: =VLOOKUP($D$19,APUs!$B$2:$I$50,7,FALSE) -> 0.85 | K25: =$G$19*(H25+I25)/J25 -> #REF! | P25: =O25*$G$19 -> 0 | T25: =S25*$G$19 -> 0 | X25: =W25*$G$19 -> 0 | AB25: =AA25*$G$19 -> 0 | AF25: =AE25*$G$19 -> 0 | AJ25: =AI25*$G$19 -> 0 | AN25: =AM25*$G$19 -> 0 | AR25: =AQ25*$G$19 -> 0 | AV25: =AU25*$G$19 -> 0 | AZ25: =AY25*$G$19 -> 0 | BD25: =BC25*$G$19 -> 0 | BH25: =BG25*$G$19 -> 0 | BI25: =O25+S25+W25+AA25+AE25+AI25+AM25+AQ25+AU25+AY25+BC25+BG25 -> 0
C26: 01.01.07 | D26: ='MH-LAM4 -1225-San Miguel-Antoni'!#REF! -> #REF! | E26: =VLOOKUP(D26,'MH-LAM4 -1225-San Miguel-Antoni'!$D$2:$E$84,2,FALSE) -> #REF! | F26: MEDIA | G26: =IF(F26="BAJA",0.8,IF(F26="MEDIA",1,IF(F26="ALTA",1.4,IF(F26="MUY ALTA",2)))) -> 1 | H26: {=G26*INDEX('MH-LAM4 -1225-San Miguel-Antoni'!$B$2:$G$68,MATCH($D$18&D26&$B$5,'MH-LAM4 -1225-San Miguel-Antoni'!$C$2:$C$68&'MH-LAM4 -1225-San Miguel-Antoni'!$D$2:$D$68&'MH-LAM4 -1225-San Miguel-Antoni'!$B$2:$B$68,0),5)/J26} -> #REF! | I26: {=G26*INDEX('MH-LAM4 -1225-San Miguel-Antoni'!$B$2:$G$68,MATCH($D$18&D26&$B$5,'MH-LAM4 -1225-San Miguel-Antoni'!$C$2:$C$68&'MH-LAM4 -1225-San Miguel-Antoni'!$D$2:$D$68&'MH-LAM4 -1225-San Miguel-Antoni'!$B$2:$B$68,0),6)/J26} -> #REF! | J26: =VLOOKUP($D$19,APUs!$B$2:$I$50,7,FALSE) -> 0.85 | K26: =$G$19*(H26+I26)/J26 -> #REF! | P26: =O26*$G$19 -> 0 | T26: =S26*$G$19 -> 0 | X26: =W26*$G$19 -> 0 | AB26: =AA26*$G$19 -> 0 | AF26: =AE26*$G$19 -> 0 | AJ26: =AI26*$G$19 -> 0 | AN26: =AM26*$G$19 -> 0 | AR26: =AQ26*$G$19 -> 0 | AV26: =AU26*$G$19 -> 0 | AZ26: =AY26*$G$19 -> 0 | BD26: =BC26*$G$19 -> 0 | BH26: =BG26*$G$19 -> 0 | BI26: =O26+S26+W26+AA26+AE26+AI26+AM26+AQ26+AU26+AY26+BC26+BG26 -> 0
C27: 03.00.00 | D27: INST. ELECTRICAS | M27: =M28 -> 0 | N27: =N28 -> 0 | O27: =O28 -> 0 | P27: =P28 -> 0 | Q27: =Q28 -> 0 | R27: =R28 -> 0 | S27: =S28 -> 0 | T27: =T28 -> 0 | ... BH27: =BH28 -> 0
C28: 03.01.00 | D28: INGENIERO ESTRUCT. SEMISENIOR | G28: =VLOOKUP(D28,APUs!$B$2:$G$50,6,FALSE) -> 14.285714 | H28: =SUM(H29:H32) -> 8.2474227 | I28: =SUM(I29:I32) -> 0 | J28: =VLOOKUP($D$28,APUs!$B$2:$I$50,7,FALSE) -> 0.97 | K28: =G28*(H28+I28)/J28 -> 121.46425 | M28: =IFERROR(AVERAGE(M29:M32),"0") -> 0 | N28: =IFERROR(AVERAGE(N29:N32),0) -> 0 | O28: =IFERROR(SUM(O29:O32),0) -> 0 | P28: =IFERROR(SUM(P29:P32),0) -> 0 | Q28: =IFERROR(AVERAGE(Q29:Q32),"0") -> 0 | R28: =IFERROR(AVERAGE(R29:R32),0) -> 0 | S28: =IFERROR(SUM(S29:S32),0) -> 0 | T28: =IFERROR(SUM(T29:T32),0) -> 0 | U28: =IFERROR(AVERAGE(U29:U32),"0") -> 0 | V28: =IFERROR(AVERAGE(V29:V32),0) -> 0 | W28: =IFERROR(SUM(W29:W32),0) -> 0 | X28: =IFERROR(SUM(X29:X32),0) -> 0 | Y28: =IFERROR(AVERAGE(Y29:Y32),"0") -> 0 | Z28: =IFERROR(AVERAGE(Z29:Z32),0) -> 0 | AA28: =IFERROR(SUM(AA29:AA32),0) -> 0 | AB28: =IFERROR(SUM(AB29:AB32),0) -> 0 | AC28: =IFERROR(AVERAGE(AC29:AC32),"0") -> 0 | AD28: =IFERROR(AVERAGE(AD29:AD32),0) -> 0 | AE28: =IFERROR(SUM(AE29:AE32),0) -> 0 | AF28: =IFERROR(SUM(AF29:AF32),0) -> 0 | AG28: =IFERROR(AVERAGE(AG29:AG32),"0") -> 0 | AH28: =IFERROR(AVERAGE(AH29:AH32),0) -> 0 | AI28: =IFERROR(SUM(AI29:AI32),0) -> 0 | AJ28: =IFERROR(SUM(AJ29:AJ32),0) -> 0 | AK28: =IFERROR(AVERAGE(AK29:AK32),"0") -> 0 | AL28: =IFERROR(AVERAGE(AL29:AL32),0) -> 0 | AM28: =IFERROR(SUM(AM29:AM32),0) -> 0 | AN28: =IFERROR(SUM(AN29:AN32),0) -> 0 | AO28: =IFERROR(AVERAGE(AO29:AO32),"0") -> 0 | AP28: =IFERROR(AVERAGE(AP29:AP32),0) -> 0 | AQ28: =IFERROR(SUM(AQ29:AQ32),0) -> 0 | AR28: =IFERROR(SUM(AR29:AR32),0) -> 0 | AS28: =IFERROR(AVERAGE(AS29:AS32),"0") -> 0 | AT28: =IFERROR(AVERAGE(AT29:AT32),0) -> 0 | AU28: =IFERROR(SUM(AU29:AU32),0) -> 0 | AV28: =IFERROR(SUM(AV29:AV32),0) -> 0 | AW28: =IFERROR(AVERAGE(AW29:AW32),"0") -> 0 | AX28: =IFERROR(AVERAGE(AX29:AX32),0) -> 0 | AY28: =IFERROR(SUM(AY29:AY32),0) -> 0 | AZ28: =IFERROR(SUM(AZ29:AZ32),0) -> 0 | BA28: =IFERROR(AVERAGE(BA29:BA32),"0") -> 0 | BB28: =IFERROR(AVERAGE(BB29:BB32),0) -> 0 | BC28: =IFERROR(SUM(BC29:BC32),0) -> 0 | BD28: =IFERROR(SUM(BD29:BD32),0) -> 0 | BE28: =IFERROR(AVERAGE(BE29:BE32),"0") -> 0 | BF28: =IFERROR(AVERAGE(BF29:BF32),0) -> 0 | BG28: =IFERROR(SUM(BG29:BG32),0) -> 0 | BH28: =IFERROR(SUM(BH29:BH32),0) -> 0 | BI28: =O28+S28+W28+AA28+AE28+AI28+AM28+AQ28+AU28+AY28+BC28+BG28 -> 0 | BJ28: =BI28*$G$28 -> 0 | BK28: =J28*(H28+I28)/(BI28) -> #DIV/0!
C29: 03.01.01 | D29: ='MH-LAM4 -1225-San Miguel-Antoni'!D11 -> IIEE - Lev. de observaciones de Muni | E29: =VLOOKUP(D29,'MH-LAM4 -1225-San Miguel-Antoni'!$D$2:$E$84,2,FALSE) -> V 3.0 - PRELIMINAR A ENTREGA A MUNI | F29: MEDIA | G29: =IF(F29="BAJA",0.8,IF(F29="MEDIA",1,IF(F29="ALTA",1.4,IF(F29="MUY ALTA",2)))) -> 1 | H29: {=G29*INDEX('MH-LAM4 -1225-San Miguel-Antoni'!$B$2:$G$68,MATCH($D$27&D29&$B$5,'MH-LAM4 -1225-San Miguel-Antoni'!$C$2:$C$68&'MH-LAM4 -1225-San Miguel-Antoni'!$D$2:$D$68&'MH-LAM4 -1225-San Miguel-Antoni'!$B$2:$B$68,0),5)/J29} -> 4.1237113 | I29: {=G29*INDEX('MH-LAM4 -1225-San Miguel-Antoni'!$B$2:$G$68,MATCH($D$27&D29&$B$5,'MH-LAM4 -1225-San Miguel-Antoni'!$C$2:$C$68&'MH-LAM4 -1225-San Miguel-Antoni'!$D$2:$D$68&'MH-LAM4 -1225-San Miguel-Antoni'!$B$2:$B$68,0),6)/J29} -> 0 | J29: =VLOOKUP($D$28,APUs!$B$2:$I$50,7,FALSE) -> 0.97 | K29: =$G$28*(H29+I29)/J29 -> 60.732126 | P29: =O29*$G$28 -> 0 | T29: =S29*$G$28 -> 0 | X29: =W29*$G$28 -> 0 | AB29: =AA29*$G$28 -> 0 | AF29: =AE29*$G$28 -> 0 | AJ29: =AI29*$G$28 -> 0 | AN29: =AM29*$G$28 -> 0 | AR29: =AQ29*$G$28 -> 0 | AV29: =AU29*$G$28 -> 0 | AZ29: =AY29*$G$28 -> 0 | BD29: =BC29*$G$28 -> 0 | BH29: =BG29*$G$28 -> 0 | BI29: =O29+S29+W29+AA29+AE29+AI29+AM29+AQ29+AU29+AY29+BC29+BG29 -> 0
C30: 03.01.02 | D30: ='MH-LAM4 -1225-San Miguel-Antoni'!D12 -> IIEE - Lev. de observaciones de Revisores | E30: =VLOOKUP(D30,'MH-LAM4 -1225-San Miguel-Antoni'!$D$2:$E$84,2,FALSE) -> V 2.0 - PRELIMINAR A ENTREGA A REVISORES | F30: MEDIA | G30: =IF(F30="BAJA",0.8,IF(F30="MEDIA",1,IF(F30="ALTA",1.4,IF(F30="MUY ALTA",2)))) -> 1 | H30: {=G30*INDEX('MH-LAM4 -1225-San Miguel-Antoni'!$B$2:$G$68,MATCH($D$27&D30&$B$5,'MH-LAM4 -1225-San Miguel-Antoni'!$C$2:$C$68&'MH-LAM4 -1225-San Miguel-Antoni'!$D$2:$D$68&'MH-LAM4 -1225-San Miguel-Antoni'!$B$2:$B$68,0),5)/J30} -> 4.1237113 | I30: {=G30*INDEX('MH-LAM4 -1225-San Miguel-Antoni'!$B$2:$G$68,MATCH($D$27&D30&$B$5,'MH-LAM4 -1225-San Miguel-Antoni'!$C$2:$C$68&'MH-LAM4 -1225-San Miguel-Antoni'!$D$2:$D$68&'MH-LAM4 -1225-San Miguel-Antoni'!$B$2:$B$68,0),6)/J30} -> 0 | J30: =VLOOKUP($D$28,APUs!$B$2:$I$50,7,FALSE) -> 0.97 | K30: =$G$28*(H30+I30)/J30 -> 60.732126 | P30: =O30*$G$28 -> 0 | T30: =S30*$G$28 -> 0 | X30: =W30*$G$28 -> 0 | AB30: =AA30*$G$28 -> 0 | AF30: =AE30*$G$28 -> 0 | AJ30: =AI30*$G$28 -> 0 | AN30: =AM30*$G$28 -> 0 | AR30: =AQ30*$G$28 -> 0 | AV30: =AU30*$G$28 -> 0 | AZ30: =AY30*$G$28 -> 0 | BD30: =BC30*$G$28 -> 0 | BH30: =BG30*$G$28 -> 0 | BI30: =O30+S30+W30+AA30+AE30+AI30+AM30+AQ30+AU30+AY30+BC30+BG30 -> 0
C31: 03.01.03 | D31: ='MH-LAM4 -1225-San Miguel-Antoni'!D13 -> IIEE - Revisión de Revisores | E31: =VLOOKUP(D31,'MH-LAM4 -1225-San Miguel-Antoni'!$D$2:$E$84,2,FALSE) -> V 2.1 - ENTREGA TÉCNICA FINAL A REVISORES | F31: MEDIA | G31: =IF(F31="BAJA",0.8,IF(F31="MEDIA",1,IF(F31="ALTA",1.4,IF(F31="MUY ALTA",2)))) -> 1 | H31: {=G31*INDEX('MH-LAM4 -1225-San Miguel-Antoni'!$B$2:$G$68,MATCH($D$27&D31&$B$5,'MH-LAM4 -1225-San Miguel-Antoni'!$C$2:$C$68&'MH-LAM4 -1225-San Miguel-Antoni'!$D$2:$D$68&'MH-LAM4 -1225-San Miguel-Antoni'!$B$2:$B$68,0),5)/J31} -> 0 | I31: {=G31*INDEX('MH-LAM4 -1225-San Miguel-Antoni'!$B$2:$G$68,MATCH($D$27&D31&$B$5,'MH-LAM4 -1225-San Miguel-Antoni'!$C$2:$C$68&'MH-LAM4 -1225-San Miguel-Antoni'!$D$2:$D$68&'MH-LAM4 -1225-San Miguel-Antoni'!$B$2:$B$68,0),6)/J31} -> 0 | J31: =VLOOKUP($D$28,APUs!$B$2:$I$50,7,FALSE) -> 0.97 | K31: =$G$28*(H31+I31)/J31 -> 0 | P31: =O31*$G$28 -> 0 | T31: =S31*$G$28 -> 0 | X31: =W31*$G$28 -> 0 | AB31: =AA31*$G$28 -> 0 | AF31: =AE31*$G$28 -> 0 | AJ31: =AI31*$G$28 -> 0 | AN31: =AM31*$G$28 -> 0 | AR31: =AQ31*$G$28 -> 0 | AV31: =AU31*$G$28 -> 0 | AZ31: =AY31*$G$28 -> 0 | BD31: =BC31*$G$28 -> 0 | BH31: =BG31*$G$28 -> 0 | BI31: =O31+S31+W31+AA31+AE31+AI31+AM31+AQ31+AU31+AY31+BC31+BG31 -> 0
C32: 03.01.03 | D32: ='MH-LAM4 -1225-San Miguel-Antoni'!D14 -> IIEE - Revisión de Municipalidad | E32: =VLOOKUP(D32,'MH-LAM4 -1225-San Miguel-Antoni'!$D$2:$E$84,2,FALSE) -> V 3.1 - ENTREGA TÉCNICA FINAL A MUNI | F32: MEDIA | G32: =IF(F32="BAJA",0.8,IF(F32="MEDIA",1,IF(F32="ALTA",1.4,IF(F32="MUY ALTA",2)))) -> 1 | H32: {=G32*INDEX('MH-LAM4 -1225-San Miguel-Antoni'!$B$2:$G$68,MATCH($D$27&D32&$B$5,'MH-LAM4 -1225-San Miguel-Antoni'!$C$2:$C$68&'MH-LAM4 -1225-San Miguel-Antoni'!$D$2:$D$68&'MH-LAM4 -1225-San Miguel-Antoni'!$B$2:$B$68,0),5)/J32} -> 0 | I32: {=G32*INDEX('MH-LAM4 -1225-San Miguel-Antoni'!$B$2:$G$68,MATCH($D$27&D32&$B$5,'MH-LAM4 -1225-San Miguel-Antoni'!$C$2:$C$68&'MH-LAM4 -1225-San Miguel-Antoni'!$D$2:$D$68&'MH-LAM4 -1225-San Miguel-Antoni'!$B$2:$B$68,0),6)/J32} -> 0 | J32: =VLOOKUP($D$28,APUs!$B$2:$I$50,7,FALSE) -> 0.97 | K32: =$G$28*(H32+I32)/J32 -> 0 | P32: =O32*$G$28 -> 0 | T32: =S32*$G$28 -> 0 | X32: =W32*$G$28 -> 0 | AB32: =AA32*$G$28 -> 0 | AF32: =AE32*$G$28 -> 0 | AJ32: =AI32*$G$28 -> 0 | AN32: =AM32*$G$28 -> 0 | AR32: =AQ32*$G$28 -> 0 | AV32: =AU32*$G$28 -> 0 | AZ32: =AY32*$G$28 -> 0 | BD32: =BC32*$G$28 -> 0 | BH32: =BG32*$G$28 -> 0 | BI32: =O32+S32+W32+AA32+AE32+AI32+AM32+AQ32+AU32+AY32+BC32+BG32 -> 0
C33: 04.00.00 | D33: INST. SANITARIAS | M33: =M34 -> 0 | N33: =N34 -> 0 | O33: =O34 -> 0 | P33: =P34 -> 0 | Q33: =Q34 -> 0 | R33: =R34 -> 0 | S33: =S34 -> 0 | T33: =T34 -> 0 | ... BH33: =BH34 -> 0
C34: 04.01.00 | D34: INGENIERO SANITARIO SEMISENIOR | G34: =VLOOKUP(D34,APUs!$B$2:$G$50,6,FALSE) -> 10.47619 | H34: =SUM(H35:H39) -> #REF! | I34: =SUM(I35:I39) -> #REF! | J34: =VLOOKUP(D34,APUs!$B$2:$I$50,7,FALSE) -> 0.9 | K34: =G34*(H34+I34)/J34 -> #REF! | M34: =IFERROR(AVERAGE(M35:M39),0) -> 0 | N34: =IFERROR(AVERAGE(N35:N39),0) -> 0 | O34: =IFERROR(SUM(O35:O39),0) -> 0 | P34: =IFERROR(SUM(P35:P39),0) -> 0 | Q34: =IFERROR(AVERAGE(Q35:Q39),0) -> 0 | R34: =IFERROR(AVERAGE(R35:R39),0) -> 0 | S34: =IFERROR(SUM(S35:S39),0) -> 0 | T34: =IFERROR(SUM(T35:T39),0) -> 0 | U34: =IFERROR(AVERAGE(U35:U39),0) -> 0 | V34: =IFERROR(AVERAGE(V35:V39),0) -> 0 | W34: =IFERROR(SUM(W35:W39),0) -> 0 | X34: =IFERROR(SUM(X35:X39),0) -> 0 | Y34: =IFERROR(AVERAGE(Y35:Y39),0) -> 0 | Z34: =IFERROR(AVERAGE(Z35:Z39),0) -> 0 | AA34: =IFERROR(SUM(AA35:AA39),0) -> 0 | AB34: =IFERROR(SUM(AB35:AB39),0) -> 0 | AC34: =IFERROR(AVERAGE(AC35:AC39),0) -> 0 | AD34: =IFERROR(AVERAGE(AD35:AD39),0) -> 0 | AE34: =IFERROR(SUM(AE35:AE39),0) -> 0 | AF34: =IFERROR(SUM(AF35:AF39),0) -> 0 | AG34: =IFERROR(AVERAGE(AG35:AG39),0) -> 0 | AH34: =IFERROR(AVERAGE(AH35:AH39),0) -> 0 | AI34: =IFERROR(SUM(AI35:AI39),0) -> 0 | AJ34: =IFERROR(SUM(AJ35:AJ39),0) -> 0 | AK34: =IFERROR(AVERAGE(AK35:AK39),0) -> 0 | AL34: =IFERROR(AVERAGE(AL35:AL39),0) -> 0 | AM34: =IFERROR(SUM(AM35:AM39),0) -> 0 | AN34: =IFERROR(SUM(AN35:AN39),0) -> 0 | AO34: =IFERROR(AVERAGE(AO35:AO39),0) -> 0 | AP34: =IFERROR(AVERAGE(AP35:AP39),0) -> 0 | AQ34: =IFERROR(SUM(AQ35:AQ39),0) -> 0 | AR34: =IFERROR(SUM(AR35:AR39),0) -> 0 | AS34: =IFERROR(AVERAGE(AS35:AS39),0) -> 0 | AT34: =IFERROR(AVERAGE(AT35:AT39),0) -> 0 | AU34: =IFERROR(SUM(AU35:AU39),0) -> 0 | AV34: =IFERROR(SUM(AV35:AV39),0) -> 0 | AW34: =IFERROR(AVERAGE(AW35:AW39),0) -> 0 | AX34: =IFERROR(AVERAGE(AX35:AX39),0) -> 0 | AY34: =IFERROR(SUM(AY35:AY39),0) -> 0 | AZ34: =IFERROR(SUM(AZ35:AZ39),0) -> 0 | BA34: =IFERROR(AVERAGE(BA35:BA39),0) -> 0 | BB34: =IFERROR(AVERAGE(BB35:BB39),0) -> 0 | BC34: =IFERROR(SUM(BC35:BC39),0) -> 0 | BD34: =IFERROR(SUM(BD35:BD39),0) -> 0 | BE34: =IFERROR(AVERAGE(BE35:BE39),0) -> 0 | BF34: =IFERROR(AVERAGE(BF35:BF39),0) -> 0 | BG34: =IFERROR(SUM(BG35:BG39),0) -> 0 | BH34: =IFERROR(SUM(BH35:BH39),0) -> 0 | BI34: =O34+S34+W34+AA34+AE34+AI34+AM34+AQ34+AU34+AY34+BC34+BG34 -> 0 | BJ34: =BI34*$G$34 -> 0 | BK34: =J34*(H34+I34)/(BI34) -> #REF!
C35: 04.01.01 | D35: ='MH-LAM4 -1225-San Miguel-Antoni'!D15 -> IISS - Revisión de Municipalidad | E35: =VLOOKUP(D35,'MH-LAM4 -1225-San Miguel-Antoni'!$D$2:$E$84,2,FALSE) -> V 3.1 - ENTREGA TÉCNICA FINAL A MUNI | F35: MEDIA | G35: =IF(F35="BAJA",0.8,IF(F35="MEDIA",1,IF(F35="ALTA",1.4,IF(F35="MUY ALTA",2)))) -> 1 | H35: {=G35*INDEX('MH-LAM4 -1225-San Miguel-Antoni'!$B$2:$G$68,MATCH($D$33&D35&$B$5,'MH-LAM4 -1225-San Miguel-Antoni'!$C$2:$C$68&'MH-LAM4 -1225-San Miguel-Antoni'!$D$2:$D$68&'MH-LAM4 -1225-San Miguel-Antoni'!$B$2:$B$68,0),5)/J35} -> 0 | I35: {=G35*INDEX('MH-LAM4 -1225-San Miguel-Antoni'!$B$2:$G$68,MATCH($D$33&D35&$B$5,'MH-LAM4 -1225-San Miguel-Antoni'!$C$2:$C$68&'MH-LAM4 -1225-San Miguel-Antoni'!$D$2:$D$68&'MH-LAM4 -1225-San Miguel-Antoni'!$B$2:$B$68,0),6)/J35} -> 0 | J35: =VLOOKUP($D$34,APUs!$B$2:$I$50,7,FALSE) -> 0.9 | K35: =$G$34*(H35+I35)/J35 -> 0 | P35: =O35*$G$34 -> 0 | T35: =S35*$G$34 -> 0 | X35: =W35*$G$34 -> 0 | AB35: =AA35*$G$34 -> 0 | AF35: =AE35*$G$34 -> 0 | AJ35: =AI35*$G$34 -> 0 | AN35: =AM35*$G$34 -> 0 | AR35: =AQ35*$G$34 -> 0 | AV35: =AU35*$G$34 -> 0 | AZ35: =AY35*$G$34 -> 0 | BD35: =BC35*$G$34 -> 0 | BH35: =BG35*$G$34 -> 0 | BI35: =O35+S35+W35+AA35+AE35+AI35+AM35+AQ35+AU35+AY35+BC35+BG35 -> 0
C36: 04.01.01 | D36: ='MH-LAM4 -1225-San Miguel-Antoni'!#REF! -> #REF! | E36: =VLOOKUP(D36,'MH-LAM4 -1225-San Miguel-Antoni'!$D$2:$E$84,2,FALSE) -> #REF! | F36: MEDIA | G36: =IF(F36="BAJA",0.8,IF(F36="MEDIA",1,IF(F36="ALTA",1.4,IF(F36="MUY ALTA",2)))) -> 1 | H36: {=G36*INDEX('MH-LAM4 -1225-San Miguel-Antoni'!$B$2:$G$68,MATCH($D$33&D36&$B$5,'MH-LAM4 -1225-San Miguel-Antoni'!$C$2:$C$68&'MH-LAM4 -1225-San Miguel-Antoni'!$D$2:$D$68&'MH-LAM4 -1225-San Miguel-Antoni'!$B$2:$B$68,0),5)/J36} -> #REF! | I36: {=G36*INDEX('MH-LAM4 -1225-San Miguel-Antoni'!$B$2:$G$68,MATCH($D$33&D36&$B$5,'MH-LAM4 -1225-San Miguel-Antoni'!$C$2:$C$68&'MH-LAM4 -1225-San Miguel-Antoni'!$D$2:$D$68&'MH-LAM4 -1225-San Miguel-Antoni'!$B$2:$B$68,0),6)/J36} -> #REF! | J36: =VLOOKUP($D$34,APUs!$B$2:$I$50,7,FALSE) -> 0.9 | K36: =$G$34*(H36+I36)/J36 -> #REF! | P36: =O36*$G$34 -> 0 | T36: =S36*$G$34 -> 0 | X36: =W36*$G$34 -> 0 | AB36: =AA36*$G$34 -> 0 | AF36: =AE36*$G$34 -> 0 | AJ36: =AI36*$G$34 -> 0 | AN36: =AM36*$G$34 -> 0 | AR36: =AQ36*$G$34 -> 0 | AV36: =AU36*$G$34 -> 0 | AZ36: =AY36*$G$34 -> 0 | BD36: =BC36*$G$34 -> 0 | BH36: =BG36*$G$34 -> 0 | BI36: =O36+S36+W36+AA36+AE36+AI36+AM36+AQ36+AU36+AY36+BC36+BG36 -> 0
C37: 04.01.01 | D37: ='MH-LAM4 -1225-San Miguel-Antoni'!#REF! -> #REF! | E37: =VLOOKUP(D37,'MH-LAM4 -1225-San Miguel-Antoni'!$D$2:$E$84,2,FALSE) -> #REF! | F37: MEDIA | G37: =IF(F37="BAJA",0.8,IF(F37="MEDIA",1,IF(F37="ALTA",1.4,IF(F37="MUY ALTA",2)))) -> 1 | H37: {=G37*INDEX('MH-LAM4 -1225-San Miguel-Antoni'!$B$2:$G$68,MATCH($D$33&D37&$B$5,'MH-LAM4 -1225-San Miguel-Antoni'!$C$2:$C$68&'MH-LAM4 -1225-San Miguel-Antoni'!$D$2:$D$68&'MH-LAM4 -1225-San Miguel-Antoni'!$B$2:$B$68,0),5)/J37} -> #REF! | I37: {=G37*INDEX('MH-LAM4 -1225-San Miguel-Antoni'!$B$2:$G$68,MATCH($D$33&D37&$B$5,'MH-LAM4 -1225-San Miguel-Antoni'!$C$2:$C$68&'MH-LAM4 -1225-San Miguel-Antoni'!$D$2:$D$68&'MH-LAM4 -1225-San Miguel-Antoni'!$B$2:$B$68,0),6)/J37} -> #REF! | J37: =VLOOKUP($D$34,APUs!$B$2:$I$50,7,FALSE) -> 0.9 | K37: =$G$34*(H37+I37)/J37 -> #REF! | P37: =O37*$G$34 -> 0 | T37: =S37*$G$34 -> 0 | X37: =W37*$G$34 -> 0 | AB37: =AA37*$G$34 -> 0 | AF37: =AE37*$G$34 -> 0 | AJ37: =AI37*$G$34 -> 0 | AN37: =AM37*$G$34 -> 0 | AR37: =AQ37*$G$34 -> 0 | AV37: =AU37*$G$34 -> 0 | AZ37: =AY37*$G$34 -> 0 | BD37: =BC37*$G$34 -> 0 | BH37: =BG37*$G$34 -> 0 | BI37: =O37+S37+W37+AA37+AE37+AI37+AM37+AQ37+AU37+AY37+BC37+BG37 -> 0
C38: 04.01.01 | D38: ='MH-LAM4 -1225-San Miguel-Antoni'!D16 -> IISS - Lev. de observaciones Muni | E38: =VLOOKUP(D38,'MH-LAM4 -1225-San Miguel-Antoni'!$D$2:$E$84,2,FALSE) -> V 3.0 - PRELIMINAR A ENTREGA A MUNI | F38: MEDIA | G38: =IF(F38="BAJA",0.8,IF(F38="MEDIA",1,IF(F38="ALTA",1.4,IF(F38="MUY ALTA",2)))) -> 1 | H38: {=G38*INDEX('MH-LAM4 -1225-San Miguel-Antoni'!$B$2:$G$68,MATCH($D$33&D38&$B$5,'MH-LAM4 -1225-San Miguel-Antoni'!$C$2:$C$68&'MH-LAM4 -1225-San Miguel-Antoni'!$D$2:$D$68&'MH-LAM4 -1225-San Miguel-Antoni'!$B$2:$B$68,0),5)/J38} -> 5.5555556 | I38: {=G38*INDEX('MH-LAM4 -1225-San Miguel-Antoni'!$B$2:$G$68,MATCH($D$33&D38&$B$5,'MH-LAM4 -1225-San Miguel-Antoni'!$C$2:$C$68&'MH-LAM4 -1225-San Miguel-Antoni'!$D$2:$D$68&'MH-LAM4 -1225-San Miguel-Antoni'!$B$2:$B$68,0),6)/J38} -> 0 | J38: =VLOOKUP($D$34,APUs!$B$2:$I$50,7,FALSE) -> 0.9 | K38: =$G$34*(H38+I38)/J38 -> 64.667842 | P38: =O38*$G$34 -> 0 | T38: =S38*$G$34 -> 0 | X38: =W38*$G$34 -> 0 | AB38: =AA38*$G$34 -> 0 | AF38: =AE38*$G$34 -> 0 | AJ38: =AI38*$G$34 -> 0 | AN38: =AM38*$G$34 -> 0 | AR38: =AQ38*$G$34 -> 0 | AV38: =AU38*$G$34 -> 0 | AZ38: =AY38*$G$34 -> 0 | BD38: =BC38*$G$34 -> 0 | BH38: =BG38*$G$34 -> 0 | BI38: =O38+S38+W38+AA38+AE38+AI38+AM38+AQ38+AU38+AY38+BC38+BG38 -> 0
C39: 04.01.01 | D39: ='MH-LAM4 -1225-San Miguel-Antoni'!#REF! -> #REF! | E39: =VLOOKUP(D39,'MH-LAM4 -1225-San Miguel-Antoni'!$D$2:$E$84,2,FALSE) -> #REF! | F39: MEDIA | G39: =IF(F39="BAJA",0.8,IF(F39="MEDIA",1,IF(F39="ALTA",1.4,IF(F39="MUY ALTA",2)))) -> 1 | H39: {=G39*INDEX('MH-LAM4 -1225-San Miguel-Antoni'!$B$2:$G$68,MATCH($D$33&D39&$B$5,'MH-LAM4 -1225-San Miguel-Antoni'!$C$2:$C$68&'MH-LAM4 -1225-San Miguel-Antoni'!$D$2:$D$68&'MH-LAM4 -1225-San Miguel-Antoni'!$B$2:$B$68,0),5)/J39} -> #REF! | I39: {=G39*INDEX('MH-LAM4 -1225-San Miguel-Antoni'!$B$2:$G$68,MATCH($D$33&D39&$B$5,'MH-LAM4 -1225-San Miguel-Antoni'!$C$2:$C$68&'MH-LAM4 -1225-San Miguel-Antoni'!$D$2:$D$68&'MH-LAM4 -1225-San Miguel-Antoni'!$B$2:$B$68,0),6)/J39} -> #REF! | J39: =VLOOKUP($D$34,APUs!$B$2:$I$50,7,FALSE) -> 0.9 | K39: =$G$34*(H39+I39)/J39 -> #REF! | P39: =O39*$G$34 -> 0 | T39: =S39*$G$34 -> 0 | X39: =W39*$G$34 -> 0 | AB39: =AA39*$G$34 -> 0 | AF39: =AE39*$G$34 -> 0 | AJ39: =AI39*$G$34 -> 0 | AN39: =AM39*$G$34 -> 0 | AR39: =AQ39*$G$34 -> 0 | AV39: =AU39*$G$34 -> 0 | AZ39: =AY39*$G$34 -> 0 | BD39: =BC39*$G$34 -> 0 | BH39: =BG39*$G$34 -> 0 | BI39: =O39+S39+W39+AA39+AE39+AI39+AM39+AQ39+AU39+AY39+BC39+BG39 -> 0
C40: 05.00.00 | D40: INST. GAS | M40: =M41 -> 0 | N40: =N41 -> 0 | O40: =O41 -> 0 | P40: =P41 -> 0 | Q40: =Q41 -> 0 | R40: =R41 -> 0 | S40: =S41 -> 0 | T40: =T41 -> 0 | ... BH40: =BH41 -> 0
C41: 05.01.00 | D41: ARQUITECTO SEMISENIOR COLEGIADO | G41: =VLOOKUP(D41,APUs!$B$2:$G$50,6,FALSE) -> 14.285714 | H41: =SUM(H42:H49) -> #REF! | I41: =SUM(I42:I49) -> #REF! | J41: =VLOOKUP(D41,APUs!$B$2:$I$50,7,FALSE) -> 0.97 | K41: =G41*(H41+I41)/J41 -> #REF! | M41: =IFERROR(AVERAGE(M42:M49),0) -> 0 | N41: =IFERROR(AVERAGE(N42:N49),0) -> 0 | O41: =IFERROR(SUM(O42:O49),0) -> 0 | P41: =IFERROR(SUM(P42:P49),0) -> 0 | Q41: =IFERROR(AVERAGE(Q42:Q49),0) -> 0 | R41: =IFERROR(AVERAGE(R42:R49),0) -> 0 | S41: =IFERROR(SUM(S42:S49),0) -> 0 | T41: =IFERROR(SUM(T42:T49),0) -> 0 | U41: =IFERROR(AVERAGE(U42:U49),0) -> 0 | V41: =IFERROR(AVERAGE(V42:V49),0) -> 0 | W41: =IFERROR(SUM(W42:W49),0) -> 0 | X41: =IFERROR(SUM(X42:X49),0) -> 0 | Y41: =IFERROR(AVERAGE(Y42:Y49),0) -> 0 | Z41: =IFERROR(AVERAGE(Z42:Z49),0) -> 0 | AA41: =IFERROR(SUM(AA42:AA49),0) -> 0 | AB41: =IFERROR(SUM(AB42:AB49),0) -> 0 | AC41: =IFERROR(AVERAGE(AC42:AC49),0) -> 0 | AD41: =IFERROR(AVERAGE(AD42:AD49),0) -> 0 | AE41: =IFERROR(SUM(AE42:AE49),0) -> 0 | AF41: =IFERROR(SUM(AF42:AF49),0) -> 0 | AG41: =IFERROR(AVERAGE(AG42:AG49),0) -> 0 | AH41: =IFERROR(AVERAGE(AH42:AH49),0) -> 0 | AI41: =IFERROR(SUM(AI42:AI49),0) -> 0 | AJ41: =IFERROR(SUM(AJ42:AJ49),0) -> 0 | AK41: =IFERROR(AVERAGE(AK42:AK49),0) -> 0 | AL41: =IFERROR(AVERAGE(AL42:AL49),0) -> 0 | AM41: =IFERROR(SUM(AM42:AM49),0) -> 0 | AN41: =IFERROR(SUM(AN42:AN49),0) -> 0 | AO41: =IFERROR(AVERAGE(AO42:AO49),0) -> 0 | AP41: =IFERROR(AVERAGE(AP42:AP49),0) -> 0 | AQ41: =IFERROR(SUM(AQ42:AQ49),0) -> 0 | AR41: =IFERROR(SUM(AR42:AR49),0) -> 0 | AS41: =IFERROR(AVERAGE(AS42:AS49),0) -> 0 | AT41: =IFERROR(AVERAGE(AT42:AT49),0) -> 0 | AU41: =IFERROR(SUM(AU42:AU49),0) -> 0 | AV41: =IFERROR(SUM(AV42:AV49),0) -> 0 | AW41: =IFERROR(AVERAGE(AW42:AW49),0) -> 0 | AX41: =IFERROR(AVERAGE(AX42:AX49),0) -> 0 | AY41: =IFERROR(SUM(AY42:AY49),0) -> 0 | AZ41: =IFERROR(SUM(AZ42:AZ49),0) -> 0 | BA41: =IFERROR(AVERAGE(BA42:BA49),0) -> 0 | BB41: =IFERROR(AVERAGE(BB42:BB49),0) -> 0 | BC41: =IFERROR(SUM(BC42:BC49),0) -> 0 | BD41: =IFERROR(SUM(BD42:BD49),0) -> 0 | BE41: =IFERROR(AVERAGE(BE42:BE49),0) -> 0 | BF41: =IFERROR(AVERAGE(BF42:BF49),0) -> 0 | BG41: =IFERROR(SUM(BG42:BG49),0) -> 0 | BH41: =IFERROR(SUM(BH42:BH49),0) -> 0 | BI41: =O41+S41+W41+AA41+AE41+AI41+AM41+AQ41+AU41+AY41+BC41+BG41 -> 0 | BJ41: =BI41*$G$41 -> 0 | BK41: =J41*(H41+I41)/(BI41) -> #REF!
C42: 05.01.01 | D42: ='MH-LAM4 -1225-San Miguel-Antoni'!#REF! -> #REF! | E42: =VLOOKUP(D42,'MH-LAM4 -1225-San Miguel-Antoni'!$D$2:$E$84,2,FALSE) -> #REF! | F42: MEDIA | G42: =IF(F42="BAJA",0.8,IF(F42="MEDIA",1,IF(F42="ALTA",1.4,IF(F42="MUY ALTA",2)))) -> 1 | H42: {=G42*INDEX('MH-LAM4 -1225-San Miguel-Antoni'!$B$2:$G$68,MATCH($D$40&D42&$B$5,'MH-LAM4 -1225-San Miguel-Antoni'!$C$2:$C$68&'MH-LAM4 -1225-San Miguel-Antoni'!$D$2:$D$68&'MH-LAM4 -1225-San Miguel-Antoni'!$B$2:$B$68,0),5)/J42} -> #REF! | I42: {=G42*INDEX('MH-LAM4 -1225-San Miguel-Antoni'!$B$2:$G$68,MATCH($D$40&D42&$B$5,'MH-LAM4 -1225-San Miguel-Antoni'!$C$2:$C$68&'MH-LAM4 -1225-San Miguel-Antoni'!$D$2:$D$68&'MH-LAM4 -1225-San Miguel-Antoni'!$B$2:$B$68,0),6)/J42} -> #REF! | J42: =VLOOKUP($D$41,APUs!$B$2:$I$50,7,FALSE) -> 0.97 | K42: =$G$41*(H42+I42)/J42 -> #REF! | P42: =O42*$G$34 -> 0 | T42: =S42*$G$34 -> 0 | X42: =W42*$G$34 -> 0 | AB42: =AA42*$G$34 -> 0 | AF42: =AE42*$G$34 -> 0 | AJ42: =AI42*$G$34 -> 0 | AN42: =AM42*$G$34 -> 0 | AR42: =AQ42*$G$34 -> 0 | AV42: =AU42*$G$34 -> 0 | AZ42: =AY42*$G$34 -> 0 | BD42: =BC42*$G$34 -> 0 | BH42: =BG42*$G$34 -> 0 | BI42: =O42+S42+W42+AA42+AE42+AI42+AM42+AQ42+AU42+AY42+BC42+BG42 -> 0
C43: 05.01.01 | D43: ='MH-LAM4 -1225-San Miguel-Antoni'!#REF! -> #REF! | E43: =VLOOKUP(D43,'MH-LAM4 -1225-San Miguel-Antoni'!$D$2:$E$84,2,FALSE) -> #REF! | F43: MEDIA | G43: =IF(F43="BAJA",0.8,IF(F43="MEDIA",1,IF(F43="ALTA",1.4,IF(F43="MUY ALTA",2)))) -> 1 | H43: {=G43*INDEX('MH-LAM4 -1225-San Miguel-Antoni'!$B$2:$G$68,MATCH($D$40&D43&$B$5,'MH-LAM4 -1225-San Miguel-Antoni'!$C$2:$C$68&'MH-LAM4 -1225-San Miguel-Antoni'!$D$2:$D$68&'MH-LAM4 -1225-San Miguel-Antoni'!$B$2:$B$68,0),5)/J43} -> #REF! | I43: {=G43*INDEX('MH-LAM4 -1225-San Miguel-Antoni'!$B$2:$G$68,MATCH($D$40&D43&$B$5,'MH-LAM4 -1225-San Miguel-Antoni'!$C$2:$C$68&'MH-LAM4 -1225-San Miguel-Antoni'!$D$2:$D$68&'MH-LAM4 -1225-San Miguel-Antoni'!$B$2:$B$68,0),6)/J43} -> #REF! | J43: =VLOOKUP($D$41,APUs!$B$2:$I$50,7,FALSE) -> 0.97 | K43: =$G$41*(H43+I43)/J43 -> #REF! | P43: =O43*$G$34 -> 0 | T43: =S43*$G$34 -> 0 | X43: =W43*$G$34 -> 0 | AB43: =AA43*$G$34 -> 0 | AF43: =AE43*$G$34 -> 0 | AJ43: =AI43*$G$34 -> 0 | AN43: =AM43*$G$34 -> 0 | AR43: =AQ43*$G$34 -> 0 | AV43: =AU43*$G$34 -> 0 | AZ43: =AY43*$G$34 -> 0 | BD43: =BC43*$G$34 -> 0 | BH43: =BG43*$G$34 -> 0 | BI43: =O43+S43+W43+AA43+AE43+AI43+AM43+AQ43+AU43+AY43+BC43+BG43 -> 0
C44: 05.01.01 | D44: ='MH-LAM4 -1225-San Miguel-Antoni'!D17 -> IIGG - Lev. de Observaciones de Muni | E44: =VLOOKUP(D44,'MH-LAM4 -1225-San Miguel-Antoni'!$D$2:$E$84,2,FALSE) -> V 3.0 - PRELIMINAR A ENTREGA A MUNI | F44: MEDIA | G44: =IF(F44="BAJA",0.8,IF(F44="MEDIA",1,IF(F44="ALTA",1.4,IF(F44="MUY ALTA",2)))) -> 1 | H44: {=G44*INDEX('MH-LAM4 -1225-San Miguel-Antoni'!$B$2:$G$68,MATCH($D$40&D44&$B$5,'MH-LAM4 -1225-San Miguel-Antoni'!$C$2:$C$68&'MH-LAM4 -1225-San Miguel-Antoni'!$D$2:$D$68&'MH-LAM4 -1225-San Miguel-Antoni'!$B$2:$B$68,0),5)/J44} -> 1.0309278 | I44: {=G44*INDEX('MH-LAM4 -1225-San Miguel-Antoni'!$B$2:$G$68,MATCH($D$40&D44&$B$5,'MH-LAM4 -1225-San Miguel-Antoni'!$C$2:$C$68&'MH-LAM4 -1225-San Miguel-Antoni'!$D$2:$D$68&'MH-LAM4 -1225-San Miguel-Antoni'!$B$2:$B$68,0),6)/J44} -> 0 | J44: =VLOOKUP($D$41,APUs!$B$2:$I$50,7,FALSE) -> 0.97 | K44: =$G$41*(H44+I44)/J44 -> 15.183031 | P44: =O44*$G$34 -> 0 | T44: =S44*$G$34 -> 0 | X44: =W44*$G$34 -> 0 | AB44: =AA44*$G$34 -> 0 | AF44: =AE44*$G$34 -> 0 | AJ44: =AI44*$G$34 -> 0 | AN44: =AM44*$G$34 -> 0 | AR44: =AQ44*$G$34 -> 0 | AV44: =AU44*$G$34 -> 0 | AZ44: =AY44*$G$34 -> 0 | BD44: =BC44*$G$34 -> 0 | BH44: =BG44*$G$34 -> 0 | BI44: =O44+S44+W44+AA44+AE44+AI44+AM44+AQ44+AU44+AY44+BC44+BG44 -> 0
C45: 05.01.01 | D45: ='MH-LAM4 -1225-San Miguel-Antoni'!D18 -> IIGG - Revisión de Municipalidad | E45: =VLOOKUP(D45,'MH-LAM4 -1225-San Miguel-Antoni'!$D$2:$E$84,2,FALSE) -> V 3.1 - ENTREGA TÉCNICA FINAL A MUNI | F45: MEDIA | G45: =IF(F45="BAJA",0.8,IF(F45="MEDIA",1,IF(F45="ALTA",1.4,IF(F45="MUY ALTA",2)))) -> 1 | H45: {=G45*INDEX('MH-LAM4 -1225-San Miguel-Antoni'!$B$2:$G$68,MATCH($D$40&D45&$B$5,'MH-LAM4 -1225-San Miguel-Antoni'!$C$2:$C$68&'MH-LAM4 -1225-San Miguel-Antoni'!$D$2:$D$68&'MH-LAM4 -1225-San Miguel-Antoni'!$B$2:$B$68,0),5)/J45} -> 0 | I45: {=G45*INDEX('MH-LAM4 -1225-San Miguel-Antoni'!$B$2:$G$68,MATCH($D$40&D45&$B$5,'MH-LAM4 -1225-San Miguel-Antoni'!$C$2:$C$68&'MH-LAM4 -1225-San Miguel-Antoni'!$D$2:$D$68&'MH-LAM4 -1225-San Miguel-Antoni'!$B$2:$B$68,0),6)/J45} -> 0 | J45: =VLOOKUP($D$41,APUs!$B$2:$I$50,7,FALSE) -> 0.97 | K45: =$G$41*(H45+I45)/J45 -> 0 | P45: =O45*$G$34 -> 0 | T45: =S45*$G$34 -> 0 | X45: =W45*$G$34 -> 0 | AB45: =AA45*$G$34 -> 0 | AF45: =AE45*$G$34 -> 0 | AJ45: =AI45*$G$34 -> 0 | AN45: =AM45*$G$34 -> 0 | AR45: =AQ45*$G$34 -> 0 | AV45: =AU45*$G$34 -> 0 | AZ45: =AY45*$G$34 -> 0 | BD45: =BC45*$G$34 -> 0 | BH45: =BG45*$G$34 -> 0 | BI45: =O45+S45+W45+AA45+AE45+AI45+AM45+AQ45+AU45+AY45+BC45+BG45 -> 0
C46: 05.01.01 | D46: ='MH-LAM4 -1225-San Miguel-Antoni'!#REF! -> #REF! | E46: =VLOOKUP(D46,'MH-LAM4 -1225-San Miguel-Antoni'!$D$2:$E$84,2,FALSE) -> #REF! | F46: MEDIA | G46: =IF(F46="BAJA",0.8,IF(F46="MEDIA",1,IF(F46="ALTA",1.4,IF(F46="MUY ALTA",2)))) -> 1 | H46: {=G46*INDEX('MH-LAM4 -1225-San Miguel-Antoni'!$B$2:$G$68,MATCH($D$40&D46&$B$5,'MH-LAM4 -1225-San Miguel-Antoni'!$C$2:$C$68&'MH-LAM4 -1225-San Miguel-Antoni'!$D$2:$D$68&'MH-LAM4 -1225-San Miguel-Antoni'!$B$2:$B$68,0),5)/J46} -> #REF! | I46: {=G46*INDEX('MH-LAM4 -1225-San Miguel-Antoni'!$B$2:$G$68,MATCH($D$40&D46&$B$5,'MH-LAM4 -1225-San Miguel-Antoni'!$C$2:$C$68&'MH-LAM4 -1225-San Miguel-Antoni'!$D$2:$D$68&'MH-LAM4 -1225-San Miguel-Antoni'!$B$2:$B$68,0),6)/J46} -> #REF! | J46: =VLOOKUP($D$41,APUs!$B$2:$I$50,7,FALSE) -> 0.97 | K46: =$G$41*(H46+I46)/J46 -> #REF! | P46: =O46*$G$34 -> 0 | T46: =S46*$G$34 -> 0 | X46: =W46*$G$34 -> 0 | AB46: =AA46*$G$34 -> 0 | AF46: =AE46*$G$34 -> 0 | AJ46: =AI46*$G$34 -> 0 | AN46: =AM46*$G$34 -> 0 | AR46: =AQ46*$G$34 -> 0 | AV46: =AU46*$G$34 -> 0 | AZ46: =AY46*$G$34 -> 0 | BD46: =BC46*$G$34 -> 0 | BH46: =BG46*$G$34 -> 0 | BI46: =O46+S46+W46+AA46+AE46+AI46+AM46+AQ46+AU46+AY46+BC46+BG46 -> 0
C47: 05.01.01 | D47: ='MH-LAM4 -1225-San Miguel-Antoni'!#REF! -> #REF! | E47: =VLOOKUP(D47,'MH-LAM4 -1225-San Miguel-Antoni'!$D$2:$E$84,2,FALSE) -> #REF! | F47: MEDIA | G47: =IF(F47="BAJA",0.8,IF(F47="MEDIA",1,IF(F47="ALTA",1.4,IF(F47="MUY ALTA",2)))) -> 1 | H47: {=G47*INDEX('MH-LAM4 -1225-San Miguel-Antoni'!$B$2:$G$68,MATCH($D$40&D47&$B$5,'MH-LAM4 -1225-San Miguel-Antoni'!$C$2:$C$68&'MH-LAM4 -1225-San Miguel-Antoni'!$D$2:$D$68&'MH-LAM4 -1225-San Miguel-Antoni'!$B$2:$B$68,0),5)/J47} -> #REF! | I47: {=G47*INDEX('MH-LAM4 -1225-San Miguel-Antoni'!$B$2:$G$68,MATCH($D$40&D47&$B$5,'MH-LAM4 -1225-San Miguel-Antoni'!$C$2:$C$68&'MH-LAM4 -1225-San Miguel-Antoni'!$D$2:$D$68&'MH-LAM4 -1225-San Miguel-Antoni'!$B$2:$B$68,0),6)/J47} -> #REF! | J47: =VLOOKUP($D$41,APUs!$B$2:$I$50,7,FALSE) -> 0.97 | K47: =$G$41*(H47+I47)/J47 -> #REF! | P47: =O47*$G$34 -> 0 | T47: =S47*$G$34 -> 0 | X47: =W47*$G$34 -> 0 | AB47: =AA47*$G$34 -> 0 | AF47: =AE47*$G$34 -> 0 | AJ47: =AI47*$G$34 -> 0 | AN47: =AM47*$G$34 -> 0 | AR47: =AQ47*$G$34 -> 0 | AV47: =AU47*$G$34 -> 0 | AZ47: =AY47*$G$34 -> 0 | BD47: =BC47*$G$34 -> 0 | BH47: =BG47*$G$34 -> 0 | BI47: =O47+S47+W47+AA47+AE47+AI47+AM47+AQ47+AU47+AY47+BC47+BG47 -> 0
C48: 05.01.01 | D48: ='MH-LAM4 -1225-San Miguel-Antoni'!#REF! -> #REF! | E48: =VLOOKUP(D48,'MH-LAM4 -1225-San Miguel-Antoni'!$D$2:$E$84,2,FALSE) -> #REF! | F48: MEDIA | G48: =IF(F48="BAJA",0.8,IF(F48="MEDIA",1,IF(F48="ALTA",1.4,IF(F48="MUY ALTA",2)))) -> 1 | H48: {=G48*INDEX('MH-LAM4 -1225-San Miguel-Antoni'!$B$2:$G$68,MATCH($D$40&D48&$B$5,'MH-LAM4 -1225-San Miguel-Antoni'!$C$2:$C$68&'MH-LAM4 -1225-San Miguel-Antoni'!$D$2:$D$68&'MH-LAM4 -1225-San Miguel-Antoni'!$B$2:$B$68,0),5)/J48} -> #REF! | I48: {=G48*INDEX('MH-LAM4 -1225-San Miguel-Antoni'!$B$2:$G$68,MATCH($D$40&D48&$B$5,'MH-LAM4 -1225-San Miguel-Antoni'!$C$2:$C$68&'MH-LAM4 -1225-San Miguel-Antoni'!$D$2:$D$68&'MH-LAM4 -1225-San Miguel-Antoni'!$B$2:$B$68,0),6)/J48} -> #REF! | J48: =VLOOKUP($D$41,APUs!$B$2:$I$50,7,FALSE) -> 0.97 | K48: =$G$41*(H48+I48)/J48 -> #REF! | P48: =O48*$G$34 -> 0 | T48: =S48*$G$34 -> 0 | X48: =W48*$G$34 -> 0 | AB48: =AA48*$G$34 -> 0 | AF48: =AE48*$G$34 -> 0 | AJ48: =AI48*$G$34 -> 0 | AN48: =AM48*$G$34 -> 0 | AR48: =AQ48*$G$34 -> 0 | AV48: =AU48*$G$34 -> 0 | AZ48: =AY48*$G$34 -> 0 | BD48: =BC48*$G$34 -> 0 | BH48: =BG48*$G$34 -> 0 | BI48: =O48+S48+W48+AA48+AE48+AI48+AM48+AQ48+AU48+AY48+BC48+BG48 -> 0
C49: 05.01.01 | D49: ='MH-LAM4 -1225-San Miguel-Antoni'!#REF! -> #REF! | E49: =VLOOKUP(D49,'MH-LAM4 -1225-San Miguel-Antoni'!$D$2:$E$84,2,FALSE) -> #REF! | F49: MEDIA | G49: =IF(F49="BAJA",0.8,IF(F49="MEDIA",1,IF(F49="ALTA",1.4,IF(F49="MUY ALTA",2)))) -> 1 | H49: {=G49*INDEX('MH-LAM4 -1225-San Miguel-Antoni'!$B$2:$G$68,MATCH($D$40&D49&$B$5,'MH-LAM4 -1225-San Miguel-Antoni'!$C$2:$C$68&'MH-LAM4 -1225-San Miguel-Antoni'!$D$2:$D$68&'MH-LAM4 -1225-San Miguel-Antoni'!$B$2:$B$68,0),5)/J49} -> #REF! | I49: {=G49*INDEX('MH-LAM4 -1225-San Miguel-Antoni'!$B$2:$G$68,MATCH($D$40&D49&$B$5,'MH-LAM4 -1225-San Miguel-Antoni'!$C$2:$C$68&'MH-LAM4 -1225-San Miguel-Antoni'!$D$2:$D$68&'MH-LAM4 -1225-San Miguel-Antoni'!$B$2:$B$68,0),6)/J49} -> #REF! | J49: =VLOOKUP($D$41,APUs!$B$2:$I$50,7,FALSE) -> 0.97 | K49: =$G$41*(H49+I49)/J49 -> #REF! | P49: =O49*$G$34 -> 0 | T49: =S49*$G$34 -> 0 | X49: =W49*$G$34 -> 0 | AB49: =AA49*$G$34 -> 0 | AF49: =AE49*$G$34 -> 0 | AJ49: =AI49*$G$34 -> 0 | AN49: =AM49*$G$34 -> 0 | AR49: =AQ49*$G$34 -> 0 | AV49: =AU49*$G$34 -> 0 | AZ49: =AY49*$G$34 -> 0 | BD49: =BC49*$G$34 -> 0 | BH49: =BG49*$G$34 -> 0 | BI49: =O49+S49+W49+AA49+AE49+AI49+AM49+AQ49+AU49+AY49+BC49+BG49 -> 0
C50: 06.00.00 | D50: SUELOS | M50: =M51 -> 0 | N50: =N51 -> 0 | O50: =O51 -> 0 | P50: =P51 -> 0 | Q50: =Q51 -> 0 | R50: =R51 -> 0 | S50: =S51 -> 0 | T50: =T51 -> 0 | ... BH50: =BH51 -> 0
C51: 06.01.00 | D51: INGENIERO ESTRUCT. SEMISENIOR | G51: =VLOOKUP(D51,APUs!$B$2:$G$50,6,FALSE) -> 14.285714 | H51: =SUM(H52:H54) -> 0 | I51: =SUM(I52:I54) -> 0 | J51: =VLOOKUP(D51,APUs!$B$2:$I$50,7,FALSE) -> 0.97 | K51: =G51*(H51+I51)/J51 -> 0 | M51: =IFERROR(AVERAGE(M52:M54),0) -> 0 | N51: =IFERROR(AVERAGE(N52:N54),0) -> 0 | O51: =IFERROR(SUM(O52:O54),0) -> 0 | P51: =IFERROR(SUM(P52:P54),0) -> 0 | Q51: =IFERROR(AVERAGE(Q52:Q54),0) -> 0 | R51: =IFERROR(AVERAGE(R52:R54),0) -> 0 | S51: =IFERROR(SUM(S52:S54),0) -> 0 | T51: =IFERROR(SUM(T52:T54),0) -> 0 | U51: =IFERROR(AVERAGE(U52:U54),0) -> 0 | V51: =IFERROR(AVERAGE(V52:V54),0) -> 0 | W51: =IFERROR(SUM(W52:W54),0) -> 0 | X51: =IFERROR(SUM(X52:X54),0) -> 0 | Y51: =IFERROR(AVERAGE(Y52:Y54),0) -> 0 | Z51: =IFERROR(AVERAGE(Z52:Z54),0) -> 0 | AA51: =IFERROR(SUM(AA52:AA54),0) -> 0 | AB51: =IFERROR(SUM(AB52:AB54),0) -> 0 | AC51: =IFERROR(AVERAGE(AC52:AC54),0) -> 0 | AD51: =IFERROR(AVERAGE(AD52:AD54),0) -> 0 | AE51: =IFERROR(SUM(AE52:AE54),0) -> 0 | AF51: =IFERROR(SUM(AF52:AF54),0) -> 0 | AG51: =IFERROR(AVERAGE(AG52:AG54),0) -> 0 | AH51: =IFERROR(AVERAGE(AH52:AH54),0) -> 0 | AI51: =IFERROR(SUM(AI52:AI54),0) -> 0 | AJ51: =IFERROR(SUM(AJ52:AJ54),0) -> 0 | AK51: =IFERROR(AVERAGE(AK52:AK54),0) -> 0 | AL51: =IFERROR(AVERAGE(AL52:AL54),0) -> 0 | AM51: =IFERROR(SUM(AM52:AM54),0) -> 0 | AN51: =IFERROR(SUM(AN52:AN54),0) -> 0 | AO51: =IFERROR(AVERAGE(AO52:AO54),0) -> 0 | AP51: =IFERROR(AVERAGE(AP52:AP54),0) -> 0 | AQ51: =IFERROR(SUM(AQ52:AQ54),0) -> 0 | AR51: =IFERROR(SUM(AR52:AR54),0) -> 0 | AS51: =IFERROR(AVERAGE(AS52:AS54),0) -> 0 | AT51: =IFERROR(AVERAGE(AT52:AT54),0) -> 0 | AU51: =IFERROR(SUM(AU52:AU54),0) -> 0 | AV51: =IFERROR(SUM(AV52:AV54),0) -> 0 | AW51: =IFERROR(AVERAGE(AW52:AW54),0) -> 0 | AX51: =IFERROR(AVERAGE(AX52:AX54),0) -> 0 | AY51: =IFERROR(SUM(AY52:AY54),0) -> 0 | AZ51: =IFERROR(SUM(AZ52:AZ54),0) -> 0 | BA51: =IFERROR(AVERAGE(BA52:BA54),0) -> 0 | BB51: =IFERROR(AVERAGE(BB52:BB54),0) -> 0 | BC51: =IFERROR(SUM(BC52:BC54),0) -> 0 | BD51: =IFERROR(SUM(BD52:BD54),0) -> 0 | BE51: =IFERROR(AVERAGE(BE52:BE54),0) -> 0 | BF51: =IFERROR(AVERAGE(BF52:BF54),0) -> 0 | BG51: =IFERROR(SUM(BG52:BG54),0) -> 0 | BH51: =IFERROR(SUM(BH52:BH54),0) -> 0 | BI51: =O51+S51+W51+AA51+AE51+AI51+AM51+AQ51+AU51+AY51+BC51+BG51 -> 0 | BJ51: =BI51*$G$34 -> 0 | BK51: =J51*(H51+I51)/(BI51) -> #DIV/0!
C52: 06.01.01 | D52: ='MH-LAM4 -1225-San Miguel-Antoni'!D19 -> EMS - Excel de ensayos | E52: =VLOOKUP(D52,'MH-LAM4 -1225-San Miguel-Antoni'!$D$2:$E$84,2,FALSE) -> V 1.0 - PRELIMINAR A LA APROBACIÓN ARQUITECTÓNICA | F52: MEDIA | G52: =IF(F52="BAJA",0.8,IF(F52="MEDIA",1,IF(F52="ALTA",1.4,IF(F52="MUY ALTA",2)))) -> 1 | H52: {=G52*INDEX('MH-LAM4 -1225-San Miguel-Antoni'!$B$2:$G$68,MATCH($D$50&D52&$B$5,'MH-LAM4 -1225-San Miguel-Antoni'!$C$2:$C$68&'MH-LAM4 -1225-San Miguel-Antoni'!$D$2:$D$68&'MH-LAM4 -1225-San Miguel-Antoni'!$B$2:$B$68,0),5)/J52} -> 0 | I52: {=G52*INDEX('MH-LAM4 -1225-San Miguel-Antoni'!$B$2:$G$68,MATCH($D$50&D52&$B$5,'MH-LAM4 -1225-San Miguel-Antoni'!$C$2:$C$68&'MH-LAM4 -1225-San Miguel-Antoni'!$D$2:$D$68&'MH-LAM4 -1225-San Miguel-Antoni'!$B$2:$B$68,0),6)/J52} -> 0 | J52: =VLOOKUP($D$34,APUs!$B$2:$I$50,7,FALSE) -> 0.9 | K52: =$G$34*(H52+I52)/J52 -> 0 | P52: =O52*$G$34 -> 0 | T52: =S52*$G$34 -> 0 | X52: =W52*$G$34 -> 0 | AB52: =AA52*$G$34 -> 0 | AF52: =AE52*$G$34 -> 0 | AJ52: =AI52*$G$34 -> 0 | AN52: =AM52*$G$34 -> 0 | AR52: =AQ52*$G$34 -> 0 | AV52: =AU52*$G$34 -> 0 | AZ52: =AY52*$G$34 -> 0 | BD52: =BC52*$G$34 -> 0 | BH52: =BG52*$G$34 -> 0 | BI52: =O52+S52+W52+AA52+AE52+AI52+AM52+AQ52+AU52+AY52+BC52+BG52 -> 0
C53: 06.01.01 | D53: ='MH-LAM4 -1225-San Miguel-Antoni'!D20 -> EMS - Plano topográfico | E53: =VLOOKUP(D53,'MH-LAM4 -1225-San Miguel-Antoni'!$D$2:$E$84,2,FALSE) -> V 2.0 - PRELIMINAR A ENTREGA A REVISORES | F53: MEDIA | G53: =IF(F53="BAJA",0.8,IF(F53="MEDIA",1,IF(F53="ALTA",1.4,IF(F53="MUY ALTA",2)))) -> 1 | H53: {=G53*INDEX('MH-LAM4 -1225-San Miguel-Antoni'!$B$2:$G$68,MATCH($D$50&D53&$B$5,'MH-LAM4 -1225-San Miguel-Antoni'!$C$2:$C$68&'MH-LAM4 -1225-San Miguel-Antoni'!$D$2:$D$68&'MH-LAM4 -1225-San Miguel-Antoni'!$B$2:$B$68,0),5)/J53} -> 0 | I53: {=G53*INDEX('MH-LAM4 -1225-San Miguel-Antoni'!$B$2:$G$68,MATCH($D$50&D53&$B$5,'MH-LAM4 -1225-San Miguel-Antoni'!$C$2:$C$68&'MH-LAM4 -1225-San Miguel-Antoni'!$D$2:$D$68&'MH-LAM4 -1225-San Miguel-Antoni'!$B$2:$B$68,0),6)/J53} -> 0 | J53: =VLOOKUP($D$34,APUs!$B$2:$I$50,7,FALSE) -> 0.9 | K53: =$G$34*(H53+I53)/J53 -> 0 | P53: =O53*$G$34 -> 0 | T53: =S53*$G$34 -> 0 | X53: =W53*$G$34 -> 0 | AB53: =AA53*$G$34 -> 0 | AF53: =AE53*$G$34 -> 0 | AJ53: =AI53*$G$34 -> 0 | AN53: =AM53*$G$34 -> 0 | AR53: =AQ53*$G$34 -> 0 | AV53: =AU53*$G$34 -> 0 | AZ53: =AY53*$G$34 -> 0 | BD53: =BC53*$G$34 -> 0 | BH53: =BG53*$G$34 -> 0 | BI53: =O53+S53+W53+AA53+AE53+AI53+AM53+AQ53+AU53+AY53+BC53+BG53 -> 0
C54: 06.01.01 | D54: ='MH-LAM4 -1225-San Miguel-Antoni'!D21 -> EMS - Informe de EMS | E54: =VLOOKUP(D54,'MH-LAM4 -1225-San Miguel-Antoni'!$D$2:$E$84,2,FALSE) -> V 2.0 - PRELIMINAR A ENTREGA A REVISORES | F54: MEDIA | G54: =IF(F54="BAJA",0.8,IF(F54="MEDIA",1,IF(F54="ALTA",1.4,IF(F54="MUY ALTA",2)))) -> 1 | H54: {=G54*INDEX('MH-LAM4 -1225-San Miguel-Antoni'!$B$2:$G$68,MATCH($D$50&D54&$B$5,'MH-LAM4 -1225-San Miguel-Antoni'!$C$2:$C$68&'MH-LAM4 -1225-San Miguel-Antoni'!$D$2:$D$68&'MH-LAM4 -1225-San Miguel-Antoni'!$B$2:$B$68,0),5)/J54} -> 0 | I54: {=G54*INDEX('MH-LAM4 -1225-San Miguel-Antoni'!$B$2:$G$68,MATCH($D$50&D54&$B$5,'MH-LAM4 -1225-San Miguel-Antoni'!$C$2:$C$68&'MH-LAM4 -1225-San Miguel-Antoni'!$D$2:$D$68&'MH-LAM4 -1225-San Miguel-Antoni'!$B$2:$B$68,0),6)/J54} -> 0 | J54: =VLOOKUP($D$34,APUs!$B$2:$I$50,7,FALSE) -> 0.9 | K54: =$G$34*(H54+I54)/J54 -> 0 | P54: =O54*$G$34 -> 0 | T54: =S54*$G$34 -> 0 | X54: =W54*$G$34 -> 0 | AB54: =AA54*$G$34 -> 0 | AF54: =AE54*$G$34 -> 0 | AJ54: =AI54*$G$34 -> 0 | AN54: =AM54*$G$34 -> 0 | AR54: =AQ54*$G$34 -> 0 | AV54: =AU54*$G$34 -> 0 | AZ54: =AY54*$G$34 -> 0 | BD54: =BC54*$G$34 -> 0 | BH54: =BG54*$G$34 -> 0 | BI54: =O54+S54+W54+AA54+AE54+AI54+AM54+AQ54+AU54+AY54+BC54+BG54 -> 0
C55: 07.00.00 | D55: GESTIÓN Y ADMINISTRACIÓN | M55: =M56 -> 0 | N55: =N56 -> 0 | O55: =O56 -> 0 | P55: =P56 -> 0 | Q55: =Q56 -> 0 | R55: =R56 -> 0 | S55: =S56 -> 0 | T55: =T56 -> 0 | ... BH55: =BH56 -> 0
C56: 07.01.00 | D56: GESTORA DE PROYECTOS | G56: =VLOOKUP(D56,APUs!$B$2:$G$50,6,FALSE) -> 16.666667 | H56: =SUM(H57:H58) -> 0 | I56: =SUM(I57:I58) -> 0 | J56: =VLOOKUP(D56,APUs!$B$2:$I$50,7,FALSE) -> 0.95 | K56: =G56*(H56+I56)/J56 -> 0 | M56: =IFERROR(AVERAGE(M57:M58),0) -> 0 | N56: =IFERROR(AVERAGE(N57:N58),0) -> 0 | O56: =IFERROR(SUM(O57:O58),0) -> 0 | P56: =IFERROR(SUM(P57:P58),0) -> 0 | Q56: =IFERROR(AVERAGE(Q57:Q58),0) -> 0 | R56: =IFERROR(AVERAGE(R57:R58),0) -> 0 | S56: =IFERROR(SUM(S57:S58),0) -> 0 | T56: =IFERROR(SUM(T57:T58),0) -> 0 | U56: =IFERROR(AVERAGE(U57:U58),0) -> 0 | V56: =IFERROR(AVERAGE(V57:V58),0) -> 0 | W56: =IFERROR(SUM(W57:W58),0) -> 0 | X56: =IFERROR(SUM(X57:X58),0) -> 0 | Y56: =IFERROR(AVERAGE(Y57:Y58),0) -> 0 | Z56: =IFERROR(AVERAGE(Z57:Z58),0) -> 0 | AA56: =IFERROR(SUM(AA57:AA58),0) -> 0 | AB56: =IFERROR(SUM(AB57:AB58),0) -> 0 | AC56: =IFERROR(AVERAGE(AC57:AC58),0) -> 0 | AD56: =IFERROR(AVERAGE(AD57:AD58),0) -> 0 | AE56: =IFERROR(SUM(AE57:AE58),0) -> 0 | AF56: =IFERROR(SUM(AF57:AF58),0) -> 0 | AG56: =IFERROR(AVERAGE(AG57:AG58),0) -> 0 | AH56: =IFERROR(AVERAGE(AH57:AH58),0) -> 0 | AI56: =IFERROR(SUM(AI57:AI58),0) -> 0 | AJ56: =IFERROR(SUM(AJ57:AJ58),0) -> 0 | AK56: =IFERROR(AVERAGE(AK57:AK58),0) -> 0 | AL56: =IFERROR(AVERAGE(AL57:AL58),0) -> 0 | AM56: =IFERROR(SUM(AM57:AM58),0) -> 0 | AN56: =IFERROR(SUM(AN57:AN58),0) -> 0 | AO56: =IFERROR(AVERAGE(AO57:AO58),0) -> 0 | AP56: =IFERROR(AVERAGE(AP57:AP58),0) -> 0 | AQ56: =IFERROR(SUM(AQ57:AQ58),0) -> 0 | AR56: =IFERROR(SUM(AR57:AR58),0) -> 0 | AS56: =IFERROR(AVERAGE(AS57:AS58),0) -> 0 | AT56: =IFERROR(AVERAGE(AT57:AT58),0) -> 0 | AU56: =IFERROR(SUM(AU57:AU58),0) -> 0 | AV56: =IFERROR(SUM(AV57:AV58),0) -> 0 | AW56: =IFERROR(AVERAGE(AW57:AW58),0) -> 0 | AX56: =IFERROR(AVERAGE(AX57:AX58),0) -> 0 | AY56: =IFERROR(SUM(AY57:AY58),0) -> 0 | AZ56: =IFERROR(SUM(AZ57:AZ58),0) -> 0 | BA56: =IFERROR(AVERAGE(BA57:BA58),0) -> 0 | BB56: =IFERROR(AVERAGE(BB57:BB58),0) -> 0 | BC56: =IFERROR(SUM(BC57:BC58),0) -> 0 | BD56: =IFERROR(SUM(BD57:BD58),0) -> 0 | BE56: =IFERROR(AVERAGE(BE57:BE58),0) -> 0 | BF56: =IFERROR(AVERAGE(BF57:BF58),0) -> 0 | BG56: =IFERROR(SUM(BG57:BG58),0) -> 0 | BH56: =IFERROR(SUM(BH57:BH58),0) -> 0 | BI56: =O56+S56+W56+AA56+AE56+AI56+AM56+AQ56+AU56+AY56+BC56+BG56 -> 0 | BJ56: =BI56*$G$41 -> 0 | BK56: =J56*(H56+I56)/(BI56) -> #DIV/0!
C57: 07.01.01 | D57: ='MH-LAM4 -1225-San Miguel-Antoni'!D22 -> TAREAS ADMINISTRATIVAS - COORDINAR ENTREGA DE EXPEDIENTE CON CLIENTE | E57: =VLOOKUP(D57,'MH-LAM4 -1225-San Miguel-Antoni'!$D$2:$E$84,2,FALSE) -> V 2.0 - PRELIMINAR A ENTREGA A REVISORES | F57: MEDIA | G57: =IF(F57="BAJA",0.8,IF(F57="MEDIA",1,IF(F57="ALTA",1.4,IF(F57="MUY ALTA",2)))) -> 1 | H57: {=G57*INDEX('MH-LAM4 -1225-San Miguel-Antoni'!$B$2:$G$68,MATCH($D$55&D57&$B$5,'MH-LAM4 -1225-San Miguel-Antoni'!$C$2:$C$68&'MH-LAM4 -1225-San Miguel-Antoni'!$D$2:$D$68&'MH-LAM4 -1225-San Miguel-Antoni'!$B$2:$B$68,0),5)/J57} -> 0 | I57: {=G57*INDEX('MH-LAM4 -1225-San Miguel-Antoni'!$B$2:$G$68,MATCH($D$55&D57&$B$5,'MH-LAM4 -1225-San Miguel-Antoni'!$C$2:$C$68&'MH-LAM4 -1225-San Miguel-Antoni'!$D$2:$D$68&'MH-LAM4 -1225-San Miguel-Antoni'!$B$2:$B$68,0),6)/J57} -> 0 | J57: =VLOOKUP($D$56,APUs!$B$2:$I$50,7,FALSE) -> 0.95 | K57: =$G$56*(H57+I57)/J57 -> 0 | P57: =O57*$G$34 -> 0 | T57: =S57*$G$34 -> 0 | X57: =W57*$G$34 -> 0 | AB57: =AA57*$G$34 -> 0 | AF57: =AE57*$G$34 -> 0 | AJ57: =AI57*$G$34 -> 0 | AN57: =AM57*$G$34 -> 0 | AR57: =AQ57*$G$34 -> 0 | AV57: =AU57*$G$34 -> 0 | AZ57: =AY57*$G$34 -> 0 | BD57: =BC57*$G$34 -> 0 | BH57: =BG57*$G$34 -> 0 | BI57: =O57+S57+W57+AA57+AE57+AI57+AM57+AQ57+AU57+AY57+BC57+BG57 -> 0
C58: 07.01.01 | D58: ='MH-LAM4 -1225-San Miguel-Antoni'!D23 -> TAREAS ADMINISTRATIVAS - Entrega de expediente impreso a cliente | E58: =VLOOKUP(D58,'MH-LAM4 -1225-San Miguel-Antoni'!$D$2:$E$84,2,FALSE) -> V 2.1 - ENTREGA TÉCNICA FINAL A REVISORES | F58: MEDIA | G58: =IF(F58="BAJA",0.8,IF(F58="MEDIA",1,IF(F58="ALTA",1.4,IF(F58="MUY ALTA",2)))) -> 1 | H58: {=G58*INDEX('MH-LAM4 -1225-San Miguel-Antoni'!$B$2:$G$68,MATCH($D$55&D58&$B$5,'MH-LAM4 -1225-San Miguel-Antoni'!$C$2:$C$68&'MH-LAM4 -1225-San Miguel-Antoni'!$D$2:$D$68&'MH-LAM4 -1225-San Miguel-Antoni'!$B$2:$B$68,0),5)/J58} -> 0 | I58: {=G58*INDEX('MH-LAM4 -1225-San Miguel-Antoni'!$B$2:$G$68,MATCH($D$55&D58&$B$5,'MH-LAM4 -1225-San Miguel-Antoni'!$C$2:$C$68&'MH-LAM4 -1225-San Miguel-Antoni'!$D$2:$D$68&'MH-LAM4 -1225-San Miguel-Antoni'!$B$2:$B$68,0),6)/J58} -> 0 | J58: =VLOOKUP($D$56,APUs!$B$2:$I$50,7,FALSE) -> 0.95 | K58: =$G$56*(H58+I58)/J58 -> 0 | P58: =O58*$G$34 -> 0 | T58: =S58*$G$34 -> 0 | X58: =W58*$G$34 -> 0 | AB58: =AA58*$G$34 -> 0 | AF58: =AE58*$G$34 -> 0 | AJ58: =AI58*$G$34 -> 0 | AN58: =AM58*$G$34 -> 0 | AR58: =AQ58*$G$34 -> 0 | AV58: =AU58*$G$34 -> 0 | AZ58: =AY58*$G$34 -> 0 | BD58: =BC58*$G$34 -> 0 | BH58: =BG58*$G$34 -> 0 | BI58: =O58+S58+W58+AA58+AE58+AI58+AM58+AQ58+AU58+AY58+BC58+BG58 -> 0

Sheet PRESUPUESTO
A1: ITEM | B1: PARTIDA / CODIGO PROYECTO | C1: COSTO DE INSUMO | D1: PRESENTACIÓN EMPAQUE | E1: UNIDADES DE MEDIDA | F1: COSTO UNITARIO | G1: CANTIDAD A UTILIZAR PROYECTADA | H1: FACTOR DE SEGURIDAD | I1: SUBTOTAL DEL COSTO | J1: CANTIDAD UTILIZADA | K1: SUBTOTAL DEL COSTO REAL | L1: % DE COSTO REAL
D2: PROYECTADA | J2: REAL
B3: ONM6 - 0126 - Chorrillos (Matellini) - Arq. Martin
A4: 01.00.00.00 | B4: COSTOS DIRECTOS | I4: =I5+I13+I32 -> #REF! | K4: =K5+K13+K32 -> 750 | L4: =IFERROR(K4/I4,0) -> 0
A5: 01.01.00.00 | B5: DESARROLLO DE PLANOS | I5: =SUM(I6:I12) -> #REF! | K5: =SUM(K6:K12) -> 0 | L5: =IFERROR(K5/I5,0) -> 0
A6: 01.02.04.01 | B6: ='CONTROL DE HORAS'!D5 -> ARQUITECTURA | C6: ='CONTROL DE HORAS'!K6 -> #REF! | D6: 1 | E6: proyecto | F6: =C6/D6 -> #REF! | G6: 1 | H6: 1.1 | I6: =F6*G6*H6 -> #REF! | K6: ='CONTROL DE HORAS'!BJ6 -> 0 | L6: =IFERROR(K6/I6,0) -> 0
A7: 01.02.04.02 | B7: ='CONTROL DE HORAS'!D18 -> ESTRUCTURAS | C7: ='CONTROL DE HORAS'!K19 -> #REF! | D7: 1 | E7: proyecto | F7: =C7/D7 -> #REF! | G7: 1 | H7: 1.1 | I7: =F7*G7*H7 -> #REF! | K7: ='CONTROL DE HORAS'!BJ19 -> 0 | L7: =IFERROR(K7/I7,0) -> 0
A8: 01.02.04.03 | B8: ='CONTROL DE HORAS'!D27 -> INST. ELECTRICAS | C8: ='CONTROL DE HORAS'!K28 -> 121.46425 | D8: 1 | E8: proyecto | F8: =C8/D8 -> 121.46425 | G8: 1 | H8: 1.1 | I8: =F8*G8*H8 -> 133.61068 | K8: ='CONTROL DE HORAS'!BJ28 -> 0 | L8: =IFERROR(K8/I8,0) -> 0
A9: 01.02.04.04 | B9: ='CONTROL DE HORAS'!D33 -> INST. SANITARIAS | C9: ='CONTROL DE HORAS'!K34 -> #REF! | D9: 1 | E9: proyecto | F9: =C9/D9 -> #REF! | G9: 1 | H9: 1.1 | I9: =F9*G9*H9 -> #REF! | K9: ='CONTROL DE HORAS'!BJ34 -> 0 | L9: =IFERROR(K9/I9,0) -> 0
A10: 01.02.04.05 | B10: ='CONTROL DE HORAS'!D40 -> INST. GAS | C10: ='CONTROL DE HORAS'!K41 -> #REF! | D10: 1 | E10: proyecto | F10: =C10/D10 -> #REF! | G10: 1 | H10: 1.1 | I10: =F10*G10*H10 -> #REF! | K10: ='CONTROL DE HORAS'!BJ41 -> 0 | L10: =IFERROR(K10/I10,0) -> 0
A11: 01.02.04.05 | B11: ='CONTROL DE HORAS'!D50 -> SUELOS | C11: ='CONTROL DE HORAS'!K42 -> #REF! | D11: 1 | E11: proyecto | F11: ='CONTROL DE HORAS'!K51 -> 0 | G11: 1 | H11: 1.1 | I11: =F11*G11*H11 -> 0 | K11: ='CONTROL DE HORAS'!BJ42 -> 0 | L11: =IFERROR(K11/I11,0) -> 0
A12: 01.02.04.05 | B12: ='CONTROL DE HORAS'!D55 -> GESTIÓN Y ADMINISTRACIÓN | C12: ='CONTROL DE HORAS'!K56 -> 0 | D12: 1 | E12: proyecto | F12: =C12/D12 -> 0 | G12: 1 | H12: 1.1 | I12: =F12*G12*H12 -> 0 | K12: ='CONTROL DE HORAS'!BJ42 -> 0 | L12: =IFERROR(K12/I12,0) -> 0
A13: 01.02.00.00 | B13: SUBCONTRATO | I13: =I14+I20+I24 -> 1261 | K13: =K14+K20+K24 -> 750 | L13: =IFERROR(K13/I13,0) -> 0.59476606
A14: 01.02.01.00 | B14: FIRMAS | I14: =SUM(I15:I19) -> 400 | K14: =SUM(K15:K19) -> 0 | L14: =IFERROR(K14/I14,0) -> 0
A15: 01.02.01.01 | B15: FIRMA DE INGENIERO ESTRUCTURAL | C15: 200 | D15: 4 | E15: proyecto | F15: =C15/D15 -> 50 | G15: 0 | H15: 1 | I15: =F15*G15*H15 -> 0 | K15: =F15*J15*H15 -> 0 | L15: =IFERROR(K15/I15,0) -> 0
A16: 01.02.01.02 | B16: FIRMA DE INGENIERO SANITARIO | C16: 200 | D16: 2 | E16: proyecto | F16: =C16/D16 -> 100 | G16: 1 | H16: 1 | I16: =F16*G16*H16 -> 100 | K16: =F16*J16*H16 -> 0 | L16: =IFERROR(K16/I16,0) -> 0
A17: 01.02.01.03 | B17: FIRMA DE INGENIERO ELÉCTRICO | C17: 200 | D17: 4 | E17: proyecto | F17: =C17/D17 -> 50 | G17: 0 | H17: 1 | I17: =F17*G17*H17 -> 0 | K17: =F17*J17*H17 -> 0 | L17: =IFERROR(K17/I17,0) -> 0
A18: 01.02.01.03 | B18: FIRMA DE INGENIERO GAS | C18: 300 | D18: 1 | E18: proyecto | F18: =C18/D18 -> 300 | G18: 1 | H18: 1 | I18: =F18*G18*H18 -> 300 | K18: =F18*J18*H18 -> 0 | L18: =IFERROR(K18/I18,0) -> 0
A19: 01.02.01.04 | B19: FIRMA DE ARQUITECTO | C19: 200 | D19: 4 | E19: proyecto | F19: =C19/D19 -> 50 | G19: 0 | H19: 1 | I19: =F19*G19*H19 -> 0 | K19: =F19*J19*H19 -> 0 | L19: =IFERROR(K19/I19,0) -> 0
A20: 01.02.02.00 | B20: MOVILIDAD | I20: =SUM(I21:I23) -> 191 | K20: =SUM(K21:K23) -> 80 | L20: =IFERROR(K20/I20,0) -> 0.41884817
A21: 01.02.02.01 | B21: MOTORIZADO PARA TRAER LOS PLANOS DE IMPRENTA | C21: 8 | D21: 1 | E21: viaje | F21: =C21/D21 -> 8 | G21: 2 | H21: 1 | I21: =F21*G21*H21 -> 16 | K21: =F21*J21*H21 -> 0 | L21: =IFERROR(K21/I21,0) -> 0
A22: 01.02.02.02 | B22: MOVILIDAD PARA HACER TRAMITES EN FACTIBILIDAD | C22: 15 | D22: 2 | E22: viaje | F22: =C22/D22 -> 7.5 | G22: 2 | H22: 1 | I22: =F22*G22*H22 -> 15 | K22: =F22*J22*H22 -> 0 | L22: =IFERROR(K22/I22,0) -> 0
A23: 01.02.02.03 | B23: MOVILIDAD PARA VISITAR AL PREDIO | C23: 30 | D23: 1 | E23: viajes | F23: 80 | G23: 2 | H23: 1 | I23: =F23*G23*H23 -> 160 | J23: 1 | K23: =F23*J23*H23 -> 80 | L23: =IFERROR(K23/I23,0) -> 0.5
A24: 01.02.03.00 | B24: SUELOS | I24: =SUM(I25:I31) -> 670 | K24: =SUM(K25:K31) -> 670 | L24: =IFERROR(K24/I24,0) -> 1
A25: 01.02.03.01 | B25: CALICATAS 3M | C25: 120 | D25: 1 | E25: calicata | F25: =C25/D25 -> 120 | G25: 1 | H25: 1 | I25: =F25*G25*H25 -> 120 | J25: 1 | K25: =F25*J25*H25 -> 120 | L25: =IFERROR(K25/I25,0) -> 1
A26: 01.02.03.02 | B26: CALICATAS 4M | C26: 350 | D26: 1 | E26: calicata | F26: =C26/D26 -> 350 | G26: 0 | H26: 1 | I26: =F26*G26*H26 -> 0 | K26: =F26*J26*H26 -> 0 | L26: =IFERROR(K26/I26,0) -> 0
A27: 01.02.03.03 | B27: CALICATAS 5M | C27: 550 | D27: 1 | E27: calicata | F27: =C27/D27 -> 550 | G27: 1 | H27: 1 | I27: =F27*G27*H27 -> 550 | J27: 1 | K27: =F27*J27*H27 -> 550 | L27: =IFERROR(K27/I27,0) -> 1
A28: 01.02.03.04 | B28: CALICATAS 6M | C28: 650 | D28: 1 | E28: calicata | F28: =C28/D28 -> 650 | G28: 0 | H28: 1 | I28: =F28*G28*H28 -> 0 | K28: =F28*J28*H28 -> 0 | L28: =IFERROR(K28/I28,0) -> 0
A29: 01.02.03.05 | B29: CALICATAS 8M | C29: 780 | D29: 1 | E29: calicata | F29: =C29/D29 -> 780 | G29: 0 | H29: 1 | I29: =F29*G29*H29 -> 0 | K29: =F29*J29*H29 -> 0 | L29: =IFERROR(K29/I29,0) -> 0
A30: 01.02.03.06 | B30: ROTURA DE PISO | C30: 60 | D30: 1 | E30: calicata | F30: =C30/D30 -> 60 | G30: 0 | H30: 1 | I30: =F30*G30*H30 -> 0 | K30: =F30*J30*H30 -> 0 | L30: =IFERROR(K30/I30,0) -> 0
A31: 01.02.03.07 | B31: ALMUERZO | C31: 20 | D31: 1 | E31: calicata | F31: =C31/D31 -> 20 | G31: 0 | H31: 1 | I31: =F31*G31*H31 -> 0 | K31: =F31*J31*H31 -> 0 | L31: =IFERROR(K31/I31,0) -> 0
A32: 01.03.00.00 | B32: PAPELERÍA Y UTILES DE OFICINA | I32: =SUM(I33:I43) -> 631.15932 | K32: =SUM(K33:K43) -> 0 | L32: =IFERROR(K32/I32,0) -> 0
A33: 01.03.01.00 | B33: ARCHIVADOR x unidad | C33: =11/1.18 -> 9.3220339 | D33: 1 | E33: unid. | F33: =C33/D33 -> 9.3220339 | G33: 12 | H33: 1.2 | I33: =F33*G33*H33 -> 134.23729 | K33: =F33*J33*H33 -> 0 | L33: =IFERROR(K33/I33,0) -> 0
A34: 01.03.02.00 | B34: LAPICERO AZUL FABER CASTELLE | C34: =10/1.18 -> 8.4745763 | D34: 50 | E34: unid. | F34: =C34/D34 -> 0.16949153 | G34: 2 | H34: 1.2 | I34: =F34*G34*H34 -> 0.40677966 | K34: =F34*J34*H34 -> 0 | L34: =IFERROR(K34/I34,0) -> 0
A35: 01.03.03.00 | B35: FOLDER MANILA | C35: =10/1.18 -> 8.4745763 | D35: 25 | E35: unid. | F35: =C35/D35 -> 0.33898305 | G35: 10 | H35: 1.2 | I35: =F35*G35*H35 -> 4.0677966 | K35: =F35*J35*H35 -> 0 | L35: =IFERROR(K35/I35,0) -> 0
A36: 01.03.04.00 | B36: FASTER | C36: =5/1.18 -> 4.2372881 | D36: 50 | E36: unid. | F36: =C36/D36 -> 0.084745763 | G36: 10 | H36: 1.2 | I36: =F36*G36*H36 -> 1.0169492 | K36: =F36*J36*H36 -> 0 | L36: =IFERROR(K36/I36,0) -> 0
A37: 01.03.05.00 | B37: SOBRE MANILA | C37: =10/1.18 -> 8.4745763 | D37: 50 | E37: unid. | F37: =C37/D37 -> 0.16949153 | G37: 1 | H37: 1.2 | I37: =F37*G37*H37 -> 0.20338983 | K37: =F37*J37*H37 -> 0 | L37: =IFERROR(K37/I37,0) -> 0
A38: 01.03.06.00 | B38: GRAPA | C38: =5/1.18 -> 4.2372881 | D38: 5000 | E38: unid. | F38: =C38/D38 -> 0.00084745763 | G38: 40 | H38: 1.2 | I38: =F38*G38*H38 -> 0.040677966 | K38: =F38*J38*H38 -> 0 | L38: =IFERROR(K38/I38,0) -> 0
A39: 01.03.07.00 | B39: IMPRESIÓN EN A4 DE OFICINA | C39: ='IMPRESIÓN A4 EN OFICINA'!G6 -> 0.3291095 | D39: 1 | E39: hoja | F39: =C39/D39 -> 0.3291095 | G39: 0 | H39: 1.2 | I39: =F39*G39*H39 -> 0 | K39: =F39*J39*H39 -> 0 | L39: =IFERROR(K39/I39,0) -> 0
A40: 01.03.08.00 | B40: PLOTEO DE HOJA A1 | C40: =3/1.18 -> 2.5423729 | D40: 1 | E40: plano | F40: =C40/D40 -> 2.5423729 | G40: 100 | H40: 1.2 | I40: =F40*G40*H40 -> 305.08475 | K40: =F40*J40*H40 -> 0 | L40: =IFERROR(K40/I40,0) -> 0
A41: 01.03.09.00 | B41: PLOTEO DE HOJA A0 | C41: =6/1.18 -> 5.0847458 | D41: 1 | E41: plano | F41: =C41/D41 -> 5.0847458 | G41: 20 | H41: 1.2 | I41: =F41*G41*H41 -> 122.0339 | K41: =F41*J41*H41 -> 0 | L41: =IFERROR(K41/I41,0) -> 0
A42: 01.03.10.00 | B42: PLOTEO DE HOJA A4 | C42: =0.2/1.18 -> 0.16949153 | D42: 1 | E42: plano | F42: =C42/D42 -> 0.16949153 | G42: 300 | H42: 1.2 | I42: =F42*G42*H42 -> 61.016949 | K42: =F42*J42*H42 -> 0 | L42: =IFERROR(K42/I42,0) -> 0
A43: 01.03.11.00 | B43: PLOTEO DE HOJA A3 | C43: =1/1.18 -> 0.84745763 | D43: 1 | E43: plano | F43: =C43/D43 -> 0.84745763 | G43: 3 | H43: 1.2 | I43: =F43*G43*H43 -> 3.0508475 | K43: =I43*J43 -> 0 | L43: =IFERROR(K43/I43,0) -> 0
A44: 02.00.00.00 | B44: COSTOS INDIRECTOS | I44: =I45 -> 2871 | K44: =K45 -> 0 | L44: =IFERROR(K44/I44,0) -> 0
A45: 02.01.00.00 | B45: GASTOS ADMINISTRATIVOS | I45: =SUM(I46:I53) -> 2871 | K45: =SUM(K46:K53) -> 0 | L45: =IFERROR(K45/I45,0) -> 0
A46: 02.01.01.00 | B46: LOCAL | C46: 1200 | D46: 1 | E46: local | F46: 2200 | G46: 0.05 | H46: 4 | I46: =F46*G46*H46 -> 440 | K46: =F46*J46*H46 -> 0 | L46: =IFERROR(K46/I46,0) -> 0
A47: 02.01.02.00 | B47: INTERNET | C47: 80 | D47: 1 | E47: mensual | F47: =C47/D47 -> 80 | G47: 0.05 | H47: 4 | I47: =F47*G47*H47 -> 16 | K47: =F47*J47*H47 -> 0 | L47: =IFERROR(K47/I47,0) -> 0
A48: 02.01.03.00 | B48: CONTABILIDAD MENSUAL | C48: 450 | D48: 1 | E48: mensual | F48: =C48/D48 -> 450 | G48: 0.05 | H48: 4 | I48: =F48*G48*H48 -> 90 | K48: =F48*J48*H48 -> 0 | L48: =IFERROR(K48/I48,0) -> 0
A49: 02.01.04.00 | B49: CONTABILIDAD ANUAL | C49: 125 | D49: 1 | E49: anual | F49: =C49/D49 -> 125 | G49: 0.05 | H49: 4 | I49: =F49*G49*H49 -> 25 | K49: =F49*J49*H49 -> 0 | L49: =IFERROR(K49/I49,0) -> 0
A50: 02.01.05.00 | B50: GERENTE GENERAL | C50: 3500 | D50: 1 | F50: =C50/D50 -> 3500 | G50: 0.05 | H50: 4 | I50: =F50*G50*H50 -> 700 | K50: =F50*J50*H50 -> 0 | L50: =IFERROR(K50/I50,0) -> 0
A51: 02.01.06.00 | B51: ADMINISTRADOR GENERAL | C51: 4000 | D51: 1 | F51: =C51/D51 -> 4000 | G51: 0.05 | H51: 4 | I51: =F51*G51*H51 -> 800 | K51: =F51*J51*H51 -> 0 | L51: =IFERROR(K51/I51,0) -> 0
A52: 02.01.07.00 | B52: AUXILIAR ADMINISTRATIVO | C52: 1500 | D52: 1 | F52: =C52/D52 -> 1500 | G52: 0.05 | H52: 4 | I52: =F52*G52*H52 -> 300 | K52: =F52*J52*H52 -> 0 | L52: =IFERROR(K52/I52,0) -> 0
A53: 02.01.08.00 | B53: GESTORA DE PROYECTOS + INGENIERA | C53: 2500 | D53: 1 | F53: =C53/D53 -> 2500 | G53: 0.05 | H53: 4 | I53: =F53*G53*H53 -> 500 | K53: =F53*J53*H53 -> 0 | L53: =IFERROR(K53/I53,0) -> 0
B54: COSTO DE VENTA FINAL | I54: =(I4+I44) -> #REF! | K54: =(K4+K44) -> 750 | L54: =IFERROR(K54/I54,0) -> 0
B55: UTILIDAD DE VENTA | H55: 0.1165 | I55: =I54*H55 -> #REF! | J55: 0.8 | K55: 2686.3662
B56: PRECIO DE VENTA | I56: =I54+I55 -> #REF! | K56: =K54+K55 -> 3436.3662 | L56: =IFERROR(K56/I56,0) -> 0

Sheet GRAFICAS
A1: TODO EL PROYECTO | G1: ESTRUCTURAS | N1: =CONCATENATE("CURVA S DE ",A1) -> CURVA S DE TODO EL PROYECTO | Y1: =CONCATENATE("CURVA S DE ",G1) -> CURVA S DE ESTRUCTURAS
A3: CALENDARIO | B3: PARCIALES | G3: CALENDARIO | H3: PARCIALES
B4: PROGRAMADO | D4: EJECUTADO | H4: PROGRAMADO | J4: EJECUTADO
B5: % PROGR. | C5: % ACUMULADO | D5: % EJEC. | E5: % ACUMULADO | H5: % PROGR. | I5: % ACUMULADO | J5: % EJEC. | K5: % ACUMULADO
A6: INICIO | B6: 0 | C6: =B6 -> 0 | D6: 0 | E6: =D6 -> 0 | G6: INICIO | H6: 0 | I6: =H6 -> 0 | J6: 0 | K6: =J6 -> 0
A7: MES 1 (PARTE 1) | B7: ='CONTROL DE HORAS'!M4 -> 0 | C7: =B7+C6 -> 0 | D7: ='CONTROL DE HORAS'!N4 -> 0 | E7: =D7+E6 -> 0 | G7: MES 1 (PARTE 1) | H7: =VLOOKUP($G$1,'CONTROL DE HORAS'!$D$5:$BH$116,8,FALSE) -> 0 | I7: =H7+I6 -> 0 | J7: =VLOOKUP($G$1,'CONTROL DE HORAS'!$D$5:$BH$116,9,FALSE) -> 0 | K7: =J7+K6 -> 0
A8: MES 1 (PARTE 2) | B8: ='CONTROL DE HORAS'!Q4 -> 0 | C8: =B8+C7 -> 0 | D8: ='CONTROL DE HORAS'!R4 -> 0 | E8: =D8+E7 -> 0 | G8: MES 1 (PARTE 2) | H8: =VLOOKUP($G$1,'CONTROL DE HORAS'!$D$5:$BH$116,12,FALSE) -> 0 | I8: =H8+I7 -> 0 | J8: =VLOOKUP($G$1,'CONTROL DE HORAS'!$D$5:$BH$116,13,FALSE) -> 0 | K8: =J8+K7 -> 0
A9: MES 2 (PARTE 1) | B9: ='CONTROL DE HORAS'!U4 -> 0 | C9: =B9+C8 -> 0 | D9: ='CONTROL DE HORAS'!V4 -> 0 | E9: =D9+E8 -> 0 | G9: MES 2 (PARTE 1) | H9: =VLOOKUP($G$1,'CONTROL DE HORAS'!$D$5:$BH$116,16,FALSE) -> 0 | I9: =H9+I8 -> 0 | J9: =VLOOKUP($G$1,'CONTROL DE HORAS'!$D$5:$BH$116,17,FALSE) -> 0 | K9: =J9+K8 -> 0
A10: MES 2 (PARTE 2) | B10: ='CONTROL DE HORAS'!Y4 -> 0 | C10: =B10+C9 -> 0 | D10: ='CONTROL DE HORAS'!Z4 -> 0 | E10: =D10+E9 -> 0 | G10: MES 2 (PARTE 2) | H10: =VLOOKUP($G$1,'CONTROL DE HORAS'!$D$5:$BH$116,20,FALSE) -> 0 | I10: =H10+I9 -> 0 | J10: =VLOOKUP($G$1,'CONTROL DE HORAS'!$D$5:$BH$116,21,FALSE) -> 0 | K10: =J10+K9 -> 0
A11: MES 3 (PARTE 1) | B11: ='CONTROL DE HORAS'!AC4 -> 0 | C11: =B11+C10 -> 0 | D11: ='CONTROL DE HORAS'!AD4 -> 0 | E11: =D11+E10 -> 0 | G11: MES 3 (PARTE 1) | H11: =VLOOKUP($G$1,'CONTROL DE HORAS'!$D$5:$BH$116,24,FALSE) -> 0 | I11: =H11+I10 -> 0 | J11: =VLOOKUP($G$1,'CONTROL DE HORAS'!$D$5:$BH$116,25,FALSE) -> 0 | K11: =J11+K10 -> 0
A12: MES 3 (PARTE 2) | B12: ='CONTROL DE HORAS'!AG4 -> 0 | C12: =B12+C11 -> 0 | D12: ='CONTROL DE HORAS'!AH4 -> 0 | E12: =D12+E11 -> 0 | G12: MES 3 (PARTE 2) | H12: =VLOOKUP($G$1,'CONTROL DE HORAS'!$D$5:$BH$116,28,FALSE) -> 0 | I12: =H12+I11 -> 0 | J12: =VLOOKUP($G$1,'CONTROL DE HORAS'!$D$5:$BH$116,29,FALSE) -> 0 | K12: =J12+K11 -> 0
A13: MES 4 (PARTE 1) | B13: ='CONTROL DE HORAS'!AK4 -> 0 | C13: =B13+C12 -> 0 | D13: ='CONTROL DE HORAS'!AL4 -> 0 | E13: =D13+E12 -> 0 | G13: MES 4 (PARTE 1) | H13: =VLOOKUP($G$1,'CONTROL DE HORAS'!$D$5:$BH$116,32,FALSE) -> 0 | I13: =H13+I12 -> 0 | J13: =VLOOKUP($G$1,'CONTROL DE HORAS'!$D$5:$BH$116,33,FALSE) -> 0 | K13: =J13+K12 -> 0
A14: MES 4 (PARTE 2) | B14: ='CONTROL DE HORAS'!AO4 -> 0 | C14: =B14+C13 -> 0 | D14: ='CONTROL DE HORAS'!AP4 -> 0 | E14: =D14+E13 -> 0 | G14: MES 4 (PARTE 2) | H14: =VLOOKUP($G$1,'CONTROL DE HORAS'!$D$5:$BH$116,36,FALSE) -> 0 | I14: =H14+I13 -> 0 | J14: =VLOOKUP($G$1,'CONTROL DE HORAS'!$D$5:$BH$116,37,FALSE) -> 0 | K14: =J14+K13 -> 0
A15: MES 5 (PARTE 1) | B15: ='CONTROL DE HORAS'!AS4 -> 0 | C15: =B15+C14 -> 0 | D15: ='CONTROL DE HORAS'!AT4 -> 0 | E15: =D15+E14 -> 0 | G15: MES 5 (PARTE 1) | H15: =VLOOKUP($G$1,'CONTROL DE HORAS'!$D$5:$BH$116,40,FALSE) -> 0 | I15: =H15+I14 -> 0 | J15: =VLOOKUP($G$1,'CONTROL DE HORAS'!$D$5:$BH$116,41,FALSE) -> 0 | K15: =J15+K14 -> 0
A16: MES 5 (PARTE 2) | B16: ='CONTROL DE HORAS'!AW4 -> 0 | C16: =B16+C15 -> 0 | D16: ='CONTROL DE HORAS'!AX4 -> 0 | E16: =D16+E15 -> 0 | G16: MES 5 (PARTE 2) | H16: =VLOOKUP($G$1,'CONTROL DE HORAS'!$D$5:$BH$116,44,FALSE) -> 0 | I16: =H16+I15 -> 0 | J16: =VLOOKUP($G$1,'CONTROL DE HORAS'!$D$5:$BH$116,45,FALSE) -> 0 | K16: =J16+K15 -> 0
A17: MES 6 (PARTE 1) | B17: ='CONTROL DE HORAS'!BA4 -> 0 | C17: =B17+C16 -> 0 | D17: ='CONTROL DE HORAS'!BB4 -> 0 | E17: =D17+E16 -> 0 | G17: MES 5 (PARTE 2) | H17: =VLOOKUP($G$1,'CONTROL DE HORAS'!$D$5:$BH$116,48,FALSE) -> 0 | I17: =H17+I16 -> 0 | J17: =VLOOKUP($G$1,'CONTROL DE HORAS'!$D$5:$BH$116,49,FALSE) -> 0 | K17: =J17+K16 -> 0
A18: MES 6 (PARTE 2) | B18: ='CONTROL DE HORAS'!BE4 -> 0 | C18: =B18+C17 -> 0 | D18: ='CONTROL DE HORAS'!BF4 -> 0 | E18: =D18+E17 -> 0 | G18: MES 5 (PARTE 2) | H18: =VLOOKUP($G$1,'CONTROL DE HORAS'!$D$5:$BH$116,52,FALSE) -> 0 | I18: =H18+I17 -> 0 | J18: =VLOOKUP($G$1,'CONTROL DE HORAS'!$D$5:$BH$116,53,FALSE) -> 0 | K18: =J18+K17 -> 0
A22: ARQUITECTURA | G22: INST. SANITARIAS | N22: =CONCATENATE("CURVA S DE ",A22) -> CURVA S DE ARQUITECTURA | Y22: =CONCATENATE("CURVA S DE ",G22) -> CURVA S DE INST. SANITARIAS
A23: CALENDARIO | B23: PARCIALES | G23: CALENDARIO | H23: PARCIALES
B24: PROGRAMADO | D24: EJECUTADO | H24: PROGRAMADO | J24: EJECUTADO
B25: % PROGR. | C25: % ACUMULADO | D25: % EJEC. | E25: % ACUMULADO | H25: % PROGR. | I25: % ACUMULADO | J25: % EJEC. | K25: % ACUMULADO
A26: INICIO | B26: 0 | C26: =B26 -> 0 | D26: 0 | E26: =D26 -> 0 | G26: INICIO | H26: 0 | I26: =H26 -> 0 | J26: 0 | K26: =J26 -> 0
A27: MES 1 (PARTE 1) | B27: =VLOOKUP($A$22,'CONTROL DE HORAS'!$D$5:$BH$116,8,FALSE) -> 0 | C27: =B27+C26 -> 0 | D27: =VLOOKUP($A$22,'CONTROL DE HORAS'!$D$5:$BH$116,9,FALSE) -> 0 | E27: =D27+E26 -> 0 | G27: MES 1 (PARTE 1) | H27: =VLOOKUP($G$22,'CONTROL DE HORAS'!$D$5:$BH$116,8,FALSE) -> 0 | I27: =H27+I26 -> 0 | J27: =VLOOKUP($G$22,'CONTROL DE HORAS'!$D$5:$BH$116,9,FALSE) -> 0 | K27: =J27+K26 -> 0
A28: MES 1 (PARTE 2) | B28: =VLOOKUP($A$22,'CONTROL DE HORAS'!$D$5:$BH$116,12,FALSE) -> 0 | C28: =B28+C27 -> 0 | D28: =VLOOKUP($A$22,'CONTROL DE HORAS'!$D$5:$BH$116,13,FALSE) -> 0 | E28: =D28+E27 -> 0 | G28: MES 1 (PARTE 2) | H28: =VLOOKUP($G$22,'CONTROL DE HORAS'!$D$5:$BH$116,12,FALSE) -> 0 | I28: =H28+I27 -> 0 | J28: =VLOOKUP($G$22,'CONTROL DE HORAS'!$D$5:$BH$116,13,FALSE) -> 0 | K28: =J28+K27 -> 0
A29: MES 2 (PARTE 1) | B29: =VLOOKUP($A$22,'CONTROL DE HORAS'!$D$5:$BH$116,16,FALSE) -> 0 | C29: =B29+C28 -> 0 | D29: =VLOOKUP($A$22,'CONTROL DE HORAS'!$D$5:$BH$116,17,FALSE) -> 0 | E29: =D29+E28 -> 0 | G29: MES 2 (PARTE 1) | H29: =VLOOKUP($G$22,'CONTROL DE HORAS'!$D$5:$BH$116,16,FALSE) -> 0 | I29: =H29+I28 -> 0 | J29: =VLOOKUP($G$22,'CONTROL DE HORAS'!$D$5:$BH$116,17,FALSE) -> 0 | K29: =J29+K28 -> 0
A30: MES 2 (PARTE 2) | B30: =VLOOKUP($A$22,'CONTROL DE HORAS'!$D$5:$BH$116,20,FALSE) -> 0 | C30: =B30+C29 -> 0 | D30: =VLOOKUP($A$22,'CONTROL DE HORAS'!$D$5:$BH$116,21,FALSE) -> 0 | E30: =D30+E29 -> 0 | G30: MES 2 (PARTE 2) | H30: =VLOOKUP($G$22,'CONTROL DE HORAS'!$D$5:$BH$116,20,FALSE) -> 0 | I30: =H30+I29 -> 0 | J30: =VLOOKUP($G$22,'CONTROL DE HORAS'!$D$5:$BH$116,21,FALSE) -> 0 | K30: =J30+K29 -> 0
A31: MES 3 (PARTE 1) | B31: =VLOOKUP($A$22,'CONTROL DE HORAS'!$D$5:$BH$116,24,FALSE) -> 0 | C31: =B31+C30 -> 0 | D31: =VLOOKUP($A$22,'CONTROL DE HORAS'!$D$5:$BH$116,25,FALSE) -> 0 | E31: =D31+E30 -> 0 | G31: MES 3 (PARTE 1) | H31: =VLOOKUP($G$22,'CONTROL DE HORAS'!$D$5:$BH$116,24,FALSE) -> 0 | I31: =H31+I30 -> 0 | J31: =VLOOKUP($G$22,'CONTROL DE HORAS'!$D$5:$BH$116,25,FALSE) -> 0 | K31: =J31+K30 -> 0
A32: MES 3 (PARTE 2) | B32: =VLOOKUP($A$22,'CONTROL DE HORAS'!$D$5:$BH$116,28,FALSE) -> 0 | C32: =B32+C31 -> 0 | D32: =VLOOKUP($A$22,'CONTROL DE HORAS'!$D$5:$BH$116,29,FALSE) -> 0 | E32: =D32+E31 -> 0 | G32: MES 3 (PARTE 2) | H32: =VLOOKUP($G$22,'CONTROL DE HORAS'!$D$5:$BH$116,28,FALSE) -> 0 | I32: =H32+I31 -> 0 | J32: =VLOOKUP($G$22,'CONTROL DE HORAS'!$D$5:$BH$116,29,FALSE) -> 0 | K32: =J32+K31 -> 0
A33: MES 4 (PARTE 1) | B33: =VLOOKUP($A$22,'CONTROL DE HORAS'!$D$5:$BH$116,32,FALSE) -> 0 | C33: =B33+C32 -> 0 | D33: =VLOOKUP($A$22,'CONTROL DE HORAS'!$D$5:$BH$116,33,FALSE) -> 0 | E33: =D33+E32 -> 0 | G33: MES 4 (PARTE 1) | H33: =VLOOKUP($G$22,'CONTROL DE HORAS'!$D$5:$BH$116,32,FALSE) -> 0 | I33: =H33+I32 -> 0 | J33: =VLOOKUP($G$22,'CONTROL DE HORAS'!$D$5:$BH$116,33,FALSE) -> 0 | K33: =J33+K32 -> 0
A34: MES 4 (PARTE 2) | B34: =VLOOKUP($A$22,'CONTROL DE HORAS'!$D$5:$BH$116,36,FALSE) -> 0 | C34: =B34+C33 -> 0 | D34: =VLOOKUP($A$22,'CONTROL DE HORAS'!$D$5:$BH$116,37,FALSE) -> 0 | E34: =D34+E33 -> 0 | G34: MES 4 (PARTE 2) | H34: =VLOOKUP($G$22,'CONTROL DE HORAS'!$D$5:$BH$116,36,FALSE) -> 0 | I34: =H34+I33 -> 0 | J34: =VLOOKUP($G$22,'CONTROL DE HORAS'!$D$5:$BH$116,37,FALSE) -> 0 | K34: =J34+K33 -> 0
A35: MES 5 (PARTE 1) | B35: =VLOOKUP($A$22,'CONTROL DE HORAS'!$D$5:$BH$116,40,FALSE) -> 0 | C35: =B35+C34 -> 0 | D35: =VLOOKUP($A$22,'CONTROL DE HORAS'!$D$5:$BH$116,41,FALSE) -> 0 | E35: =D35+E34 -> 0 | G35: MES 5 (PARTE 1) | H35: =VLOOKUP($G$22,'CONTROL DE HORAS'!$D$5:$BH$116,40,FALSE) -> 0 | I35: =H35+I34 -> 0 | J35: =VLOOKUP($G$22,'CONTROL DE HORAS'!$D$5:$BH$116,41,FALSE) -> 0 | K35: =J35+K34 -> 0
A36: MES 5 (PARTE 2) | B36: =VLOOKUP($A$22,'CONTROL DE HORAS'!$D$5:$BH$116,44,FALSE) -> 0 | C36: =B36+C35 -> 0 | D36: =VLOOKUP($A$22,'CONTROL DE HORAS'!$D$5:$BH$116,45,FALSE) -> 0 | E36: =D36+E35 -> 0 | G36: MES 5 (PARTE 2) | H36: =VLOOKUP($G$22,'CONTROL DE HORAS'!$D$5:$BH$116,44,FALSE) -> 0 | I36: =H36+I35 -> 0 | J36: =VLOOKUP($G$22,'CONTROL DE HORAS'!$D$5:$BH$116,45,FALSE) -> 0 | K36: =J36+K35 -> 0
A37: MES 5 (PARTE 2) | B37: =VLOOKUP($A$22,'CONTROL DE HORAS'!$D$5:$BH$116,48,FALSE) -> 0 | C37: =B37+C36 -> 0 | D37: =VLOOKUP($A$22,'CONTROL DE HORAS'!$D$5:$BH$116,49,FALSE) -> 0 | E37: =D37+E36 -> 0 | G37: MES 5 (PARTE 2) | H37: =VLOOKUP($G$22,'CONTROL DE HORAS'!$D$5:$BH$116,48,FALSE) -> 0 | I37: =H37+I36 -> 0 | J37: =VLOOKUP($G$22,'CONTROL DE HORAS'!$D$5:$BH$116,49,FALSE) -> 0 | K37: =J37+K36 -> 0
A38: MES 5 (PARTE 2) | B38: =VLOOKUP($A$22,'CONTROL DE HORAS'!$D$5:$BH$116,52,FALSE) -> 0 | C38: =B38+C37 -> 0 | D38: =VLOOKUP($A$22,'CONTROL DE HORAS'!$D$5:$BH$116,53,FALSE) -> 0 | E38: =D38+E37 -> 0 | G38: MES 5 (PARTE 2) | H38: =VLOOKUP($G$22,'CONTROL DE HORAS'!$D$5:$BH$116,52,FALSE) -> 0 | I38: =H38+I37 -> 0 | J38: =VLOOKUP($G$22,'CONTROL DE HORAS'!$D$5:$BH$116,53,FALSE) -> 0 | K38: =J38+K37 -> 0
A43: INST. ELECTRICAS | G43: SUELOS | N43: =CONCATENATE("CURVA S DE ",A43) -> CURVA S DE INST. ELECTRICAS | Y43: =CONCATENATE("CURVA S DE ",G43) -> CURVA S DE SUELOS
A44: CALENDARIO | B44: PARCIALES | G44: CALENDARIO | H44: PARCIALES
B45: PROGRAMADO | D45: EJECUTADO | H45: PROGRAMADO | J45: EJECUTADO
B46: % PROGR. | C46: % ACUMULADO | D46: % EJEC. | E46: % ACUMULADO | H46: % PROGR. | I46: % ACUMULADO | J46: % EJEC. | K46: % ACUMULADO
A47: INICIO | B47: 0 | C47: =B47 -> 0 | D47: 0 | E47: =D47 -> 0 | G47: INICIO | H47: 0 | I47: =H47 -> 0 | J47: 0 | K47: =J47 -> 0
A48: MES 1 (PARTE 1) | B48: =VLOOKUP($A$43,'CONTROL DE HORAS'!$D$5:$BH$116,8,FALSE) -> 0 | C48: =B48+C47 -> 0 | D48: =VLOOKUP($A$43,'CONTROL DE HORAS'!$D$5:$BH$116,9,FALSE) -> 0 | E48: =D48+E47 -> 0 | G48: MES 1 (PARTE 1) | H48: =VLOOKUP($G$43,'CONTROL DE HORAS'!$D$5:$BH$116,8,FALSE) -> 0 | I48: =H48+I47 -> 0 | J48: =VLOOKUP($G$43,'CONTROL DE HORAS'!$D$5:$BH$116,9,FALSE) -> 0 | K48: =J48+K47 -> 0
A49: MES 1 (PARTE 2) | B49: =VLOOKUP($A$43,'CONTROL DE HORAS'!$D$5:$BH$116,12,FALSE) -> 0 | C49: =B49+C48 -> 0 | D49: =VLOOKUP($A$43,'CONTROL DE HORAS'!$D$5:$BH$116,13,FALSE) -> 0 | E49: =D49+E48 -> 0 | G49: MES 1 (PARTE 2) | H49: =VLOOKUP($G$43,'CONTROL DE HORAS'!$D$5:$BH$116,12,FALSE) -> 0 | I49: =H49+I48 -> 0 | J49: =VLOOKUP($G$43,'CONTROL DE HORAS'!$D$5:$BH$116,13,FALSE) -> 0 | K49: =J49+K48 -> 0
A50: MES 2 (PARTE 1) | B50: =VLOOKUP($A$43,'CONTROL DE HORAS'!$D$5:$BH$116,16,FALSE) -> 0 | C50: =B50+C49 -> 0 | D50: =VLOOKUP($A$43,'CONTROL DE HORAS'!$D$5:$BH$116,17,FALSE) -> 0 | E50: =D50+E49 -> 0 | G50: MES 2 (PARTE 1) | H50: =VLOOKUP($G$43,'CONTROL DE HORAS'!$D$5:$BH$116,16,FALSE) -> 0 | I50: =H50+I49 -> 0 | J50: =VLOOKUP($G$43,'CONTROL DE HORAS'!$D$5:$BH$116,17,FALSE) -> 0 | K50: =J50+K49 -> 0
A51: MES 2 (PARTE 2) | B51: =VLOOKUP($A$43,'CONTROL DE HORAS'!$D$5:$BH$116,20,FALSE) -> 0 | C51: =B51+C50 -> 0 | D51: =VLOOKUP($A$43,'CONTROL DE HORAS'!$D$5:$BH$116,21,FALSE) -> 0 | E51: =D51+E50 -> 0 | G51: MES 2 (PARTE 2) | H51: =VLOOKUP($G$43,'CONTROL DE HORAS'!$D$5:$BH$116,20,FALSE) -> 0 | I51: =H51+I50 -> 0 | J51: =VLOOKUP($G$43,'CONTROL DE HORAS'!$D$5:$BH$116,21,FALSE) -> 0 | K51: =J51+K50 -> 0
A52: MES 3 (PARTE 1) | B52: =VLOOKUP($A$43,'CONTROL DE HORAS'!$D$5:$BH$116,24,FALSE) -> 0 | C52: =B52+C51 -> 0 | D52: =VLOOKUP($A$43,'CONTROL DE HORAS'!$D$5:$BH$116,25,FALSE) -> 0 | E52: =D52+E51 -> 0 | G52: MES 3 (PARTE 1) | H52: =VLOOKUP($G$43,'CONTROL DE HORAS'!$D$5:$BH$116,24,FALSE) -> 0 | I52: =H52+I51 -> 0 | J52: =VLOOKUP($G$43,'CONTROL DE HORAS'!$D$5:$BH$116,25,FALSE) -> 0 | K52: =J52+K51 -> 0
A53: MES 3 (PARTE 2) | B53: =VLOOKUP($A$43,'CONTROL DE HORAS'!$D$5:$BH$116,28,FALSE) -> 0 | C53: =B53+C52 -> 0 | D53: =VLOOKUP($A$43,'CONTROL DE HORAS'!$D$5:$BH$116,29,FALSE) -> 0 | E53: =D53+E52 -> 0 | G53: MES 3 (PARTE 2) | H53: =VLOOKUP($G$43,'CONTROL DE HORAS'!$D$5:$BH$116,28,FALSE) -> 0 | I53: =H53+I52 -> 0 | J53: =VLOOKUP($G$43,'CONTROL DE HORAS'!$D$5:$BH$116,29,FALSE) -> 0 | K53: =J53+K52 -> 0
A54: MES 4 (PARTE 1) | B54: =VLOOKUP($A$43,'CONTROL DE HORAS'!$D$5:$BH$116,32,FALSE) -> 0 | C54: =B54+C53 -> 0 | D54: =VLOOKUP($A$43,'CONTROL DE HORAS'!$D$5:$BH$116,33,FALSE) -> 0 | E54: =D54+E53 -> 0 | G54: MES 4 (PARTE 1) | H54: =VLOOKUP($G$43,'CONTROL DE HORAS'!$D$5:$BH$116,32,FALSE) -> 0 | I54: =H54+I53 -> 0 | J54: =VLOOKUP($G$43,'CONTROL DE HORAS'!$D$5:$BH$116,33,FALSE) -> 0 | K54: =J54+K53 -> 0
A55: MES 4 (PARTE 2) | B55: =VLOOKUP($A$43,'CONTROL DE HORAS'!$D$5:$BH$116,36,FALSE) -> 0 | C55: =B55+C54 -> 0 | D55: =VLOOKUP($A$43,'CONTROL DE HORAS'!$D$5:$BH$116,37,FALSE) -> 0 | E55: =D55+E54 -> 0 | G55: MES 4 (PARTE 2) | H55: =VLOOKUP($G$43,'CONTROL DE HORAS'!$D$5:$BH$116,36,FALSE) -> 0 | I55: =H55+I54 -> 0 | J55: =VLOOKUP($G$43,'CONTROL DE HORAS'!$D$5:$BH$116,37,FALSE) -> 0 | K55: =J55+K54 -> 0
A56: MES 5 (PARTE 1) | B56: =VLOOKUP($A$43,'CONTROL DE HORAS'!$D$5:$BH$116,40,FALSE) -> 0 | C56: =B56+C55 -> 0 | D56: =VLOOKUP($A$43,'CONTROL DE HORAS'!$D$5:$BH$116,41,FALSE) -> 0 | E56: =D56+E55 -> 0 | G56: MES 5 (PARTE 1) | H56: =VLOOKUP($G$43,'CONTROL DE HORAS'!$D$5:$BH$116,40,FALSE) -> 0 | I56: =H56+I55 -> 0 | J56: =VLOOKUP($G$43,'CONTROL DE HORAS'!$D$5:$BH$116,41,FALSE) -> 0 | K56: =J56+K55 -> 0
A57: MES 5 (PARTE 2) | B57: =VLOOKUP($A$43,'CONTROL DE HORAS'!$D$5:$BH$116,44,FALSE) -> 0 | C57: =B57+C56 -> 0 | D57: =VLOOKUP($A$43,'CONTROL DE HORAS'!$D$5:$BH$116,45,FALSE) -> 0 | E57: =D57+E56 -> 0 | G57: MES 5 (PARTE 2) | H57: =VLOOKUP($G$43,'CONTROL DE HORAS'!$D$5:$BH$116,44,FALSE) -> 0 | I57: =H57+I56 -> 0 | J57: =VLOOKUP($G$43,'CONTROL DE HORAS'!$D$5:$BH$116,45,FALSE) -> 0 | K57: =J57+K56 -> 0
A58: MES 5 (PARTE 2) | B58: =VLOOKUP($A$43,'CONTROL DE HORAS'!$D$5:$BH$116,48,FALSE) -> 0 | C58: =B58+C57 -> 0 | D58: =VLOOKUP($A$43,'CONTROL DE HORAS'!$D$5:$BH$116,49,FALSE) -> 0 | E58: =D58+E57 -> 0 | G58: MES 5 (PARTE 2) | H58: =VLOOKUP($G$43,'CONTROL DE HORAS'!$D$5:$BH$116,48,FALSE) -> 0 | I58: =H58+I57 -> 0 | J58: =VLOOKUP($G$43,'CONTROL DE HORAS'!$D$5:$BH$116,49,FALSE) -> 0 | K58: =J58+K57 -> 0
A59: MES 5 (PARTE 2) | B59: =VLOOKUP($A$43,'CONTROL DE HORAS'!$D$5:$BH$116,52,FALSE) -> 0 | C59: =B59+C58 -> 0 | D59: =VLOOKUP($A$43,'CONTROL DE HORAS'!$D$5:$BH$116,53,FALSE) -> 0 | E59: =D59+E58 -> 0 | G59: MES 5 (PARTE 2) | H59: =VLOOKUP($G$43,'CONTROL DE HORAS'!$D$5:$BH$116,52,FALSE) -> 0 | I59: =H59+I58 -> 0 | J59: =VLOOKUP($G$43,'CONTROL DE HORAS'!$D$5:$BH$116,53,FALSE) -> 0 | K59: =J59+K58 -> 0

Sheet IMPRESIÓN A4 EN OFICINA
A1: ESTRUCTURA DE COSTOS , IMPRESIÓN A4 EN OFICINA
A2: DESCRIPCIÓN DE INSUMOS | B2: COSTO DE INSUMO | C2: PRESENTACIÓN EMPAQUE | D2: UNIDADES DE MEDIDA | E2: COSTO UNITARIO | F2: CANTIDAD A UTILIZAR | G2: SUBTOTAL DEL COSTO
A3: PAPEL BOND x 1 ciento | B3: =12/1.18 -> 10.169492 | C3: 500 | D3: hojas | E3: =B3/C3 -> 0.020338983 | F3: 1 | G3: =E3*F3 -> 0.020338983
A4: TINTA DE IMPRESORA BLANCO Y NEGRO O COLOR | B4: =40*4/1.18 -> 135.59322 | C4: 70 | D4: ml | E4: =B4/C4 -> 1.937046 | F4: =0.064/4 -> 0.016 | G4: =E4*F4 -> 0.030992736
A5: MANTENIMIENTO DE IMPRESORA | B5: 100 | C5: 360 | D5: dias | E5: =B5/C5 -> 0.27777778 | F5: 1 | G5: =E5*F5 -> 0.27777778
F6: SUB TOTAL | G6: =SUM(G3:G5) -> 0.3291095 | H6: sin igv
